Workbook

Sheet Analysis
B1: Estimating Department _ KPI build
E2: Week | I2: 28
C4: The power BI reports will be sent by email each Monday
C5: Update the Relevent Green Tab with the data
C6: Check the week number formula in the last row goes to the bottom
C7: Refresh the pivot Table on the relevant Pink Tab
C8: The data should pull through into the Estimating KPI tab - you will need to update the week number in cell E2 to drive the formulas
B10: Avg Quote Time - Power BI Report - Saved on Tab of Same Name
C11: This report shows the hours taken to close an estimate
C12: This feeds the Quality KPI
B14: Estimate Time - Power BI Report - Saved on Tab of Same Name
C15: This report shows the estimates and data on those completed on time
C16: This feeds the Productivity and the Delivery KPI

Sheet Estimating KPIs
B1: Owner | C1: Julian Sparrow
D2: Completed up to week | E2: 42 | F2: update | G2: Data to Sun | N2: =+N7+2 -> 45669 | O2: =+O7+2 -> 45676 | P2: =+P7+2 -> 45683 | Q2: =+Q7+2 -> 45690 | R2: =+R7+2 -> 45697 | S2: =+S7+2 -> 45704 | T2: =+T7+2 -> 45711 | U2: =+U7+2 -> 45718 | ... BM2: =+BM7+2 -> 46026
B4: =IF(E2<(E3),"Overdue","Current") -> Current | D4: Submission | E4: Weekly | M4: =IF(M6>$E$3,"Future",IF(M6>$E$2,"OD",IF($E$2>=M6,"Calc"))) -> Future | N4: =IF(N6>$E$2,"Future",IF(N6>$E$2,"OD",IF($E$2>=N6,"Calc"))) -> Calc | O4: =IF(O6>$E$2,"Future",IF(O6>$E$2,"OD",IF($E$2>=O6,"Calc"))) -> Calc | P4: =IF(P6>$E$2,"Future",IF(P6>$E$2,"OD",IF($E$2>=P6,"Calc"))) -> Calc | Q4: =IF(Q6>$E$2,"Future",IF(Q6>$E$2,"OD",IF($E$2>=Q6,"Calc"))) -> Calc | R4: =IF(R6>$E$2,"Future",IF(R6>$E$2,"OD",IF($E$2>=R6,"Calc"))) -> Calc | S4: =IF(S6>$E$2,"Future",IF(S6>$E$2,"OD",IF($E$2>=S6,"Calc"))) -> Calc | T4: =IF(T6>$E$2,"Future",IF(T6>$E$2,"OD",IF($E$2>=T6,"Calc"))) -> Calc | U4: =IF(U6>$E$2,"Future",IF(U6>$E$2,"OD",IF($E$2>=U6,"Calc"))) -> Calc | ... BM4: =IF(BM6>$E$2,"Future",IF(BM6>$E$2,"OD",IF($E$2>=BM6,"Calc"))) -> Future | BN4: =IF($E$2>=BN6,"Calc",IF(BN6>$E$2,IF(BN12>0,"Not Calc yet","Future"))) -> Future
B6: Department: | C6: HR Monthly | G6: Commentary [in relation to current week, trend and outlook] | H6: Week | I6: =J6-1 -> 49 | J6: =K6-1 -> 50 | K6: =L6-1 -> 51 | L6: 52 | M6: 1 | N6: =M6+1 -> 2 | O6: =N6+1 -> 3 | P6: =O6+1 -> 4 | Q6: =P6+1 -> 5 | R6: =Q6+1 -> 6 | S6: =R6+1 -> 7 | T6: =S6+1 -> 8 | U6: =T6+1 -> 9 | ... BM6: =BL6+1 -> 53 | BN6: YTD
B7: Category | C7: KPI | D7: Measure | E7: UOM | F7: Sign | H7: Date (Fri) | I7: =J7-7 -> 45632 | J7: =K7-7 -> 45639 | K7: =L7-7 -> 45646 | L7: =M7-7 -> 45653 | M7: 45660 | N7: =M7+7 -> 45667 | O7: =N7+7 -> 45674 | P7: =O7+7 -> 45681 | Q7: =P7+7 -> 45688 | R7: =Q7+7 -> 45695 | S7: =R7+7 -> 45702 | T7: =S7+7 -> 45709 | U7: =T7+7 -> 45716 | ... BM7: =BL7+7 -> 46024
B8: Productivity | C8: Quotes Issues | D8: Count of quotes issued | E8: Count | F8: Under Breach | G8: Target Based on Qtr 1 actuals | H8: Target | M8: Blank | N8: =IF(N6>$E$2,"",126) -> 126 | O8: =IF(O6>$E$2,"",126) -> 126 | P8: =IF(P6>$E$2,"",126) -> 126 | Q8: =IF(Q6>$E$2,"",126) -> 126 | R8: =IF(R6>$E$2,"",126) -> 126 | S8: =IF(S6>$E$2,"",126) -> 126 | T8: =IF(T6>$E$2,"",126) -> 126 | U8: =IF(U6>$E$2,"",126) -> 126 | ... BN8: =IF(BN6>$E$2,"",126)
H9: Actual | M9: Blank | N9: =IFERROR(IF(N6>$E$2,"",+GETPIVOTDATA("Count of Estimating Request: Estimate Request No.",'Pivot of Estimate time'!$B$3,"week No",N6)),"No Data") -> 102 | O9: =IFERROR(IF(O6>$E$2,"",+GETPIVOTDATA("Count of Estimating Request: Estimate Request No.",'Pivot of Estimate time'!$B$3,"week No",O6)),"No Data") -> 127 | P9: =IFERROR(IF(P6>$E$2,"",+GETPIVOTDATA("Count of Estimating Request: Estimate Request No.",'Pivot of Estimate time'!$B$3,"week No",P6)),"No Data") -> 106 | Q9: =IFERROR(IF(Q6>$E$2,"",+GETPIVOTDATA("Count of Estimating Request: Estimate Request No.",'Pivot of Estimate time'!$B$3,"week No",Q6)),"No Data") -> 150 | R9: =IFERROR(IF(R6>$E$2,"",+GETPIVOTDATA("Count of Estimating Request: Estimate Request No.",'Pivot of Estimate time'!$B$3,"week No",R6)),"No Data") -> 135 | S9: =IFERROR(IF(S6>$E$2,"",+GETPIVOTDATA("Count of Estimating Request: Estimate Request No.",'Pivot of Estimate time'!$B$3,"week No",S6)),"No Data") -> 133 | T9: =IFERROR(IF(T6>$E$2,"",+GETPIVOTDATA("Count of Estimating Request: Estimate Request No.",'Pivot of Estimate time'!$B$3,"week No",T6)),"No Data") -> 130 | U9: =IFERROR(IF(U6>$E$2,"",+GETPIVOTDATA("Count of Estimating Request: Estimate Request No.",'Pivot of Estimate time'!$B$3,"week No",U6)),"No Data") -> 132 | ... BN9: =IFERROR(IF(BN6>$E$2,"",+GETPIVOTDATA("Count of Estimating Request: Estimate Request No.",'Pivot of Estimate time'!$B$3,"week No",BN6)),"No Data")
H10: Variance | M10: =IF(M9="Blank","Blank",IF(M9="TBC","TBC",IF(M9="Undefined","Undefined",IF(M$4="OD","OD",IF(M$6>$E$2,"",IF((M9-M8)>=0,"G",IF((M9-(M8*0.95))>=0,"A","R"))))))) -> Blank | N10: =IF(N9="Blank","Blank",IF(N9="TBC","TBC",IF(N9="Undefined","Undefined",IF(N$4="OD","OD",IF(N$9="No Data","No Data",IF(N$6>$E$2,"",IF((N9-N8)>=0,"G",IF((N9-(N8*0.95))>=0,"A","R")))))))) -> R | O10: =IF(O9="Blank","Blank",IF(O9="TBC","TBC",IF(O9="Undefined","Undefined",IF(O$4="OD","OD",IF(O$9="No Data","No Data",IF(O$6>$E$2,"",IF((O9-O8)>=0,"G",IF((O9-(O8*0.95))>=0,"A","R")))))))) -> G | P10: =IF(P9="Blank","Blank",IF(P9="TBC","TBC",IF(P9="Undefined","Undefined",IF(P$4="OD","OD",IF(P$9="No Data","No Data",IF(P$6>$E$2,"",IF((P9-P8)>=0,"G",IF((P9-(P8*0.95))>=0,"A","R")))))))) -> R | Q10: =IF(Q9="Blank","Blank",IF(Q9="TBC","TBC",IF(Q9="Undefined","Undefined",IF(Q$4="OD","OD",IF(Q$9="No Data","No Data",IF(Q$6>$E$2,"",IF((Q9-Q8)>=0,"G",IF((Q9-(Q8*0.95))>=0,"A","R")))))))) -> G | R10: =IF(R9="Blank","Blank",IF(R9="TBC","TBC",IF(R9="Undefined","Undefined",IF(R$4="OD","OD",IF(R$9="No Data","No Data",IF(R$6>$E$2,"",IF((R9-R8)>=0,"G",IF((R9-(R8*0.95))>=0,"A","R")))))))) -> G | S10: =IF(S9="Blank","Blank",IF(S9="TBC","TBC",IF(S9="Undefined","Undefined",IF(S$4="OD","OD",IF(S$9="No Data","No Data",IF(S$6>$E$2,"",IF((S9-S8)>=0,"G",IF((S9-(S8*0.95))>=0,"A","R")))))))) -> G | T10: =IF(T9="Blank","Blank",IF(T9="TBC","TBC",IF(T9="Undefined","Undefined",IF(T$4="OD","OD",IF(T$9="No Data","No Data",IF(T$6>$E$2,"",IF((T9-T8)>=0,"G",IF((T9-(T8*0.95))>=0,"A","R")))))))) -> G | U10: =IF(U9="Blank","Blank",IF(U9="TBC","TBC",IF(U9="Undefined","Undefined",IF(U$4="OD","OD",IF(U$9="No Data","No Data",IF(U$6>$E$2,"",IF((U9-U8)>=0,"G",IF((U9-(U8*0.95))>=0,"A","R")))))))) -> G | ... AV10: =IF(AV9="Blank","Blank",IF(AV9="TBC","TBC",IF(AV9="Undefined","Undefined",IF(AV$4="OD","OD",IF(AV$9="No Data","No Data",IF(AV$6>$E$2,"",IF((AV9-AV8)>=0,"G",IF((AV9-(AV8*0.95))>=0,"A","R")))))))) -> R | AW10: =IF(AW9="Blank","Blank", IF(AW9="TBC","TBC", IF(AW9="Undefined","Undefined", IF(AW$4="OD","OD", IF(AW$9="No Data","No Data", IF(AW$6>$E$2,"", IF((AW9-AW8)>=0,"G", IF((AW9-(AW8*0.95))>=0,"A", "R")))))))) -> G | AX10: =IF(AX9="Blank","Blank",IF(AX9="TBC","TBC",IF(AX9="Undefined","Undefined",IF(AX$4="OD","OD",IF(AX$9="No Data","No Data",IF(AX$6>$E$2,"",IF((AX9-AX8)>=0,"G",IF((AX9-(AX8*0.95))>=0,"A","R")))))))) -> R | AY10: =IF(AY9="Blank","Blank",IF(AY9="TBC","TBC",IF(AY9="Undefined","Undefined",IF(AY$4="OD","OD",IF(AY$9="No Data","No Data",IF(AY$6>$E$2,"",IF((AY9-AY8)>=0,"G",IF((AY9-(AY8*0.95))>=0,"A","R")))))))) -> R | AZ10: =IF(AZ9="Blank","Blank",IF(AZ9="TBC","TBC",IF(AZ9="Undefined","Undefined",IF(AZ$4="OD","OD",IF(AZ$9="No Data","No Data",IF(AZ$6>$E$2,"",IF((AZ9-AZ8)>=0,"G",IF((AZ9-(AZ8*0.95))>=0,"A","R")))))))) -> R | BA10: =IF(BA9="Blank","Blank",IF(BA9="TBC","TBC",IF(BA9="Undefined","Undefined",IF(BA$4="OD","OD",IF(BA$9="No Data","No Data",IF(BA$6>$E$2,"",IF((BA9-BA8)>=0,"G",IF((BA9-(BA8*0.95))>=0,"A","R")))))))) -> A | BB10: =IF(BB9="Blank","Blank",IF(BB9="TBC","TBC",IF(BB9="Undefined","Undefined",IF(BB$4="OD","OD",IF(BB$9="No Data","No Data",IF(BB$6>$E$2,"",IF((BB9-BB8)>=0,"G",IF((BB9-(BB8*0.95))>=0,"A","R")))))))) -> A | BC10: =IF(BC9="Blank","Blank",IF(BC9="TBC","TBC",IF(BC9="Undefined","Undefined",IF(BC$4="OD","OD",IF(BC$9="No Data","No Data",IF(BC$6>$E$2,"",IF((BC9-BC8)>=0,"G",IF((BC9-(BC8*0.95))>=0,"A","R")))))))) | BD10: =IF(BD9="Blank","Blank",IF(BD9="TBC","TBC",IF(BD9="Undefined","Undefined",IF(BD$4="OD","OD",IF(BD$9="No Data","No Data",IF(BD$6>$E$2,"",IF((BD9-BD8)>=0,"G",IF((BD9-(BD8*0.95))>=0,"A","R")))))))) | BE10: =IF(BE9="Blank","Blank",IF(BE9="TBC","TBC",IF(BE9="Undefined","Undefined",IF(BE$4="OD","OD",IF(BE$9="No Data","No Data",IF(BE$6>$E$2,"",IF((BE9-BE8)>=0,"G",IF((BE9-(BE8*0.95))>=0,"A","R")))))))) | ... BM10: =IF(BM9="Blank","Blank",IF(BM9="TBC","TBC",IF(BM9="Undefined","Undefined",IF(BM$4="OD","OD",IF(BM$9="No Data","No Data",IF(BM$6>$E$2,"",IF((BM9-BM8)>=0,"G",IF((BM9-(BM8*0.95))>=0,"A","R"))))))))
B11: Delivery | C11: Quotes Issues on Time | D11: Percentage of quotes issues on time (TBC all of export only) | E11: Percentage | F11: Under Breach | G11: Target Based on Qtr 1 actuals | H11: Target | M11: Blank | N11: =IF(N6>$E$2,"",85) -> 85 | O11: =IF(O6>$E$2,"",85) -> 85 | P11: =IF(P6>$E$2,"",85) -> 85 | Q11: =IF(Q6>$E$2,"",85) -> 85 | R11: =IF(R6>$E$2,"",85) -> 85 | S11: =IF(S6>$E$2,"",85) -> 85 | T11: =IF(T6>$E$2,"",85) -> 85 | U11: =IF(U6>$E$2,"",85) -> 85 | ... BN11: =IF(BN6>$E$2,"",85)
H12: Actual | M12: Blank | N12: =IFERROR(IF(N6>$E$2,"",+GETPIVOTDATA("Sum of On Time / Late",'Pivot of Estimate time'!$B$3,"week No",N6)/GETPIVOTDATA("Count of Estimating Request: Estimate Request No.",'Pivot of Estimate time'!$B$3,"week No",N6)*100),"No Data") -> 96.078431 | O12: =IFERROR(IF(O6>$E$2,"",+GETPIVOTDATA("Sum of On Time / Late",'Pivot of Estimate time'!$B$3,"week No",O6)/GETPIVOTDATA("Count of Estimating Request: Estimate Request No.",'Pivot of Estimate time'!$B$3,"week No",O6)*100),"No Data") -> 87.401575 | P12: =IFERROR(IF(P6>$E$2,"",+GETPIVOTDATA("Sum of On Time / Late",'Pivot of Estimate time'!$B$3,"week No",P6)/GETPIVOTDATA("Count of Estimating Request: Estimate Request No.",'Pivot of Estimate time'!$B$3,"week No",P6)*100),"No Data") -> 79.245283 | Q12: =IFERROR(IF(Q6>$E$2,"",+GETPIVOTDATA("Sum of On Time / Late",'Pivot of Estimate time'!$B$3,"week No",Q6)/GETPIVOTDATA("Count of Estimating Request: Estimate Request No.",'Pivot of Estimate time'!$B$3,"week No",Q6)*100),"No Data") -> 84 | R12: =IFERROR(IF(R6>$E$2,"",+GETPIVOTDATA("Sum of On Time / Late",'Pivot of Estimate time'!$B$3,"week No",R6)/GETPIVOTDATA("Count of Estimating Request: Estimate Request No.",'Pivot of Estimate time'!$B$3,"week No",R6)*100),"No Data") -> 85.185185 | S12: =IFERROR(IF(S6>$E$2,"",+GETPIVOTDATA("Sum of On Time / Late",'Pivot of Estimate time'!$B$3,"week No",S6)/GETPIVOTDATA("Count of Estimating Request: Estimate Request No.",'Pivot of Estimate time'!$B$3,"week No",S6)*100),"No Data") -> 87.218045 | T12: =IFERROR(IF(T6>$E$2,"",+GETPIVOTDATA("Sum of On Time / Late",'Pivot of Estimate time'!$B$3,"week No",T6)/GETPIVOTDATA("Count of Estimating Request: Estimate Request No.",'Pivot of Estimate time'!$B$3,"week No",T6)*100),"No Data") -> 87.692308 | U12: =IFERROR(IF(U6>$E$2,"",+GETPIVOTDATA("Sum of On Time / Late",'Pivot of Estimate time'!$B$3,"week No",U6)/GETPIVOTDATA("Count of Estimating Request: Estimate Request No.",'Pivot of Estimate time'!$B$3,"week No",U6)*100),"No Data") -> 86.363636 | ... BM12: =IFERROR(IF(BM6>$E$2,"",+GETPIVOTDATA("Sum of On Time / Late",'Pivot of Estimate time'!$B$3,"week No",BM6)/GETPIVOTDATA("Count of Estimating Request: Estimate Request No.",'Pivot of Estimate time'!$B$3,"week No",BM6)*100),"No Data")
H13: Variance | M13: =IF(M12="Blank","Blank",IF(M12="TBC","TBC",IF(M12="Undefined","Undefined",IF(M$4="OD","OD",IF(M$6>$E$2,"",IF((M12-M11)>=0,"G",IF((M12-(M11*0.95))>=0,"A","R"))))))) -> Blank | N13: =IF(N12="Blank","Blank",IF(N12="TBC","TBC",IF(N12="Undefined","Undefined",IF(N12="No Data","No Data",IF(N$4="OD","OD",IF(N$6>$E$2,"",IF((N12-N11)>=0,"G",IF((N12-(N11*0.95))>=0,"A","R")))))))) -> G | O13: =IF(O12="Blank","Blank",IF(O12="TBC","TBC",IF(O12="Undefined","Undefined",IF(O12="No Data","No Data",IF(O$4="OD","OD",IF(O$6>$E$2,"",IF((O12-O11)>=0,"G",IF((O12-(O11*0.95))>=0,"A","R")))))))) -> G | P13: =IF(P12="Blank","Blank",IF(P12="TBC","TBC",IF(P12="Undefined","Undefined",IF(P12="No Data","No Data",IF(P$4="OD","OD",IF(P$6>$E$2,"",IF((P12-P11)>=0,"G",IF((P12-(P11*0.95))>=0,"A","R")))))))) -> R | Q13: =IF(Q12="Blank","Blank",IF(Q12="TBC","TBC",IF(Q12="Undefined","Undefined",IF(Q12="No Data","No Data",IF(Q$4="OD","OD",IF(Q$6>$E$2,"",IF((Q12-Q11)>=0,"G",IF((Q12-(Q11*0.95))>=0,"A","R")))))))) -> A | R13: =IF(R12="Blank","Blank",IF(R12="TBC","TBC",IF(R12="Undefined","Undefined",IF(R12="No Data","No Data",IF(R$4="OD","OD",IF(R$6>$E$2,"",IF((R12-R11)>=0,"G",IF((R12-(R11*0.95))>=0,"A","R")))))))) -> G | S13: =IF(S12="Blank","Blank",IF(S12="TBC","TBC",IF(S12="Undefined","Undefined",IF(S12="No Data","No Data",IF(S$4="OD","OD",IF(S$6>$E$2,"",IF((S12-S11)>=0,"G",IF((S12-(S11*0.95))>=0,"A","R")))))))) -> G | T13: =IF(T12="Blank","Blank",IF(T12="TBC","TBC",IF(T12="Undefined","Undefined",IF(T12="No Data","No Data",IF(T$4="OD","OD",IF(T$6>$E$2,"",IF((T12-T11)>=0,"G",IF((T12-(T11*0.95))>=0,"A","R")))))))) -> G | U13: =IF(U12="Blank","Blank",IF(U12="TBC","TBC",IF(U12="Undefined","Undefined",IF(U12="No Data","No Data",IF(U$4="OD","OD",IF(U$6>$E$2,"",IF((U12-U11)>=0,"G",IF((U12-(U11*0.95))>=0,"A","R")))))))) -> G | ... BN13: =IF(BN12="Blank","Blank",IF(BN12="TBC","TBC",IF(BN12="Undefined","Undefined",IF(BN12="No Data","No Data",IF(BN$4="OD","OD",IF(BN$6>$E$2,"",IF((BN12-BN11)>=0,"G",IF((BN12-(BN11*0.95))>=0,"A","R"))))))))
B14: Quality | C14: Estimated Hours | D14: Hours used on estimations, (further split by division) | E14: Hours | F14: Over Breach | G14: Target Based on Qtr 1 actuals | H14: Target | M14: Blank | N14: =IF(N6>$E$2,"",28) -> 28 | O14: =IF(O6>$E$2,"",28) -> 28 | P14: =IF(P6>$E$2,"",28) -> 28 | Q14: =IF(Q6>$E$2,"",28) -> 28 | R14: =IF(R6>$E$2,"",28) -> 28 | S14: =IF(S6>$E$2,"",28) -> 28 | T14: =IF(T6>$E$2,"",28) -> 28 | U14: =IF(U6>$E$2,"",28) -> 28 | ... BN14: =IF(BN6>$E$2,"",28)
H15: Actual | M15: Blank | N15: =IFERROR(IF(N6>$E$2,"",+GETPIVOTDATA("Sum of Hours Taken to Close",'Pivot Avg Quote Time '!$B$5,"week No",N6)/GETPIVOTDATA("Count of Estimating Request: Estimate Request No.",'Pivot Avg Quote Time '!$B$5,"week No",N6)),"No Data") -> 60.596774 | O15: =IFERROR(IF(O6>$E$2,"",+GETPIVOTDATA("Sum of Hours Taken to Close",'Pivot Avg Quote Time '!$B$5,"week No",O6)/GETPIVOTDATA("Count of Estimating Request: Estimate Request No.",'Pivot Avg Quote Time '!$B$5,"week No",O6)),"No Data") -> 21.351351 | P15: =IFERROR(IF(P6>$E$2,"",+GETPIVOTDATA("Sum of Hours Taken to Close",'Pivot Avg Quote Time '!$B$5,"week No",P6)/GETPIVOTDATA("Count of Estimating Request: Estimate Request No.",'Pivot Avg Quote Time '!$B$5,"week No",P6)),"No Data") -> 29.637681 | Q15: =IFERROR(IF(Q6>$E$2,"",+GETPIVOTDATA("Sum of Hours Taken to Close",'Pivot Avg Quote Time '!$B$5,"week No",Q6)/GETPIVOTDATA("Count of Estimating Request: Estimate Request No.",'Pivot Avg Quote Time '!$B$5,"week No",Q6)),"No Data") -> 29.119048 | R15: =IFERROR(IF(R6>$E$2,"",+GETPIVOTDATA("Sum of Hours Taken to Close",'Pivot Avg Quote Time '!$B$5,"week No",R6)/GETPIVOTDATA("Count of Estimating Request: Estimate Request No.",'Pivot Avg Quote Time '!$B$5,"week No",R6)),"No Data") -> 32.630769 | S15: =IFERROR(IF(S6>$E$2,"",+GETPIVOTDATA("Sum of Hours Taken to Close",'Pivot Avg Quote Time '!$B$5,"week No",S6)/GETPIVOTDATA("Count of Estimating Request: Estimate Request No.",'Pivot Avg Quote Time '!$B$5,"week No",S6)),"No Data") -> 22.584615 | T15: =IFERROR(IF(T6>$E$2,"",+GETPIVOTDATA("Sum of Hours Taken to Close",'Pivot Avg Quote Time '!$B$5,"week No",T6)/GETPIVOTDATA("Count of Estimating Request: Estimate Request No.",'Pivot Avg Quote Time '!$B$5,"week No",T6)),"No Data") -> 31.144737 | U15: =IFERROR(IF(U6>$E$2,"",+GETPIVOTDATA("Sum of Hours Taken to Close",'Pivot Avg Quote Time '!$B$5,"week No",U6)/GETPIVOTDATA("Count of Estimating Request: Estimate Request No.",'Pivot Avg Quote Time '!$B$5,"week No",U6)),"No Data") -> 19.615385 | ... BN15: =IFERROR(IF(BN6>$E$2,"",+GETPIVOTDATA("Sum of Hours Taken to Close",'Pivot Avg Quote Time '!$B$5,"week No",BN6)/GETPIVOTDATA("Count of Estimating Request: Estimate Request No.",'Pivot Avg Quote Time '!$B$5,"week No",BN6)),"No Data")
H16: Variance | M16: =IF(M15="Blank","Blank",IF(M15="TBC","TBC",IF(M15="Undefined","Undefined",IF(M$4="OD","OD",IF(M$6>$E$2,"",IF((M15-M14)<=0,"G",IF((M15-(M14*0.95))<=0,"A","R"))))))) -> Blank | N16: =IF(N15="Blank","Blank",IF(N15="TBC","TBC",IF(N15="Undefined","Undefined",IF(N15="No data","No Data",IF(N$4="OD","OD",IF(N$6>$E$2,"",IF((N15-N14)<=0,"G",IF((N15-(N14/0.95))<=0,"A","R")))))))) -> R | O16: =IF(O15="Blank","Blank",IF(O15="TBC","TBC",IF(O15="Undefined","Undefined",IF(O15="No data","No Data",IF(O$4="OD","OD",IF(O$6>$E$2,"",IF((O15-O14)<=0,"G",IF((O15-(O14/0.95))<=0,"A","R")))))))) -> G | P16: =IF(P15="Blank","Blank",IF(P15="TBC","TBC",IF(P15="Undefined","Undefined",IF(P15="No data","No Data",IF(P$4="OD","OD",IF(P$6>$E$2,"",IF((P15-P14)<=0,"G",IF((P15-(P14/0.95))<=0,"A","R")))))))) -> R | Q16: =IF(Q15="Blank","Blank",IF(Q15="TBC","TBC",IF(Q15="Undefined","Undefined",IF(Q15="No data","No Data",IF(Q$4="OD","OD",IF(Q$6>$E$2,"",IF((Q15-Q14)<=0,"G",IF((Q15-(Q14/0.95))<=0,"A","R")))))))) -> A | R16: =IF(R15="Blank","Blank",IF(R15="TBC","TBC",IF(R15="Undefined","Undefined",IF(R15="No data","No Data",IF(R$4="OD","OD",IF(R$6>$E$2,"",IF((R15-R14)<=0,"G",IF((R15-(R14/0.95))<=0,"A","R")))))))) -> R | S16: =IF(S15="Blank","Blank",IF(S15="TBC","TBC",IF(S15="Undefined","Undefined",IF(S15="No data","No Data",IF(S$4="OD","OD",IF(S$6>$E$2,"",IF((S15-S14)<=0,"G",IF((S15-(S14/0.95))<=0,"A","R")))))))) -> G | T16: =IF(T15="Blank","Blank",IF(T15="TBC","TBC",IF(T15="Undefined","Undefined",IF(T15="No data","No Data",IF(T$4="OD","OD",IF(T$6>$E$2,"",IF((T15-T14)<=0,"G",IF((T15-(T14/0.95))<=0,"A","R")))))))) -> R | U16: =IF(U15="Blank","Blank",IF(U15="TBC","TBC",IF(U15="Undefined","Undefined",IF(U15="No data","No Data",IF(U$4="OD","OD",IF(U$6>$E$2,"",IF((U15-U14)<=0,"G",IF((U15-(U14/0.95))<=0,"A","R")))))))) -> G | ... BM16: =IF(BM15="Blank","Blank",IF(BM15="TBC","TBC",IF(BM15="Undefined","Undefined",IF(BM15="No data","No Data",IF(BM$4="OD","OD",IF(BM$6>$E$2,"",IF((BM15-BM14)<=0,"G",IF((BM15-(BM14/0.95))<=0,"A","R"))))))))
B17: Cost | C17: Rate of Sales per square meter | D17: Value of sales per Sq meter (Power BI data but excludes those with an item per SQM below 0.03) | E17: £ | F17: Under Breach | G17: Target set but may be reevaluated | H17: Target | M17: Blank | N17: TBC | O17: TBC | P17: TBC | Q17: TBC | R17: TBC | S17: TBC | T17: TBC | U17: TBC | V17: TBC | W17: TBC | X17: TBC | Y17: TBC | Z17: TBC | AA17: TBC | AB17: TBC | AC17: TBC | AD17: TBC | AE17: TBC | AF17: TBC | AG17: TBC | AH17: 75 | AI17: 75 | AJ17: 75 | AK17: 75 | AL17: 75 | AM17: 75 | AN17: 75 | AO17: 75 | AP17: 75 | AQ17: 75 | AR17: 75 | AS17: 75 | AT17: 75 | AU17: 75 | AV17: 75 | AW17: 75 | AX17: 75 | AY17: 75 | AZ17: 75 | BA17: 75 | BB17: 75 | BC17: 0 | BD17: 0 | BE17: 0 | BF17: 0 | BG17: 0 | BH17: 0 | BI17: 0 | BJ17: 0 | BK17: 0 | BL17: 0 | BM17: 0
H18: Actual | M18: Blank | N18: TBC | O18: TBC | P18: TBC | Q18: TBC | R18: TBC | S18: TBC | T18: TBC | U18: TBC | V18: TBC | W18: TBC | X18: TBC | Y18: TBC | Z18: TBC | AA18: TBC | AB18: TBC | AC18: TBC | AD18: TBC | AE18: TBC | AF18: TBC | AG18: TBC | AH18: =+'SQM Wk 22'!N1 -> 75.655769 | AI18: =+' SQM Wk 23'!N1 -> 87.727857 | AJ18: =+'SQM Wk 24'!O1 -> 82.874878 | AK18: =+'SQM Wk 25'!O1 -> 82.126 | AL18: =+'SQM Wk 26'!O1 -> 72.681429 | AM18: =+'SQM WK27'!O1 -> 78.721579 | AN18: =+'SQM WK28'!O1 -> 82.652727 | AO18: =+'SQM WK29'!O1 -> 72.047273 | AP18: =+'SQM WK30'!O1 -> 68.755625 | AQ18: =+'SQM WK31'!O1 -> 103.18844 | AR18: =+'SQM WK32'!O1 -> 69.103333 | AS18: =+'SQM WK33'!O1 -> 77.475625 | AT18: =+'SQM WK 34'!O1 -> 63.224062 | AU18: =+' SQM WK 35'!O1 -> 150.0293 | AV18: =+SQMWK36!O1 -> 70.96 | AW18: =+'SQM WK37'!O1 -> 79.844902 | AX18: =+'SQM WK 38'!O1 -> 79.964756 | AY18: =+'SQM WK39'!O1 -> 107.59414 | AZ18: =+'SQM WK 40'!O1 -> 80.211034 | BA18: =+'SQM WK41'!O1 -> 79.488621 | BB18: =+'SQM WK42'!O1 -> 80.659884
H19: Variance | M19: =IF(M18="Blank","Blank",IF(M18="TBC","TBC",IF(M18="Undefined","Undefined",IF(M$4="OD","OD",IF(M$6>$E$2,"",IF((M18-M17)>=0,"G",IF((M18-(M17*0.95))>=0,"A","R"))))))) -> Blank | N19: =IF(N18="Blank","Blank",IF(N18="TBC","TBC",IF(N18="Undefined","Undefined",IF(N$4="OD","OD",IF(N$6>$E$2,"",IF((N18-N17)>=0,"G",IF((N18-(N17*0.95))>=0,"A","R"))))))) -> TBC | O19: =IF(O18="Blank","Blank",IF(O18="TBC","TBC",IF(O18="Undefined","Undefined",IF(O$4="OD","OD",IF(O$6>$E$2,"",IF((O18-O17)>=0,"G",IF((O18-(O17*0.95))>=0,"A","R"))))))) -> TBC | P19: =IF(P18="Blank","Blank",IF(P18="TBC","TBC",IF(P18="Undefined","Undefined",IF(P$4="OD","OD",IF(P$6>$E$2,"",IF((P18-P17)>=0,"G",IF((P18-(P17*0.95))>=0,"A","R"))))))) -> TBC | Q19: =IF(Q18="Blank","Blank",IF(Q18="TBC","TBC",IF(Q18="Undefined","Undefined",IF(Q$4="OD","OD",IF(Q$6>$E$2,"",IF((Q18-Q17)>=0,"G",IF((Q18-(Q17*0.95))>=0,"A","R"))))))) -> TBC | R19: =IF(R18="Blank","Blank",IF(R18="TBC","TBC",IF(R18="Undefined","Undefined",IF(R$4="OD","OD",IF(R$6>$E$2,"",IF((R18-R17)>=0,"G",IF((R18-(R17*0.95))>=0,"A","R"))))))) -> TBC | S19: =IF(S18="Blank","Blank",IF(S18="TBC","TBC",IF(S18="Undefined","Undefined",IF(S$4="OD","OD",IF(S$6>$E$2,"",IF((S18-S17)>=0,"G",IF((S18-(S17*0.95))>=0,"A","R"))))))) -> TBC | T19: =IF(T18="Blank","Blank",IF(T18="TBC","TBC",IF(T18="Undefined","Undefined",IF(T$4="OD","OD",IF(T$6>$E$2,"",IF((T18-T17)>=0,"G",IF((T18-(T17*0.95))>=0,"A","R"))))))) -> TBC | ... BM19: =IF(BM18="Blank","Blank",IF(BM18="TBC","TBC",IF(BM18="Undefined","Undefined",IF(BM$4="OD","OD",IF(BM$6>$E$2,"",IF((BM18-BM17)>=0,"G",IF((BM18-(BM17*0.95))>=0,"A","R")))))))
B21: R | C21: KPI is worse than Target | N21: Avg wek 1-13 used as target | Z21: The targets above are the avg of Q1 2025
B22: A | C22: KPI is <5% worse than Target | N22: =AVERAGE(N9:Y9) -> 126.83333 | Z22: But can be reset if needed
B23: G | C23: KPI is better than Target | N23: =AVERAGE(N12:Y12) -> 84.54126
B24: TBC | C24: Missing Submission | N24: =AVERAGE(N15:Y15) -> 28.704464 | Z24: The cost KPI isnt yet being reported - the above actual values are done by removing those £SQ meter below 0.03 on the power BI report
B25: Blank | C25: No Submission | Z25: But awaiting your work this week before updating the actual report

Sheet Pivot Avg Quote Time 
B3: Blank | C3: (Multiple Items)
B5: Row Labels | C5: Count of Estimating Request: Estimate Request No. | D5: Sum of Hours Taken to Close
B6: (blank)
B7: 2 | C7: 62 | D7: 3757
B8: 3 | C8: 74 | D8: 1580
B9: 4 | C9: 69 | D9: 2045
B10: 5 | C10: 84 | D10: 2446
B11: 6 | C11: 65 | D11: 2121
B12: 7 | C12: 65 | D12: 1468
B13: 8 | C13: 76 | D13: 2367
B14: 9 | C14: 78 | D14: 1530
B15: 10 | C15: 81 | D15: 1719
B16: 11 | C16: 62 | D16: 1154
B17: 12 | C17: 80 | D17: 2489
B18: 13 | C18: 86 | D18: 2307
... B47: 42 | C47: 62 | D47: 1624
B48: Grand Total | C48: 2663 | D48: 82849

Sheet Pivot of Estimate time
B1: On Time / Late | C1: (All)
B3: Row Labels | C3: Sum of On Time / Late | D3: Count of Estimating Request: Estimate Request No.
B4: FALSE | C4: 0 | D4: 1
B5: (blank)
B6: 2 | C6: 98 | D6: 102
B7: 3 | C7: 111 | D7: 127
B8: 4 | C8: 84 | D8: 106
B9: 5 | C9: 126 | D9: 150
B10: 6 | C10: 115 | D10: 135
B11: 7 | C11: 116 | D11: 133
B12: 8 | C12: 114 | D12: 130
B13: 9 | C13: 114 | D13: 132
B14: 10 | C14: 95 | D14: 124
B15: 11 | C15: 106 | D15: 119
B16: 12 | C16: 92 | D16: 124
B17: 13 | C17: 114 | D17: 140
... B46: 42 | C46: 101 | D46: 123
B47: Grand Total | C47: 3894 | D47: 4929

Sheet Avg Quote Time
A1: Estimating Request: Estimate Request No. | B1: Hours Taken to Close | C1: Date/Time Closed | D1: Sales Division | E1: Blank | F1: week No
A2: EST-000029602 | C2: 45664 | D2: Australia | E2: =IF(B2=0,"Blank","Not Blank") -> Blank | F2: =_xlfn.XLOOKUP(C2,'Wk no''s'!B:B,'Wk no''s'!C:C,FALSE) -> 2
A3: EST-000029181 | B3: 136 | C3: 45665 | D3: France | E3: =IF(B3=0,"Blank","Not Blank") -> Not Blank | F3: =_xlfn.XLOOKUP(C3,'Wk no''s'!B:B,'Wk no''s'!C:C,FALSE) -> 2
A4: EST-000027498 | C4: 45667 | D4: Ireland | E4: =IF(B4=0,"Blank","Not Blank") -> Blank | F4: =_xlfn.XLOOKUP(C4,'Wk no''s'!B:B,'Wk no''s'!C:C,FALSE) -> 2
A5: EST-000029222 | C5: 45667 | D5: Ireland | E5: =IF(B5=0,"Blank","Not Blank") -> Blank | F5: =_xlfn.XLOOKUP(C5,'Wk no''s'!B:B,'Wk no''s'!C:C,FALSE) -> 2
A6: EST-000029242 | C6: 45667 | D6: Ireland | E6: =IF(B6=0,"Blank","Not Blank") -> Blank | F6: =_xlfn.XLOOKUP(C6,'Wk no''s'!B:B,'Wk no''s'!C:C,FALSE) -> 2
A7: EST-000029264 | C7: 45667 | D7: Ireland | E7: =IF(B7=0,"Blank","Not Blank") -> Blank | F7: =_xlfn.XLOOKUP(C7,'Wk no''s'!B:B,'Wk no''s'!C:C,FALSE) -> 2
A8: EST-000029366 | C8: 45667 | D8: Ireland | E8: =IF(B8=0,"Blank","Not Blank") -> Blank | F8: =_xlfn.XLOOKUP(C8,'Wk no''s'!B:B,'Wk no''s'!C:C,FALSE) -> 2
A9: EST-000029486 | C9: 45667 | D9: Ireland | E9: =IF(B9=0,"Blank","Not Blank") -> Blank | F9: =_xlfn.XLOOKUP(C9,'Wk no''s'!B:B,'Wk no''s'!C:C,FALSE) -> 2
A10: EST-000029544 | C10: 45663 | D10: Ireland | E10: =IF(B10=0,"Blank","Not Blank") -> Blank | F10: =_xlfn.XLOOKUP(C10,'Wk no''s'!B:B,'Wk no''s'!C:C,FALSE) -> 2
A11: EST-000029536 | C11: 45663 | D11: Ireland | E11: =IF(B11=0,"Blank","Not Blank") -> Blank | F11: =_xlfn.XLOOKUP(C11,'Wk no''s'!B:B,'Wk no''s'!C:C,FALSE) -> 2
A12: EST-000029538 | C12: 45663 | D12: Ireland | E12: =IF(B12=0,"Blank","Not Blank") -> Blank | F12: =_xlfn.XLOOKUP(C12,'Wk no''s'!B:B,'Wk no''s'!C:C,FALSE) -> 2
A13: EST-000029558 | C13: 45663 | D13: Ireland | E13: =IF(B13=0,"Blank","Not Blank") -> Blank | F13: =_xlfn.XLOOKUP(C13,'Wk no''s'!B:B,'Wk no''s'!C:C,FALSE) -> 2
A14: EST-000029569 | C14: 45664 | D14: Ireland | E14: =IF(B14=0,"Blank","Not Blank") -> Blank | F14: =_xlfn.XLOOKUP(C14,'Wk no''s'!B:B,'Wk no''s'!C:C,FALSE) -> 2
A15: EST-000029594 | C15: 45664 | D15: Ireland | E15: =IF(B15=0,"Blank","Not Blank") -> Blank | F15: =_xlfn.XLOOKUP(C15,'Wk no''s'!B:B,'Wk no''s'!C:C,FALSE) -> 2
... A23: EST-000029778 | C23: 45667 | D23: Ireland | E23: =IF(B23=0,"Blank","Not Blank") -> Blank | F23: =_xlfn.XLOOKUP(C23,'Wk no''s'!B:B,'Wk no''s'!C:C,FALSE) -> 2
A24: EST-000028482 | B24: 280 | C24: 45664 | D24: Middle East | E24: =IF(B24=0,"Blank","Not Blank") -> Not Blank | F24: =_xlfn.XLOOKUP(C24,'Wk no''s'!B:B,'Wk no''s'!C:C,FALSE) -> 2
A25: EST-000028764 | B25: 232 | C25: 45664 | D25: Middle East | E25: =IF(B25=0,"Blank","Not Blank") -> Not Blank | F25: =_xlfn.XLOOKUP(C25,'Wk no''s'!B:B,'Wk no''s'!C:C,FALSE) -> 2
A26: EST-000029302 | B26: 128 | C26: 45663 | D26: Middle East | E26: =IF(B26=0,"Blank","Not Blank") -> Not Blank | F26: =_xlfn.XLOOKUP(C26,'Wk no''s'!B:B,'Wk no''s'!C:C,FALSE) -> 2
A27: EST-000029532 | B27: 8 | C27: 45664 | D27: Middle East | E27: =IF(B27=0,"Blank","Not Blank") -> Not Blank | F27: =_xlfn.XLOOKUP(C27,'Wk no''s'!B:B,'Wk no''s'!C:C,FALSE) -> 2
A28: EST-000029533 | B28: 0 | C28: 45663 | D28: Middle East | E28: =IF(B28=0,"Blank","Not Blank") -> Blank | F28: =_xlfn.XLOOKUP(C28,'Wk no''s'!B:B,'Wk no''s'!C:C,FALSE) -> 2
A29: EST-000029534 | B29: 8 | C29: 45664 | D29: Middle East | E29: =IF(B29=0,"Blank","Not Blank") -> Not Blank | F29: =_xlfn.XLOOKUP(C29,'Wk no''s'!B:B,'Wk no''s'!C:C,FALSE) -> 2
A30: EST-000029628 | B30: 24 | C30: 45667 | D30: Middle East | E30: =IF(B30=0,"Blank","Not Blank") -> Not Blank | F30: =_xlfn.XLOOKUP(C30,'Wk no''s'!B:B,'Wk no''s'!C:C,FALSE) -> 2
A31: EST-000029667 | B31: 8 | C31: 45667 | D31: Middle East | E31: =IF(B31=0,"Blank","Not Blank") -> Not Blank | F31: =_xlfn.XLOOKUP(C31,'Wk no''s'!B:B,'Wk no''s'!C:C,FALSE) -> 2
A32: EST-000029687 | B32: 8 | C32: 45667 | D32: Middle East | E32: =IF(B32=0,"Blank","Not Blank") -> Not Blank | F32: =_xlfn.XLOOKUP(C32,'Wk no''s'!B:B,'Wk no''s'!C:C,FALSE) -> 2
A33: EST-000029717 | B33: 8 | C33: 45667 | D33: Middle East | E33: =IF(B33=0,"Blank","Not Blank") -> Not Blank | F33: =_xlfn.XLOOKUP(C33,'Wk no''s'!B:B,'Wk no''s'!C:C,FALSE) -> 2
A34: EST-000028580 | B34: 256 | C34: 45663 | D34: Rest of the World | E34: =IF(B34=0,"Blank","Not Blank") -> Not Blank | F34: =_xlfn.XLOOKUP(C34,'Wk no''s'!B:B,'Wk no''s'!C:C,FALSE) -> 2
A35: EST-000029353 | B35: 105 | C35: 45663 | D35: Rest of the World | E35: =IF(B35=0,"Blank","Not Blank") -> Not Blank | F35: =_xlfn.XLOOKUP(C35,'Wk no''s'!B:B,'Wk no''s'!C:C,FALSE) -> 2
... A41: EST-000029587 | B41: -7 | C41: 45664 | D41: Rest of the World | E41: =IF(B41=0,"Blank","Not Blank") -> Not Blank | F41: =_xlfn.XLOOKUP(C41,'Wk no''s'!B:B,'Wk no''s'!C:C,FALSE) -> 2
A42: EST-000029643 | C42: 45667 | D42: Rest of the World | E42: =IF(B42=0,"Blank","Not Blank") -> Blank | F42: =_xlfn.XLOOKUP(C42,'Wk no''s'!B:B,'Wk no''s'!C:C,FALSE) -> 2
A43: EST-000029647 | B43: 0 | C43: 45665 | D43: Rest of the World | E43: =IF(B43=0,"Blank","Not Blank") -> Blank | F43: =_xlfn.XLOOKUP(C43,'Wk no''s'!B:B,'Wk no''s'!C:C,FALSE) -> 2
A44: EST-000029685 | C44: 45665 | D44: Rest of the World | E44: =IF(B44=0,"Blank","Not Blank") -> Blank | F44: =_xlfn.XLOOKUP(C44,'Wk no''s'!B:B,'Wk no''s'!C:C,FALSE) -> 2
A45: EST-000029699 | C45: 45667 | D45: Rest of the World | E45: =IF(B45=0,"Blank","Not Blank") -> Blank | F45: =_xlfn.XLOOKUP(C45,'Wk no''s'!B:B,'Wk no''s'!C:C,FALSE) -> 2
A46: EST-000028931 | B46: 128 | C46: 45664 | D46: UK | E46: =IF(B46=0,"Blank","Not Blank") -> Not Blank | F46: =_xlfn.XLOOKUP(C46,'Wk no''s'!B:B,'Wk no''s'!C:C,FALSE) -> 2
A47: EST-000028937 | B47: 192 | C47: 45667 | D47: UK | E47: =IF(B47=0,"Blank","Not Blank") -> Not Blank | F47: =_xlfn.XLOOKUP(C47,'Wk no''s'!B:B,'Wk no''s'!C:C,FALSE) -> 2
A48: EST-000029411 | B48: 0 | C48: 45664 | D48: UK | E48: =IF(B48=0,"Blank","Not Blank") -> Blank | F48: =_xlfn.XLOOKUP(C48,'Wk no''s'!B:B,'Wk no''s'!C:C,FALSE) -> 2
A49: EST-000029477 | B49: 112 | C49: 45665 | D49: UK | E49: =IF(B49=0,"Blank","Not Blank") -> Not Blank | F49: =_xlfn.XLOOKUP(C49,'Wk no''s'!B:B,'Wk no''s'!C:C,FALSE) -> 2
A50: EST-000029487 | B50: 128 | C50: 45667 | D50: UK | E50: =IF(B50=0,"Blank","Not Blank") -> Not Blank | F50: =_xlfn.XLOOKUP(C50,'Wk no''s'!B:B,'Wk no''s'!C:C,FALSE) -> 2
A51: EST-000029510 | C51: 45663 | D51: UK | E51: =IF(B51=0,"Blank","Not Blank") -> Blank | F51: =_xlfn.XLOOKUP(C51,'Wk no''s'!B:B,'Wk no''s'!C:C,FALSE) -> 2
A52: EST-000029506 | B52: 97 | C52: 45665 | D52: UK | E52: =IF(B52=0,"Blank","Not Blank") -> Not Blank | F52: =_xlfn.XLOOKUP(C52,'Wk no''s'!B:B,'Wk no''s'!C:C,FALSE) -> 2
A53: EST-000029507 | C53: 45663 | D53: UK | E53: =IF(B53=0,"Blank","Not Blank") -> Blank | F53: =_xlfn.XLOOKUP(C53,'Wk no''s'!B:B,'Wk no''s'!C:C,FALSE) -> 2
A54: EST-000029508 | B54: 81 | C54: 45663 | D54: UK | E54: =IF(B54=0,"Blank","Not Blank") -> Not Blank | F54: =_xlfn.XLOOKUP(C54,'Wk no''s'!B:B,'Wk no''s'!C:C,FALSE) -> 2
A55: EST-000029511 | C55: 45663 | D55: UK | E55: =IF(B55=0,"Blank","Not Blank") -> Blank | F55: =_xlfn.XLOOKUP(C55,'Wk no''s'!B:B,'Wk no''s'!C:C,FALSE) -> 2
A56: EST-000029513 | B56: 88 | C56: 45663 | D56: UK | E56: =IF(B56=0,"Blank","Not Blank") -> Not Blank | F56: =_xlfn.XLOOKUP(C56,'Wk no''s'!B:B,'Wk no''s'!C:C,FALSE) -> 2
A57: EST-000029515 | B57: 88 | C57: 45663 | D57: UK | E57: =IF(B57=0,"Blank","Not Blank") -> Not Blank | F57: =_xlfn.XLOOKUP(C57,'Wk no''s'!B:B,'Wk no''s'!C:C,FALSE) -> 2
A58: EST-000029516 | C58: 45663 | D58: UK | E58: =IF(B58=0,"Blank","Not Blank") -> Blank | F58: =_xlfn.XLOOKUP(C58,'Wk no''s'!B:B,'Wk no''s'!C:C,FALSE) -> 2
A59: EST-000029518 | C59: 45663 | D59: UK | E59: =IF(B59=0,"Blank","Not Blank") -> Blank | F59: =_xlfn.XLOOKUP(C59,'Wk no''s'!B:B,'Wk no''s'!C:C,FALSE) -> 2
A60: EST-000029523 | B60: 8 | C60: 45664 | D60: UK | E60: =IF(B60=0,"Blank","Not Blank") -> Not Blank | F60: =_xlfn.XLOOKUP(C60,'Wk no''s'!B:B,'Wk no''s'!C:C,FALSE) -> 2
A61: EST-000029537 | B61: 0 | C61: 45663 | D61: UK | E61: =IF(B61=0,"Blank","Not Blank") -> Blank | F61: =_xlfn.XLOOKUP(C61,'Wk no''s'!B:B,'Wk no''s'!C:C,FALSE) -> 2
A62: EST-000029535 | C62: 45663 | D62: UK | E62: =IF(B62=0,"Blank","Not Blank") -> Blank | F62: =_xlfn.XLOOKUP(C62,'Wk no''s'!B:B,'Wk no''s'!C:C,FALSE) -> 2
A63: EST-000029539 | C63: 45663 | D63: UK | E63: =IF(B63=0,"Blank","Not Blank") -> Blank | F63: =_xlfn.XLOOKUP(C63,'Wk no''s'!B:B,'Wk no''s'!C:C,FALSE) -> 2
A64: EST-000029540 | C64: 45663 | D64: UK | E64: =IF(B64=0,"Blank","Not Blank") -> Blank | F64: =_xlfn.XLOOKUP(C64,'Wk no''s'!B:B,'Wk no''s'!C:C,FALSE) -> 2
A65: EST-000029541 | C65: 45663 | D65: UK | E65: =IF(B65=0,"Blank","Not Blank") -> Blank | F65: =_xlfn.XLOOKUP(C65,'Wk no''s'!B:B,'Wk no''s'!C:C,FALSE) -> 2
A66: EST-000029542 | B66: 16 | C66: 45665 | D66: UK | E66: =IF(B66=0,"Blank","Not Blank") -> Not Blank | F66: =_xlfn.XLOOKUP(C66,'Wk no''s'!B:B,'Wk no''s'!C:C,FALSE) -> 2
A67: EST-000029543 | C67: 45663 | D67: UK | E67: =IF(B67=0,"Blank","Not Blank") -> Blank | F67: =_xlfn.XLOOKUP(C67,'Wk no''s'!B:B,'Wk no''s'!C:C,FALSE) -> 2
A68: EST-000029545 | C68: 45663 | D68: UK | E68: =IF(B68=0,"Blank","Not Blank") -> Blank | F68: =_xlfn.XLOOKUP(C68,'Wk no''s'!B:B,'Wk no''s'!C:C,FALSE) -> 2
A69: EST-000029546 | B69: 0 | C69: 45663 | D69: UK | E69: =IF(B69=0,"Blank","Not Blank") -> Blank | F69: =_xlfn.XLOOKUP(C69,'Wk no''s'!B:B,'Wk no''s'!C:C,FALSE) -> 2
A70: EST-000029547 | C70: 45663 | D70: UK | E70: =IF(B70=0,"Blank","Not Blank") -> Blank | F70: =_xlfn.XLOOKUP(C70,'Wk no''s'!B:B,'Wk no''s'!C:C,FALSE) -> 2
A71: EST-000029557 | C71: 45663 | D71: UK | E71: =IF(B71=0,"Blank","Not Blank") -> Blank | F71: =_xlfn.XLOOKUP(C71,'Wk no''s'!B:B,'Wk no''s'!C:C,FALSE) -> 2
A72: EST-000029549 | B72: 8 | C72: 45664 | D72: UK | E72: =IF(B72=0,"Blank","Not Blank") -> Not Blank | F72: =_xlfn.XLOOKUP(C72,'Wk no''s'!B:B,'Wk no''s'!C:C,FALSE) -> 2
A73: EST-000029554 | B73: 0 | C73: 45663 | D73: UK | E73: =IF(B73=0,"Blank","Not Blank") -> Blank | F73: =_xlfn.XLOOKUP(C73,'Wk no''s'!B:B,'Wk no''s'!C:C,FALSE) -> 2
A74: EST-000029550 | C74: 45663 | D74: UK | E74: =IF(B74=0,"Blank","Not Blank") -> Blank | F74: =_xlfn.XLOOKUP(C74,'Wk no''s'!B:B,'Wk no''s'!C:C,FALSE) -> 2
A75: EST-000029551 | B75: 16 | C75: 45666 | D75: UK | E75: =IF(B75=0,"Blank","Not Blank") -> Not Blank | F75: =_xlfn.XLOOKUP(C75,'Wk no''s'!B:B,'Wk no''s'!C:C,FALSE) -> 2
A76: EST-000029552 | B76: 0 | C76: 45663 | D76: UK | E76: =IF(B76=0,"Blank","Not Blank") -> Blank | F76: =_xlfn.XLOOKUP(C76,'Wk no''s'!B:B,'Wk no''s'!C:C,FALSE) -> 2
A77: EST-000029553 | B77: 0 | C77: 45663 | D77: UK | E77: =IF(B77=0,"Blank","Not Blank") -> Blank | F77: =_xlfn.XLOOKUP(C77,'Wk no''s'!B:B,'Wk no''s'!C:C,FALSE) -> 2
A78: EST-000029555 | C78: 45663 | D78: UK | E78: =IF(B78=0,"Blank","Not Blank") -> Blank | F78: =_xlfn.XLOOKUP(C78,'Wk no''s'!B:B,'Wk no''s'!C:C,FALSE) -> 2
A79: EST-000029556 | C79: 45663 | D79: UK | E79: =IF(B79=0,"Blank","Not Blank") -> Blank | F79: =_xlfn.XLOOKUP(C79,'Wk no''s'!B:B,'Wk no''s'!C:C,FALSE) -> 2
A80: EST-000029559 | C80: 45663 | D80: UK | E80: =IF(B80=0,"Blank","Not Blank") -> Blank | F80: =_xlfn.XLOOKUP(C80,'Wk no''s'!B:B,'Wk no''s'!C:C,FALSE) -> 2
A81: EST-000029560 | C81: 45663 | D81: UK | E81: =IF(B81=0,"Blank","Not Blank") -> Blank | F81: =_xlfn.XLOOKUP(C81,'Wk no''s'!B:B,'Wk no''s'!C:C,FALSE) -> 2
A82: EST-000029561 | C82: 45663 | D82: UK | E82: =IF(B82=0,"Blank","Not Blank") -> Blank | F82: =_xlfn.XLOOKUP(C82,'Wk no''s'!B:B,'Wk no''s'!C:C,FALSE) -> 2
A83: EST-000029562 | C83: 45663 | D83: UK | E83: =IF(B83=0,"Blank","Not Blank") -> Blank | F83: =_xlfn.XLOOKUP(C83,'Wk no''s'!B:B,'Wk no''s'!C:C,FALSE) -> 2
A84: EST-000029564 | B84: 0 | C84: 45663 | D84: UK | E84: =IF(B84=0,"Blank","Not Blank") -> Blank | F84: =_xlfn.XLOOKUP(C84,'Wk no''s'!B:B,'Wk no''s'!C:C,FALSE) -> 2
A85: EST-000029565 | B85: 0 | C85: 45663 | D85: UK | E85: =IF(B85=0,"Blank","Not Blank") -> Blank | F85: =_xlfn.XLOOKUP(C85,'Wk no''s'!B:B,'Wk no''s'!C:C,FALSE) -> 2
A86: EST-000029566 | B86: 32 | C86: 45667 | D86: UK | E86: =IF(B86=0,"Blank","Not Blank") -> Not Blank | F86: =_xlfn.XLOOKUP(C86,'Wk no''s'!B:B,'Wk no''s'!C:C,FALSE) -> 2
A87: EST-000029568 | B87: 0 | C87: 45663 | D87: UK | E87: =IF(B87=0,"Blank","Not Blank") -> Blank | F87: =_xlfn.XLOOKUP(C87,'Wk no''s'!B:B,'Wk no''s'!C:C,FALSE) -> 2
A88: EST-000029570 | B88: 0 | C88: 45663 | D88: UK | E88: =IF(B88=0,"Blank","Not Blank") -> Blank | F88: =_xlfn.XLOOKUP(C88,'Wk no''s'!B:B,'Wk no''s'!C:C,FALSE) -> 2
A89: EST-000029572 | B89: 24 | C89: 45666 | D89: UK | E89: =IF(B89=0,"Blank","Not Blank") -> Not Blank | F89: =_xlfn.XLOOKUP(C89,'Wk no''s'!B:B,'Wk no''s'!C:C,FALSE) -> 2
A90: EST-000029573 | C90: 45663 | D90: UK | E90: =IF(B90=0,"Blank","Not Blank") -> Blank | F90: =_xlfn.XLOOKUP(C90,'Wk no''s'!B:B,'Wk no''s'!C:C,FALSE) -> 2
A91: EST-000029582 | B91: 0 | C91: 45665 | D91: UK | E91: =IF(B91=0,"Blank","Not Blank") -> Blank | F91: =_xlfn.XLOOKUP(C91,'Wk no''s'!B:B,'Wk no''s'!C:C,FALSE) -> 2
A92: EST-000029576 | C92: 45663 | D92: UK | E92: =IF(B92=0,"Blank","Not Blank") -> Blank | F92: =_xlfn.XLOOKUP(C92,'Wk no''s'!B:B,'Wk no''s'!C:C,FALSE) -> 2
A93: EST-000029577 | C93: 45663 | D93: UK | E93: =IF(B93=0,"Blank","Not Blank") -> Blank | F93: =_xlfn.XLOOKUP(C93,'Wk no''s'!B:B,'Wk no''s'!C:C,FALSE) -> 2
A94: EST-000029578 | C94: 45663 | D94: UK | E94: =IF(B94=0,"Blank","Not Blank") -> Blank | F94: =_xlfn.XLOOKUP(C94,'Wk no''s'!B:B,'Wk no''s'!C:C,FALSE) -> 2
A95: EST-000029580 | B95: 0 | C95: 45664 | D95: UK | E95: =IF(B95=0,"Blank","Not Blank") -> Blank | F95: =_xlfn.XLOOKUP(C95,'Wk no''s'!B:B,'Wk no''s'!C:C,FALSE) -> 2
A96: EST-000029583 | C96: 45664 | D96: UK | E96: =IF(B96=0,"Blank","Not Blank") -> Blank | F96: =_xlfn.XLOOKUP(C96,'Wk no''s'!B:B,'Wk no''s'!C:C,FALSE) -> 2
A97: EST-000029584 | C97: 45663 | D97: UK | E97: =IF(B97=0,"Blank","Not Blank") -> Blank | F97: =_xlfn.XLOOKUP(C97,'Wk no''s'!B:B,'Wk no''s'!C:C,FALSE) -> 2
A98: EST-000029590 | B98: 0 | C98: 45663 | D98: UK | E98: =IF(B98=0,"Blank","Not Blank") -> Blank | F98: =_xlfn.XLOOKUP(C98,'Wk no''s'!B:B,'Wk no''s'!C:C,FALSE) -> 2
A99: EST-000029591 | B99: 15 | C99: 45664 | D99: UK | E99: =IF(B99=0,"Blank","Not Blank") -> Not Blank | F99: =_xlfn.XLOOKUP(C99,'Wk no''s'!B:B,'Wk no''s'!C:C,FALSE) -> 2
A100: EST-000029592 | B100: 23 | C100: 45665 | D100: UK | E100: =IF(B100=0,"Blank","Not Blank") -> Not Blank | F100: =_xlfn.XLOOKUP(C100,'Wk no''s'!B:B,'Wk no''s'!C:C,FALSE) -> 2
A101: EST-000029593 | B101: 15 | C101: 45664 | D101: UK | E101: =IF(B101=0,"Blank","Not Blank") -> Not Blank | F101: =_xlfn.XLOOKUP(C101,'Wk no''s'!B:B,'Wk no''s'!C:C,FALSE) -> 2
A102: EST-000029595 | B102: 0 | C102: 45664 | D102: UK | E102: =IF(B102=0,"Blank","Not Blank") -> Blank | F102: =_xlfn.XLOOKUP(C102,'Wk no''s'!B:B,'Wk no''s'!C:C,FALSE) -> 2
A103: EST-000029596 | B103: 0 | C103: 45663 | D103: UK | E103: =IF(B103=0,"Blank","Not Blank") -> Blank | F103: =_xlfn.XLOOKUP(C103,'Wk no''s'!B:B,'Wk no''s'!C:C,FALSE) -> 2
A104: EST-000029597 | B104: 0 | C104: 45663 | D104: UK | E104: =IF(B104=0,"Blank","Not Blank") -> Blank | F104: =_xlfn.XLOOKUP(C104,'Wk no''s'!B:B,'Wk no''s'!C:C,FALSE) -> 2
A105: EST-000029598 | C105: 45663 | D105: UK | E105: =IF(B105=0,"Blank","Not Blank") -> Blank | F105: =_xlfn.XLOOKUP(C105,'Wk no''s'!B:B,'Wk no''s'!C:C,FALSE) -> 2
A106: EST-000029600 | B106: 0 | C106: 45664 | D106: UK | E106: =IF(B106=0,"Blank","Not Blank") -> Blank | F106: =_xlfn.XLOOKUP(C106,'Wk no''s'!B:B,'Wk no''s'!C:C,FALSE) -> 2
A107: EST-000029605 | C107: 45664 | D107: UK | E107: =IF(B107=0,"Blank","Not Blank") -> Blank | F107: =_xlfn.XLOOKUP(C107,'Wk no''s'!B:B,'Wk no''s'!C:C,FALSE) -> 2
A108: EST-000029604 | C108: 45664 | D108: UK | E108: =IF(B108=0,"Blank","Not Blank") -> Blank | F108: =_xlfn.XLOOKUP(C108,'Wk no''s'!B:B,'Wk no''s'!C:C,FALSE) -> 2
A109: EST-000029606 | C109: 45664 | D109: UK | E109: =IF(B109=0,"Blank","Not Blank") -> Blank | F109: =_xlfn.XLOOKUP(C109,'Wk no''s'!B:B,'Wk no''s'!C:C,FALSE) -> 2
A110: EST-000029607 | B110: 0 | C110: 45664 | D110: UK | E110: =IF(B110=0,"Blank","Not Blank") -> Blank | F110: =_xlfn.XLOOKUP(C110,'Wk no''s'!B:B,'Wk no''s'!C:C,FALSE) -> 2
A111: EST-000029608 | B111: 0 | C111: 45664 | D111: UK | E111: =IF(B111=0,"Blank","Not Blank") -> Blank | F111: =_xlfn.XLOOKUP(C111,'Wk no''s'!B:B,'Wk no''s'!C:C,FALSE) -> 2
A112: EST-000029610 | B112: 0 | C112: 45664 | D112: UK | E112: =IF(B112=0,"Blank","Not Blank") -> Blank | F112: =_xlfn.XLOOKUP(C112,'Wk no''s'!B:B,'Wk no''s'!C:C,FALSE) -> 2
...

Sheet Estimating on time
A1: Estimating Request: Estimate Request No. | B1: Project Name | C1: Estimating Request: Owner Name | D1: Complete By Date | E1: Date/Time Closed | F1: On Time / Late | G1: Date Closed | H1: Sales Division | I1: Extract Date | J1: week No
A2: EST-000034253 | B2: BRINDLEY PLACE NO 2 EXTENSION BIRMINGHAM | C2: Estimating | D2: 45814 | F2: 0 | H2: UK | I2: =LEFT(G2,10) | J2: =_xlfn.XLOOKUP(I2,'Wk no''s'!D:D,'Wk no''s'!C:C,FALSE) -> FALSE
A3: EST-000029558 | B3: AIRBUS FITOUT 5TH FLOOR GEORGES DOCK 5 & 6 DUBLIN | C3: Venees Ling | D3: 45664 | E3: 45663 | F3: 1 | G3: 06/01/2025, 12:14 | H3: Ireland | I3: =LEFT(G3,10) -> 06/01/2025 | J3: =_xlfn.XLOOKUP(I3,'Wk no''s'!D:D,'Wk no''s'!C:C,FALSE) -> 2
A4: EST-000029544 | B4: ASTELLAS PROJECT ABLE TRALEE KERRY | C4: Venees Ling | D4: 45664 | E4: 45663 | F4: 1 | G4: 06/01/2025, 09:11 | H4: Ireland | I4: =LEFT(G4,10) -> 06/01/2025 | J4: =_xlfn.XLOOKUP(I4,'Wk no''s'!D:D,'Wk no''s'!C:C,FALSE) -> 2
A5: EST-000029778 | B5: DUBLIN AIRPORT T1 MEZZANINE LOUNGE | C5: Venees Ling | D5: 45670 | E5: 45667 | F5: 1 | G5: 10/01/2025, 14:20 | H5: Ireland | I5: =LEFT(G5,10) -> 10/01/2025 | J5: =_xlfn.XLOOKUP(I5,'Wk no''s'!D:D,'Wk no''s'!C:C,FALSE) -> 2
A6: EST-000029536 | B6: DUBLIN AIRPORT T1 MEZZANINE LOUNGE | C6: Venees Ling | D6: 45664 | E6: 45663 | F6: 1 | G6: 06/01/2025, 16:14 | H6: Ireland | I6: =LEFT(G6,10) -> 06/01/2025 | J6: =_xlfn.XLOOKUP(I6,'Wk no''s'!D:D,'Wk no''s'!C:C,FALSE) -> 2
A7: EST-000029538 | B7: IPUT 3 DUBLIN LANDINGS | C7: Venees Ling | D7: 45664 | E7: 45663 | F7: 1 | G7: 06/01/2025, 08:41 | H7: Ireland | I7: =LEFT(G7,10) -> 06/01/2025 | J7: =_xlfn.XLOOKUP(I7,'Wk no''s'!D:D,'Wk no''s'!C:C,FALSE) -> 2
A8: EST-000029714 | B8: PORTLAOISE GARDA DIVISIONAL HQ | C8: Venees Ling | D8: 45667 | E8: 45666 | F8: 1 | G8: 09/01/2025, 11:06 | H8: Ireland | I8: =LEFT(G8,10) -> 09/01/2025 | J8: =_xlfn.XLOOKUP(I8,'Wk no''s'!D:D,'Wk no''s'!C:C,FALSE) -> 2
A9: EST-000029760 | B9: PPG SHANNON CO CLARE | C9: Venees Ling | D9: 45670 | E9: 45667 | F9: 1 | G9: 10/01/2025, 09:53 | H9: Ireland | I9: =LEFT(G9,10) -> 10/01/2025 | J9: =_xlfn.XLOOKUP(I9,'Wk no''s'!D:D,'Wk no''s'!C:C,FALSE) -> 2
A10: EST-000029678 | B10: RDS ANGLESEA STAND BALLSBRIDGE | C10: Venees Ling | D10: 45666 | E10: 45666 | F10: 1 | G10: 09/01/2025, 10:51 | H10: Ireland | I10: =LEFT(G10,10) -> 09/01/2025 | J10: =_xlfn.XLOOKUP(I10,'Wk no''s'!D:D,'Wk no''s'!C:C,FALSE) -> 2
A11: EST-000029628 | B11: ELSEWEDY CABLE TELECOM ADMIN BLDG RAMADAN EGYPT | C11: Christine Moring | D11: 45666 | E11: 45667 | F11: 0 | G11: 10/01/2025, 15:09 | H11: Middle East | I11: =LEFT(G11,10) -> 10/01/2025 | J11: =_xlfn.XLOOKUP(I11,'Wk no''s'!D:D,'Wk no''s'!C:C,FALSE) -> 2
A12: EST-000029717 | B12: EXPO CITY MICRO OFFICES DUBAI | C12: Christine Moring | D12: 45671 | E12: 45667 | F12: 1 | G12: 10/01/2025, 10:32 | H12: Middle East | I12: =LEFT(G12,10) -> 10/01/2025 | J12: =_xlfn.XLOOKUP(I12,'Wk no''s'!D:D,'Wk no''s'!C:C,FALSE) -> 2
A13: EST-000029532 | B13: EXPO CITY MICRO OFFICES DUBAI | C13: Christine Moring | D13: 45666 | E13: 45664 | F13: 1 | G13: 07/01/2025, 11:39 | H13: Middle East | I13: =LEFT(G13,10) -> 07/01/2025 | J13: =_xlfn.XLOOKUP(I13,'Wk no''s'!D:D,'Wk no''s'!C:C,FALSE) -> 2
A14: EST-000029533 | B14: NDA - DEWA HQ TROX TILES DUBAI | C14: Julian Sparrow | D14: 45666 | E14: 45663 | F14: 1 | G14: 06/01/2025, 15:30 | H14: Middle East | I14: =LEFT(G14,10) -> 06/01/2025 | J14: =_xlfn.XLOOKUP(I14,'Wk no''s'!D:D,'Wk no''s'!C:C,FALSE) -> 2
... A4930: EST-000037614 | B4930: WHITE STREET 124-125 | C4930: Ian Liegeois | D4930: 45936 | E4930: 45944 | F4930: 0 | G4930: 14/10/2025, 21:45 | H4930: USA | I4930: =LEFT(G4930,10) -> 14/10/2025 | J4930: =_xlfn.XLOOKUP(I4930,'Wk no''s'!D:D,'Wk no''s'!C:C,FALSE) -> 42

Sheet SQM WK42
A1: Line Name | B1: Quantity | C1: Net Unit Price Currency | D1: Net Unit Price | E1: Net Total Currency | F1: Net Total | G1: Item SQM | H1: Line SQM | I1: Â£/SQM Currency | J1: Â£/SQM | K1: Description | L1: Project Owner: Full Name | M1: Sales Region | N1: Project Name | O1: =AVERAGE(O2:O87) -> 80.659884 | P1: =AVERAGE(P2:P87) -> 80.602823
A2: QL-0326303 | B2: 95 | C2: GBP | D2: 28.8 | E2: GBP | F2: 2736 | G2: 0.36 | H2: 34.2 | I2: GBP | J2: 80 | K2: SYS 330 TILE STEEL 1200mm X 300mm S1820 10 RAL 9010 20% WRAPPED 16 80 KG SQUARE | L2: Becky Titley | M2: Scotland | N2: ROCKSTAR BARCLAY HOUSE PHASE 4 GF FACILITIES EDINBURGH | O2: =IF(G2<0.03,"",J2) -> 80 | P2: =+F2/H2 -> 80
A3: QL-0324166 | B3: 867 | C3: GBP | D3: 25.12 | E3: GBP | F3: 21779.04 | G3: 0.36 | H3: 312.12 | I3: GBP | J3: 69.78 | K3: SYS 330 TILE STEEL 1200mm X 300mm 1522 10 RAL 9010 20% WRAPPED 16 80 KG SQUARE | L3: Ben Bishop | M3: Northern Home Counties | N3: GROVE BUSINESS PARK BLOCKS E F AND G OXFORD | O3: =IF(G3<0.03,"",J3) -> 69.78 | P3: =+F3/H3 -> 69.777778
A4: QL-0256352 | B4: 1246 | C4: GBP | D4: 17.99 | E4: GBP | F4: 22415.54 | G4: 0.33 | H4: 411.18 | I4: GBP | J4: 54.52 | K4: SYS 330 TILE STEEL 1100mm X 300mm 1522 10 RAL 9010 20% BLACK ADHESIVE TISSUE SQUARE (RAL TBC) | L4: David Baylis | M4: North | N4: BANK HOUSE REDEVELOPMENT LEEDS | O4: =IF(G4<0.03,"",J4) -> 54.52 | P4: =+F4/H4 -> 54.515152
A5: QL-0256366 | B5: 363 | C5: GBP | D5: 17.99 | E5: GBP | F5: 6530.37 | G5: 0.33 | H5: 119.79 | I5: GBP | J5: 54.52 | K5: SYS 330 TILE STEEL 1100mm X 300mm 1522 10 RAL 9010 20% BLACK ADHESIVE TISSUE SQUARE (RAL TBC) | L5: David Baylis | M5: North | N5: BANK HOUSE REDEVELOPMENT LEEDS | O5: =IF(G5<0.03,"",J5) -> 54.52 | P5: =+F5/H5 -> 54.515152
A6: QL-0321142 | B6: 90 | C6: GBP | D6: 65.7 | E6: GBP | F6: 5913 | G6: 0.9 | H6: 81 | I6: GBP | J6: 73 | K6: SYS 330 TILE STEEL 1500mm X 600mm 1522 10 RAL 9010 20% WRAPPED 16 80 KG SQUARE | L6: David Baylis | M6: Wales | N6: WREXHAM AFC KOP STAND GROUND FLOOR | O6: =IF(G6<0.03,"",J6) -> 73 | P6: =+F6/H6 -> 73
A7: QL-0328271 | B7: 30 | C7: GBP | D7: 36.41 | E7: GBP | F7: 1092.3 | G7: 0.27 | H7: 8.09 | I7: GBP | J7: 135 | K7: SYS 330 TILE STEEL 899mm X 300mm D1821 10 RAL 9016 20% WRAPPED 16 80 KG SQUARE | L7: Eurshell Fearon | M7: London | N7: MOORFIELDS NO 21 DEUTSCHE BANK REFURB LONDON | O7: =IF(G7<0.03,"",J7) -> 135 | P7: =+F7/H7 -> 135.01854
A8: QL-0328272 | B8: 14 | C8: GBP | D8: 54.43 | E8: GBP | F8: 762.02 | G8: 0.4 | H8: 5.64 | I8: GBP | J8: 135 | K8: SYS 330 TILE STEEL 1344mm X 300mm D1821 10 RAL 9016 20% WRAPPED 16 80 KG SQUARE | L8: Eurshell Fearon | M8: London | N8: MOORFIELDS NO 21 DEUTSCHE BANK REFURB LONDON | O8: =IF(G8<0.03,"",J8) -> 135 | P8: =+F8/H8 -> 135.10993
A9: QL-0328273 | B9: 5 | C9: GBP | D9: 26.28 | E9: GBP | F9: 131.4 | G9: 0.19 | H9: 0.97 | I9: GBP | J9: 134.98 | K9: SYS 330 TILE STEEL 649mm X 300mm D1821 10 RAL 9016 20% WRAPPED 16 80 KG SQUARE | L9: Eurshell Fearon | M9: London | N9: MOORFIELDS NO 21 DEUTSCHE BANK REFURB LONDON | O9: =IF(G9<0.03,"",J9) -> 134.98 | P9: =+F9/H9 -> 135.46392
A10: QL-0328278 | B10: 10 | C10: GBP | D10: 72.86 | E10: GBP | F10: 728.6 | G10: 0.54 | H10: 5.4 | I10: GBP | J10: 135 | K10: SYS 330 TILE STEEL 1799mm X 300mm D1821 10 RAL 9016 20% WRAPPED 16 80 KG SQUARE | L10: Eurshell Fearon | M10: London | N10: MOORFIELDS NO 21 DEUTSCHE BANK REFURB LONDON | O10: =IF(G10<0.03,"",J10) -> 135 | P10: =+F10/H10 -> 134.92593
A11: QL-0328279 | B11: 2 | C11: GBP | D11: 44.51 | E11: GBP | F11: 89.02 | G11: 0.33 | H11: 0.66 | I11: GBP | J11: 135 | K11: SYS 330 TILE STEEL 1099mm X 300mm D1821 10 RAL 9016 20% WRAPPED 16 80 KG SQUARE | L11: Eurshell Fearon | M11: London | N11: MOORFIELDS NO 21 DEUTSCHE BANK REFURB LONDON | O11: =IF(G11<0.03,"",J11) -> 135 | P11: =+F11/H11 -> 134.87879
A12: QL-0328277 | B12: 6 | C12: GBP | D12: 36.41 | E12: GBP | F12: 218.46 | G12: 0.27 | H12: 1.62 | I12: GBP | J12: 135 | K12: SYS 330 TILE STEEL 899mm X 300mm D1821 10 RAL 9016 20% WRAPPED 16 80 KG SQUARE | L12: Eurshell Fearon | M12: London | N12: MOORFIELDS NO 21 DEUTSCHE BANK REFURB LONDON | O12: =IF(G12<0.03,"",J12) -> 135 | P12: =+F12/H12 -> 134.85185
A13: QL-0328282 | B13: 9 | C13: GBP | D13: 36.41 | E13: GBP | F13: 327.69 | G13: 0.27 | H13: 2.43 | I13: GBP | J13: 135 | K13: SYS 330 TILE STEEL 899mm X 300mm D1821 10 RAL 9016 20% WRAPPED 16 80 KG SQUARE | L13: Eurshell Fearon | M13: London | N13: MOORFIELDS NO 21 DEUTSCHE BANK REFURB LONDON | O13: =IF(G13<0.03,"",J13) -> 135 | P13: =+F13/H13 -> 134.85185
... A121: QL-0328671 | B121: 162 | C121: GBP | D121: 95.72 | E121: GBP | F121: 15506.64 | G121: 1.4 | H121: 226.8 | I121: GBP | J121: 68.37 | K121: SYS 330 TILE STEEL 2800mm X 500mm 2227 10 RAL 9010 20% WRAPPED 16 80 KG SQUARE | L121: Sam James | M121: London | N121: RADSTOCK HOUSE ECCLESTON STREET NO 3-5 LONDON | O121: =IF(G121<0.03,"",J121) -> 68.37 | P121: =+F121/H121 -> 68.371429

Sheet SQM WK41
A1: Line Name | B1: Quantity | C1: Net Unit Price Currency | D1: Net Unit Price | E1: Net Total Currency | F1: Net Total | G1: Item SQM | H1: Line SQM | I1: Â£/SQM Currency | J1: Â£/SQM | K1: Description | L1: Project Owner: Full Name | M1: Sales Region | N1: Project Name | O1: =AVERAGE(O2:O87) -> 79.488621 | P1: =AVERAGE(P2:P87) -> 79.420119
A2: QL-0320155 | B2: 3778 | C2: GBP | D2: 25.25 | E2: GBP | F2: 95394.5 | G2: 0.36 | H2: 1360.08 | I2: GBP | J2: 70.14 | K2: SYS 330 TILE STEEL 1200mm X 300mm 1522 10 RAL 9010 20% AB WRAPPED 16 80 KG SQUARE | L2: Ben Bishop | M2: Northern Home Counties | N2: PROJECT VITRUM FLRS 1 & 2 CAMBRIDGE | O2: =IF(G2<0.03,"",J2) -> 70.14 | P2: =+F2/H2 -> 70.138889
A3: QL-0320174 | B3: 5 | C3: GBP | D3: 46.33 | E3: GBP | F3: 231.65 | G3: 0.35 | H3: 1.73 | I3: GBP | J3: 134.25 | K3: SYS 330 TILE STEEL 1190mm X 290mm PLAIN RAL 9010 20% AB NO INFILL SERVICE TILE CS-07 FUME HOOD | L3: Ben Bishop | M3: Northern Home Counties | N3: PROJECT VITRUM FLRS 1 & 2 CAMBRIDGE | O3: =IF(G3<0.03,"",J3) -> 134.25 | P3: =+F3/H3 -> 133.90173
A4: QL-0320177 | B4: 5 | C4: GBP | D4: 42.79 | E4: GBP | F4: 213.95 | G4: 0.35 | H4: 1.73 | I4: GBP | J4: 123.99 | K4: SYS 330 TILE STEEL 1190mm X 290mm PLAIN RAL 9010 20% AB NO INFILL SERVICE TILE CS-04 SERVES 4 BENCHES | L4: Ben Bishop | M4: Northern Home Counties | N4: PROJECT VITRUM FLRS 1 & 2 CAMBRIDGE | O4: =IF(G4<0.03,"",J4) -> 123.99 | P4: =+F4/H4 -> 123.67052
A5: QL-0320178 | B5: 12 | C5: GBP | D5: 39.34 | E5: GBP | F5: 472.08 | G5: 0.35 | H5: 4.14 | I5: GBP | J5: 114 | K5: SYS 330 TILE STEEL 1190mm X 290mm PLAIN RAL 9010 20% AB NO INFILL SERVICE TILE CS-03 SERVES 4 BENCHES | L5: Ben Bishop | M5: Northern Home Counties | N5: PROJECT VITRUM FLRS 1 & 2 CAMBRIDGE | O5: =IF(G5<0.03,"",J5) -> 114 | P5: =+F5/H5 -> 114.02899
A6: QL-0320175 | B6: 26 | C6: GBP | D6: 32.18 | E6: GBP | F6: 836.68 | G6: 0.35 | H6: 8.97 | I6: GBP | J6: 93.25 | K6: SYS 330 TILE STEEL 1190mm X 290mm PLAIN RAL 9010 20% AB NO INFILL SERVICE TILE CS-06 SERVES TO BENCHES | L6: Ben Bishop | M6: Northern Home Counties | N6: PROJECT VITRUM FLRS 1 & 2 CAMBRIDGE | O6: =IF(G6<0.03,"",J6) -> 93.25 | P6: =+F6/H6 -> 93.275362
A7: QL-0320176 | B7: 6 | C7: GBP | D7: 42.79 | E7: GBP | F7: 256.74 | G7: 0.35 | H7: 2.07 | I7: GBP | J7: 123.99 | K7: SYS 330 TILE STEEL 1190mm X 290mm PLAIN RAL 9010 20% AB NO INFILL SERVICE TILE CS-05 SERVES 4 BENCHES | L7: Ben Bishop | M7: Northern Home Counties | N7: PROJECT VITRUM FLRS 1 & 2 CAMBRIDGE | O7: =IF(G7<0.03,"",J7) -> 123.99 | P7: =+F7/H7 -> 124.02899
A8: QL-0320179 | B8: 25 | C8: GBP | D8: 55.88 | E8: GBP | F8: 1397 | G8: 0.35 | H8: 8.63 | I8: GBP | J8: 161.92 | K8: SYS 330 TILE STEEL 1190mm X 290mm PLAIN RAL 9010 20% AB NO INFILL SERVICE TILE CS-02 SERVES 4 BENCHES | L8: Ben Bishop | M8: Northern Home Counties | N8: PROJECT VITRUM FLRS 1 & 2 CAMBRIDGE | O8: =IF(G8<0.03,"",J8) -> 161.92 | P8: =+F8/H8 -> 161.87717
A9: QL-0320180 | B9: 26 | C9: GBP | D9: 47.39 | E9: GBP | F9: 1232.14 | G9: 0.35 | H9: 8.97 | I9: GBP | J9: 137.32 | K9: SYS 330 TILE STEEL 1190mm X 290mm PLAIN RAL 9010 20% AB NO INFILL SERVICE TILE FE-01 FUME HOOD EXHAUST CEILING TILE | L9: Ben Bishop | M9: Northern Home Counties | N9: PROJECT VITRUM FLRS 1 & 2 CAMBRIDGE | O9: =IF(G9<0.03,"",J9) -> 137.32 | P9: =+F9/H9 -> 137.36232
A10: QL-0318333 | B10: 3 | C10: GBP | D10: 36 | E10: GBP | F10: 108 | G10: 0.48 | H10: 1.44 | I10: GBP | J10: 75 | K10: SYS 330 TILE STEEL 800mm X 600mm 1522 10 RAL 9010 20% WRAPPED 16 80 KG SQUARE | L10: Eurshell Fearon | M10: London | N10: ALDERMANBURY SQUARE NO 1 FLOOR 2 REFURB LONDON | O10: =IF(G10<0.03,"",J10) -> 75 | P10: =+F10/H10 -> 75
A11: QL-0318334 | B11: 3 | C11: GBP | D11: 40.5 | E11: GBP | F11: 121.5 | G11: 0.54 | H11: 1.62 | I11: GBP | J11: 75 | K11: SYS 330 TILE STEEL 900mm X 600mm 1522 10 RAL 9010 20% WRAPPED 16 80 KG SQUARE | L11: Eurshell Fearon | M11: London | N11: ALDERMANBURY SQUARE NO 1 FLOOR 2 REFURB LONDON | O11: =IF(G11<0.03,"",J11) -> 75 | P11: =+F11/H11 -> 75
A12: QL-0318332 | B12: 1 | C12: GBP | D12: 27 | E12: GBP | F12: 27 | G12: 0.36 | H12: 0.36 | I12: GBP | J12: 75 | K12: SYS 330 TILE STEEL 1200mm X 300mm 1522 10 RAL 9010 20% WRAPPED 16 80 KG SQUARE | L12: Eurshell Fearon | M12: London | N12: ALDERMANBURY SQUARE NO 1 FLOOR 2 REFURB LONDON | O12: =IF(G12<0.03,"",J12) -> 75 | P12: =+F12/H12 -> 75
A13: QL-0318335 | B13: 1 | C13: GBP | D13: 20.25 | E13: GBP | F13: 20.25 | G13: 0.27 | H13: 0.27 | I13: GBP | J13: 75 | K13: SYS 330 TILE STEEL 900mm X 300mm 1522 10 RAL 9010 20% WRAPPED 16 80 KG SQUARE | L13: Eurshell Fearon | M13: London | N13: ALDERMANBURY SQUARE NO 1 FLOOR 2 REFURB LONDON | O13: =IF(G13<0.03,"",J13) -> 75 | P13: =+F13/H13 -> 75
A14: QL-0318331 | B14: 34 | C14: GBP | D14: 54 | E14: GBP | F14: 1836 | G14: 0.72 | H14: 24.48 | I14: GBP | J14: 75 | K14: SYS 330 TILE STEEL 1200mm X 600mm 1522 10 RAL 9010 20% WRAPPED 16 80 KG SQUARE | L14: Eurshell Fearon | M14: London | N14: ALDERMANBURY SQUARE NO 1 FLOOR 2 REFURB LONDON
A15: QL-0317008 | B15: 140 | C15: GBP | D15: 48.45 | E15: GBP | F15: 6783 | G15: 0.71 | H15: 99.75 | I15: GBP | J15: 68 | K15: SYS 330 TILE 1424 x 500mm S1820 20 RAL 9010 FT WRAPPED 18 80 KG SQUARE | L15: Eurshell Fearon | M15: Midlands | N15: SNOW HILL BLDG 1 QUEENSWAY FLR 10 REFURB BIRMINGHAM | O15: =IF(G15<0.03,"",J15) -> 68 | P15: =+F15/H15 -> 68
A16: QL-0316844 | B16: 1 | C16: GBP | D16: 14.31 | E16: GBP | F16: 14.31 | G16: 0.27 | H16: 0.27 | I16: GBP | J16: 53 | K16: SYS 330 TILE STEEL 900mm X 300mm PLAIN RAL 9016 20% WRAPPED 16 80 KG SQUARE OUT TURN TO LONG EDGES | L16: Jack Turnbull | M16: London | N16: MADDOX STREET NO 31 - 33 CAT A LONDON | O16: =IF(G16<0.03,"",J16) -> 53 | P16: =+F16/H16 -> 53
A17: QL-0316845 | B17: 4 | C17: GBP | D17: 9.54 | E17: GBP | F17: 38.16 | G17: 0.18 | H17: 0.72 | I17: GBP | J17: 53 | K17: SYS 330 TILE STEEL 600mm X 300mm PLAIN RAL 9016 20% WRAPPED 16 80 KG SQUARE OUT TURN TO LONG EDGES | L17: Jack Turnbull | M17: London | N17: MADDOX STREET NO 31 - 33 CAT A LONDON | O17: =IF(G17<0.03,"",J17) -> 53 | P17: =+F17/H17 -> 53
A18: QL-0316842 | B18: 20 | C18: GBP | D18: 32.38 | E18: GBP | F18: 647.6 | G18: 0.43 | H18: 8.52 | I18: GBP | J18: 76.01 | K18: SYS 330 TILE STEEL 1420mm X 300mm 1003 OVERALL RAL 9016 20% WRAPPED 16 80 KG SQUARE | L18: Jack Turnbull | M18: London | N18: MADDOX STREET NO 31 - 33 CAT A LONDON | O18: =IF(G18<0.03,"",J18) -> 76.01 | P18: =+F18/H18 -> 76.00939
A19: QL-0316843 | B19: 110 | C19: GBP | D19: 25.54 | E19: GBP | F19: 2809.4 | G19: 0.34 | H19: 36.96 | I19: GBP | J19: 76.01 | K19: SYS 330 TILE STEEL 1120mm X 300mm 1003 OVERALL RAL 9016 20% WRAPPED 16 80 KG SQUARE | L19: Jack Turnbull | M19: London | N19: MADDOX STREET NO 31 - 33 CAT A LONDON | O19: =IF(G19<0.03,"",J19) -> 76.01 | P19: =+F19/H19 -> 76.011905
A20: QL-0316854 | B20: 36 | C20: GBP | D20: 25.54 | E20: GBP | F20: 919.44 | G20: 0.34 | H20: 12.1 | I20: GBP | J20: 76.01 | K20: SYS 330 TILE STEEL 1120mm X 300mm 1003 OVERALL RAL 9016 20% WRAPPED 16 80 KG SQUARE | L20: Jack Turnbull | M20: London | N20: MADDOX STREET NO 31 - 33 CAT A LONDON | O20: =IF(G20<0.03,"",J20) -> 76.01 | P20: =+F20/H20 -> 75.986777
A21: QL-0316891 | B21: 179 | C21: GBP | D21: 25.54 | E21: GBP | F21: 4571.66 | G21: 0.34 | H21: 60.14 | I21: GBP | J21: 76.01 | K21: SYS 330 TILE STEEL 1120mm X 300mm 1003 OVERALL RAL 9016 20% WRAPPED 16 80 KG SQUARE | L21: Jack Turnbull | M21: London | N21: MADDOX STREET NO 31 - 33 CAT A LONDON | O21: =IF(G21<0.03,"",J21) -> 76.01 | P21: =+F21/H21 -> 76.01696
A22: QL-0316855 | B22: 3 | C22: GBP | D22: 9.54 | E22: GBP | F22: 28.62 | G22: 0.18 | H22: 0.54 | I22: GBP | J22: 53 | K22: SYS 330 TILE STEEL 600mm X 300mm PLAIN RAL 9016 20% WRAPPED 16 80 KG SQUARE OUT TURN TO LONG EDGES | L22: Jack Turnbull | M22: London | N22: MADDOX STREET NO 31 - 33 CAT A LONDON | O22: =IF(G22<0.03,"",J22) -> 53 | P22: =+F22/H22 -> 53
A23: QL-0316892 | B23: 30 | C23: GBP | D23: 32.38 | E23: GBP | F23: 971.4 | G23: 0.43 | H23: 12.78 | I23: GBP | J23: 76.01 | K23: SYS 330 TILE STEEL 1420mm X 300mm 1003 OVERALL RAL 9016 20% WRAPPED 16 80 KG SQUARE | L23: Jack Turnbull | M23: London | N23: MADDOX STREET NO 31 - 33 CAT A LONDON | O23: =IF(G23<0.03,"",J23) -> 76.01 | P23: =+F23/H23 -> 76.00939
A24: QL-0316895 | B24: 4 | C24: GBP | D24: 19.08 | E24: GBP | F24: 76.32 | G24: 0.36 | H24: 1.44 | I24: GBP | J24: 53 | K24: SYS 330 TILE STEEL 1200mm X 300mm PLAIN RAL 9016 20% WRAPPED 16 80 KG SQUARE OUT TURN TO LONG EDGES | L24: Jack Turnbull | M24: London | N24: MADDOX STREET NO 31 - 33 CAT A LONDON | O24: =IF(G24<0.03,"",J24) -> 53 | P24: =+F24/H24 -> 53
A25: QL-0316859 | B25: 212 | C25: GBP | D25: 25.54 | E25: GBP | F25: 5414.48 | G25: 0.34 | H25: 71.23 | I25: GBP | J25: 76.01 | K25: SYS 330 TILE STEEL 1120mm X 300mm 1003 OVERALL RAL 9016 20% WRAPPED 16 80 KG SQUARE | L25: Jack Turnbull | M25: London | N25: MADDOX STREET NO 31 - 33 CAT A LONDON | O25: =IF(G25<0.03,"",J25) -> 76.01 | P25: =+F25/H25 -> 76.014039
A26: QL-0316893 | B26: 30 | C26: GBP | D26: 18.7 | E26: GBP | F26: 561 | G26: 0.25 | H26: 7.38 | I26: GBP | J26: 76.02 | K26: SYS 330 TILE STEEL 820mm X 300mm 1003 OVERALL RAL 9016 20% WRAPPED 16 80 KG SQUARE | L26: Jack Turnbull | M26: London | N26: MADDOX STREET NO 31 - 33 CAT A LONDON | O26: =IF(G26<0.03,"",J26) -> 76.02 | P26: =+F26/H26 -> 76.01626
... A60: QL-0312938 | B60: 4 | C60: GBP | D60: 12.76 | E60: GBP | F60: 51.04 | G60: 0.09 | H60: 0.36 | I60: GBP | J60: 141.78 | K60: SYS 330 TILE STEEL 600mm X 150mm 1522 10 RAL 9010 20% WRAPPED 16 80 KG SQUARE | L60: Jack Wingfield | M60: London | N60: QUEENSBERRY HOUSE OLD BURLINGTON STREET NO 3 CAT B LONDON | O60: =IF(G60<0.03,"",J60) -> 141.78 | P60: =+F60/H60 -> 141.77778
A61: QL-0312939 | B61: 28 | C61: GBP | D61: 13.45 | E61: GBP | F61: 376.6 | G61: 0.18 | H61: 5.04 | I61: GBP | J61: 74.72 | K61: SYS 330 TILE STEEL 600mm X 300mm 1522 10 RAL 9010 20% WRAPPED 16 80 KG SQUARE | L61: Jack Wingfield | M61: London | N61: QUEENSBERRY HOUSE OLD BURLINGTON STREET NO 3 CAT B LONDON
A62: QL-0312944 | B62: 34 | C62: GBP | D62: 20.18 | E62: GBP | F62: 686.12 | G62: 0.27 | H62: 9.18 | I62: GBP | J62: 74.74 | K62: SYS 330 TILE STEEL 900mm X 300mm 1522 10 RAL 9010 20% WRAPPED 16 80 KG SQUARE | L62: Jack Wingfield | M62: London | N62: QUEENSBERRY HOUSE OLD BURLINGTON STREET NO 3 CAT B LONDON
A63: QL-0312942 | B63: 6 | C63: GBP | D63: 19.06 | E63: GBP | F63: 114.36 | G63: 0.26 | H63: 1.53 | I63: GBP | J63: 74.75 | K63: SYS 330 TILE STEEL 850mm X 300mm 1522 10 RAL 9010 20% WRAPPED 16 80 KG SQUARE | L63: Jack Wingfield | M63: London | N63: QUEENSBERRY HOUSE OLD BURLINGTON STREET NO 3 CAT B LONDON
A64: QL-0312943 | B64: 15 | C64: GBP | D64: 19.62 | E64: GBP | F64: 294.3 | G64: 0.26 | H64: 3.94 | I64: GBP | J64: 74.74 | K64: SYS 330 TILE STEEL 875mm X 300mm 1522 10 RAL 9010 20% WRAPPED 16 80 KG SQUARE | L64: Jack Wingfield | M64: London | N64: QUEENSBERRY HOUSE OLD BURLINGTON STREET NO 3 CAT B LONDON
A65: QL-0312937 | B65: 56 | C65: GBP | D65: 13 | E65: GBP | F65: 728 | G65: 0.17 | H65: 9.74 | I65: GBP | J65: 74.71 | K65: SYS 330 TILE STEEL 580mm X 300mm 1522 10 RAL 9010 20% WRAPPED 16 80 KG SQUARE | L65: Jack Wingfield | M65: London | N65: QUEENSBERRY HOUSE OLD BURLINGTON STREET NO 3 CAT B LONDON
A66: QL-0312955 | B66: 40 | C66: GBP | D66: 29.71 | E66: GBP | F66: 1188.4 | G66: 0.4 | H66: 15.9 | I66: GBP | J66: 74.74 | K66: SYS 330 TILE STEEL 1325mm X 300mm 1522 10 RAL 9010 20% WRAPPED 16 80 KG SQUARE | L66: Jack Wingfield | M66: London | N66: QUEENSBERRY HOUSE OLD BURLINGTON STREET NO 3 CAT B LONDON
A67: QL-0312956 | B67: 50 | C67: GBP | D67: 15.13 | E67: GBP | F67: 756.5 | G67: 0.2 | H67: 10.13 | I67: GBP | J67: 74.72 | K67: SYS 330 TILE STEEL 1350mm X 150mm 1522 10 RAL 9010 20% WRAPPED 16 80 KG SQUARE | L67: Jack Wingfield | M67: London | N67: QUEENSBERRY HOUSE OLD BURLINGTON STREET NO 3 CAT B LONDON
A68: QL-0312954 | B68: 4 | C68: GBP | D68: 24.75 | E68: GBP | F68: 99 | G68: 0.33 | H68: 1.33 | I68: GBP | J68: 74.72 | K68: SYS 330 TILE STEEL 1325mm X 250mm 1522 10 RAL 9010 20% WRAPPED 16 80 KG SQUARE | L68: Jack Wingfield | M68: London | N68: QUEENSBERRY HOUSE OLD BURLINGTON STREET NO 3 CAT B LONDON
A69: QL-0312957 | B69: 8 | C69: GBP | D69: 15.69 | E69: GBP | F69: 125.52 | G69: 0.21 | H69: 1.68 | I69: GBP | J69: 74.71 | K69: SYS 330 TILE STEEL 1400mm X 150mm 1522 10 RAL 9010 20% WRAPPED 16 80 KG SQUARE | L69: Jack Wingfield | M69: London | N69: QUEENSBERRY HOUSE OLD BURLINGTON STREET NO 3 CAT B LONDON
A70: QL-0312958 | B70: 16 | C70: GBP | D70: 20.92 | E70: GBP | F70: 334.72 | G70: 0.28 | H70: 4.48 | I70: GBP | J70: 74.71 | K70: SYS 330 TILE STEEL 1400mm X 200mm 1522 10 RAL 9010 20% WRAPPED 16 80 KG SQUARE | L70: Jack Wingfield | M70: London | N70: QUEENSBERRY HOUSE OLD BURLINGTON STREET NO 3 CAT B LONDON
A71: QL-0312961 | B71: 4 | C71: GBP | D71: 32.51 | E71: GBP | F71: 130.04 | G71: 0.44 | H71: 1.74 | I71: GBP | J71: 74.74 | K71: SYS 330 TILE STEEL 1450mm X 300mm 1522 10 RAL 9010 20% WRAPPED 16 80 KG SQUARE | L71: Jack Wingfield | M71: London | N71: QUEENSBERRY HOUSE OLD BURLINGTON STREET NO 3 CAT B LONDON
A72: QL-0312962 | B72: 32 | C72: GBP | D72: 33.63 | E72: GBP | F72: 1076.16 | G72: 0.45 | H72: 14.4 | I72: GBP | J72: 74.73 | K72: SYS 330 TILE STEEL 1500mm X 300mm 1522 10 RAL 9010 20% WRAPPED 16 80 KG SQUARE | L72: Jack Wingfield | M72: London | N72: QUEENSBERRY HOUSE OLD BURLINGTON STREET NO 3 CAT B LONDON
... A114: QL-0318298 | B114: 412 | C114: GBP | D114: 24.33 | E114: GBP | F114: 10023.96 | G114: 0.17 | H114: 70.04 | I114: GBP | J114: 143.12 | K114: SYS 330 TILE STEEL 850mm X 200mm 1522 10 RAL 9010 FT WRAPPED 16 80 KG SQUARE | L114: Sam James | M114: London | N114: DUKES HOTEL CORRIDOR CEILINGS MAYFAIR LONDON

Sheet SQM WK 40
A1: Line Name | B1: Quantity | C1: Net Unit Price Currency | D1: Net Unit Price | E1: Net Total Currency | F1: Net Total | G1: Item SQM | H1: Line SQM | I1: Â£/SQM Currency | J1: Â£/SQM | K1: Description | L1: Project Owner: Full Name | M1: Sales Region | N1: Project Name | O1: =AVERAGE(O2:O87) -> 80.211034 | P1: =AVERAGE(P2:P87) -> 80.210402
A2: QL-0309454 | B2: 22 | C2: GBP | D2: 22.71 | E2: GBP | F2: 499.62 | G2: 0.24 | H2: 5.34 | I2: GBP | J2: 93.57 | K2: SYS 330 TILE STEEL 809mm X 300mm 1522 10 RAL 9010 20% WRAPPED 16 80 KG SQUARE | L2: Ben Bishop | M2: Midlands | N2: COLMORE SQUARE NO 1 GROUND FLOOR BIRMINGHAM | O2: =IF(G2<0.03,"",J2) -> 93.57 | P2: =+F2/H2 -> 93.561798
A3: QL-0311344 | B3: 18 | C3: GBP | D3: 26.63 | E3: GBP | F3: 479.34 | G3: 0.29 | H3: 5.18 | I3: GBP | J3: 92.47 | K3: SYS 330 TILE STEEL 960mm X 300mm 1522 10 RAL 9010 20% WRAPPED 16 80 KG SQUARE | L3: Ben Bishop | M3: Midlands | N3: COLMORE SQUARE NO 1 GROUND FLOOR BIRMINGHAM | O3: =IF(G3<0.03,"",J3) -> 92.47 | P3: =+F3/H3 -> 92.53668
A4: QL-0316298 | B4: 1290 | C4: GBP | D4: 25.25 | E4: GBP | F4: 32572.5 | G4: 0.36 | H4: 464.4 | I4: GBP | J4: 70.14 | K4: SYS 330 TILE STEEL 1200mm X 300mm 1522 10 RAL 9010 20% WRAPPED 16 80 KG CLOSED ENDS | L4: Ben Bishop | M4: Northern Home Counties | N4: STATION ROAD NO 21 FLRS 4 & 5 CAMBRIDGE | O4: =IF(G4<0.03,"",J4) -> 70.14 | P4: =+F4/H4 -> 70.138889
A5: QL-0316260 | B5: 1960 | C5: GBP | D5: 25.25 | E5: GBP | F5: 49490 | G5: 0.36 | H5: 705.6 | I5: GBP | J5: 70.14 | K5: SYS 330 TILE STEEL 1200mm X 300mm 1522 10 RAL 9010 20% WRAPPED 16 80 KG CLOSED ENDS | L5: Ben Bishop | M5: Northern Home Counties | N5: STATION ROAD NO 21 FLRS 4 & 5 CAMBRIDGE | O5: =IF(G5<0.03,"",J5) -> 70.14 | P5: =+F5/H5 -> 70.138889
A6: QL-0316163 | B6: 905 | C6: GBP | D6: 29.33 | E6: GBP | F6: 26543.65 | G6: 0.36 | H6: 325.8 | I6: GBP | J6: 81.47 | K6: SYS 330 TILE 600mm X 600mm 1522 10 RAL 7022 30% 30mm THK RW4 BLACK TISSUE WRAPPED ACOUSTIC PAD | L6: Ed Fagan | M6: London | N6: BROADGATE NO 1-2 CAT B JLL AMR LONDON | O6: =IF(G6<0.03,"",J6) -> 81.47 | P6: =+F6/H6 -> 81.472222
A7: QL-0315484 | B7: 3875 | C7: GBP | D7: 24.59 | E7: GBP | F7: 95286.25 | G7: 0.36 | H7: 1393.84 | I7: GBP | J7: 68.36 | K7: SYS 330 TILE STEEL 1199mm X 300mm 1522 10 RAL 9010 20% BLACK ADHESIVE TISSUE SQUARE | L7: Jack Turnbull | M7: London | N7: KING WILLIAM STREET NO 45 REGIS HOUSE PH2 LONDON | O7: =IF(G7<0.03,"",J7) -> 68.36 | P7: =+F7/H7 -> 68.362402
A8: QL-0310997 | B8: 30 | C8: GBP | D8: 63.9 | E8: GBP | F8: 1917 | G8: 0.6 | H8: 18 | I8: GBP | J8: 106.5 | K8: SYS 330 TILE AL 1000mm X 600mm LEAF-SMALL RAL 9003 20% WRAPPED 16 80 KG SQUARE | L8: Jack Turnbull | M8: London | N8: WARWICK COURT CAT B EGYM LONDON | O8: =IF(G8<0.03,"",J8) -> 106.5 | P8: =+F8/H8 -> 106.5
A9: QL-0311008 | B9: 24 | C9: GBP | D9: 71.57 | E9: GBP | F9: 1717.68 | G9: 0.67 | H9: 16.13 | I9: GBP | J9: 106.5 | K9: SYS 330 TILE AL 1120mm X 600mm LEAF-SMALL RAL 9003 20% WRAPPED 16 80 KG SQUARE | L9: Jack Turnbull | M9: London | N9: WARWICK COURT CAT B EGYM LONDON | O9: =IF(G9<0.03,"",J9) -> 106.5 | P9: =+F9/H9 -> 106.48977
A10: QL-0311006 | B10: 24 | C10: GBP | D10: 34.51 | E10: GBP | F10: 828.24 | G10: 0.32 | H10: 7.78 | I10: GBP | J10: 106.51 | K10: SYS 330 TILE AL 540mm X 600mm LEAF-SMALL RAL 9003 20% WRAPPED 16 80 KG SQUARE | L10: Jack Turnbull | M10: London | N10: WARWICK COURT CAT B EGYM LONDON | O10: =IF(G10<0.03,"",J10) -> 106.51 | P10: =+F10/H10 -> 106.45758
A11: QL-0311007 | B11: 8 | C11: GBP | D11: 109.91 | E11: GBP | F11: 879.28 | G11: 1.03 | H11: 8.26 | I11: GBP | J11: 106.5 | K11: SYS 330 TILE AL 1720mm X 600mm LEAF-SMALL RAL 9003 20% WRAPPED 16 80 KG SQUARE | L11: Jack Turnbull | M11: London | N11: WARWICK COURT CAT B EGYM LONDON | O11: =IF(G11<0.03,"",J11) -> 106.5 | P11: =+F11/H11 -> 106.45036
A12: QL-0310968 | B12: 8 | C12: GBP | D12: 76.68 | E12: GBP | F12: 613.44 | G12: 0.72 | H12: 5.76 | I12: GBP | J12: 106.5 | K12: SYS 330 TILE AL 1200mm X 600mm LEAF-SMALL RAL 9003 20% WRAPPED 16 80 KG SQUARE | L12: Jack Turnbull | M12: London | N12: WARWICK COURT CAT B EGYM LONDON | O12: =IF(G12<0.03,"",J12) -> 106.5 | P12: =+F12/H12 -> 106.5
A13: QL-0310142 | B13: 380 | C13: GBP | D13: 17.98 | E13: GBP | F13: 6832.4 | G13: 0.36 | H13: 136.8 | I13: GBP | J13: 49.94 | K13: SYS 330 TILE STEEL 1200mm X 300mm 1522 10 RAL 9010 20% WRAPPED 16 80 KG SQUARE | L13: Jack Wingfield | M13: London | N13: BRITISH LIBRARY SOUND & VISION FIT OUT LONDON | O13: =IF(G13<0.03,"",J13) -> 49.94 | P13: =+F13/H13 -> 49.944444
A14: QL-0312544 | B14: 299 | C14: GBP | D14: 62.59 | E14: GBP | F14: 18714.41 | G14: 0 | H14: 0 | J14: #Error! | K14: SYS 330 TILE SYS 330 TILE STEEL 1500mm x 600mm 2051 10 RAL 5018 WRAPPED 16 80 KG LIGHT TURQUOISE BLUE FINISH, TBC | L14: Jack Wingfield | M14: London | N14: KINGS CROSS CENTRAL GOOGLE HQ KGX1 CAT B LONDON
A15: QL-0311837 | B15: 327 | C15: GBP | D15: 44.08 | E15: GBP | F15: 14414.16 | G15: 0.72 | H15: 235.44 | I15: GBP | J15: 61.22 | K15: SYS 330 TILE 1200mm X 600mm 1003 OVERALL RAL 9010 20% WRAPPED 16 80 KG SQUARE | L15: Mark Guest | M15: South East | N15: AWE HUB ALDERMASTON ENGINEERING WING LEVEL 02 ALDERMASTON | O15: =IF(G15<0.03,"",J15) -> 61.22 | P15: =+F15/H15 -> 61.222222
A16: QL-0311846 | B16: 608 | C16: GBP | D16: 22.04 | E16: GBP | F16: 13400.32 | G16: 0.36 | H16: 218.88 | I16: GBP | J16: 61.22 | K16: SYS 330 TILE STEEL 600mm X 600mm 1003 OVERALL RAL 9010 20% WRAPPED 16 80 KG SQUARE | L16: Mark Guest | M16: South East | N16: AWE HUB ALDERMASTON ENGINEERING WING LEVEL 02 ALDERMASTON | O16: =IF(G16<0.03,"",J16) -> 61.22 | P16: =+F16/H16 -> 61.222222
A17: QL-0311855 | B17: 385 | C17: GBP | D17: 44.08 | E17: GBP | F17: 16970.8 | G17: 0.72 | H17: 277.2 | I17: GBP | J17: 61.22 | K17: SYS 330 TILE STEEL 1200mm X 600mm 1513 10 RAL 9010 20% WRAPPED 16 80 KG SQUARE | L17: Mark Guest | M17: South East | N17: AWE HUB ALDERMASTON ENGINEERING WING LEVEL 02 ALDERMASTON | O17: =IF(G17<0.03,"",J17) -> 61.22 | P17: =+F17/H17 -> 61.222222
A18: QL-0316077 | B18: 38 | C18: GBP | D18: 31.5 | E18: GBP | F18: 1197 | G18: 0.42 | H18: 15.96 | I18: GBP | J18: 75 | K18: SYS 330 TILE STEEL 1400mm X 300mm 1522 10 RAL 9010 20% WRAPPED 16 80 KG SQUARE | L18: Nick Drake | M18: London | N18: SAVILE ROW NO 23 ROKOS FLR 2-3 LONDON | O18: =IF(G18<0.03,"",J18) -> 75 | P18: =+F18/H18 -> 75
A19: QL-0316078 | B19: 100 | C19: GBP | D19: 27 | E19: GBP | F19: 2700 | G19: 0.36 | H19: 36 | I19: GBP | J19: 75 | K19: SYS 330 TILE STEEL 1200mm X 300mm 1522 10 RAL 9010 20% WRAPPED 16 80 KG SQUARE | L19: Nick Drake | M19: London | N19: SAVILE ROW NO 23 ROKOS FLR 2-3 LONDON | O19: =IF(G19<0.03,"",J19) -> 75 | P19: =+F19/H19 -> 75
A20: QL-0315180 | B20: 15 | C20: GBP | D20: 72 | E20: GBP | F20: 1080 | G20: 0.9 | H20: 13.5 | I20: GBP | J20: 80 | K20: SYS 330 TILE STEEL 1500mm X 600mm 1522 10 RAL 9010 20% WRAPPED 16 80 KG SQUARE HORIZON | L20: Nick Drake | M20: London | N20: SOUTHAMPTON ROW NO 31 HOLBORN LINKS PH 2 LONDON | O20: =IF(G20<0.03,"",J20) -> 80 | P20: =+F20/H20 -> 80
A21: QL-0312700 | B21: 14 | C21: GBP | D21: 28.8 | E21: GBP | F21: 403.2 | G21: 0.36 | H21: 5.04 | I21: GBP | J21: 80 | K21: SYS 330 TILE STEEL 1200mm X 300mm 1003 OVERALL RAL 9016 20% WRAPPED 16 80 KG SQUARE | L21: Peter Gray | M21: London | N21: FINSBURY SQUARE NO 38 LONDON | O21: =IF(G21<0.03,"",J21) -> 80 | P21: =+F21/H21 -> 80
A22: QL-0312701 | B22: 5 | C22: GBP | D22: 36 | E22: GBP | F22: 180 | G22: 0.45 | H22: 2.25 | I22: GBP | J22: 80 | K22: SYS 330 TILE STEEL 1500mm X 300mm 1003 OVERALL RAL 9016 20% WRAPPED 16 80 KG SQUARE | L22: Peter Gray | M22: London | N22: FINSBURY SQUARE NO 38 LONDON | O22: =IF(G22<0.03,"",J22) -> 80 | P22: =+F22/H22 -> 80
A23: QL-0312699 | B23: 3 | C23: GBP | D23: 48 | E23: GBP | F23: 144 | G23: 0.6 | H23: 1.8 | I23: GBP | J23: 80 | K23: SYS 330 TILE STEEL 1500mm X 400mm 1003 OVERALL RAL 9016 20% WRAPPED 16 80 KG SQUARE TO BE CUT ON SITE BY OTHERS | L23: Peter Gray | M23: London | N23: FINSBURY SQUARE NO 38 LONDON | O23: =IF(G23<0.03,"",J23) -> 80 | P23: =+F23/H23 -> 80
A24: QL-0312667 | B24: 7 | C24: GBP | D24: 28.8 | E24: GBP | F24: 201.6 | G24: 0.36 | H24: 2.52 | I24: GBP | J24: 80 | K24: SYS 330 TILE STEEL 1200mm X 300mm 1003 OVERALL RAL 9016 20% WRAPPED 16 80 KG SQUARE | L24: Peter Gray | M24: London | N24: FINSBURY SQUARE NO 38 LONDON | O24: =IF(G24<0.03,"",J24) -> 80 | P24: =+F24/H24 -> 80
A25: QL-0312670 | B25: 14 | C25: GBP | D25: 28.8 | E25: GBP | F25: 403.2 | G25: 0.36 | H25: 5.04 | I25: GBP | J25: 80 | K25: SYS 330 TILE STEEL 1200mm X 300mm 1003 OVERALL RAL 9016 20% WRAPPED 16 80 KG SQUARE | L25: Peter Gray | M25: London | N25: FINSBURY SQUARE NO 38 LONDON | O25: =IF(G25<0.03,"",J25) -> 80 | P25: =+F25/H25 -> 80
A26: QL-0312708 | B26: 15 | C26: GBP | D26: 48 | E26: GBP | F26: 720 | G26: 0.6 | H26: 9 | I26: GBP | J26: 80 | K26: SYS 330 TILE STEEL 1500mm X 400mm 1003 OVERALL RAL 9016 20% WRAPPED 16 80 KG SQUARE | L26: Peter Gray | M26: London | N26: FINSBURY SQUARE NO 38 LONDON | O26: =IF(G26<0.03,"",J26) -> 80 | P26: =+F26/H26 -> 80
... A60: QL-0313052 | B60: 349 | C60: GBP | D60: 28.35 | E60: GBP | F60: 9894.15 | G60: 0.41 | H60: 141.35 | I60: GBP | J60: 70 | K60: SYS 330 TILE STEEL 1350mm X 300mm 1522 10 RAL 9016 20% WRAPPED 16 80 KG SQUARE | L60: Sam James | M60: London | N60: PALL MALL NO 48 FLOOR 6 LONDON | O60: =IF(G60<0.03,"",J60) -> 70 | P60: =+F60/H60 -> 69.997524

Sheet SQM WK39
A1: Line Name | B1: Quantity | C1: Net Unit Price Currency | D1: Net Unit Price | E1: Net Total Currency | F1: Net Total | G1: Item SQM | H1: Line SQM | I1: Â£/SQM Currency | J1: Â£/SQM | K1: Description | L1: Project Owner: Full Name | M1: Sales Region | N1: Project Name | O1: =AVERAGE(O2:O87) -> 107.59414 | P1: =AVERAGE(P2:P87) -> 107.59182
A2: QL-0301453 | B2: 755 | C2: GBP | D2: 38.28 | E2: GBP | F2: 28901.4 | G2: 0.66 | H2: 498.3 | I2: GBP | J2: 58 | K2: SYS 330 TILE STEEL 2200mm X 300mm 1522 10 RAL 9010 20% WRAPPED 16 80 KG SQUARE | L2: Becky Titley | M2: North | N2: PILGRIM STREET PHASE 3 BUILDING 1 & 2 NEWCASTLE | O2: =IF(G2<0.03,"",J2) -> 58 | P2: =+F2/H2 -> 58
A3: QL-0301451 | B3: 1509 | C3: GBP | D3: 20.88 | E3: GBP | F3: 31507.92 | G3: 0.36 | H3: 543.24 | I3: GBP | J3: 58 | K3: SYS 330 TILE STEEL 1200mm X 300mm 1522 10 RAL 9010 20% WRAPPED 16 80 KG SQUARE | L3: Becky Titley | M3: North | N3: PILGRIM STREET PHASE 3 BUILDING 1 & 2 NEWCASTLE | O3: =IF(G3<0.03,"",J3) -> 58 | P3: =+F3/H3 -> 58
A4: QL-0308238 | B4: 32 | C4: GBP | D4: 55 | E4: GBP | F4: 1760 | G4: 0.25 | H4: 8 | I4: GBP | J4: 220 | K4: SYS 330 TILE 500mm X 500mm 3939 FABRIC STATIC WRAPPED 16 80 KG SQUARE SYSTEM 330/200 CAMIRA BLAZER TREVELYAN | L4: David Baylis | M4: North | N4: LUMINA VILLAGE FORMER KELLOGGS SITE - 440 APTS MANCHESTER | O4: =IF(G4<0.03,"",J4) -> 220 | P4: =+F4/H4 -> 220
A5: QL-0308241 | B5: 42 | C5: GBP | D5: 55 | E5: GBP | F5: 2310 | G5: 0.25 | H5: 10.5 | I5: GBP | J5: 220 | K5: SYS 330 TILE 500mm X 500mm 3939 FABRIC STATIC WRAPPED 16 80 KG SQUARE SYSTEM 330/200 CAMIRA BLAZER TREVELYAN | L5: David Baylis | M5: North | N5: LUMINA VILLAGE FORMER KELLOGGS SITE - 440 APTS MANCHESTER | O5: =IF(G5<0.03,"",J5) -> 220 | P5: =+F5/H5 -> 220
A6: QL-0308249 | B6: 17 | C6: GBP | D6: 55 | E6: GBP | F6: 935 | G6: 0.25 | H6: 4.25 | I6: GBP | J6: 220 | K6: SYS 330 TILE 500mm X 500mm 3939 FABRIC STATIC WRAPPED 16 80 KG SQUARE SYSTEM 330/200 CAMIRA BLAZER TREVELYAN | L6: David Baylis | M6: North | N6: LUMINA VILLAGE FORMER KELLOGGS SITE - 440 APTS MANCHESTER | O6: =IF(G6<0.03,"",J6) -> 220 | P6: =+F6/H6 -> 220
A7: QL-0308248 | B7: 10 | C7: GBP | D7: 55 | E7: GBP | F7: 550 | G7: 0.25 | H7: 2.5 | I7: GBP | J7: 220 | K7: SYS 330 TILE 500mm X 500mm 3939 FABRIC STATIC WRAPPED 16 80 KG SQUARE SYSTEM 330/200 CAMIRA BLAZER TREVELYAN | L7: David Baylis | M7: North | N7: LUMINA VILLAGE FORMER KELLOGGS SITE - 440 APTS MANCHESTER | O7: =IF(G7<0.03,"",J7) -> 220 | P7: =+F7/H7 -> 220
A8: QL-0308250 | B8: 32 | C8: GBP | D8: 55 | E8: GBP | F8: 1760 | G8: 0.25 | H8: 8 | I8: GBP | J8: 220 | K8: SYS 330 TILE 500mm X 500mm 3939 FABRIC STATIC WRAPPED 16 80 KG SQUARE SYSTEM 330/200 CAMIRA BLAZER TREVELYAN | L8: David Baylis | M8: North | N8: LUMINA VILLAGE FORMER KELLOGGS SITE - 440 APTS MANCHESTER | O8: =IF(G8<0.03,"",J8) -> 220 | P8: =+F8/H8 -> 220
A9: QL-0309214 | B9: 193 | C9: GBP | D9: 26.98 | E9: GBP | F9: 5207.14 | G9: 0.36 | H9: 69.42 | I9: GBP | J9: 75.01 | K9: SYS 330 TILE STEEL 1199mm X 300mm 3136 10 RAL 9010 20% WRAPPED 16 80 KG SQUARE | L9: Eurshell Fearon | M9: Northern Home Counties | N9: GSK BUILDING 2 GROUND FLR LAB STEVENAGE | O9: =IF(G9<0.03,"",J9) -> 75.01 | P9: =+F9/H9 -> 75.009219
A10: QL-0309506 | B10: 1557 | C10: GBP | D10: 28.75 | E10: GBP | F10: 44763.75 | G10: 0.36 | H10: 560.52 | I10: GBP | J10: 79.86 | K10: SYS 330 TILE STEEL 1200mm X 300mm 1522 10 RAL 9010 20% WRAPPED 25 80 KG SQUARE 50MM DEEP TO LONG EDGES | L10: Jack Turnbull | M10: London | N10: GRESHAM STREET NO 99 LVL 3 & 4 LONDON | O10: =IF(G10<0.03,"",J10) -> 79.86 | P10: =+F10/H10 -> 79.861111
A11: QL-0304445 | B11: 54 | C11: GBP | D11: 178.2 | E11: GBP | F11: 9622.8 | G11: 0.81 | H11: 43.74 | I11: GBP | J11: 220 | K11: SYS 330 TILE 900mm X 900mm FABRIC STATIC SQUARE CAMIRA QUEST WHELK FABRIC | L11: Jack Wingfield | M11: London | N11: GRESHAM STREET NO 10 MOODYS CORP CAT B FABRIC LONDON | O11: =IF(G11<0.03,"",J11) -> 220 | P11: =+F11/H11 -> 220
A12: QL-0304442 | B12: 182 | C12: GBP | D12: 178.2 | E12: GBP | F12: 32432.4 | G12: 0.81 | H12: 147.42 | I12: GBP | J12: 220 | K12: SYS 330 TILE 900mm X 900mm FABRIC STATIC SQUARE CAMIRA QUEST SALT FABRIC | L12: Jack Wingfield | M12: London | N12: GRESHAM STREET NO 10 MOODYS CORP CAT B FABRIC LONDON | O12: =IF(G12<0.03,"",J12) -> 220 | P12: =+F12/H12 -> 220
A13: QL-0301628 | B13: 1329 | C13: GBP | D13: 31.39 | E13: GBP | F13: 41717.31 | G13: 0.42 | H13: 558.18 | I13: GBP | J13: 74.74 | K13: SYS 330 TILE STEEL 1400mm X 300mm 1522 10 RAL 9010 20% WRAPPED 16 80 KG SQUARE | L13: Jack Wingfield | M13: London | N13: QUEENSBERRY HOUSE OLD BURLINGTON STREET NO 3 CAT B LONDON | O13: =IF(G13<0.03,"",J13) -> 74.74 | P13: =+F13/H13 -> 74.738095
... A30: QL-0305457 | B30: 162 | C30: GBP | D30: 47.86 | E30: GBP | F30: 7753.32 | G30: 0.7 | H30: 113.4 | I30: GBP | J30: 68.37 | K30: SYS 330 TILE STEEL 1400mm X 500mm 2227 10 RAL 9010 20% WRAPPED 16 80 KG SQUARE | L30: Sam James | M30: London | N30: RADSTOCK HOUSE ECCLESTON STREET NO 3-5 LONDON | O30: =IF(G30<0.03,"",J30) -> 68.37 | P30: =+F30/H30 -> 68.371429

Sheet SQM WK 38
A1: Line Name | B1: Quantity | C1: Net Unit Price Currency | D1: Net Unit Price | E1: Net Total Currency | F1: Net Total | G1: Item SQM | H1: Line SQM | I1: Â£/SQM Currency | J1: Â£/SQM | K1: Description | L1: Project Owner: Full Name | M1: Sales Region | N1: Project Name | O1: =AVERAGE(O2:O87) -> 79.964756 | P1: =AVERAGE(P2:P87) -> 90.732861
A2: QL-0301594 | B2: 68 | C2: GBP | D2: 22.48 | E2: GBP | F2: 1528.64 | G2: 0.02 | H2: 1.57 | I2: GBP | J2: 973.16 | K2: SYS 330 TILE STEEL 308mm X 75mm 1522 10 RAL 9010 20% WRAPPED 16 80 KG SQUARE HOOK ON LONG EDGES | L2: Becky Titley | M2: Scotland | N2: JPMC ARGYLE STREET GLASGOW | O2: =IF(G2<0.03,"",J2) | P2: =+F2/H2 -> 973.65605
A3: QL-0302239 | B3: 10 | C3: GBP | D3: 26.31 | E3: GBP | F3: 263.1 | G3: 0.6 | H3: 6 | I3: GBP | J3: 43.85 | K3: SYS 330 TILE STEEL 1200mm X 500mm PLAIN RAL 9010 20% NO INFILL SQUARE | L3: Becky Titley | M3: Scotland | N3: WAVERLEY GATE FLR 2 REFURB EDINBURGH | O3: =IF(G3<0.03,"",J3) -> 43.85 | P3: =+F3/H3 -> 43.85
A4: QL-0302238 | B4: 27 | C4: GBP | D4: 32.89 | E4: GBP | F4: 888.03 | G4: 0.75 | H4: 20.25 | I4: GBP | J4: 43.85 | K4: SYS 330 TILE STEEL 1500mm X 500mm PLAIN RAL 9010 20% NO INFILL SQUARE | L4: Becky Titley | M4: Scotland | N4: WAVERLEY GATE FLR 2 REFURB EDINBURGH | O4: =IF(G4<0.03,"",J4) -> 43.85 | P4: =+F4/H4 -> 43.853333
A5: QL-0296083 | B5: 88 | C5: GBP | D5: 30.78 | E5: GBP | F5: 2708.64 | G5: 0.54 | H5: 47.52 | I5: GBP | J5: 57 | K5: SYS 330 TILE STEEL 1800mm X 300mm 1522 10 RAL 9010 20% WRAPPED 16 80 KG SQUARE | L5: David Baylis | M5: North | N5: ST HELENS TOWN CENTRE REDEVELOPMENT OFFICE BLOCK | O5: =IF(G5<0.03,"",J5) -> 57 | P5: =+F5/H5 -> 57
A6: QL-0296082 | B6: 1303 | C6: GBP | D6: 20.52 | E6: GBP | F6: 26737.56 | G6: 0.36 | H6: 469.08 | I6: GBP | J6: 57 | K6: SYS 330 TILE STEEL 1200mm X 300mm 1522 10 RAL 9010 20% WRAPPED 16 80 KG SQUARE | L6: David Baylis | M6: North | N6: ST HELENS TOWN CENTRE REDEVELOPMENT OFFICE BLOCK | O6: =IF(G6<0.03,"",J6) -> 57 | P6: =+F6/H6 -> 57
A7: QL-0302345 | B7: 334 | C7: GBP | D7: 37.1 | E7: GBP | F7: 12391.4 | G7: 0.41 | H7: 135.27 | I7: GBP | J7: 91.6 | K7: SYS 330 TILE 1349 x 300mm 1522 10 RAL 9010 20% WRAPPED 25 45 KG SQUARE 50mm HIGH SIDES, & 25x45kg/m3 BLACK TISSUE WRAPPED PAD, SEE DRG. | L7: Eurshell Fearon | M7: London | N7: NOVA NORTH BRESSENDEN PLACE NO 11 REFURB LONDON | O7: =IF(G7<0.03,"",J7) -> 91.6 | P7: =+F7/H7 -> 91.604938
A8: QL-0300738 | B8: 88 | C8: GBP | D8: 66.3 | E8: GBP | F8: 5834.4 | G8: 0.78 | H8: 68.64 | I8: GBP | J8: 85 | K8: SYS 330 TILE STEEL 1300mm X 600mm 1003 OVERALL WRAPPED 16 80 KG SQUARE FINISH D2525 ANODIC BRONZE Y2214F | L8: Jack Wingfield | M8: London | N8: BAKER STREET NO 25 CAT B FORTRESS FIG FLOOR 5 LONDON | O8: =IF(G8<0.03,"",J8) -> 85 | P8: =+F8/H8 -> 85
A9: QL-0300737 | B9: 56 | C9: GBP | D9: 66.3 | E9: GBP | F9: 3712.8 | G9: 0.78 | H9: 43.68 | I9: GBP | J9: 85 | K9: SYS 330 TILE STEEL 1300mm X 600mm 1003 OVERALL WRAPPED 16 80 KG SQUARE FINISH D2525 ANODIC BRONZE Y2214F | L9: Jack Wingfield | M9: London | N9: BAKER STREET NO 25 CAT B FORTRESS FIG FLOOR 5 LONDON | O9: =IF(G9<0.03,"",J9) -> 85 | P9: =+F9/H9 -> 85
A10: QL-0300739 | B10: 8 | C10: GBP | D10: 107.1 | E10: GBP | F10: 856.8 | G10: 1.26 | H10: 10.08 | I10: GBP | J10: 85 | K10: SYS 330 TILE STEEL 2100mm X 600mm 1003 OVERALL WRAPPED 16 80 KG SQUARE FINISH D2525 ANODIC BRONZE Y2214F | L10: Jack Wingfield | M10: London | N10: BAKER STREET NO 25 CAT B FORTRESS FIG FLOOR 5 LONDON | O10: =IF(G10<0.03,"",J10) -> 85 | P10: =+F10/H10 -> 85
A11: QL-0299911 | B11: 13249 | C11: GBP | D11: 29.06 | E11: GBP | F11: 385015.94 | G11: 0.39 | H11: 5167.11 | I11: GBP | J11: 74.51 | K11: SYS 330 TILE STEEL 1300mm X 300mm 1522 10 RAL 9010 20% WRAPPED 16 80 KG SQUARE | L11: Jack Wingfield | M11: London | N11: BEDFONT LAKES BUILDING 10 LAKESHORE FELTHAM LONDON | O11: =IF(G11<0.03,"",J11) -> 74.51 | P11: =+F11/H11 -> 74.512821
A12: QL-0301622 | B12: 234 | C12: GBP | D12: 31.39 | E12: GBP | F12: 7345.26 | G12: 0.42 | H12: 98.28 | I12: GBP | J12: 74.74 | K12: SYS 330 TILE STEEL 1400mm X 300mm 1522 10 RAL 9010 20% WRAPPED 16 80 KG SQUARE | L12: Jack Wingfield | M12: London | N12: QUEENSBERRY HOUSE OLD BURLINGTON STREET NO 3 CAT A LONDON | O12: =IF(G12<0.03,"",J12) -> 74.74 | P12: =+F12/H12 -> 74.738095
A13: QL-0288779 | B13: 1311 | C13: GBP | D13: 21.06 | E13: GBP | F13: 27609.66 | G13: 0.36 | H13: 471.96 | I13: GBP | J13: 58.5 | K13: SYS 330 TILE STEEL 1200mm X 300mm 6051 BORDERS A/S RAL 9010 20% BLACK ADHESIVE TISSUE | L13: Jay Adams | M13: Northern Home Counties | N13: JIC &TSL JOHN INNES CENTRE BUILDING NORWICH | O13: =IF(G13<0.03,"",J13) -> 58.5 | P13: =+F13/H13 -> 58.5
... A84: QL-0242003 | B84: 367 | C84: GBP | D84: 67.5 | E84: GBP | F84: 24772.5 | G84: 0.9 | H84: 330.3 | I84: GBP | J84: 75 | K84: SYS 330 TILE STEEL 1500mm X 600mm 1522 10 RAL 9016 20% WRAPPED 16 80 KG SQUARE | L84: Sam James | M84: London | N84: VICTORIA STREET NO 105 EVERCORE CAT B FIT OUT LONDON | O84: =IF(G84<0.03,"",J84) -> 75 | P84: =+F84/H84 -> 75

Sheet SQM WK37
A1: Line Name | B1: Quantity | C1: Net Unit Price Currency | D1: Net Unit Price | E1: Net Total Currency | F1: Net Total | G1: Item SQM | H1: Line SQM | I1: Â£/SQM Currency | J1: Â£/SQM | K1: Description | L1: Project Owner: Full Name | M1: Sales Region | N1: Project Name | O1: =AVERAGE(O2:O87) -> 79.844902 | P1: =AVERAGE(P2:P87) -> 79.843209
A2: QL-0290076 | B2: 17 | C2: GBP | D2: 19.64 | E2: GBP | F2: 333.88 | G2: 0.36 | H2: 6.12 | I2: GBP | J2: 54.56 | K2: SYS 330 TILE STEEL 600mm X 600mm 1061 OVERALL RAL 9005 30% NO INFILL SQUARE | L2: Becky Titley | M2: Scotland | N2: EDINBURGH QUAYSIDE 1 L0A FCA FITOUT EDINBURGH | O2: =IF(G2<0.03,"",J2) -> 54.56 | P2: =+F2/H2 -> 54.555556
A3: QL-0293453 | B3: 116 | C3: GBP | D3: 60.7 | E3: GBP | F3: 7041.2 | G3: 0.4 | H3: 46.95 | I3: GBP | J3: 149.99 | K3: SYS 330 TILE STEEL 1349mm X 300mm 2227 10 RAL 9016 20% WRAPPED 16 80 KG SQUARE | L3: Eurshell Fearon | M3: London | N3: MOORFIELDS NO 21 DEUTSCHE BANK REFURB LONDON | O3: =IF(G3<0.03,"",J3) -> 149.99 | P3: =+F3/H3 -> 149.97231
A4: QL-0288894 | B4: 1 | C4: GBP | D4: 20.52 | E4: GBP | F4: 20.52 | G4: 0.27 | H4: 0.27 | I4: GBP | J4: 76 | K4: SYS 330 TILE STEEL 900mm X 300mm 1003 OVERALL RAL 9016 20% WRAPPED 16 80 KG SQUARE OUT TURN TO LONG EDGES | L4: Jack Turnbull | M4: London | N4: MADDOX STREET NO 31 - 33 CAT A LONDON | O4: =IF(G4<0.03,"",J4) -> 76 | P4: =+F4/H4 -> 76
A5: QL-0288895 | B5: 4 | C5: GBP | D5: 13.68 | E5: GBP | F5: 54.72 | G5: 0.18 | H5: 0.72 | I5: GBP | J5: 76 | K5: SYS 330 TILE STEEL 600mm X 300mm 1003 OVERALL RAL 9016 20% WRAPPED 16 80 KG SQUARE OUT TURN TO LONG EDGES | L5: Jack Turnbull | M5: London | N5: MADDOX STREET NO 31 - 33 CAT A LONDON | O5: =IF(G5<0.03,"",J5) -> 76 | P5: =+F5/H5 -> 76
A6: QL-0288934 | B6: 36 | C6: GBP | D6: 27.36 | E6: GBP | F6: 984.96 | G6: 0.36 | H6: 12.96 | I6: GBP | J6: 76 | K6: SYS 330 TILE STEEL 1200mm X 300mm 1003 OVERALL RAL 9016 20% WRAPPED 16 80 KG SQUARE | L6: Jack Turnbull | M6: London | N6: MADDOX STREET NO 31 - 33 CAT A LONDON | O6: =IF(G6<0.03,"",J6) -> 76 | P6: =+F6/H6 -> 76
A7: QL-0288936 | B7: 3 | C7: GBP | D7: 13.68 | E7: GBP | F7: 41.04 | G7: 0.18 | H7: 0.54 | I7: GBP | J7: 76 | K7: SYS 330 TILE STEEL 600mm X 300mm 1003 OVERALL RAL 9016 20% WRAPPED 16 80 KG SQUARE OUT TURN TO LONG EDGES | L7: Jack Turnbull | M7: London | N7: MADDOX STREET NO 31 - 33 CAT A LONDON | O7: =IF(G7<0.03,"",J7) -> 76 | P7: =+F7/H7 -> 76
A8: QL-0288950 | B8: 4 | C8: GBP | D8: 27.36 | E8: GBP | F8: 109.44 | G8: 0.36 | H8: 1.44 | I8: GBP | J8: 76 | K8: SYS 330 TILE STEEL 1200mm X 300mm 1003 OVERALL RAL 9016 20% WRAPPED 16 80 KG SQUARE OUT TURN TO LONG EDGES | L8: Jack Turnbull | M8: London | N8: MADDOX STREET NO 31 - 33 CAT A LONDON | O8: =IF(G8<0.03,"",J8) -> 76 | P8: =+F8/H8 -> 76
A9: QL-0288949 | B9: 8 | C9: GBP | D9: 34.2 | E9: GBP | F9: 273.6 | G9: 0.45 | H9: 3.6 | I9: GBP | J9: 76 | K9: SYS 330 TILE STEEL 1500mm X 300mm 1003 OVERALL RAL 9016 20% WRAPPED 16 80 KG SQUARE OUT TURN TO LONG EDGES | L9: Jack Turnbull | M9: London | N9: MADDOX STREET NO 31 - 33 CAT A LONDON | O9: =IF(G9<0.03,"",J9) -> 76 | P9: =+F9/H9 -> 76
A10: QL-0288944 | B10: 212 | C10: GBP | D10: 27.36 | E10: GBP | F10: 5800.32 | G10: 0.36 | H10: 76.32 | I10: GBP | J10: 76 | K10: SYS 330 TILE STEEL 1200mm X 300mm 1003 OVERALL RAL 9016 20% WRAPPED 16 80 KG SQUARE | L10: Jack Turnbull | M10: London | N10: MADDOX STREET NO 31 - 33 CAT A LONDON | O10: =IF(G10<0.03,"",J10) -> 76 | P10: =+F10/H10 -> 76
A11: QL-0288945 | B11: 27 | C11: GBP | D11: 20.52 | E11: GBP | F11: 554.04 | G11: 0.27 | H11: 7.29 | I11: GBP | J11: 76 | K11: SYS 330 TILE STEEL 900mm X 300mm 1003 OVERALL RAL 9016 20% WRAPPED 16 80 KG SQUARE | L11: Jack Turnbull | M11: London | N11: MADDOX STREET NO 31 - 33 CAT A LONDON | O11: =IF(G11<0.03,"",J11) -> 76 | P11: =+F11/H11 -> 76
A12: QL-0288943 | B12: 27 | C12: GBP | D12: 34.2 | E12: GBP | F12: 923.4 | G12: 0.45 | H12: 12.15 | I12: GBP | J12: 76 | K12: SYS 330 TILE STEEL 1500mm X 300mm 1003 OVERALL RAL 9016 20% WRAPPED 16 80 KG SQUARE | L12: Jack Turnbull | M12: London | N12: MADDOX STREET NO 31 - 33 CAT A LONDON | O12: =IF(G12<0.03,"",J12) -> 76 | P12: =+F12/H12 -> 76
A13: QL-0288956 | B13: 212 | C13: GBP | D13: 27.36 | E13: GBP | F13: 5800.32 | G13: 0.36 | H13: 76.32 | I13: GBP | J13: 76 | K13: SYS 330 TILE STEEL 1200mm X 300mm 1003 OVERALL RAL 9016 20% WRAPPED 16 80 KG SQUARE | L13: Jack Turnbull | M13: London | N13: MADDOX STREET NO 31 - 33 CAT A LONDON | O13: =IF(G13<0.03,"",J13) -> 76 | P13: =+F13/H13 -> 76
... A52: QL-0290903 | B52: 42 | C52: GBP | D52: 20.74 | E52: GBP | F52: 871.08 | G52: 0.3 | H52: 12.44 | I52: GBP | J52: 70.01 | K52: SYS 330 TILE STEEL 790mm X 375mm D1821 10 RAL 9010 20% WRAPPED 16 80 KG SQUARE | L52: Sam James | M52: London | N52: CANNON STREET NO 45 CAT B GLOBAL RELAY FLOORS 3-5 LONDON | O52: =IF(G52<0.03,"",J52) -> 70.01 | P52: =+F52/H52 -> 70.022508

Sheet SQMWK36
A1: Line Name | B1: Quantity | C1: Net Unit Price Currency | D1: Net Unit Price | E1: Net Total Currency | F1: Net Total | G1: Item SQM | H1: Line SQM | I1: Â£/SQM Currency | J1: Â£/SQM | K1: Description | L1: Project Owner: Full Name | M1: Sales Region | N1: Project Name | O1: =AVERAGE(O2:O87) -> 70.96 | P1: =AVERAGE(P2:P87) -> 70.960269
A2: QL-0284598 | B2: 667 | C2: GBP | D2: 25.2 | E2: GBP | F2: 16808.4 | G2: 0.36 | H2: 240.12 | I2: GBP | J2: 70 | K2: SYS 330 TILE STEEL 1200mm X 300mm 4050 35 RAL 9010 20% NO INFILL SQUARE | L2: David Baylis | M2: North | N2: UNI OF LEEDS GARSTANG LAB REFURB | O2: =IF(G2<0.03,"",J2) -> 70 | P2: =+F2/H2 -> 70
A3: QL-0286320 | B3: 5 | C3: GBP | D3: 55.44 | E3: GBP | F3: 277.2 | G3: 0.72 | H3: 3.6 | I3: GBP | J3: 77 | K3: SYS 330 TILE STEEL 1200mm X 600mm 1003 OVERALL RAL 9001 30% HIGH PERFORMANCE INFILL SQUARE | L3: Eurshell Fearon | M3: Midlands | N3: EURSHELL MISC TILE & GRID 2025 | O3: =IF(G3<0.03,"",J3) -> 77 | P3: =+F3/H3 -> 77
A4: QL-0286762 | B4: 11600 | C4: GBP | D4: 23.61 | E4: GBP | F4: 273876 | G4: 0.36 | H4: 4176 | I4: GBP | J4: 65.58 | K4: SYS 330 TILE STEEL 1200mm X 300mm 1522 10 RAL 9016 20% WRAPPED 16 80 KG SQUARE | L4: Nick Drake | M4: Northern Home Counties | N4: CAMBRIDGE NORTH ONE MILTON AVENUE CAMBRIDGE | O4: =IF(G4<0.03,"",J4) -> 65.58 | P4: =+F4/H4 -> 65.583333
A5: QL-0289341 | B5: 724 | C5: GBP | D5: 23.4 | E5: GBP | F5: 16941.6 | G5: 0.36 | H5: 260.64 | I5: GBP | J5: 65 | K5: SYS 330 TILE STEEL 1200mm X 300mm 1522 10 RAL 9010 20% WRAPPED 16 80 KG SQUARE | L5: Peter Gray | M5: London | N5: MONUMENT STREET NO 16-18 LONDON | O5: =IF(G5<0.03,"",J5) -> 65 | P5: =+F5/H5 -> 65
A6: QL-0284463 | B6: 1546 | C6: GBP | D6: 26.65 | E6: GBP | F6: 41200.9 | G6: 0.36 | H6: 556.1 | I6: GBP | J6: 74.09 | K6: SYS 330 TILE STEEL 1199mm X 300mm 1522 10 RAL 9016 20% WRAPPED 16 80 KG SQUARE | L6: Sam James | M6: London | N6: QUEEN VICTORIA STREET NO 160 FLRS G-1 LONDON | O6: =IF(G6<0.03,"",J6) -> 74.09 | P6: =+F6/H6 -> 74.089013
A7: QL-0284470 | B7: 2142 | C7: GBP | D7: 26.65 | E7: GBP | F7: 57084.3 | G7: 0.36 | H7: 770.48 | I7: GBP | J7: 74.09 | K7: SYS 330 TILE STEEL 1199mm X 300mm 1522 10 RAL 9016 20% WRAPPED 16 80 KG SQUARE | L7: Sam James | M7: London | N7: QUEEN VICTORIA STREET NO 160 FLRS G-1 LONDON | O7: =IF(G7<0.03,"",J7) -> 74.09 | P7: =+F7/H7 -> 74.089269

Sheet  SQM WK 35
A1: Line Name | B1: Quantity | C1: Net Unit Price Currency | D1: Net Unit Price | E1: Net Total Currency | F1: Net Total | G1: Item SQM | H1: Line SQM | I1: Â£/SQM Currency | J1: Â£/SQM | K1: Description | L1: Project Owner: Full Name | M1: Sales Region | N1: Project Name | O1: =AVERAGE(O2:O87) -> 150.0293 | P1: =AVERAGE(P2:P87) -> 149.99556
A2: QL-0281573 | B2: 134 | C2: GBP | D2: 37.38 | E2: GBP | F2: 5008.92 | G2: 0.58 | H2: 77.05 | I2: GBP | J2: 65.01 | K2: SYS 330 TILE STEEL 1150mm X 500mm 1522 10 RAL 7035 30% WRAPPED 16 80 KG SQUARE | L2: David Baylis | M2: North | N2: COBALT HOUSING LOWER HOUSE LANE LIVERPOOL | O2: =IF(G2<0.03,"",J2) -> 65.01 | P2: =+F2/H2 -> 65.008696
A3: QL-0281572 | B3: 420 | C3: GBP | D3: 48.75 | E3: GBP | F3: 20475 | G3: 0.75 | H3: 315 | I3: GBP | J3: 65 | K3: SYS 330 TILE STEEL 1500mm X 500mm 1522 10 RAL 7035 30% WRAPPED 16 80 KG SQUARE | L3: David Baylis | M3: North | N3: COBALT HOUSING LOWER HOUSE LANE LIVERPOOL | O3: =IF(G3<0.03,"",J3) -> 65 | P3: =+F3/H3 -> 65
A4: QL-0283814 | B4: 10 | C4: GBP | D4: 62.13 | E4: GBP | F4: 621.3 | G4: 0.72 | H4: 7.2 | I4: GBP | J4: 86.29 | K4: SYS 330 TILE STEEL 1200mm X 600mm 1003 OVERALL HIGH PERFORMANCE INFILL SQUARE FINISH RAL 230 50 10, 30% | L4: Emily Judges | M4: London | N4: BROMPTON ROAD NO 161 OFFICE REFURB LONDON | O4: =IF(G4<0.03,"",J4) -> 86.29 | P4: =+F4/H4 -> 86.291667
A5: QL-0283856 | B5: 5 | C5: GBP | D5: 62.13 | E5: GBP | F5: 310.65 | G5: 0.72 | H5: 3.6 | I5: GBP | J5: 86.29 | K5: SYS 330 TILE STEEL 1200mm X 600mm 1003 OVERALL HIGH PERFORMANCE INFILL SQUARE FINISH RAL 230 50 10, 30% | L5: Emily Judges | M5: London | N5: BROMPTON ROAD NO 161 OFFICE REFURB LONDON | O5: =IF(G5<0.03,"",J5) -> 86.29 | P5: =+F5/H5 -> 86.291667
A6: QL-0283896 | B6: 7 | C6: GBP | D6: 62.13 | E6: GBP | F6: 434.91 | G6: 0.72 | H6: 5.04 | I6: GBP | J6: 86.29 | K6: SYS 330 TILE STEEL 1200mm X 600mm 1003 OVERALL HIGH PERFORMANCE INFILL SQUARE FINISH RAL 230 50 10, 30% | L6: Emily Judges | M6: London | N6: BROMPTON ROAD NO 161 OFFICE REFURB LONDON | O6: =IF(G6<0.03,"",J6) -> 86.29 | P6: =+F6/H6 -> 86.291667
A7: QL-0272926 | B7: 2196 | C7: GBP | D7: 27.02 | E7: GBP | F7: 59335.92 | G7: 0.36 | H7: 790.56 | I7: GBP | J7: 75.06 | K7: SYS 330 TILE STEEL 1200mm X 300mm 1522 10 RAL 9010 20% WRAPPED 16 80 KG SQUARE | L7: Emily Judges | M7: London | N7: THAVIES INN HOUSE HOLBORN CIRCUS NO 1 LONDON | O7: =IF(G7<0.03,"",J7) -> 75.06 | P7: =+F7/H7 -> 75.055556
A8: QL-0272943 | B8: 4597 | C8: GBP | D8: 173.88 | E8: GBP | F8: 799326.36 | G8: 0.64 | H8: 2960.47 | I8: GBP | J8: 270 | K8: SYS 330 TILE STEEL 1120mm X 575mm 3939 OVERALL WRAPPED 16 80 KG FABRIC TILE BLAZER DARTMOUTH | L8: Emily Judges | M8: London | N8: THAVIES INN HOUSE HOLBORN CIRCUS NO 1 LONDON | O8: =IF(G8<0.03,"",J8) -> 270 | P8: =+F8/H8 -> 269.99982
A9: QL-0272960 | B9: 18 | C9: GBP | D9: 199.64 | E9: GBP | F9: 3593.52 | G9: 0.64 | H9: 11.59 | I9: GBP | J9: 310 | K9: SYS 330 TILE STEEL 1120mm X 575mm 3939 OVERALL WRAPPED 16 80 KG FABRIC TILE BLAZER DARTMOUTH C/W CURVED NOTCH L/H S15 | L9: Emily Judges | M9: London | N9: THAVIES INN HOUSE HOLBORN CIRCUS NO 1 LONDON | O9: =IF(G9<0.03,"",J9) -> 310 | P9: =+F9/H9 -> 310.05349
A10: QL-0272959 | B10: 9 | C10: GBP | D10: 136.07 | E10: GBP | F10: 1224.63 | G10: 0.47 | H10: 4.22 | I10: GBP | J10: 290 | K10: SYS 330 TILE STEEL 816mm X 575mm 3939 OVERALL WRAPPED 16 80 KG FABRIC TILE BLAZER DARTMOUTH TRIANGULAR TILE S14 | L10: Emily Judges | M10: London | N10: THAVIES INN HOUSE HOLBORN CIRCUS NO 1 LONDON | O10: =IF(G10<0.03,"",J10) -> 290 | P10: =+F10/H10 -> 290.19668
A11: QL-0272958 | B11: 9 | C11: GBP | D11: 75.6 | E11: GBP | F11: 680.4 | G11: 0.28 | H11: 2.52 | I11: GBP | J11: 270 | K11: SYS 330 TILE STEEL 1120mm X 250mm 3939 OVERALL WRAPPED 16 80 KG FABRIC TILE BLAZER DARTMOUTH S13 | L11: Emily Judges | M11: London | N11: THAVIES INN HOUSE HOLBORN CIRCUS NO 1 LONDON | O11: =IF(G11<0.03,"",J11) -> 270 | P11: =+F11/H11 -> 270
A12: QL-0272957 | B12: 1 | C12: GBP | D12: 289.07 | E12: GBP | F12: 289.07 | G12: 1 | H12: 1 | I12: GBP | J12: 290 | K12: SYS 330 TILE STEEL 890mm X 1120mm 3939 OVERALL WRAPPED 16 80 KG FABRIC TILE BLAZER DARTMOUTH TRAPEZOIDAL TILE S12 | L12: Emily Judges | M12: London | N12: THAVIES INN HOUSE HOLBORN CIRCUS NO 1 LONDON | O12: =IF(G12<0.03,"",J12) -> 290 | P12: =+F12/H12 -> 289.07
A13: QL-0272964 | B13: 8 | C13: GBP | D13: 323.18 | E13: GBP | F13: 2585.44 | G13: 1.11 | H13: 8.92 | I13: GBP | J13: 290 | K13: SYS 330 TILE STEEL 1120mm X 995mm 3939 OVERALL WRAPPED 16 80 KG FABRIC TILE BLAZER DARTMOUTH TRAPEZOIDAL TILE S19 | L13: Emily Judges | M13: London | N13: THAVIES INN HOUSE HOLBORN CIRCUS NO 1 LONDON | O13: =IF(G13<0.03,"",J13) -> 290 | P13: =+F13/H13 -> 289.84753
... A87: QL-0278407 | B87: 1012 | C87: GBP | D87: 32.39 | E87: GBP | F87: 32778.68 | G87: 0.38 | H87: 379.5 | I87: GBP | J87: 86.37 | K87: SYS 330 TILE STEEL 1500mm X 250mm 2227 OVERALL RAL 9016 20% WRAPPED 16 80 KG SQUARE 40mm DEEP | L87: Peter Gray | M87: London | N87: SOUTH MOLTON TRIANGLE DEVELOPMENT NORTH BLOCK LONDON | O87: =IF(G87<0.03,"",J87) -> 86.37 | P87: =+F87/H87 -> 86.373333

Sheet SQM WK 34
A1: Line Name | B1: Quantity | C1: Net Unit Price Currency | D1: Net Unit Price | E1: Net Total Currency | F1: Net Total | G1: Item SQM | H1: Line SQM | I1: Â£/SQM Currency | J1: Â£/SQM | K1: Description | L1: Project Owner: Full Name | M1: Sales Region | N1: Project Name | O1: =AVERAGE(O2:O33) -> 63.224062 | P1: =AVERAGE(P2:P33) -> 63.224042
A2: QL-0274314 | B2: 1330 | C2: GBP | D2: 26.15 | E2: GBP | F2: 34779.5 | G2: 0.45 | H2: 598.5 | I2: GBP | J2: 58.11 | K2: SYS 330 TILE STEEL 1500mm X 300mm 1522 10 RAL 9010 20% WRAPPED 16 80 KG SQUARE | L2: Becky Titley | M2: North | N2: DARLINGTON ECONOMIC CAMPUS BRUNSWICK ST DARLINGTON | O2: =IF(G2<0.03,"",J2) -> 58.11 | P2: =+F2/H2 -> 58.111111
A3: QL-0276356 | B3: 86 | C3: GBP | D3: 45.73 | E3: GBP | F3: 3932.78 | G3: 0.72 | H3: 61.92 | I3: GBP | J3: 63.51 | K3: SYS 330 TILE STEEL 1200mm X 600mm 1147 35 BLACK ADHESIVE TISSUE SQUARE FINISH SUNSET COPPER Y225G1 D2525 | L3: David Baylis | M3: North | N3: THE FAIRFAX PHASE 1 RESIDENTIAL MANCHESTER | O3: =IF(G3<0.03,"",J3) -> 63.51 | P3: =+F3/H3 -> 63.513889
A4: QL-0274280 | B4: 10 | C4: GBP | D4: 37.74 | E4: GBP | F4: 377.4 | G4: 0.56 | H4: 5.55 | I4: GBP | J4: 68 | K4: SYS 330 TILE STEEL 1850mm X 300mm PLAIN RAL 9010 20% WRAPPED 16 80 KG SQUARE | L4: Emily Judges | M4: London | N4: ADMIRALTY ARCH WALDORF ASTORIA HOTEL LONDON | O4: =IF(G4<0.03,"",J4) -> 68 | P4: =+F4/H4 -> 68
A5: QL-0274279 | B5: 10 | C5: GBP | D5: 25.5 | E5: GBP | F5: 255 | G5: 0.38 | H5: 3.75 | I5: GBP | J5: 68 | K5: SYS 330 TILE STEEL 1250mm X 300mm PLAIN RAL 9010 20% WRAPPED 16 80 KG SQUARE | L5: Emily Judges | M5: London | N5: ADMIRALTY ARCH WALDORF ASTORIA HOTEL LONDON | O5: =IF(G5<0.03,"",J5) -> 68 | P5: =+F5/H5 -> 68
A6: QL-0274278 | B6: 10 | C6: GBP | D6: 42.02 | E6: GBP | F6: 420.2 | G6: 0.62 | H6: 6.18 | I6: GBP | J6: 67.99 | K6: SYS 330 TILE STEEL 2060mm X 300mm PLAIN RAL 9010 20% WRAPPED 16 80 KG SQUARE | L6: Emily Judges | M6: London | N6: ADMIRALTY ARCH WALDORF ASTORIA HOTEL LONDON | O6: =IF(G6<0.03,"",J6) -> 67.99 | P6: =+F6/H6 -> 67.993528
A7: QL-0274277 | B7: 10 | C7: GBP | D7: 38.76 | E7: GBP | F7: 387.6 | G7: 0.57 | H7: 5.7 | I7: GBP | J7: 68 | K7: SYS 330 TILE STEEL 1900mm X 300mm PLAIN RAL 9010 20% WRAPPED 16 80 KG SQUARE | L7: Emily Judges | M7: London | N7: ADMIRALTY ARCH WALDORF ASTORIA HOTEL LONDON | O7: =IF(G7<0.03,"",J7) -> 68 | P7: =+F7/H7 -> 68
A8: QL-0270729 | B8: 1150 | C8: GBP | D8: 61.55 | E8: GBP | F8: 70782.5 | G8: 0.81 | H8: 931.5 | I8: GBP | J8: 75.99 | K8: SYS 330 TILE STEEL 1350mm X 600mm 1522 10 RAL 9016 20% WRAPPED 16 80 KG SQUARE | L8: Jack Wingfield | M8: London | N8: BEDFONT LAKES BUILDING 11 CISCO FELTHAM LONDON | O8: =IF(G8<0.03,"",J8) -> 75.99 | P8: =+F8/H8 -> 75.987654
A9: QL-0270722 | B9: 1092 | C9: GBP | D9: 30.78 | E9: GBP | F9: 33611.76 | G9: 0.41 | H9: 442.26 | I9: GBP | J9: 76 | K9: SYS 330 TILE STEEL 1350mm X 300mm 1522 10 RAL 9016 20% WRAPPED 16 80 KG SQUARE | L9: Jack Wingfield | M9: London | N9: BEDFONT LAKES BUILDING 11 CISCO FELTHAM LONDON | O9: =IF(G9<0.03,"",J9) -> 76 | P9: =+F9/H9 -> 76
A10: QL-0275433 | B10: 120 | C10: GBP | D10: 31.39 | E10: GBP | F10: 3766.8 | G10: 0.42 | H10: 50.4 | I10: GBP | J10: 74.74 | K10: SYS 330 TILE STEEL 1400mm X 300mm 1522 10 RAL 9010 20% WRAPPED 16 80 KG SQUARE | L10: Jack Wingfield | M10: London | N10: QUEENSBERRY HOUSE OLD BURLINGTON STREET NO 3 MOCK UP LONDON | O10: =IF(G10<0.03,"",J10) -> 74.74 | P10: =+F10/H10 -> 74.738095
A11: QL-0275417 | B11: 48 | C11: GBP | D11: 24.66 | E11: GBP | F11: 1183.68 | G11: 0.33 | H11: 15.84 | I11: GBP | J11: 74.73 | K11: SYS 330 TILE STEEL 1100mm X 300mm 1522 10 RAL 9010 20% WRAPPED 18 80 KG SQUARE | L11: Jack Wingfield | M11: London | N11: QUEENSBERRY HOUSE OLD BURLINGTON STREET NO 3 MOCK UP LONDON | O11: =IF(G11<0.03,"",J11) -> 74.73 | P11: =+F11/H11 -> 74.727273
A12: QL-0272685 | B12: 1515 | C12: GBP | D12: 34.71 | E12: GBP | F12: 52585.65 | G12: 0.36 | H12: 551.76 | I12: GBP | J12: 95.3 | K12: SYS 330 TILE 1213 X 300MM D1522 10 RAL 9010 20% WRAPPED 16 80 KG SQUARE | L12: Nick Drake | M12: Midlands | N12: ONE COLMORE SQUARE FLR 8 BIRMINGHAM | O12: =IF(G12<0.03,"",J12) -> 95.3 | P12: =+F12/H12 -> 95.305296
A13: QL-0277300 | B13: 2487 | C13: GBP | D13: 23.82 | E13: GBP | F13: 59240.34 | G13: 0.36 | H13: 895.32 | I13: GBP | J13: 66.17 | K13: SYS 330 TILE STEEL 1200mm X 300mm 1522 10 RAL 9010 20% WRAPPED 16 80 KG | L13: Nick Drake | M13: Northern Home Counties | N13: STATION ROAD NO 21 FLRS 4 & 5 CAMBRIDGE | O13: =IF(G13<0.03,"",J13) -> 66.17 | P13: =+F13/H13 -> 66.166667
... A67: QL-0284470 | B67: 2142 | C67: GBP | D67: 26.65 | E67: GBP | F67: 57084.3 | G67: 0.36 | H67: 770.48 | I67: GBP | J67: 74.09 | K67: SYS 330 TILE STEEL 1199mm X 300mm 1522 10 RAL 9016 20% WRAPPED 16 80 KG SQUARE | L67: Sam James | M67: London | N67: QUEEN VICTORIA STREET NO 160 FLRS G-1 LONDON | O67: =IF(G67<0.03,"",J67) -> 74.09 | P67: =+F67/H67 -> 74.089269

Sheet SQM WK33
A1: Line Name | B1: Quantity | C1: Net Unit Price Currency | D1: Net Unit Price | E1: Net Total Currency | F1: Net Total | G1: Item SQM | H1: Line SQM | I1: Â£/SQM Currency | J1: Â£/SQM | K1: Description | L1: Project Owner: Full Name | M1: Sales Region | N1: Project Name | O1: =AVERAGE(O2:O33) -> 77.475625 | P1: =AVERAGE(P2:P33) -> 77.471612
A2: QL-0269106 | B2: 113 | C2: GBP | D2: 19.39 | E2: GBP | F2: 2191.07 | G2: 0.35 | H2: 39.83 | I2: GBP | J2: 55.01 | K2: SYS 330 TILE STEEL 1175mm X 300mm 1522 10 RAL 9010 20% WRAPPED 16 80 KG SQUARE | L2: Becky Titley | M2: North | N2: CITY GATE 1 GROUND 4TH & 5TH FLOORS NEWCASTLE | O2: =IF(G2<0.03,"",J2) -> 55.01 | P2: =+F2/H2 -> 55.010545
A3: QL-0268724 | B3: 1389 | C3: GBP | D3: 45.06 | E3: GBP | F3: 62588.34 | G3: 0.72 | H3: 1000.08 | I3: GBP | J3: 62.58 | K3: SYS 330 TILE GALV 1200mm X 600mm 1522 10 RAL 9010 20% WRAPPED 16 80 KG SQUARE | L3: David Baylis | M3: North | N3: LISBON STREET STUDENT ACCOMMODATION LEEDS | O3: =IF(G3<0.03,"",J3) -> 62.58 | P3: =+F3/H3 -> 62.583333
A4: QL-0268718 | B4: 1389 | C4: GBP | D4: 40.28 | E4: GBP | F4: 55948.92 | G4: 0.72 | H4: 1000.08 | I4: GBP | J4: 55.94 | K4: SYS 330 TILE GALV 1200mm X 600mm 1522 10 RAL 9010 20% BLACK ADHESIVE TISSUE SQUARE | L4: David Baylis | M4: North | N4: LISBON STREET STUDENT ACCOMMODATION LEEDS | O4: =IF(G4<0.03,"",J4) -> 55.94 | P4: =+F4/H4 -> 55.944444
A5: QL-0273041 | B5: 10 | C5: GBP | D5: 39.88 | E5: GBP | F5: 398.8 | G5: 0.36 | H5: 3.6 | I5: GBP | J5: 110.78 | K5: SYS 330 TILE 1199 X 300MM S1820 10 RAL 9010 20% WRAPPED 16 80 KG SQUARE | L5: Emily Judges | M5: London | N5: PALMER STREET NO 21 ASTICUS BUILDING NESO LONDON | O5: =IF(G5<0.03,"",J5) -> 110.78 | P5: =+F5/H5 -> 110.77778
A6: QL-0273042 | B6: 10 | C6: GBP | D6: 39.88 | E6: GBP | F6: 398.8 | G6: 0.36 | H6: 3.6 | I6: GBP | J6: 110.78 | K6: SYS 330 TILE 1194 x 297mm S1820 10 RAL 9010 20% WRAPPED 18 80 KG SQUARE | L6: Emily Judges | M6: London | N6: PALMER STREET NO 21 ASTICUS BUILDING NESO LONDON | O6: =IF(G6<0.03,"",J6) -> 110.78 | P6: =+F6/H6 -> 110.77778
A7: QL-0268694 | B7: 230 | C7: GBP | D7: 49.88 | E7: GBP | F7: 11472.4 | G7: 0.71 | H7: 163.88 | I7: GBP | J7: 70.01 | K7: SYS 330 TILE 1424 x 500mm S1820 20 RAL 9010 FT WRAPPED 18 80 KG SQUARE | L7: Eurshell Fearon | M7: Midlands | N7: SNOW HILL BLDG 2 BIRMINGHAM | O7: =IF(G7<0.03,"",J7) -> 70.01 | P7: =+F7/H7 -> 70.004882
A8: QL-0268700 | B8: 20 | C8: GBP | D8: 34.56 | E8: GBP | F8: 691.2 | G8: 0.29 | H8: 5.7 | I8: GBP | J8: 121.26 | K8: SYS 330 TILE 1424 x 200mm S1820 20 RAL 9010 FT WRAPPED 18 80 KG SQUARE | L8: Eurshell Fearon | M8: Midlands | N8: SNOW HILL BLDG 2 BIRMINGHAM | O8: =IF(G8<0.03,"",J8) -> 121.26 | P8: =+F8/H8 -> 121.26316
A9: QL-0270653 | B9: 110 | C9: GBP | D9: 33.75 | E9: GBP | F9: 3712.5 | G9: 0.45 | H9: 49.5 | I9: GBP | J9: 75 | K9: SYS 330 TILE 1499 x 300mm 5149 15 RAL 9010 20% WRAPPED 16 80 KG SQUARE | L9: Jack Turnbull | M9: London | N9: BISHOPSGATE NO 8 FLOOR 36 JB DRAX FITOUT LONDON | O9: =IF(G9<0.03,"",J9) -> 75 | P9: =+F9/H9 -> 75
A10: QL-0269269 | B10: 452 | C10: GBP | D10: 23.4 | E10: GBP | F10: 10576.8 | G10: 0.36 | H10: 162.72 | I10: GBP | J10: 65 | K10: SYS 330 TILE STEEL 1200mm X 300mm 1522 10 RAL 9016 20% BLACK ADHESIVE TISSUE SQUARE | L10: Jack Turnbull | M10: London | N10: ORION HOUSE UPPER ST MARTINS LANE FLRS 12-15 LONDON | O10: =IF(G10<0.03,"",J10) -> 65 | P10: =+F10/H10 -> 65
A11: QL-0269277 | B11: 312 | C11: GBP | D11: 23.4 | E11: GBP | F11: 7300.8 | G11: 0.36 | H11: 112.32 | I11: GBP | J11: 65 | K11: SYS 330 TILE STEEL 1200mm X 300mm 1522 10 RAL 9016 20% BLACK ADHESIVE TISSUE SQUARE | L11: Jack Turnbull | M11: London | N11: ORION HOUSE UPPER ST MARTINS LANE FLRS 12-15 LONDON | O11: =IF(G11<0.03,"",J11) -> 65 | P11: =+F11/H11 -> 65
A12: QL-0269262 | B12: 854 | C12: GBP | D12: 23.4 | E12: GBP | F12: 19983.6 | G12: 0.36 | H12: 307.44 | I12: GBP | J12: 65 | K12: SYS 330 TILE STEEL 1200mm X 300mm 1522 10 RAL 9016 20% BLACK ADHESIVE TISSUE SQUARE | L12: Jack Turnbull | M12: London | N12: ORION HOUSE UPPER ST MARTINS LANE FLRS 12-15 LONDON | O12: =IF(G12<0.03,"",J12) -> 65 | P12: =+F12/H12 -> 65
A13: QL-0272057 | B13: 16154 | C13: GBP | D13: 26.46 | E13: GBP | F13: 427434.84 | G13: 0.36 | H13: 5815.44 | I13: GBP | J13: 73.5 | K13: SYS 330 TILE STEEL 1200mm X 300mm 1522 10 RAL 9010 20% WRAPPED 16 80 KG SQUARE | L13: Jack Turnbull | M13: London | N13: OXFORD ROAD NO 97 PROSPECT HOUSE CAT A LONDON | O13: =IF(G13<0.03,"",J13) -> 73.5 | P13: =+F13/H13 -> 73.5
... A63: QL-0271404 | B63: 12 | C63: GBP | D63: 96.28 | E63: GBP | F63: 1155.36 | G63: 0.58 | H63: 6.98 | I63: GBP | J63: 165.42 | K63: SYS 330 TILE 1503 x 387mm 25 WRAPPED 16 80 KG SQUARE C/W GLASS FIBRE FLEECE - BESPOKE FLUTED PERF WITH PLAIN ZONE - FINISH: INTERPON ANODIC YW201E (METALLIC MATT) | L63: Sam James | M63: London | N63: STEPHEN STREET NO 1-2 FLOOR 9 & 10 ADDITIONALS LONDON | O63: =IF(G63<0.03,"",J63) -> 165.42 | P63: =+F63/H63 -> 165.52436

Sheet SQM WK32
A1: Line Name | B1: Quantity | C1: Net Unit Price Currency | D1: Net Unit Price | E1: Net Total Currency | F1: Net Total | G1: Item SQM | H1: Line SQM | I1: Â£/SQM Currency | J1: Â£/SQM | K1: Description | L1: Project Owner: Full Name | M1: Sales Region | N1: Project Name | O1: =AVERAGE(O2:O33) -> 69.103333 | P1: =AVERAGE(P2:P33) -> 69.102027
A2: QL-0263983 | B2: 153 | C2: GBP | D2: 29.15 | E2: GBP | F2: 4459.95 | G2: 0.55 | H2: 84.15 | I2: GBP | J2: 53 | K2: SYS 330 TILE STEEL 1100mm X 500mm PLAIN RAL 9010 FT NO INFILL SQUARE | L2: Becky Titley | M2: Scotland | N2: QUEENSFERRY STREET NO 1-8 HOTEL EDINBURGH | O2: =IF(G2<0.03,"",J2) -> 53 | P2: =+F2/H2 -> 53
A3: QL-0263976 | B3: 920 | C3: GBP | D3: 23.85 | E3: GBP | F3: 21942 | G3: 0.45 | H3: 414 | I3: GBP | J3: 53 | K3: SYS 330 TILE STEEL 900mm X 500mm PLAIN RAL 9010 FT NO INFILL SQUARE | L3: Becky Titley | M3: Scotland | N3: QUEENSFERRY STREET NO 1-8 HOTEL EDINBURGH | O3: =IF(G3<0.03,"",J3) -> 53 | P3: =+F3/H3 -> 53
A4: QL-0266891 | B4: 150 | C4: GBP | D4: 16.2 | E4: GBP | F4: 2430 | G4: 0.27 | H4: 40.5 | I4: GBP | J4: 60 | K4: SYS 330 TILE STEEL 900mm X 300mm 3136 15 RAL 9010 20% WRAPPED 16 80 KG SQUARE | L4: David Fry | M4: South West | N4: BRISTOL AIRPORT TERMINAL TRANSFORMATION EXTENSIONS | O4: =IF(G4<0.03,"",J4) -> 60 | P4: =+F4/H4 -> 60
A5: QL-0265393 | B5: 1168 | C5: GBP | D5: 21.47 | E5: GBP | F5: 25076.96 | G5: 0.3 | H5: 350.4 | I5: GBP | J5: 71.57 | K5: SYS 330 TILE STEEL 1000mm X 300mm 1522 10 RAL 9010 20% WRAPPED 16 80 KG SQUARE | L5: Eurshell Fearon | M5: London | N5: SLOANE SQUARE HOUSE FLOORS 1-2 CEG LONDON | O5: =IF(G5<0.03,"",J5) -> 71.57 | P5: =+F5/H5 -> 71.566667
A6: QL-0264143 | B6: 360 | C6: GBP | D6: 22.62 | E6: GBP | F6: 8143.2 | G6: 0.36 | H6: 129.6 | I6: GBP | J6: 62.83 | K6: SYS 330 TILE STEEL 1200mm X 300mm PLAIN RAL 5017 NO INFILL SQUARE | L6: Jack Turnbull | M6: London | N6: CANARY WHARF BANK STREET NO 50 BUPA FLOOR G-1 LONDON | O6: =IF(G6<0.03,"",J6) -> 62.83 | P6: =+F6/H6 -> 62.833333
A7: QL-0264147 | B7: 140 | C7: GBP | D7: 21.6 | E7: GBP | F7: 3024 | G7: 0.36 | H7: 50.4 | I7: GBP | J7: 60 | K7: SYS 330 TILE STEEL 1200mm X 300mm PLAIN RAL 9010 20% NO INFILL SQUARE | L7: Jack Turnbull | M7: London | N7: CANARY WHARF BANK STREET NO 50 BUPA FLOOR G-1 LONDON | O7: =IF(G7<0.03,"",J7) -> 60 | P7: =+F7/H7 -> 60
A8: QL-0264154 | B8: 290 | C8: GBP | D8: 18 | E8: GBP | F8: 5220 | G8: 0.3 | H8: 87 | I8: GBP | J8: 60 | K8: SYS 330 TILE STEEL 1000mm X 300mm PLAIN RAL 9010 20% NO INFILL SQUARE | L8: Jack Turnbull | M8: London | N8: CANARY WHARF BANK STREET NO 50 BUPA FLOOR G-1 LONDON | O8: =IF(G8<0.03,"",J8) -> 60 | P8: =+F8/H8 -> 60
A9: QL-0264668 | B9: 9 | C9: GBP | D9: 92.81 | E9: GBP | F9: 835.29 | G9: 1.24 | H9: 11.14 | I9: GBP | J9: 75 | K9: SYS 330 TILE 1499 X 825MM D1522 10 RAL 9010 20% WRAPPED 16 80 KG SQUARE | L9: Jack Turnbull | M9: London | N9: NOVA VICTORIA BUILDING 6A N2 BRESSENDEN PLACE CAT A LONDON | O9: =IF(G9<0.03,"",J9) -> 75 | P9: =+F9/H9 -> 74.981149
A10: QL-0264667 | B10: 72 | C10: GBP | D10: 67.5 | E10: GBP | F10: 4860 | G10: 0.9 | H10: 64.8 | I10: GBP | J10: 75 | K10: SYS 330 TILE 1499 X 600MM D1522 10 RAL 9010 20% WRAPPED 16 80 KG SQUARE | L10: Jack Turnbull | M10: London | N10: NOVA VICTORIA BUILDING 6A N2 BRESSENDEN PLACE CAT A LONDON | O10: =IF(G10<0.03,"",J10) -> 75 | P10: =+F10/H10 -> 75
A11: QL-0264797 | B11: 4 | C11: GBP | D11: 67.5 | E11: GBP | F11: 270 | G11: 0.9 | H11: 3.6 | I11: GBP | J11: 75 | K11: SYS 330 TILE 1499 X 600MM D1522 10 RAL 9010 20% WRAPPED 16 80 KG SQUARE | L11: Jack Turnbull | M11: London | N11: NOVA VICTORIA BUILDING 6A N2 BRESSENDEN PLACE CAT A LONDON | O11: =IF(G11<0.03,"",J11) -> 75 | P11: =+F11/H11 -> 75
A12: QL-0264681 | B12: 24 | C12: GBP | D12: 67.5 | E12: GBP | F12: 1620 | G12: 0.9 | H12: 21.6 | I12: GBP | J12: 75 | K12: SYS 330 TILE 1499 X 600MM D1522 10 RAL 9010 20% WRAPPED 16 80 KG SQUARE | L12: Jack Turnbull | M12: London | N12: NOVA VICTORIA BUILDING 6A N2 BRESSENDEN PLACE CAT A LONDON | O12: =IF(G12<0.03,"",J12) -> 75 | P12: =+F12/H12 -> 75
A13: QL-0264675 | B13: 36 | C13: GBP | D13: 67.5 | E13: GBP | F13: 2430 | G13: 0.9 | H13: 32.4 | I13: GBP | J13: 75 | K13: SYS 330 TILE 1499 X 600MM D1522 10 RAL 9010 20% WRAPPED 16 80 KG SQUARE | L13: Jack Turnbull | M13: London | N13: NOVA VICTORIA BUILDING 6A N2 BRESSENDEN PLACE CAT A LONDON | O13: =IF(G13<0.03,"",J13) -> 75 | P13: =+F13/H13 -> 75
... A25: QL-0264561 | B25: 1546 | C25: GBP | D25: 26.65 | E25: GBP | F25: 41200.9 | G25: 0.36 | H25: 556.1 | I25: GBP | J25: 74.09 | K25: SYS 330 TILE STEEL 1199mm X 300mm 1522 10 RAL 9016 20% WRAPPED 16 80 KG SQUARE | L25: Sam James | M25: London | N25: QUEEN VICTORIA STREET NO 160 FLRS G-1 LONDON | O25: =IF(G25<0.03,"",J25) -> 74.09 | P25: =+F25/H25 -> 74.089013

Sheet SQM WK31
A1: Line Name | B1: Quantity | C1: Net Unit Price Currency | D1: Net Unit Price | E1: Net Total Currency | F1: Net Total | G1: Item SQM | H1: Line SQM | I1: Â£/SQM Currency | J1: Â£/SQM | K1: Description | L1: Project Owner: Full Name | M1: Sales Region | N1: Project Name | O1: =AVERAGE(O2:O33) -> 103.18844 | P1: =AVERAGE(P2:P33) -> 103.34037
A2: QL-0249817 | B2: 1069 | C2: GBP | D2: 35.54 | E2: GBP | F2: 37992.26 | G2: 0.45 | H2: 481.05 | I2: GBP | J2: 78.98 | K2: SYS 330 TILE STEEL 1500mm X 300mm 1522 10 RAL 9010 20% WRAPPED 16 80 KG SQUARE | L2: Becky Titley | M2: North | N2: DARLINGTON ECONOMIC CAMPUS BRUNSWICK ST DARLINGTON | O2: =IF(G2<0.03,"",J2) -> 78.98 | P2: =+F2/H2 -> 78.977778
A3: QL-0249815 | B3: 1660 | C3: GBP | D3: 66.33 | E3: GBP | F3: 110107.8 | G3: 0.84 | H3: 1394.4 | I3: GBP | J3: 78.96 | K3: SYS 330 TILE STEEL 1200mm X 700mm 1522 10 RAL 9010 20% WRAPPED 16 80 KG SQUARE | L3: Becky Titley | M3: North | N3: DARLINGTON ECONOMIC CAMPUS BRUNSWICK ST DARLINGTON | O3: =IF(G3<0.03,"",J3) -> 78.96 | P3: =+F3/H3 -> 78.964286
A4: QL-0249810 | B4: 324 | C4: GBP | D4: 56.86 | E4: GBP | F4: 18422.64 | G4: 0.72 | H4: 233.28 | I4: GBP | J4: 78.97 | K4: SYS 330 TILE STEEL 1200mm X 600mm 1522 10 RAL 9010 20% WRAPPED 16 80 KG SQUARE | L4: Becky Titley | M4: North | N4: DARLINGTON ECONOMIC CAMPUS BRUNSWICK ST DARLINGTON | O4: =IF(G4<0.03,"",J4) -> 78.97 | P4: =+F4/H4 -> 78.972222
A5: QL-0262885 | B5: 12 | C5: GBP | D5: 57.52 | E5: GBP | F5: 690.24 | G5: 0.86 | H5: 10.34 | I5: GBP | J5: 66.76 | K5: SYS 330 TILE 2094 x 411.25mm 1810 10 MW616i WRAPPED 16 80 KG SQUARE 10mm OUT-TURNS - FINISH: PPC INTERPON 310 MW616i CHROMIUM - SEE DRG | L5: Becky Titley | M5: Scotland | N5: CITY POINT L1 AND LGF HAYMARKET TERRACE NO 65 EDINBURGH | O5: =IF(G5<0.03,"",J5) -> 66.76 | P5: =+F5/H5 -> 66.754352
A6: QL-0262890 | B6: 2 | C6: GBP | D6: 51.85 | E6: GBP | F6: 103.7 | G6: 0.38 | H6: 0.75 | I6: GBP | J6: 137.56 | K6: SYS 330 TILE STEEL 2094mm X 180mm PLAIN MW616i SYS 330 TILE 2094 x 180mm PLAIN MW616i RECT FLG R/F APT 1995 x 55mm CENTRAL SQUARE 10mm OUT-TURNS - FINISH: PPC INTERPON 310 MW616i CHROMIUM - SEE DRG | L6: Becky Titley | M6: Scotland | N6: CITY POINT L1 AND LGF HAYMARKET TERRACE NO 65 EDINBURGH | O6: =IF(G6<0.03,"",J6) -> 137.56 | P6: =+F6/H6 -> 138.26667
A7: QL-0262896 | B7: 16 | C7: GBP | D7: 58.2 | E7: GBP | F7: 931.2 | G7: 0.87 | H7: 13.94 | I7: GBP | J7: 66.79 | K7: SYS 330 TILE STEEL 2119mm X 411.25mm 1810 10 MW616i WRAPPED 16 80 KG SQUARE 10mm OUT-TURNS - FINISH: PPC INTERPON 310 MW616i CHROMIUM - SEE DRG | L7: Becky Titley | M7: Scotland | N7: CITY POINT L1 AND LGF HAYMARKET TERRACE NO 65 EDINBURGH | O7: =IF(G7<0.03,"",J7) -> 66.79 | P7: =+F7/H7 -> 66.800574
A8: QL-0262894 | B8: 1 | C8: GBP | D8: 41.97 | E8: GBP | F8: 41.97 | G8: 0.27 | H8: 0.27 | I8: GBP | J8: 154.34 | K8: SYS 330 TILE 1825mm X 149mm PLAIN MW616i 15 mm PLAIN MW616i NO INFILL SQUARE INFILL TILE - SUPPORTED ON LONG SIDES - FINISH: PPC INTERPON 310 MW616i CHROMIUM | L8: Becky Titley | M8: Scotland | N8: CITY POINT L1 AND LGF HAYMARKET TERRACE NO 65 EDINBURGH | O8: =IF(G8<0.03,"",J8) -> 154.34 | P8: =+F8/H8 -> 155.44444
A9: QL-0262884 | B9: 1 | C9: GBP | D9: 45.14 | E9: GBP | F9: 45.14 | G9: 0.19 | H9: 0.19 | I9: GBP | J9: 241.71 | K9: SYS 330 TILE 1245 x 149 x 15 mm PLAIN MW616i NO INFILL SQUARE INFILL TILE - SUPPORTED ON LONG SIDES - FINISH: PPC INTERPON 310 MW616i CHROMIUM - SEE DRG | L9: Becky Titley | M9: Scotland | N9: CITY POINT L1 AND LGF HAYMARKET TERRACE NO 65 EDINBURGH | O9: =IF(G9<0.03,"",J9) -> 241.71 | P9: =+F9/H9 -> 237.57895
A10: QL-0262902 | B10: 18 | C10: GBP | D10: 63.09 | E10: GBP | F10: 1135.62 | G10: 0.94 | H10: 17 | I10: GBP | J10: 66.79 | K10: SYS 330 TILE STEEL 2094mm X 451.11mm 1810 10 MW616i WRAPPED 16 80 KG SQUARE 10mm OUT-TURNS - FINISH: PPC INTERPON 310 MW616i CHROMIUM - SEE DRG | L10: Becky Titley | M10: Scotland | N10: CITY POINT L1 AND LGF HAYMARKET TERRACE NO 65 EDINBURGH | O10: =IF(G10<0.03,"",J10) -> 66.79 | P10: =+F10/H10 -> 66.801176
A11: QL-0262903 | B11: 2 | C11: GBP | D11: 40.45 | E11: GBP | F11: 80.9 | G11: 0.26 | H11: 0.52 | I11: GBP | J11: 154.34 | K11: SYS 330 TILE STEEL 1758.9mm X 149mm PLAIN MW616i 15 mm MW616i NO INFILL SQUARE INFILL TILE - SUPPORTED ON LONG SIDES - FINISH: PPC INTERPON 310 MW616i CHROMIUM - SEE DRG | L11: Becky Titley | M11: Scotland | N11: CITY POINT L1 AND LGF HAYMARKET TERRACE NO 65 EDINBURGH | O11: =IF(G11<0.03,"",J11) -> 154.34 | P11: =+F11/H11 -> 155.57692
A12: QL-0262826 | B12: 2 | C12: GBP | D12: 25.55 | E12: GBP | F12: 51.1 | G12: 0.21 | H12: 0.43 | I12: GBP | J12: 118.88 | K12: SYS 330 TILE STEEL 1194mm X 180mm PLAIN MW616i SYS 330 TILE PLAIN MW616i RECT FLG R/F APT 1095 x 55mm CENTRAL SQUARE 10mm OUT-TURNS - FINISH: PPC INTERPON 310 MW616i CHROMIUM - SEE DRG | L12: Becky Titley | M12: Scotland | N12: CITY POINT L1 AND LGF HAYMARKET TERRACE NO 65 EDINBURGH | O12: =IF(G12<0.03,"",J12) -> 118.88 | P12: =+F12/H12 -> 118.83721
A13: QL-0262823 | B13: 12 | C13: GBP | D13: 33.14 | E13: GBP | F13: 397.68 | G13: 0.49 | H13: 5.83 | I13: GBP | J13: 68.19 | K13: SYS 330 TILE 1194 x 406.67mm 1810 10 MW616i WRAPPED 16 80 KG SQUARE 10mm OUT-TURNS - FINISH: PPC INTERPON 310 MW616i CHROMIUM - SEE DRG | L13: Becky Titley | M13: Scotland | N13: CITY POINT L1 AND LGF HAYMARKET TERRACE NO 65 EDINBURGH | O13: =IF(G13<0.03,"",J13) -> 68.19 | P13: =+F13/H13 -> 68.212693
... A58: QL-0259460 | B58: 155 | C58: GBP | D58: 25.2 | E58: GBP | F58: 3906 | G58: 0.36 | H58: 55.8 | I58: GBP | J58: 70 | K58: SYS 330 TILE STEEL 1200mm X 300mm 1522 10 RAL 9010 20% WRAPPED 16 80 KG SQUARE | L58: Sam James | M58: South East | N58: UNIT 6A IMPRIMO PARK LOUGHTON | O58: =IF(G58<0.03,"",J58) -> 70 | P58: =+F58/H58 -> 70

Sheet SQM WK30
A1: Line Name | B1: Quantity | C1: Net Unit Price Currency | D1: Net Unit Price | E1: Net Total Currency | F1: Net Total | G1: Item SQM | H1: Line SQM | I1: Â£/SQM Currency | J1: Â£/SQM | K1: Description | L1: Project Owner: Full Name | M1: Sales Region | N1: Project Name | O1: =AVERAGE(O2:O33) -> 68.755625 | P1: =AVERAGE(P2:P33) -> 68.754998
A2: QL-0253222 | B2: 623 | C2: GBP | D2: 23.85 | E2: GBP | F2: 14858.55 | G2: 0.45 | H2: 280.35 | I2: GBP | J2: 53 | K2: SYS 330 TILE STEEL 900mm X 500mm PLAIN RAL 9010 FT NO INFILL SQUARE | L2: Becky Titley | M2: Scotland | N2: QUEENSFERRY STREET NO 1-8 HOTEL EDINBURGH | O2: =IF(G2<0.03,"",J2) -> 53 | P2: =+F2/H2 -> 53
A3: QL-0253218 | B3: 2075 | C3: GBP | D3: 14.31 | E3: GBP | F3: 29693.25 | G3: 0.27 | H3: 560.25 | I3: GBP | J3: 53 | K3: SYS 330 TILE STEEL 900mm X 300mm PLAIN RAL 9010 FT NO INFILL SQUARE | L3: Becky Titley | M3: Scotland | N3: QUEENSFERRY STREET NO 1-8 HOTEL EDINBURGH | O3: =IF(G3<0.03,"",J3) -> 53 | P3: =+F3/H3 -> 53
A4: QL-0253223 | B4: 374 | C4: GBP | D4: 39.75 | E4: GBP | F4: 14866.5 | G4: 0.75 | H4: 280.5 | I4: GBP | J4: 53 | K4: SYS 330 TILE STEEL 1500mm X 500mm PLAIN RAL 9010 FT NO INFILL SQUARE | L4: Becky Titley | M4: Scotland | N4: QUEENSFERRY STREET NO 1-8 HOTEL EDINBURGH | O4: =IF(G4<0.03,"",J4) -> 53 | P4: =+F4/H4 -> 53
A5: QL-0255818 | B5: 556 | C5: GBP | D5: 9.08 | E5: GBP | F5: 5048.48 | G5: 0.18 | H5: 100.08 | I5: GBP | J5: 50.44 | K5: SYS 330 TILE STEEL 600mm X 300mm PLAIN RAL 9010 20% NO INFILL SQUARE | L5: David Baylis | M5: North | N5: ADDRESS TBC OFFICE PROJECT MANCHESTER | O5: =IF(G5<0.03,"",J5) -> 50.44 | P5: =+F5/H5 -> 50.444444
A6: QL-0255816 | B6: 371 | C6: GBP | D6: 13.62 | E6: GBP | F6: 5053.02 | G6: 0.27 | H6: 100.17 | I6: GBP | J6: 50.44 | K6: SYS 330 TILE STEEL 900mm X 300mm PLAIN RAL 9010 20% NO INFILL SQUARE | L6: David Baylis | M6: North | N6: ADDRESS TBC OFFICE PROJECT MANCHESTER | O6: =IF(G6<0.03,"",J6) -> 50.44 | P6: =+F6/H6 -> 50.444444
A7: QL-0256352 | B7: 1246 | C7: GBP | D7: 17.99 | E7: GBP | F7: 22415.54 | G7: 0.33 | H7: 411.18 | I7: GBP | J7: 54.52 | K7: SYS 330 TILE STEEL 1100mm X 300mm 1522 10 RAL 9010 20% BLACK ADHESIVE TISSUE SQUARE (RAL TBC) | L7: David Baylis | M7: North | N7: BANK HOUSE REDEVELOPMENT LEEDS | O7: =IF(G7<0.03,"",J7) -> 54.52 | P7: =+F7/H7 -> 54.515152
A8: QL-0256366 | B8: 363 | C8: GBP | D8: 17.99 | E8: GBP | F8: 6530.37 | G8: 0.33 | H8: 119.79 | I8: GBP | J8: 54.52 | K8: SYS 330 TILE STEEL 1100mm X 300mm 1522 10 RAL 9010 20% BLACK ADHESIVE TISSUE SQUARE (RAL TBC) | L8: David Baylis | M8: North | N8: BANK HOUSE REDEVELOPMENT LEEDS | O8: =IF(G8<0.03,"",J8) -> 54.52 | P8: =+F8/H8 -> 54.515152
A9: QL-0250458 | B9: 7 | C9: GBP | D9: 49.61 | E9: GBP | F9: 347.27 | G9: 0.72 | H9: 5.04 | I9: GBP | J9: 68.9 | K9: SYS 330 TILE STEEL 1200mm X 600mm 1522 10 RAL 9010 20% WRAPPED 16 80 KG | L9: Emily Judges | M9: London | N9: STOCKLEY PARK ROUNDWOOD AVENUE NO 6 PROJECT JUMPER LONDON | O9: =IF(G9<0.03,"",J9) -> 68.9 | P9: =+F9/H9 -> 68.902778
A10: QL-0250441 | B10: 28 | C10: GBP | D10: 24.8 | E10: GBP | F10: 694.4 | G10: 0.36 | H10: 10.08 | I10: GBP | J10: 68.89 | K10: SYS 330 TILE STEEL 600mm X 600mm 1522 10 RAL 9010 20% WRAPPED 16 80 KG | L10: Emily Judges | M10: London | N10: STOCKLEY PARK ROUNDWOOD AVENUE NO 6 PROJECT JUMPER LONDON | O10: =IF(G10<0.03,"",J10) -> 68.89 | P10: =+F10/H10 -> 68.888889
A11: QL-0250421 | B11: 46 | C11: GBP | D11: 49.61 | E11: GBP | F11: 2282.06 | G11: 0.72 | H11: 33.12 | I11: GBP | J11: 68.9 | K11: SYS 330 TILE STEEL 1200mm X 600mm 1522 10 RAL 9010 20% WRAPPED 16 80 KG | L11: Emily Judges | M11: London | N11: STOCKLEY PARK ROUNDWOOD AVENUE NO 6 PROJECT JUMPER LONDON | O11: =IF(G11<0.03,"",J11) -> 68.9 | P11: =+F11/H11 -> 68.902778
A12: QL-0250466 | B12: 69 | C12: GBP | D12: 24.8 | E12: GBP | F12: 1711.2 | G12: 0.36 | H12: 24.84 | I12: GBP | J12: 68.89 | K12: SYS 330 TILE STEEL 600mm X 600mm 1522 10 RAL 9010 20% WRAPPED 16 80 KG | L12: Emily Judges | M12: London | N12: STOCKLEY PARK ROUNDWOOD AVENUE NO 6 PROJECT JUMPER LONDON | O12: =IF(G12<0.03,"",J12) -> 68.89 | P12: =+F12/H12 -> 68.888889
A13: QL-0254798 | B13: 22 | C13: GBP | D13: 24.8 | E13: GBP | F13: 545.6 | G13: 0.36 | H13: 7.92 | I13: GBP | J13: 68.89 | K13: SYS 330 TILE STEEL 600mm X 600mm 1522 10 RAL 9016 20% WRAPPED 16 80 KG | L13: Emily Judges | M13: South East | N13: ONE LUDLOW OFFICE SUITE 2 MAIDENHEAD | O13: =IF(G13<0.03,"",J13) -> 68.89 | P13: =+F13/H13 -> 68.888889
... A33: QL-0253294 | B33: 8 | C33: GBP | D33: 51.17 | E33: GBP | F33: 409.36 | G33: 0.57 | H33: 4.59 | I33: GBP | J33: 89.19 | K33: SYS 330 TILE AL 1350mm X 425mm LEAF-SMALL RAL 9006 30% NO INFILL SQUARE | L33: Sam James | M33: Northern Home Counties | N33: WITAN GATE HOUSE REFURB PHASE 2 LIFT LOBBY MILTON KEYNES | O33: =IF(G33<0.03,"",J33) -> 89.19 | P33: =+F33/H33 -> 89.185185

Sheet SQM WK29
A1: Line Name | B1: Quantity | C1: Net Unit Price Currency | D1: Net Unit Price | E1: Net Total Currency | F1: Net Total | G1: Item SQM | H1: Line SQM | I1: Â£/SQM Currency | J1: Â£/SQM | K1: Description | L1: Project Owner: Full Name | M1: Sales Region | N1: Project Name | O1: =AVERAGE(O2:O34) -> 72.047273 | P1: =AVERAGE(P2:P34) -> 72.047182
A2: QL-0247728 | B2: 12 | C2: GBP | D2: 17.33 | E2: GBP | F2: 207.96 | G2: 0.36 | H2: 4.32 | I2: GBP | J2: 48.14 | K2: SYS 330 TILE 1200mm X 300mm 1522 10 RAL 9006 30% BLACK ADHESIVE TISSUE SQUARE HOOK AND LAY ON SHORT EDGES | L2: Becky Titley | M2: Scotland | N2: ST VINCENT STREET NO 151-155 FLR 4 GLASGOW | O2: =IF(G2<0.03,"",J2) -> 48.14 | P2: =+F2/H2 -> 48.138889
A3: QL-0247727 | B3: 43 | C3: GBP | D3: 17.33 | E3: GBP | F3: 745.19 | G3: 0.36 | H3: 15.48 | I3: GBP | J3: 48.14 | K3: SYS 330 TILE 1200mm X 300mm 1522 10 RAL 9006 30% BLACK ADHESIVE TISSUE SQUARE LAY ON LONG EDGES | L3: Becky Titley | M3: Scotland | N3: ST VINCENT STREET NO 151-155 FLR 4 GLASGOW | O3: =IF(G3<0.03,"",J3) -> 48.14 | P3: =+F3/H3 -> 48.138889
A4: QL-0249774 | B4: 15 | C4: GBP | D4: 22.35 | E4: GBP | F4: 335.25 | G4: 0.29 | H4: 4.39 | I4: GBP | J4: 76.33 | K4: SYS 330 TILE 975 X 300MM D1522 15 RAL 9010 20% WRAPPED 16 80 KG SQUARE | L4: Chris Edge | M4: North | N4: SPINNINGFIELDS NO 1 9TH FLOOR REFURB MANCHESTER | O4: =IF(G4<0.03,"",J4) -> 76.33 | P4: =+F4/H4 -> 76.366743
A5: QL-0249775 | B5: 26 | C5: GBP | D5: 40.45 | E5: GBP | F5: 1051.7 | G5: 0.41 | H5: 10.53 | I5: GBP | J5: 99.88 | K5: SYS 330 TILE 1349 x 300mm 1522 BORDERS A/S RAL 9010 20% RECT FLG APT 1255.5x99.5mm CENTRAL SQUARE BLACK ACOUSTIC FOAM TO REAR THEN 6mm BLACK ACOUSTIC FOAM, SEE DRG | L5: Chris Edge | M5: North | N5: SPINNINGFIELDS NO 1 9TH FLOOR REFURB MANCHESTER | O5: =IF(G5<0.03,"",J5) -> 99.88 | P5: =+F5/H5 -> 99.876543
A6: QL-0249773 | B6: 660 | C6: GBP | D6: 30.91 | E6: GBP | F6: 20400.6 | G6: 0.41 | H6: 267.3 | I6: GBP | J6: 76.32 | K6: SYS 330 TILE 1349 X 300MM D1522 15 RAL 9010 20% WRAPPED 16 80 KG SQUARE | L6: Chris Edge | M6: North | N6: SPINNINGFIELDS NO 1 9TH FLOOR REFURB MANCHESTER | O6: =IF(G6<0.03,"",J6) -> 76.32 | P6: =+F6/H6 -> 76.320988
A7: QL-0250003 | B7: 7 | C7: GBP | D7: 29.1 | E7: GBP | F7: 203.7 | G7: 0.45 | H7: 3.15 | I7: GBP | J7: 64.67 | K7: SYS 330 TILE STEEL 1500mm X 300mm 1522 10 WRAPPED 16 80 KG SQUARE RAL 3002 30% GLOSS | L7: David Baylis | M7: North | N7: BALLAM ROAD BEAVERBROOK HQ LYTHAM ST ANNES | O7: =IF(G7<0.03,"",J7) -> 64.67 | P7: =+F7/H7 -> 64.666667
A8: QL-0249989 | B8: 10 | C8: GBP | D8: 34.92 | E8: GBP | F8: 349.2 | G8: 0.54 | H8: 5.4 | I8: GBP | J8: 64.67 | K8: SYS 330 TILE STEEL 1800mm X 300mm 1522 10 WRAPPED 16 80 KG SQUARE RAL 3002 30% GLOSS | L8: David Baylis | M8: North | N8: BALLAM ROAD BEAVERBROOK HQ LYTHAM ST ANNES | O8: =IF(G8<0.03,"",J8) -> 64.67 | P8: =+F8/H8 -> 64.666667
A9: QL-0249998 | B9: 67 | C9: GBP | D9: 29.1 | E9: GBP | F9: 1949.7 | G9: 0.45 | H9: 30.15 | I9: GBP | J9: 64.67 | K9: SYS 330 TILE STEEL 1500mm X 300mm 1522 10 WRAPPED 16 80 KG SQUARE RAL 3002 30% GLOSS | L9: David Baylis | M9: North | N9: BALLAM ROAD BEAVERBROOK HQ LYTHAM ST ANNES | O9: =IF(G9<0.03,"",J9) -> 64.67 | P9: =+F9/H9 -> 64.666667
A10: QL-0249975 | B10: 132 | C10: GBP | D10: 23.28 | E10: GBP | F10: 3072.96 | G10: 0.36 | H10: 47.52 | I10: GBP | J10: 64.67 | K10: SYS 330 TILE STEEL 1200mm X 300mm 1522 10 WRAPPED 16 80 KG SQUARE RAL 3002 30% GLOSS | L10: David Baylis | M10: North | N10: BALLAM ROAD BEAVERBROOK HQ LYTHAM ST ANNES | O10: =IF(G10<0.03,"",J10) -> 64.67 | P10: =+F10/H10 -> 64.666667
A11: QL-0249980 | B11: 146 | C11: GBP | D11: 23.28 | E11: GBP | F11: 3398.88 | G11: 0.36 | H11: 52.56 | I11: GBP | J11: 64.67 | K11: SYS 330 TILE STEEL 1200mm X 300mm 1522 10 WRAPPED 16 80 KG SQUARE RAL 3002 30% GLOSS | L11: David Baylis | M11: North | N11: BALLAM ROAD BEAVERBROOK HQ LYTHAM ST ANNES | O11: =IF(G11<0.03,"",J11) -> 64.67 | P11: =+F11/H11 -> 64.666667
A12: QL-0249418 | B12: 18 | C12: GBP | D12: 17.25 | E12: GBP | F12: 310.5 | G12: 0.18 | H12: 3.24 | I12: GBP | J12: 95.83 | K12: SYS 330 TILE STEEL 600mm X 300mm 1522 10 RAL 9010 20% BLACK ADHESIVE TISSUE SQUARE | L12: David Baylis | M12: North | N12: KING STREET NO 1 3RD FLR WC REFURB MANCHESTER | O12: =IF(G12<0.03,"",J12) -> 95.83 | P12: =+F12/H12 -> 95.833333
A13: QL-0249411 | B13: 27 | C13: GBP | D13: 18.13 | E13: GBP | F13: 489.51 | G13: 0.27 | H13: 7.29 | I13: GBP | J13: 67.15 | K13: SYS 330 TILE STEEL 900mm X 300mm 1522 10 RAL 9010 20% BLACK ADHESIVE TISSUE SQUARE | L13: David Baylis | M13: North | N13: KING STREET NO 1 3RD FLR WC REFURB MANCHESTER | O13: =IF(G13<0.03,"",J13) -> 67.15 | P13: =+F13/H13 -> 67.148148
... A34: QL-0248306 | B34: 318 | C34: GBP | D34: 28.11 | E34: GBP | F34: 8938.98 | G34: 0.31 | H34: 99.22 | I34: GBP | J34: 90.1 | K34: SYS 330 TILE STEEL 1040mm X 300mm 2414 10 RAL 9010 20% WRAPPED 16 80 KG SQUARE 45mm DEEP | L34: Peter Gray | M34: London | N34: INTERNATIONAL HOUSE ST KATHARINES DOCK FLOOR 4 LONDON | O34: =IF(G34<0.03,"",J34) -> 90.1 | P34: =+F34/H34 -> 90.092522

Sheet SQM WK28
A1: Line Name | B1: Quantity | C1: Net Unit Price Currency | D1: Net Unit Price | E1: Net Total Currency | F1: Net Total | G1: Item SQM | H1: Line SQM | I1: Â£/SQM Currency | J1: Â£/SQM | K1: Description | L1: Project Owner: Full Name | M1: Sales Region | N1: Project Name | O1: =AVERAGE(O2:O45) -> 82.652727 | P1: =AVERAGE(P2:P45) -> 82.64793
A2: QL-0244727 | B2: 735 | C2: GBP | D2: 21.2 | E2: GBP | F2: 15582 | G2: 0.36 | H2: 264.6 | I2: GBP | J2: 58.89 | K2: SYS 330 TILE STEEL 1200mm X 300mm 1522 10 RAL 9010 20% BLACK ADHESIVE TISSUE SQUARE | L2: Chris Edge | M2: North | N2: FIRST STREET PLOT 9A GPA CAT B MANCHESTER | O2: =IF(G2<0.03,"",J2) -> 58.89 | P2: =+F2/H2 -> 58.888889
A3: QL-0239366 | B3: 707 | C3: GBP | D3: 35.31 | E3: GBP | F3: 24964.17 | G3: 0.57 | H3: 402.99 | I3: GBP | J3: 61.95 | K3: SYS 330 TILE STEEL 1900mm X 300mm 1522 10 RAL 9010 20% WRAPPED 16 80 KG SQUARE | L3: Chris Edge | M3: North | N3: MANCHESTER SCIENCE PARK GREENHEYS PROJECT | O3: =IF(G3<0.03,"",J3) -> 61.95 | P3: =+F3/H3 -> 61.947368
A4: QL-0239365 | B4: 84 | C4: GBP | D4: 33.44 | E4: GBP | F4: 2808.96 | G4: 0.54 | H4: 45.36 | I4: GBP | J4: 61.93 | K4: SYS 330 TILE STEEL 1800mm X 300mm 1522 10 RAL 9010 20% WRAPPED 16 80 KG SQUARE | L4: Chris Edge | M4: North | N4: MANCHESTER SCIENCE PARK GREENHEYS PROJECT | O4: =IF(G4<0.03,"",J4) -> 61.93 | P4: =+F4/H4 -> 61.925926
A5: QL-0239368 | B5: 20 | C5: GBP | D5: 55.75 | E5: GBP | F5: 1115 | G5: 0.9 | H5: 18 | I5: GBP | J5: 61.94 | K5: SYS 330 TILE STEEL 3000mm X 300mm 1522 10 RAL 9010 20% WRAPPED 16 80 KG SQUARE | L5: Chris Edge | M5: North | N5: MANCHESTER SCIENCE PARK GREENHEYS PROJECT | O5: =IF(G5<0.03,"",J5) -> 61.94 | P5: =+F5/H5 -> 61.944444
A6: QL-0239367 | B6: 20 | C6: GBP | D6: 37.16 | E6: GBP | F6: 743.2 | G6: 0.6 | H6: 12 | I6: GBP | J6: 61.93 | K6: SYS 330 TILE STEEL 2000mm X 300mm 1522 10 RAL 9010 20% WRAPPED 16 80 KG SQUARE | L6: Chris Edge | M6: North | N6: MANCHESTER SCIENCE PARK GREENHEYS PROJECT | O6: =IF(G6<0.03,"",J6) -> 61.93 | P6: =+F6/H6 -> 61.933333
A7: QL-0239350 | B7: 624 | C7: GBP | D7: 21.76 | E7: GBP | F7: 13578.24 | G7: 0.33 | H7: 205.92 | I7: GBP | J7: 65.94 | K7: SYS 330 TILE STEEL 1100mm X 300mm OB19 20 RAL 9010 20% WRAPPED 16 80 KG SQUARE | L7: Chris Edge | M7: North | N7: MANCHESTER SCIENCE PARK GREENHEYS PROJECT | O7: =IF(G7<0.03,"",J7) -> 65.94 | P7: =+F7/H7 -> 65.939394
A8: QL-0239352 | B8: 350 | C8: GBP | D8: 25.72 | E8: GBP | F8: 9002 | G8: 0.39 | H8: 136.5 | I8: GBP | J8: 65.95 | K8: SYS 330 TILE STEEL 1300mm X 300mm OB19 20 RAL 9010 20% WRAPPED 16 80 KG SQUARE | L8: Chris Edge | M8: North | N8: MANCHESTER SCIENCE PARK GREENHEYS PROJECT | O8: =IF(G8<0.03,"",J8) -> 65.95 | P8: =+F8/H8 -> 65.948718
A9: QL-0239351 | B9: 20 | C9: GBP | D9: 23.74 | E9: GBP | F9: 474.8 | G9: 0.36 | H9: 7.2 | I9: GBP | J9: 65.94 | K9: SYS 330 TILE STEEL 1200mm X 300mm OB19 20 RAL 9010 20% WRAPPED 16 80 KG SQUARE | L9: Chris Edge | M9: North | N9: MANCHESTER SCIENCE PARK GREENHEYS PROJECT | O9: =IF(G9<0.03,"",J9) -> 65.94 | P9: =+F9/H9 -> 65.944444
A10: QL-0239354 | B10: 490 | C10: GBP | D10: 29.67 | E10: GBP | F10: 14538.3 | G10: 0.45 | H10: 220.5 | I10: GBP | J10: 65.93 | K10: SYS 330 TILE STEEL 1500mm X 300mm OB19 20 RAL 9010 20% WRAPPED 16 80 KG SQUARE | L10: Chris Edge | M10: North | N10: MANCHESTER SCIENCE PARK GREENHEYS PROJECT | O10: =IF(G10<0.03,"",J10) -> 65.93 | P10: =+F10/H10 -> 65.933333
A11: QL-0239353 | B11: 140 | C11: GBP | D11: 27.71 | E11: GBP | F11: 3879.4 | G11: 0.42 | H11: 58.8 | I11: GBP | J11: 65.98 | K11: SYS 330 TILE STEEL 1400mm X 300mm OB19 20 RAL 9010 20% WRAPPED 16 80 KG SQUARE | L11: Chris Edge | M11: North | N11: MANCHESTER SCIENCE PARK GREENHEYS PROJECT | O11: =IF(G11<0.03,"",J11) -> 65.98 | P11: =+F11/H11 -> 65.97619
A12: QL-0239356 | B12: 707 | C12: GBP | D12: 37.59 | E12: GBP | F12: 26576.13 | G12: 0.57 | H12: 402.99 | I12: GBP | J12: 65.95 | K12: SYS 330 TILE STEEL 1900mm X 300mm OB19 20 RAL 9010 20% WRAPPED 16 80 KG SQUARE | L12: Chris Edge | M12: North | N12: MANCHESTER SCIENCE PARK GREENHEYS PROJECT | O12: =IF(G12<0.03,"",J12) -> 65.95 | P12: =+F12/H12 -> 65.947368
A13: QL-0239355 | B13: 84 | C13: GBP | D13: 35.61 | E13: GBP | F13: 2991.24 | G13: 0.54 | H13: 45.36 | I13: GBP | J13: 65.94 | K13: SYS 330 TILE STEEL 1800mm X 300mm OB19 20 RAL 9010 20% WRAPPED 16 80 KG SQUARE | L13: Chris Edge | M13: North | N13: MANCHESTER SCIENCE PARK GREENHEYS PROJECT | O13: =IF(G13<0.03,"",J13) -> 65.94 | P13: =+F13/H13 -> 65.944444
... A45: QL-0242126 | B45: 2504 | C45: GBP | D45: 22.89 | E45: GBP | F45: 57316.56 | G45: 0.36 | H45: 901.44 | I45: GBP | J45: 63.58 | K45: SYS 330 TILE STEEL 1200mm X 300mm 1513 10 RAL 9010 20% WRAPPED 16 80 KG | L45: Sam James | M45: South East | N45: JOHNSON & JOHNSON STAR HOUSE NO 20 MAIDENHEAD | O45: =IF(G45<0.03,"",J45) -> 63.58 | P45: =+F45/H45 -> 63.583333

Sheet SQM WK27
A1: Line Name | B1: Quantity | C1: Net Unit Price Currency | D1: Net Unit Price | E1: Net Total Currency | F1: Net Total | G1: Item SQM | H1: Line SQM | I1: Â£/SQM Currency | J1: Â£/SQM | K1: Description | L1: Project Owner: Full Name | M1: Sales Region | N1: Project Name | O1: =AVERAGE(O2:O22) -> 78.721579 | P1: =AVERAGE(P2:P58) -> 78.721131
A2: QL-0241503 | B2: 9 | C2: GBP | D2: 15.82 | E2: GBP | F2: 142.38 | G2: 0.45 | H2: 4.05 | I2: GBP | J2: 35.16 | K2: SYS 330 TILE STEEL 900mm X 500mm PLAIN RAL 9010 FT 10% NO INFILL SQUARE | L2: Becky Titley | M2: Scotland | N2: QUEENSFERRY STREET NO 1-8 HOTEL EDINBURGH | O2: =IF(G2<0.03,"",J2) -> 35.16 | P2: =+F2/H2 -> 35.155556
A3: QL-0241502 | B3: 3 | C3: GBP | D3: 19.22 | E3: GBP | F3: 57.66 | G3: 0.55 | H3: 1.65 | I3: GBP | J3: 34.95 | K3: SYS 330 TILE STEEL 1100mm X 500mm PLAIN RAL 9010 FT 10% NO INFILL SQUARE | L3: Becky Titley | M3: Scotland | N3: QUEENSFERRY STREET NO 1-8 HOTEL EDINBURGH | O3: =IF(G3<0.03,"",J3) -> 34.95 | P3: =+F3/H3 -> 34.945455
A4: QL-0240402 | B4: 206 | C4: GBP | D4: 36.94 | E4: GBP | F4: 7609.64 | G4: 0.72 | H4: 148.32 | I4: GBP | J4: 51.31 | K4: SYS 330 TILE STEEL 1200mm X 600mm 1522 10 RAL 9010 20% BLACK ADHESIVE TISSUE SQUARE | L4: Becky Titley | M4: Scotland | N4: STUDENT ACCOMODATION JOCKS LODGE EDINBURGH | O4: =IF(G4<0.03,"",J4) -> 51.31 | P4: =+F4/H4 -> 51.305556
A5: QL-0236872 | B5: 80 | C5: GBP | D5: 38.62 | E5: GBP | F5: 3089.6 | G5: 0.36 | H5: 28.8 | I5: GBP | J5: 107.28 | K5: SYS 330 TILE AL 600mm X 600mm S0702 ULTRA OVERALL RAL 9010 20% TISSUE WRAPPED 16 80 KG SQUARE | L5: Chris Edge | M5: North | N5: AIREDALE HOSPITAL MRI AREA KEIGHLEY | O5: =IF(G5<0.03,"",J5) -> 107.28 | P5: =+F5/H5 -> 107.27778
A6: QL-0240937 | B6: 128 | C6: GBP | D6: 22.88 | E6: GBP | F6: 2928.64 | G6: 0.36 | H6: 46.08 | I6: GBP | J6: 63.56 | K6: SYS 330 TILE STEEL 1200mm X 300mm 1522 10 RAL 9010 20% WRAPPED 16 80 KG SQUARE | L6: David Fry | M6: South West | N6: UNIVERSITY OF EXETER DUCKES MEADOW | O6: =IF(G6<0.03,"",J6) -> 63.56 | P6: =+F6/H6 -> 63.555556
A7: QL-0239764 | B7: 33 | C7: GBP | D7: 53.91 | E7: GBP | F7: 1779.03 | G7: 0.72 | H7: 23.76 | I7: GBP | J7: 74.88 | K7: SYS 330 TILE STEEL 1200mm X 600mm S1820 10 RAL 9010 20% WRAPPED 16 80 KG SQUARE | L7: Ed Fagan | M7: London | N7: BISHOPSGATE NO 22 LEVEL 9 AMWINS REFURB LONDON | O7: =IF(G7<0.03,"",J7) -> 74.88 | P7: =+F7/H7 -> 74.875
A8: QL-0239783 | B8: 45 | C8: GBP | D8: 26.96 | E8: GBP | F8: 1213.2 | G8: 0.36 | H8: 16.2 | I8: GBP | J8: 74.89 | K8: SYS 330 TILE STEEL 1200mm X 300mm S1820 10 RAL 9010 20% WRAPPED 16 80 KG | L8: Ed Fagan | M8: London | N8: BISHOPSGATE NO 22 LEVEL 9 AMWINS REFURB LONDON | O8: =IF(G8<0.03,"",J8) -> 74.89 | P8: =+F8/H8 -> 74.888889
A9: QL-0238435 | B9: 22 | C9: GBP | D9: 23.4 | E9: GBP | F9: 514.8 | G9: 0.36 | H9: 7.92 | I9: GBP | J9: 65 | K9: SYS 330 TILE STEEL 600mm X 600mm 1522 10 RAL 9016 20% WRAPPED 16 80 KG | L9: Emily Judges | M9: South East | N9: ONE LUDLOW MAIDENHEAD | O9: =IF(G9<0.03,"",J9) -> 65 | P9: =+F9/H9 -> 65
A10: QL-0238434 | B10: 348 | C10: GBP | D10: 46.8 | E10: GBP | F10: 16286.4 | G10: 0.72 | H10: 250.56 | I10: GBP | J10: 65 | K10: SYS 330 TILE STEEL 1200mm X 600mm 1522 10 RAL 9016 20% WRAPPED 16 80 KG SQUARE | L10: Emily Judges | M10: South East | N10: ONE LUDLOW MAIDENHEAD | O10: =IF(G10<0.03,"",J10) -> 65 | P10: =+F10/H10 -> 65
A11: QL-0240798 | B11: 3888 | C11: GBP | D11: 71.56 | E11: GBP | F11: 278225.28 | G11: 1.02 | H11: 3965.76 | I11: GBP | J11: 70.16 | K11: SYS 330 TILE STEEL 1700mm X 600mm S1820 10 RAL 9016 20% WRAPPED 16 80 KG SQUARE | L11: Nick Drake | M11: Midlands | N11: BRINDLEY PLACE NO 5 REFURB PHASE 2 BIRMINGHAM | O11: =IF(G11<0.03,"",J11) -> 70.16 | P11: =+F11/H11 -> 70.156863
A12: QL-0236797 | B12: 100 | C12: GBP | D12: 27.36 | E12: GBP | F12: 2736 | G12: 0.36 | H12: 36 | I12: GBP | J12: 76 | K12: SYS 330 TILE 1199 x 300mm 1522 10 RAL 9010 20% WRAPPED 16 80 KG SQUARE | L12: Oliver Brosch | M12: London | N12: BISHOPSGATE NO 199 CAT B FLR G COWI LONDON | O12: =IF(G12<0.03,"",J12) -> 76 | P12: =+F12/H12 -> 76
A13: QL-0239190 | B13: 2289 | C13: GBP | D13: 31.68 | E13: GBP | F13: 72515.52 | G13: 0.45 | H13: 1033.68 | I13: GBP | J13: 70.15 | K13: SYS 330 TILE STEEL 1344mm X 336mm 1522 10 RAL 9010 20% WRAPPED 16 80 KG SQUARE | L13: Peter Gray | M13: London | N13: PETERBOROUGH COURT FLEET STREET CAT B ITOCHU FLRS 1 & 7 | O13: =IF(G13<0.03,"",J13) -> 70.15 | P13: =+F13/H13 -> 70.152775
... A20: QL-0240014 | B20: 510 | C20: GBP | D20: 97.6 | E20: GBP | F20: 49776 | G20: 0.58 | H20: 296.65 | I20: GBP | J20: 167.8 | K20: SYS 330 TILE 1503mm X 387mm WRAPPED 16 80 KG BESPOKE FLUTED PERFORATION, FINISH: INTERPON ANODIC YW201E (METALLIC MATT) C/W BLACK GLASS FIBRE FLEECE | L20: Sam James | M20: London | N20: STEPHEN STREET NO 1-2 FLOOR 7 LONDON | O20: =IF(G20<0.03,"",J20) -> 167.8 | P20: =+F20/H20 -> 167.7937
O21: =IF(G21<0.03,"",J21)
O22: =IF(G22<0.03,"",J22)

Sheet SQM Wk 26
A1: Line Name | B1: Quantity | C1: Net Unit Price Currency | D1: Net Unit Price | E1: Net Total Currency | F1: Net Total | G1: Item SQM | H1: Line SQM | I1: Â£/SQM Currency | J1: Â£/SQM | K1: Description | L1: Project Owner: Full Name | M1: Sales Region | N1: Project Name | O1: =AVERAGE(O2:O22) -> 72.681429 | P1: =AVERAGE(P2:P58) -> 72.674276
A2: QL-0232684 | B2: 256 | C2: GBP | D2: 22.85 | E2: GBP | F2: 5849.6 | G2: 0.36 | H2: 92.01 | I2: GBP | J2: 63.58 | K2: SYS 330 TILE STEEL 599mm X 600mm 1522 10 RAL 9010 20% WRAPPED 16 80 KG SQUARE | L2: David Fry | M2: South West | N2: BABOCK BUILDING NO 100 A BRISTOL | O2: =IF(G2<0.03,"",J2) -> 63.58 | P2: =+F2/H2 -> 63.575698
A3: QL-0232674 | B3: 550 | C3: GBP | D3: 45.78 | E3: GBP | F3: 25179 | G3: 0.72 | H3: 396 | I3: GBP | J3: 63.58 | K3: SYS 330 TILE 1199 x 600mm 1522 10 RAL 9010 20% WRAPPED 18 80 KG SQUARE | L3: David Fry | M3: South West | N3: BABOCK BUILDING NO 100 A BRISTOL | O3: =IF(G3<0.03,"",J3) -> 63.58 | P3: =+F3/H3 -> 63.583333
A4: QL-0232683 | B4: 3 | C4: GBP | D4: 45.9 | E4: GBP | F4: 137.7 | G4: 0.72 | H4: 2.17 | I4: GBP | J4: 63.59 | K4: SYS 330 TILE STEEL 1203mm X 600mm 1522 10 RAL 9010 20% WRAPPED 16 80 KG SQUARE | L4: David Fry | M4: South West | N4: BABOCK BUILDING NO 100 A BRISTOL | O4: =IF(G4<0.03,"",J4) -> 63.59 | P4: =+F4/H4 -> 63.456221
A5: QL-0232661 | B5: 75 | C5: GBP | D5: 28.62 | E5: GBP | F5: 2146.5 | G5: 0.45 | H5: 33.75 | I5: GBP | J5: 63.6 | K5: SYS 330 TILE 1499 x 300mm 1522 10 RAL 9010 20% WRAPPED 16 80 KG SQUARE | L5: David Fry | M5: South West | N5: BABOCK BUILDING NO 100 A BRISTOL | O5: =IF(G5<0.03,"",J5) -> 63.6 | P5: =+F5/H5 -> 63.6
A6: QL-0230961 | B6: 13 | C6: GBP | D6: 38.7 | E6: GBP | F6: 503.1 | G6: 0.45 | H6: 5.85 | I6: GBP | J6: 86 | K6: SYS 330 TILE STEEL 1500mm X 300mm S0702 ULTRA OVERALL RAL 9010 20% BLACK ADHESIVE TISSUE SQUARE | L6: Ed Fagan | M6: London | N6: GATWICK AIRPORT MISC 2025 | O6: =IF(G6<0.03,"",J6) -> 86 | P6: =+F6/H6 -> 86
A7: QL-0230963 | B7: 21 | C7: GBP | D7: 23.76 | E7: GBP | F7: 498.96 | G7: 0.27 | H7: 5.67 | I7: GBP | J7: 88 | K7: SYS 330 TILE STEEL 900mm X 300mm S0702 ULTRA OVERALL RAL 9010 20% BLACK ADHESIVE TISSUE SQUARE | L7: Ed Fagan | M7: London | N7: GATWICK AIRPORT MISC 2025 | O7: =IF(G7<0.03,"",J7) -> 88 | P7: =+F7/H7 -> 88
A8: QL-0230962 | B8: 11 | C8: GBP | D8: 31.32 | E8: GBP | F8: 344.52 | G8: 0.36 | H8: 3.96 | I8: GBP | J8: 87 | K8: SYS 330 TILE STEEL 1200mm X 300mm S0702 ULTRA OVERALL RAL 9010 20% BLACK ADHESIVE TISSUE SQUARE | L8: Ed Fagan | M8: London | N8: GATWICK AIRPORT MISC 2025 | O8: =IF(G8<0.03,"",J8) -> 87 | P8: =+F8/H8 -> 87
A9: QL-0230964 | B9: 335 | C9: GBP | D9: 14.04 | E9: GBP | F9: 4703.4 | G9: 0.18 | H9: 60.3 | I9: GBP | J9: 78 | K9: SYS 330 TILE STEEL 600mm X 300mm S0702 ULTRA OVERALL RAL 9010 20% BLACK ADHESIVE TISSUE SQUARE | L9: Ed Fagan | M9: London | N9: GATWICK AIRPORT MISC 2025 | O9: =IF(G9<0.03,"",J9) -> 78 | P9: =+F9/H9 -> 78
A10: QL-0229749 | B10: 6245 | C10: GBP | D10: 31.23 | E10: GBP | F10: 195031.35 | G10: 0.42 | H10: 2622.9 | I10: GBP | J10: 74.36 | K10: SYS 330 TILE STEEL 1400mm X 300mm 1522 10 RAL 9010 20% WRAPPED 16 80 KG SQUARE | L10: Ed Fagan | M10: London | N10: LIVERPOOL STREET NO 1 CAT B DENTONS FLRS 2-5 LONDON | O10: =IF(G10<0.03,"",J10) -> 74.36 | P10: =+F10/H10 -> 74.357143
A11: QL-0229756 | B11: 200 | C11: GBP | D11: 16.06 | E11: GBP | F11: 3212 | G11: 0.21 | H11: 42 | I11: GBP | J11: 76.48 | K11: SYS 330 TILE STEEL 700mm X 300mm 1522 10 RAL 9010 20% WRAPPED 16 80 KG SQUARE | L11: Ed Fagan | M11: London | N11: LIVERPOOL STREET NO 1 CAT B DENTONS FLRS 2-5 LONDON | O11: =IF(G11<0.03,"",J11) -> 76.48 | P11: =+F11/H11 -> 76.47619
A12: QL-0229763 | B12: 300 | C12: GBP | D12: 26.77 | E12: GBP | F12: 8031 | G12: 0.36 | H12: 108 | I12: GBP | J12: 74.36 | K12: SYS 330 TILE STEEL 1200mm X 300mm 1522 10 RAL 9010 20% WRAPPED 16 80 KG SQUARE | L12: Ed Fagan | M12: London | N12: LIVERPOOL STREET NO 1 CAT B DENTONS FLRS 2-5 LONDON | O12: =IF(G12<0.03,"",J12) -> 74.36 | P12: =+F12/H12 -> 74.361111
A13: QL-0232317 | B13: 4076 | C13: GBP | D13: 27.27 | E13: GBP | F13: 111152.52 | G13: 0.37 | H13: 1497.93 | I13: GBP | J13: 74.2 | K13: SYS 330 TILE STEEL 1050mm X 350mm 1522 10 RAL 9010 20% WRAPPED 16 80 KG SQUARE | L13: Emily Judges | M13: London | N13: HOLBORN VIADUCT NO 61 - 65 DEVELOPMENT LONDON | O13: =IF(G13<0.03,"",J13) -> 74.2 | P13: =+F13/H13 -> 74.204082
... A22: QL-0233755 | B22: 2504 | C22: GBP | D22: 22.89 | E22: GBP | F22: 57316.56 | G22: 0.36 | H22: 901.44 | I22: GBP | J22: 63.58 | K22: SYS 330 TILE STEEL 1200mm X 300mm 1513 10 RAL 9010 20% WRAPPED 16 80 KG | L22: Sam James | M22: South East | N22: JOHNSON & JOHNSON STAR HOUSE NO 20 MAIDENHEAD | O22: =IF(G22<0.03,"",J22) -> 63.58 | P22: =+F22/H22 -> 63.583333

Sheet SQM Wk 25
A1: Line Name | B1: Quantity | C1: Net Unit Price Currency | D1: Net Unit Price | E1: Net Total Currency | F1: Net Total | G1: Item SQM | H1: Line SQM | I1: Â£/SQM Currency | J1: Â£/SQM | K1: Description | L1: Project Owner: Full Name | M1: Sales Region | N1: Project Name | O1: =AVERAGE(O2:O80) -> 82.126 | P1: =AVERAGE(P2:P80) -> #DIV/0!
A2: QL-0226839 | B2: 7444 | C2: GBP | D2: 37.38 | E2: GBP | F2: 278256.72 | G2: 0.75 | H2: 5583 | I2: GBP | J2: 49.84 | K2: SYS 330 TILE STEEL 1500mm X 500mm PLAIN RAL 9010 20% NO INFILL SQUARE | L2: Chris Edge | M2: North | N2: ONE TONY WILSON PLACE MANCHESTER | O2: =IF(G2<0.03,"",J2) -> 49.84 | P2: =+F2/H2 -> 49.84
A3: QL-0225440 | B3: 5 | C3: GBP | D3: 14.41 | E3: GBP | F3: 72.05 | G3: 0.22 | H3: 1.11 | I3: GBP | J3: 65 | K3: SYS 330 TILE STEEL 739mm X 300mm 4050 35 RAL 9016 20% WRAPPED 16 80 KG SQUARE | L3: Ed Fagan | M3: London | N3: CLIFFORD STREET NO 7 CAT A REFURB FLOORS 1 & 5 LONDON | O3: =IF(G3<0.03,"",J3) -> 65 | P3: =+F3/H3 -> 64.90991
A4: QL-0225442 | B4: 29 | C4: GBP | D4: 20.77 | E4: GBP | F4: 602.33 | G4: 0.32 | H4: 9.27 | I4: GBP | J4: 65.01 | K4: SYS 330 TILE STEEL 1065mm X 300mm 4050 35 RAL 9016 20% WRAPPED 16 80 KG SQUARE | L4: Ed Fagan | M4: London | N4: CLIFFORD STREET NO 7 CAT A REFURB FLOORS 1 & 5 LONDON | O4: =IF(G4<0.03,"",J4) -> 65.01 | P4: =+F4/H4 -> 64.976268
A5: QL-0225443 | B5: 73 | C5: GBP | D5: 23.4 | E5: GBP | F5: 1708.2 | G5: 0.36 | H5: 26.28 | I5: GBP | J5: 65 | K5: SYS 330 TILE STEEL 1200mm X 300mm 4050 35 RAL 9016 20% WRAPPED 16 80 KG SQUARE | L5: Ed Fagan | M5: London | N5: CLIFFORD STREET NO 7 CAT A REFURB FLOORS 1 & 5 LONDON | O5: =IF(G5<0.03,"",J5) -> 65 | P5: =+F5/H5 -> 65
A6: QL-0225444 | B6: 10 | C6: GBP | D6: 17.84 | E6: GBP | F6: 178.4 | G6: 0.27 | H6: 2.75 | I6: GBP | J6: 64.99 | K6: SYS 330 TILE STEEL 915mm X 300mm 4050 35 RAL 9016 20% WRAPPED 16 80 KG SQUARE | L6: Ed Fagan | M6: London | N6: CLIFFORD STREET NO 7 CAT A REFURB FLOORS 1 & 5 LONDON | O6: =IF(G6<0.03,"",J6) -> 64.99 | P6: =+F6/H6 -> 64.872727
A7: QL-0225445 | B7: 10 | C7: GBP | D7: 20.36 | E7: GBP | F7: 203.6 | G7: 0.31 | H7: 3.13 | I7: GBP | J7: 65.01 | K7: SYS 330 TILE STEEL 1044mm X 300mm 4050 35 RAL 9016 20% WRAPPED 16 80 KG SQUARE | L7: Ed Fagan | M7: London | N7: CLIFFORD STREET NO 7 CAT A REFURB FLOORS 1 & 5 LONDON | O7: =IF(G7<0.03,"",J7) -> 65.01 | P7: =+F7/H7 -> 65.047923
A8: QL-0225441 | B8: 7 | C8: GBP | D8: 19.4 | E8: GBP | F8: 135.8 | G8: 0.3 | H8: 2.09 | I8: GBP | J8: 64.99 | K8: SYS 330 TILE STEEL 995mm X 300mm 4050 35 RAL 9016 20% WRAPPED 16 80 KG SQUARE | L8: Ed Fagan | M8: London | N8: CLIFFORD STREET NO 7 CAT A REFURB FLOORS 1 & 5 LONDON | O8: =IF(G8<0.03,"",J8) -> 64.99 | P8: =+F8/H8 -> 64.976077
A9: QL-0228463 | B9: 103 | C9: GBP | D9: 19.8 | E9: GBP | F9: 2039.4 | G9: 0.36 | H9: 37.08 | I9: GBP | J9: 55 | K9: SYS 330 TILE STEEL 1200mm X 300mm PLAIN RAL 9010 20% NO INFILL SQUARE | L9: Emily Judges | M9: London | N9: GILTSPUR STREET NO 20 CAT B OCTOPUS LONDON | O9: =IF(G9<0.03,"",J9) -> 55 | P9: =+F9/H9 -> 55
A10: QL-0226794 | B10: 348 | C10: GBP | D10: 46.8 | E10: GBP | F10: 16286.4 | G10: 0.72 | H10: 250.56 | I10: GBP | J10: 65 | K10: SYS 330 TILE STEEL 1200mm X 600mm 1522 10 RAL 9016 20% WRAPPED 16 80 KG SQUARE | L10: Emily Judges | M10: South East | N10: ONE LUDLOW MAIDENHEAD | O10: =IF(G10<0.03,"",J10) -> 65 | P10: =+F10/H10 -> 65
A11: QL-0226795 | B11: 22 | C11: GBP | D11: 23.4 | E11: GBP | F11: 514.8 | G11: 0.36 | H11: 7.92 | I11: GBP | J11: 65 | K11: SYS 330 TILE STEEL 600mm X 600mm 1522 10 RAL 9016 20% WRAPPED 16 80 KG | L11: Emily Judges | M11: South East | N11: ONE LUDLOW MAIDENHEAD | O11: =IF(G11<0.03,"",J11) -> 65 | P11: =+F11/H11 -> 65
A12: QL-0226823 | B12: 78 | C12: GBP | D12: 25.2 | E12: GBP | F12: 1965.6 | G12: 0.36 | H12: 28.08 | I12: GBP | J12: 70 | K12: SYS 330 TILE STEEL 1200mm X 300mm 1522 10 RAL 9010 20% WRAPPED 16 80 KG SQUARE | L12: Eurshell Fearon | M12: London | N12: TUDOR STREET NO 1 FLR 2 REFURB LONDON | O12: =IF(G12<0.03,"",J12) -> 70 | P12: =+F12/H12 -> 70
A13: QL-0226807 | B13: 148 | C13: GBP | D13: 23.1 | E13: GBP | F13: 3418.8 | G13: 0.33 | H13: 48.84 | I13: GBP | J13: 70 | K13: SYS 330 TILE STEEL 1100mm X 300mm 1522 10 RAL 9010 20% WRAPPED 16 80 KG SQUARE | L13: Eurshell Fearon | M13: London | N13: TUDOR STREET NO 1 FLR 2 REFURB LONDON | O13: =IF(G13<0.03,"",J13) -> 70 | P13: =+F13/H13 -> 70
... A36: QL-0227678 | B36: 92 | C36: GBP | D36: 24.71 | E36: GBP | F36: 2273.32 | G36: 0.27 | H36: 24.84 | I36: GBP | J36: 91.52 | K36: SYS 330 TILE STEEL 1500mm X 180mm PLAIN RAL 9016 20% NO INFILL SQUARE 40mm DEEP RECT FLG 1350mm x 60mm CENTRAL | L36: Peter Gray | M36: London | N36: SOUTH MOLTON TRIANGLE DEVELOPMENT NORTH BLOCK LONDON | O36: =IF(G36<0.03,"",J36) -> 91.52 | P36: =+F36/H36 -> 91.518519
O37: =IF(G37<0.03,"",J37) | P37: =+F37/H37 -> #DIV/0!
O38: =IF(G38<0.03,"",J38) | P38: =+F38/H38 -> #DIV/0!
O39: =IF(G39<0.03,"",J39) | P39: =+F39/H39 -> #DIV/0!
O40: =IF(G40<0.03,"",J40) | P40: =+F40/H40 -> #DIV/0!
O41: =IF(G41<0.03,"",J41) | P41: =+F41/H41 -> #DIV/0!
O42: =IF(G42<0.03,"",J42) | P42: =+F42/H42 -> #DIV/0!
O43: =IF(G43<0.03,"",J43) | P43: =+F43/H43 -> #DIV/0!

Sheet SQM Wk 24
A1: Line Name | B1: Quantity | C1: Net Unit Price Currency | D1: Net Unit Price | E1: Net Total Currency | F1: Net Total | G1: Item SQM | H1: Line SQM | I1: Â£/SQM Currency | J1: Â£/SQM | K1: Description | L1: Project Owner: Full Name | M1: Sales Region | N1: Project Name | O1: =AVERAGE(O2:O80) -> 82.874878 | P1: =AVERAGE(P2:P80) -> 129.67158
A2: QL-0218074 | B2: 598 | C2: GBP | D2: 17.05 | E2: GBP | F2: 10195.9 | G2: 0.36 | H2: 215.28 | I2: GBP | J2: 47.36 | K2: SYS 330 TILE STEEL 600mm X 600mm PLAIN RAL 9010 20% NO INFILL SQUARE | L2: Becky Titley | M2: Scotland | N2: UNI OF GLASGOW KEYSTONE BUILDING | O2: =IF(G2<0.03,"",J2) -> 47.36 | P2: =+F2/H2 -> 47.361111
A3: QL-0218087 | B3: 50 | C3: GBP | D3: 8.16 | E3: GBP | F3: 408 | G3: 0.12 | H3: 6 | I3: GBP | J3: 68 | K3: SYS 330 TILE STEEL 1000mm X 120mm PLAIN RAL 9010 20% NO INFILL SQUARE OUT TURNS ON LONG SIDES | L3: Becky Titley | M3: Scotland | N3: UNI OF GLASGOW KEYSTONE BUILDING | O3: =IF(G3<0.03,"",J3) -> 68 | P3: =+F3/H3 -> 68
A4: QL-0218038 | B4: 126 | C4: GBP | D4: 24.68 | E4: GBP | F4: 3109.68 | G4: 0.42 | H4: 52.92 | I4: GBP | J4: 58.76 | K4: SYS 330 TILE STEEL 700mm X 600mm 1522 10 RAL 9010 20% WRAPPED 16 80 KG SQUARE | L4: Becky Titley | M4: Scotland | N4: UNI OF GLASGOW KEYSTONE BUILDING | O4: =IF(G4<0.03,"",J4) -> 58.76 | P4: =+F4/H4 -> 58.761905
A5: QL-0218040 | B5: 671 | C5: GBP | D5: 35.26 | E5: GBP | F5: 23659.46 | G5: 0.6 | H5: 402.6 | I5: GBP | J5: 58.77 | K5: SYS 330 TILE STEEL 1000mm X 600mm 1522 10 RAL 9010 20% WRAPPED 16 80 KG SQUARE | L5: Becky Titley | M5: Scotland | N5: UNI OF GLASGOW KEYSTONE BUILDING | O5: =IF(G5<0.03,"",J5) -> 58.77 | P5: =+F5/H5 -> 58.766667
A6: QL-0218039 | B6: 202 | C6: GBP | D6: 31.74 | E6: GBP | F6: 6411.48 | G6: 0.54 | H6: 109.08 | I6: GBP | J6: 58.78 | K6: SYS 330 TILE STEEL 900mm X 600mm 1522 10 RAL 9010 20% WRAPPED 16 80 KG SQUARE | L6: Becky Titley | M6: Scotland | N6: UNI OF GLASGOW KEYSTONE BUILDING | O6: =IF(G6<0.03,"",J6) -> 58.78 | P6: =+F6/H6 -> 58.777778
A7: QL-0218041 | B7: 48 | C7: GBP | D7: 56.42 | E7: GBP | F7: 2708.16 | G7: 0.96 | H7: 46.08 | I7: GBP | J7: 58.77 | K7: SYS 330 TILE STEEL 1600mm X 600mm 1522 10 RAL 9010 20% WRAPPED 16 80 KG SQUARE | L7: Becky Titley | M7: Scotland | N7: UNI OF GLASGOW KEYSTONE BUILDING | O7: =IF(G7<0.03,"",J7) -> 58.77 | P7: =+F7/H7 -> 58.770833
A8: QL-0222743 | B8: 145 | C8: GBP | D8: 23.4 | E8: GBP | F8: 3393 | G8: 0.36 | H8: 52.2 | I8: GBP | J8: 65 | K8: SYS 330 TILE STEEL 1200mm X 300mm 1522 10 RAL 9010 20% WRAPPED 16 80 KG SQUARE | L8: Chris Edge | M8: North | N8: PICCADILLY PLACE NO 3 FLR 6 & 7 REFURB MANCHESTER | O8: =IF(G8<0.03,"",J8) -> 65 | P8: =+F8/H8 -> 65
A9: QL-0220441 | B9: 22 | C9: GBP | D9: 89.6 | E9: GBP | F9: 1971.2 | G9: 1.28 | H9: 28.16 | I9: GBP | J9: 70 | K9: SYS 330 TILE STEEL 1600mm X 800mm 1522 10 RAL 9016 20% WRAPPED 16 80 KG SQUARE | L9: Chris Edge | M9: North | N9: PROJECT NEXUS MANCHESTER | O9: =IF(G9<0.03,"",J9) -> 70 | P9: =+F9/H9 -> 70
A10: QL-0220269 | B10: 246 | C10: GBP | D10: 50.19 | E10: GBP | F10: 12346.74 | G10: 0.72 | H10: 177.12 | I10: GBP | J10: 69.71 | K10: SYS 330 TILE STEEL 1200mm X 600mm 1522 10 RAL 9010 20% WRAPPED 16 80 KG SQUARE | L10: Chris Edge | M10: North | N10: WELLINGTON PLAZA LEEDS | O10: =IF(G10<0.03,"",J10) -> 69.71 | P10: =+F10/H10 -> 69.708333
A11: QL-0222650 | B11: 725 | C11: GBP | D11: 46.87 | E11: GBP | F11: 33980.75 | G11: 0.72 | H11: 522 | I11: GBP | J11: 65.1 | K11: SYS 330 TILE STEEL 1200mm X 600mm 4050 35 RAL 9016 20% WRAPPED 16 80 KG SQUARE | L11: Ed Fagan | M11: London | N11: BAKER STREET NO 25 CAT B MOELIS FLOORS 3-4 LONDON | O11: =IF(G11<0.03,"",J11) -> 65.1 | P11: =+F11/H11 -> 65.097222
A12: QL-0222719 | B12: 14 | C12: GBP | D12: 23.44 | E12: GBP | F12: 328.16 | G12: 0.36 | H12: 5.04 | I12: GBP | J12: 65.11 | K12: SYS 330 TILE STEEL 600mm X 600mm 4050 35 RAL 9016 20% WRAPPED 16 80 KG SQUARE | L12: Ed Fagan | M12: London | N12: BAKER STREET NO 25 CAT B MOELIS FLOORS 3-4 LONDON | O12: =IF(G12<0.03,"",J12) -> 65.11 | P12: =+F12/H12 -> 65.111111
A13: QL-0222665 | B13: 725 | C13: GBP | D13: 29.3 | E13: GBP | F13: 21242.5 | G13: 0.45 | H13: 326.25 | I13: GBP | J13: 65.11 | K13: SYS 330 TILE STEEL 1200mm X 375mm 4050 35 RAL 9016 20% WRAPPED 16 80 KG SQUARE | L13: Ed Fagan | M13: London | N13: BAKER STREET NO 25 CAT B MOELIS FLOORS 3-4 LONDON | O13: =IF(G13<0.03,"",J13) -> 65.11 | P13: =+F13/H13 -> 65.111111
... A43: QL-0219262 | B43: 5201 | C43: GBP | D43: 40.94 | E43: GBP | F43: 212928.94 | G43: 0.46 | H43: 2387.26 | I43: GBP | J43: 89.19 | K43: SYS 330 TILE AL 1350mm X 340mm LEAF-SMALL RAL 9006 30% NO INFILL SQUARE | L43: Sam James | M43: Northern Home Counties | N43: WITAN GATE HOUSE OFFICE REFURB PHASE 2 MILTON KEYNES | O43: =IF(G43<0.03,"",J43) -> 89.19 | P43: =+F43/H43 -> 89.193862

Sheet  SQM Wk 23
A1: Line Name | B1: Quantity | C1: Net Unit Price Currency | D1: Net Unit Price | E1: Net Total Currency | F1: Net Total | G1: Item SQM | H1: Line SQM | I1: Â£/SQM Currency | J1: Â£/SQM | K1: Project Owner: Full Name | L1: Sales Region | M1: Project Name | N1: =AVERAGE(N2:N81) -> 87.727857 | O1: =AVERAGE(O2:O81) -> 87.724497
A2: QL-0216189 | B2: 176 | C2: GBP | D2: 134.93 | E2: GBP | F2: 23747.68 | G2: 1.01 | H2: 178.28 | I2: GBP | J2: 133.21 | K2: Ed Fagan | L2: London | M2: NEWGATE STREET NO 81 BT CENTRE HSBC AMR LONDON | N2: =IF(G2<0.03,"",J2) -> 133.21 | O2: =+F2/H2 -> 133.2044
A3: QL-0216190 | B3: 348 | C3: GBP | D3: 134.93 | E3: GBP | F3: 46955.64 | G3: 1.01 | H3: 352.5 | I3: GBP | J3: 133.21 | K3: Ed Fagan | L3: London | M3: NEWGATE STREET NO 81 BT CENTRE HSBC AMR LONDON | N3: =IF(G3<0.03,"",J3) -> 133.21 | O3: =+F3/H3 -> 133.20749
A4: QL-0216191 | B4: 148 | C4: GBP | D4: 144.37 | E4: GBP | F4: 21366.76 | G4: 0.99 | H4: 145.93 | I4: GBP | J4: 146.42 | K4: Ed Fagan | L4: London | M4: NEWGATE STREET NO 81 BT CENTRE HSBC AMR LONDON | N4: =IF(G4<0.03,"",J4) -> 146.42 | O4: =+F4/H4 -> 146.41787
A5: QL-0216192 | B5: 88 | C5: GBP | D5: 134.93 | E5: GBP | F5: 11873.84 | G5: 0.99 | H5: 86.77 | I5: GBP | J5: 136.85 | K5: Ed Fagan | L5: London | M5: NEWGATE STREET NO 81 BT CENTRE HSBC AMR LONDON | N5: =IF(G5<0.03,"",J5) -> 136.85 | O5: =+F5/H5 -> 136.84269
A6: QL-0216193 | B6: 88 | C6: GBP | D6: 138.06 | E6: GBP | F6: 12149.28 | G6: 0.99 | H6: 86.77 | I6: GBP | J6: 140.02 | K6: Ed Fagan | L6: London | M6: NEWGATE STREET NO 81 BT CENTRE HSBC AMR LONDON | N6: =IF(G6<0.03,"",J6) -> 140.02 | O6: =+F6/H6 -> 140.01706
A7: QL-0216194 | B7: 352 | C7: GBP | D7: 67.63 | E7: GBP | F7: 23805.76 | G7: 0.97 | H7: 339.96 | I7: GBP | J7: 70.03 | K7: Ed Fagan | L7: London | M7: NEWGATE STREET NO 81 BT CENTRE HSBC AMR LONDON | N7: =IF(G7<0.03,"",J7) -> 70.03 | O7: =+F7/H7 -> 70.025179
A8: QL-0216195 | B8: 208 | C8: GBP | D8: 77.99 | E8: GBP | F8: 16221.92 | G8: 0.93 | H8: 194.29 | I8: GBP | J8: 83.49 | K8: Ed Fagan | L8: London | M8: NEWGATE STREET NO 81 BT CENTRE HSBC AMR LONDON | N8: =IF(G8<0.03,"",J8) -> 83.49 | O8: =+F8/H8 -> 83.493335
A9: QL-0216196 | B9: 88 | C9: GBP | D9: 125.5 | E9: GBP | F9: 11044 | G9: 0.93 | H9: 82.2 | I9: GBP | J9: 134.35 | K9: Ed Fagan | L9: London | M9: NEWGATE STREET NO 81 BT CENTRE HSBC AMR LONDON | N9: =IF(G9<0.03,"",J9) -> 134.35 | O9: =+F9/H9 -> 134.35523
A10: QL-0216197 | B10: 200 | C10: GBP | D10: 125.58 | E10: GBP | F10: 25116 | G10: 0.99 | H10: 197.2 | I10: GBP | J10: 127.37 | K10: Ed Fagan | L10: London | M10: NEWGATE STREET NO 81 BT CENTRE HSBC AMR LONDON | N10: =IF(G10<0.03,"",J10) -> 127.37 | O10: =+F10/H10 -> 127.36308
A11: QL-0216198 | B11: 200 | C11: GBP | D11: 82.27 | E11: GBP | F11: 16454 | G11: 0.96 | H11: 191.84 | I11: GBP | J11: 85.77 | K11: Ed Fagan | L11: London | M11: NEWGATE STREET NO 81 BT CENTRE HSBC AMR LONDON | N11: =IF(G11<0.03,"",J11) -> 85.77 | O11: =+F11/H11 -> 85.769391
A12: QL-0216199 | B12: 200 | C12: GBP | D12: 84.29 | E12: GBP | F12: 16858 | G12: 0.93 | H12: 185.54 | I12: GBP | J12: 90.86 | K12: Ed Fagan | L12: London | M12: NEWGATE STREET NO 81 BT CENTRE HSBC AMR LONDON | N12: =IF(G12<0.03,"",J12) -> 90.86 | O12: =+F12/H12 -> 90.859114
A13: QL-0217160 | B13: 70 | C13: GBP | D13: 73.23 | E13: GBP | F13: 5126.1 | G13: 1.08 | H13: 75.6 | I13: GBP | J13: 67.81 | K13: Emily Judges | L13: London | M13: FCDO KING CHARLES STREET REFURB LONDON | N13: =IF(G13<0.03,"",J13) -> 67.81 | O13: =+F13/H13 -> 67.805556
... A43: QL-0217257 | B43: 139 | C43: GBP | D43: 22.17 | E43: GBP | F43: 3081.63 | G43: 0.36 | H43: 50.04 | I43: GBP | J43: 61.58 | K43: Sam James | L43: Northern Home Counties | M43: GSK LAB BUILDING 2 BASEMENT STEVENAGE | N43: =IF(G43<0.03,"",J43) -> 61.58 | O43: =+F43/H43 -> 61.583333
J44: =AVERAGE(J2:J43) -> 87.727857

Sheet SQM Wk 22
A1: Line Name | B1: Quantity | C1: Net Unit Price Currency | D1: Net Unit Price | E1: Net Total Currency | F1: Net Total | G1: Item SQM | H1: Line SQM | I1: Â£/SQM Currency | J1: Â£/SQM | K1: Project Owner: Full Name | L1: Sales Region | M1: Project Name | N1: =AVERAGE(N2:N81) -> 75.655769 | O1: =AVERAGE(O2:O81) -> 752.53882
A2: QL-0213463 | B2: 132 | C2: GBP | D2: 21.96 | E2: GBP | F2: 2898.72 | G2: 0.36 | H2: 47.52 | I2: GBP | J2: 61 | K2: Chris Edge | L2: North | M2: BALLAM ROAD BEAVERBROOK HQ LYTHAM ST ANNES | N2: =IF(G2<0.03,"",J2) -> 61 | O2: =IFERROR(+F2/H2,"") -> 61 | P2: excluding 0.01 and 0.02 which were distoring the results
A3: QL-0213506 | B3: 146 | C3: GBP | D3: 21.96 | E3: GBP | F3: 3206.16 | G3: 0.36 | H3: 52.56 | I3: GBP | J3: 61 | K3: Chris Edge | L3: North | M3: BALLAM ROAD BEAVERBROOK HQ LYTHAM ST ANNES | N3: =IF(G3<0.03,"",J3) -> 61 | O3: =IFERROR(+F3/H3,"") -> 61
A4: QL-0213524 | B4: 10 | C4: GBP | D4: 32.94 | E4: GBP | F4: 329.4 | G4: 0.54 | H4: 5.4 | I4: GBP | J4: 61 | K4: Chris Edge | L4: North | M4: BALLAM ROAD BEAVERBROOK HQ LYTHAM ST ANNES | N4: =IF(G4<0.03,"",J4) -> 61 | O4: =IFERROR(+F4/H4,"") -> 61
A5: QL-0213744 | B5: 67 | C5: GBP | D5: 27.45 | E5: GBP | F5: 1839.15 | G5: 0.45 | H5: 30.15 | I5: GBP | J5: 61 | K5: Chris Edge | L5: North | M5: BALLAM ROAD BEAVERBROOK HQ LYTHAM ST ANNES | N5: =IF(G5<0.03,"",J5) -> 61 | O5: =IFERROR(+F5/H5,"") -> 61
A6: QL-0213749 | B6: 7 | C6: GBP | D6: 27.45 | E6: GBP | F6: 192.15 | G6: 0.45 | H6: 3.15 | I6: GBP | J6: 61 | K6: Chris Edge | L6: North | M6: BALLAM ROAD BEAVERBROOK HQ LYTHAM ST ANNES | N6: =IF(G6<0.03,"",J6) -> 61 | O6: =IFERROR(+F6/H6,"") -> 61
A7: QL-0213152 | B7: 31425 | C7: GBP | D7: 53.45 | E7: GBP | F7: 1679666.2 | G7: 0.72 | H7: 22635.43 | I7: GBP | J7: 74.21 | K7: Ed Fagan | L7: London | M7: BRITISH AIRWAYS HQ WATERSIDE PH 2 HARMONDSWORTH | N7: =IF(G7<0.03,"",J7) -> 74.21 | O7: =IFERROR(+F7/H7,"") -> 74.205184
A8: QL-0213154 | B8: 22482 | C8: GBP | D8: 49.64 | E8: GBP | F8: 1116006.5 | G8: 0.71 | H8: 15968.74 | I8: GBP | J8: 69.89 | K8: Ed Fagan | L8: London | M8: BRITISH AIRWAYS HQ WATERSIDE PH 2 HARMONDSWORTH | N8: =IF(G8<0.03,"",J8) -> 69.89 | O8: =IFERROR(+F8/H8,"") -> 69.886947
A9: QL-0213169 | B9: 22482 | C9: GBP | D9: 50.34 | E9: GBP | F9: 1131743.9 | G9: 0.72 | H9: 16193.78 | I9: GBP | J9: 69.89 | K9: Ed Fagan | L9: London | M9: BRITISH AIRWAYS HQ WATERSIDE PH 2 HARMONDSWORTH | N9: =IF(G9<0.03,"",J9) -> 69.89 | O9: =IFERROR(+F9/H9,"") -> 69.887567
A10: QL-0213193 | B10: 22482 | C10: GBP | D10: 82.16 | E10: GBP | F10: 1847121.1 | G10: 0.72 | H10: 16193.78 | I10: GBP | J10: 114.06 | K10: Ed Fagan | L10: London | M10: BRITISH AIRWAYS HQ WATERSIDE PH 2 HARMONDSWORTH | N10: =IF(G10<0.03,"",J10) -> 114.06 | O10: =IFERROR(+F10/H10,"") -> 114.06362
A11: QL-0213199 | B11: 31425 | C11: GBP | D11: 83.37 | E11: GBP | F11: 2619902.2 | G11: 0.72 | H11: 22635.43 | I11: GBP | J11: 115.74 | K11: Ed Fagan | L11: London | M11: BRITISH AIRWAYS HQ WATERSIDE PH 2 HARMONDSWORTH | N11: =IF(G11<0.03,"",J11) -> 115.74 | O11: =IFERROR(+F11/H11,"") -> 115.74343
A12: QL-0213214 | B12: 22482 | C12: GBP | D12: 82.73 | E12: GBP | F12: 1859935.9 | G12: 0.71 | H12: 15968.74 | I12: GBP | J12: 116.47 | K12: Ed Fagan | L12: London | M12: BRITISH AIRWAYS HQ WATERSIDE PH 2 HARMONDSWORTH | N12: =IF(G12<0.03,"",J12) -> 116.47 | O12: =IFERROR(+F12/H12,"") -> 116.47355
A13: QL-0212921 | B13: 44 | C13: GBP | D13: 77.35 | E13: GBP | F13: 3403.4 | G13: 0.91 | H13: 40.04 | I13: GBP | J13: 85 | K13: Emily Judges | L13: London | M13: CHARLOTTE STREET NO 80 AURUM FIT OUT FLOOR 2 LONDON | N13: =IF(G13<0.03,"",J13) -> 85 | O13: =IFERROR(+F13/H13,"") -> 85
A14: QL-0212938 | B14: 33 | C14: GBP | D14: 101.31 | E14: GBP | F14: 3343.23 | G14: 1.21 | H14: 40.04 | I14: GBP | J14: 83.5 | K14: Emily Judges | L14: London | M14: CHARLOTTE STREET NO 80 AURUM FIT OUT FLOOR 2 LONDON | N14: =IF(G14<0.03,"",J14) -> 83.5 | O14: =IFERROR(+F14/H14,"") -> 83.497253
... A56: QL-0212058 | B56: 2 | C56: GBP | D56: 32.98 | E56: GBP | F56: 65.96 | G56: 0.02 | H56: 0.03 | I56: GBP | J56: 2061.25 | K56: Peter Gray | L56: London | M56: THREADNEEDLE STREET NO 60 CAT A FLOOR 8 LONDON | N56: =IF(G56<0.03,"",J56) | O56: =IFERROR(+F56/H56,"") -> 2198.6667
A57: QL-0212080 | B57: 2 | C57: GBP | D57: 79.77 | E57: GBP | F57: 159.54 | G57: 0 | H57: 0 | J57: #Error! | K57: Peter Gray | L57: London | M57: THREADNEEDLE STREET NO 60 CAT A FLOOR 8 LONDON | N57: =IF(G57<0.03,"",J57) | O57: =IFERROR(+F57/H57,"")
A58: QL-0212086 | B58: 2 | C58: GBP | D58: 13.11 | E58: GBP | F58: 26.22 | G58: 0.01 | H58: 0.01 | I58: GBP | J58: 2061.32 | K58: Peter Gray | L58: London | M58: THREADNEEDLE STREET NO 60 CAT A FLOOR 8 LONDON | N58: =IF(G58<0.03,"",J58) | O58: =IFERROR(+F58/H58,"") -> 2622
A59: QL-0212087 | B59: 2 | C59: GBP | D59: 32.98 | E59: GBP | F59: 65.96 | G59: 0.02 | H59: 0.03 | I59: GBP | J59: 2061.25 | K59: Peter Gray | L59: London | M59: THREADNEEDLE STREET NO 60 CAT A FLOOR 8 LONDON | N59: =IF(G59<0.03,"",J59) | O59: =IFERROR(+F59/H59,"") -> 2198.6667
A60: QL-0212100 | B60: 2 | C60: GBP | D60: 61.95 | E60: GBP | F60: 123.9 | G60: 0 | H60: 0 | J60: #Error! | K60: Peter Gray | L60: London | M60: THREADNEEDLE STREET NO 60 CAT A FLOOR 8 LONDON | N60: =IF(G60<0.03,"",J60) | O60: =IFERROR(+F60/H60,"")
A61: QL-0212104 | B61: 2 | C61: GBP | D61: 13.11 | E61: GBP | F61: 26.22 | G61: 0.01 | H61: 0.01 | I61: GBP | J61: 2061.32 | K61: Peter Gray | L61: London | M61: THREADNEEDLE STREET NO 60 CAT A FLOOR 8 LONDON | N61: =IF(G61<0.03,"",J61) | O61: =IFERROR(+F61/H61,"") -> 2622
A62: QL-0212105 | B62: 2 | C62: GBP | D62: 32.98 | E62: GBP | F62: 65.96 | G62: 0.02 | H62: 0.03 | I62: GBP | J62: 2061.25 | K62: Peter Gray | L62: London | M62: THREADNEEDLE STREET NO 60 CAT A FLOOR 8 LONDON | N62: =IF(G62<0.03,"",J62) | O62: =IFERROR(+F62/H62,"") -> 2198.6667
A63: QL-0212126 | B63: 8 | C63: GBP | D63: 32.98 | E63: GBP | F63: 263.84 | G63: 0.02 | H63: 0.13 | I63: GBP | J63: 2061.25 | K63: Peter Gray | L63: London | M63: THREADNEEDLE STREET NO 60 CAT A FLOOR 8 LONDON | N63: =IF(G63<0.03,"",J63) | O63: =IFERROR(+F63/H63,"") -> 2029.5385
A64: QL-0212134 | B64: 1 | C64: GBP | D64: 32.98 | E64: GBP | F64: 32.98 | G64: 0.02 | H64: 0.02 | I64: GBP | J64: 2061.25 | K64: Peter Gray | L64: London | M64: THREADNEEDLE STREET NO 60 CAT A FLOOR 8 LONDON | N64: =IF(G64<0.03,"",J64) | O64: =IFERROR(+F64/H64,"") -> 1649
A65: QL-0212145 | B65: 1 | C65: GBP | D65: 13.11 | E65: GBP | F65: 13.11 | G65: 0.01 | H65: 0.01 | I65: GBP | J65: 2061.32 | K65: Peter Gray | L65: London | M65: THREADNEEDLE STREET NO 60 CAT A FLOOR 8 LONDON | N65: =IF(G65<0.03,"",J65) | O65: =IFERROR(+F65/H65,"") -> 1311
A66: QL-0212150 | B66: 2 | C66: GBP | D66: 13.11 | E66: GBP | F66: 26.22 | G66: 0.01 | H66: 0.01 | I66: GBP | J66: 2061.32 | K66: Peter Gray | L66: London | M66: THREADNEEDLE STREET NO 60 CAT A FLOOR 8 LONDON | N66: =IF(G66<0.03,"",J66) | O66: =IFERROR(+F66/H66,"") -> 2622
A67: QL-0212163 | B67: 1 | C67: GBP | D67: 67.28 | E67: GBP | F67: 67.28 | G67: 0.77 | H67: 0.77 | I67: GBP | J67: 87.62 | K67: Peter Gray | L67: London | M67: THREADNEEDLE STREET NO 60 CAT A FLOOR 8 LONDON | N67: =IF(G67<0.03,"",J67) -> 87.62 | O67: =IFERROR(+F67/H67,"") -> 87.376623
A68: QL-0212171 | B68: 2 | C68: GBP | D68: 13.11 | E68: GBP | F68: 26.22 | G68: 0.01 | H68: 0.01 | I68: GBP | J68: 2061.32 | K68: Peter Gray | L68: London | M68: THREADNEEDLE STREET NO 60 CAT A FLOOR 8 LONDON | N68: =IF(G68<0.03,"",J68) | O68: =IFERROR(+F68/H68,"") -> 2622
A69: QL-0212172 | B69: 1 | C69: GBP | D69: 32.98 | E69: GBP | F69: 32.98 | G69: 0.02 | H69: 0.02 | I69: GBP | J69: 2061.25 | K69: Peter Gray | L69: London | M69: THREADNEEDLE STREET NO 60 CAT A FLOOR 8 LONDON | N69: =IF(G69<0.03,"",J69) | O69: =IFERROR(+F69/H69,"") -> 1649
A70: QL-0212187 | B70: 1 | C70: GBP | D70: 67.28 | E70: GBP | F70: 67.28 | G70: 0.77 | H70: 0.77 | I70: GBP | J70: 87.62 | K70: Peter Gray | L70: London | M70: THREADNEEDLE STREET NO 60 CAT A FLOOR 8 LONDON | N70: =IF(G70<0.03,"",J70) -> 87.62 | O70: =IFERROR(+F70/H70,"") -> 87.376623
A71: QL-0212195 | B71: 3 | C71: GBP | D71: 13.11 | E71: GBP | F71: 39.33 | G71: 0.01 | H71: 0.02 | I71: GBP | J71: 2061.32 | K71: Peter Gray | L71: London | M71: THREADNEEDLE STREET NO 60 CAT A FLOOR 8 LONDON | N71: =IF(G71<0.03,"",J71) | O71: =IFERROR(+F71/H71,"") -> 1966.5
A72: QL-0212196 | B72: 3 | C72: GBP | D72: 32.98 | E72: GBP | F72: 98.94 | G72: 0.02 | H72: 0.05 | I72: GBP | J72: 2061.25 | K72: Peter Gray | L72: London | M72: THREADNEEDLE STREET NO 60 CAT A FLOOR 8 LONDON | N72: =IF(G72<0.03,"",J72) | O72: =IFERROR(+F72/H72,"") -> 1978.8
... A81: QL-0211286 | B81: 1905 | C81: GBP | D81: 21.6 | E81: GBP | F81: 41148 | G81: 0.36 | H81: 685.8 | I81: GBP | J81: 60 | K81: Sam James | L81: Northern Home Counties | M81: UNI OF EAST ANGLIA NORWICH CAMPUS | N81: =IF(G81<0.03,"",J81) -> 60 | O81: =IFERROR(+F81/H81,"") -> 60

Sheet Wk no's
B1: Date | C1: Week No | D1: Date in Text Format
B2: 45658 | C2: 1 | D2: =TEXT(B2,"DD")&"/"&TEXT(B2,"MM")&"/"&TEXT(B2,"YYYY") -> 01/01/2025
B3: =+B2+1 -> 45659 | C3: 1 | D3: =TEXT(B3,"DD")&"/"&TEXT(B3,"MM")&"/"&TEXT(B3,"YYYY") -> 02/01/2025
A4: =TEXT(B4,"ddd") -> Fri | B4: =+B3+1 -> 45660 | C4: =IF(A4="Sat",C3+1,C3) -> 1 | D4: =TEXT(B4,"DD")&"/"&TEXT(B4,"MM")&"/"&TEXT(B4,"YYYY") -> 03/01/2025
A5: =TEXT(B5,"ddd") -> Sat | B5: =+B4+1 -> 45661 | C5: =IF(A5="Sat",C4+1,C4) -> 2 | D5: =TEXT(B5,"DD")&"/"&TEXT(B5,"MM")&"/"&TEXT(B5,"YYYY") -> 04/01/2025
A6: =TEXT(B6,"ddd") -> Sun | B6: =+B5+1 -> 45662 | C6: =IF(A6="Sat",C5+1,C5) -> 2 | D6: =TEXT(B6,"DD")&"/"&TEXT(B6,"MM")&"/"&TEXT(B6,"YYYY") -> 05/01/2025
A7: =TEXT(B7,"ddd") -> Mon | B7: =+B6+1 -> 45663 | C7: =IF(A7="Sat",C6+1,C6) -> 2 | D7: =TEXT(B7,"DD")&"/"&TEXT(B7,"MM")&"/"&TEXT(B7,"YYYY") -> 06/01/2025
A8: =TEXT(B8,"ddd") -> Tue | B8: =+B7+1 -> 45664 | C8: =IF(A8="Sat",C7+1,C7) -> 2 | D8: =TEXT(B8,"DD")&"/"&TEXT(B8,"MM")&"/"&TEXT(B8,"YYYY") -> 07/01/2025
A9: =TEXT(B9,"ddd") -> Wed | B9: =+B8+1 -> 45665 | C9: =IF(A9="Sat",C8+1,C8) -> 2 | D9: =TEXT(B9,"DD")&"/"&TEXT(B9,"MM")&"/"&TEXT(B9,"YYYY") -> 08/01/2025
A10: =TEXT(B10,"ddd") -> Thu | B10: =+B9+1 -> 45666 | C10: =IF(A10="Sat",C9+1,C9) -> 2 | D10: =TEXT(B10,"DD")&"/"&TEXT(B10,"MM")&"/"&TEXT(B10,"YYYY") -> 09/01/2025
A11: =TEXT(B11,"ddd") -> Fri | B11: =+B10+1 -> 45667 | C11: =IF(A11="Sat",C10+1,C10) -> 2 | D11: =TEXT(B11,"DD")&"/"&TEXT(B11,"MM")&"/"&TEXT(B11,"YYYY") -> 10/01/2025
A12: =TEXT(B12,"ddd") -> Sat | B12: =+B11+1 -> 45668 | C12: =IF(A12="Sat",C11+1,C11) -> 3 | D12: =TEXT(B12,"DD")&"/"&TEXT(B12,"MM")&"/"&TEXT(B12,"YYYY") -> 11/01/2025
A13: =TEXT(B13,"ddd") -> Sun | B13: =+B12+1 -> 45669 | C13: =IF(A13="Sat",C12+1,C12) -> 3 | D13: =TEXT(B13,"DD")&"/"&TEXT(B13,"MM")&"/"&TEXT(B13,"YYYY") -> 12/01/2025
A14: =TEXT(B14,"ddd") -> Mon | B14: =+B13+1 -> 45670 | C14: =IF(A14="Sat",C13+1,C13) -> 3 | D14: =TEXT(B14,"DD")&"/"&TEXT(B14,"MM")&"/"&TEXT(B14,"YYYY") -> 13/01/2025
A15: =TEXT(B15,"ddd") -> Tue | B15: =+B14+1 -> 45671 | C15: =IF(A15="Sat",C14+1,C14) -> 3 | D15: =TEXT(B15,"DD")&"/"&TEXT(B15,"MM")&"/"&TEXT(B15,"YYYY") -> 14/01/2025
... A366: =TEXT(B366,"ddd") -> Wed | B366: =+B365+1 -> 46022 | C366: =IF(A366="Sat",C365+1,C365) -> 53 | D366: =TEXT(B366,"DD")&"/"&TEXT(B366,"MM")&"/"&TEXT(B366,"YYYY") -> 31/12/2025
