Workbook
Name Display_Week: '[1]High Level'!$D$3
Name Project_Start: '[1]High Level'!$D$2

Sheet KPI Linked Table for Report
A1: =_xlfn.XLOOKUP('KPI Linked Table for Report'!C1,'Week No''s'!B3:B55,'Week No''s'!C3:C55) -> 45947 | B1: Current Week | C1: 42 | E1: Top KPI's by Department - Last 5 week Data | P1: Week | Q1: Week | S1: =+X8 -> 42 | W1: =+X9 -> 45947 | AC1: automatic | AE1: Week | AF1: =+S1 -> 42 | AH1: =+AI9 -> 45947
A2: Sep | B2: Current Month | C2: =_xlfn.XLOOKUP('KPI Linked Table for Report'!A2,'Week No''s'!E:E,'Week No''s'!F:F,0) -> 9 | F2: Displayed below is a mixture of the actual KPI result and the KPI Calc i.e. actual result / Target (In some cases this is inverted) depending on whether the test is adverse if above or below see column M for the definition
D3: Week Ending | F3: The KPI Calc Colours are - Green if KPI Calc is 100% or Greater , Amber if between 95% and 99.9%, Red if lower than 95% | P3: =+R3-1 -> 38 | R3: =+T3-1 -> 39 | T3: =+V3-1 -> 40 | V3: =+X3-1 -> 41 | X3: =+C1 -> 42 | AC3: <<<<Update Wk nos here
D4: Mth no | AE4: Test results by week - 1st Block some are actual results
F5: In HR and Finance there are Monthly KPIs these are noted by the M in the "Freq" column. The "WK" column De
C6: Tab | F6: Department | G6: Manager | H6: Freq | I6: Wk | J6: Category | K6: KPI | L6: UOM | M6: Shown | P6: Week KPI Calc | AE6: Week KPI Calc | AF6: Week KPI Calc | AG6: Week KPI Calc | AH6: Week KPI Calc | AI6: Week KPI Calc
A7: Lookup Drivers for | F7: Mth No | H7: For Monthly KPIs | P7: =_xlfn.XLOOKUP('KPI Linked Table for Report'!P8,'KPI Analysis'!$CU$7:$EU$7,'KPI Analysis'!$CU$8:$EU$8) -> 8 | R7: =_xlfn.XLOOKUP('KPI Linked Table for Report'!R8,'KPI Analysis'!$CU$7:$EU$7,'KPI Analysis'!$CU$8:$EU$8) -> 8 | T7: =_xlfn.XLOOKUP('KPI Linked Table for Report'!T8,'KPI Analysis'!$CU$7:$EU$7,'KPI Analysis'!$CU$8:$EU$8) -> 9 | V7: =_xlfn.XLOOKUP('KPI Linked Table for Report'!V8,'KPI Analysis'!$CU$7:$EU$7,'KPI Analysis'!$CU$8:$EU$8) -> 9 | X7: =_xlfn.XLOOKUP('KPI Linked Table for Report'!X8,'KPI Analysis'!$CU$7:$EU$7,'KPI Analysis'!$CU$8:$EU$8) -> 9 | AC7: automatic | AE7: =_xlfn.XLOOKUP('KPI Linked Table for Report'!AE8,'KPI Analysis'!$CU$7:$EU$7,'KPI Analysis'!$CU$8:$EU$8) -> 8 | AF7: =_xlfn.XLOOKUP('KPI Linked Table for Report'!AF8,'KPI Analysis'!$CU$7:$EU$7,'KPI Analysis'!$CU$8:$EU$8) -> 8 | AG7: =_xlfn.XLOOKUP('KPI Linked Table for Report'!AG8,'KPI Analysis'!$CU$7:$EU$7,'KPI Analysis'!$CU$8:$EU$8) -> 9 | AH7: =_xlfn.XLOOKUP('KPI Linked Table for Report'!AH8,'KPI Analysis'!$CU$7:$EU$7,'KPI Analysis'!$CU$8:$EU$8) -> 9 | AI7: =_xlfn.XLOOKUP('KPI Linked Table for Report'!AI8,'KPI Analysis'!$CU$7:$EU$7,'KPI Analysis'!$CU$8:$EU$8) -> 9
F8: Wk No | H8: For Weekly KPI's | M8: A | P8: =+P3 -> 38 | R8: =+R3 -> 39 | T8: =+T3 -> 40 | V8: =+V3 -> 41 | X8: =+X3 -> 42 | AC8: automatic | AE8: =+AF8-1 -> 38 | AF8: =+AG8-1 -> 39 | AG8: =+AH8-1 -> 40 | AH8: =+AI8-1 -> 41 | AI8: =+AF1 -> 42
F9: Date | H9: Week Ending (Fri) | P9: =_xlfn.XLOOKUP(P8,EHS!$M$6:$BM$6,EHS!$M$7:$BM$7) -> 45919 | R9: =_xlfn.XLOOKUP(R8,EHS!$M$6:$BM$6,EHS!$M$7:$BM$7) -> 45926 | T9: =_xlfn.XLOOKUP(T8,EHS!$M$6:$BM$6,EHS!$M$7:$BM$7) -> 45933 | V9: =_xlfn.XLOOKUP(V8,EHS!$M$6:$BM$6,EHS!$M$7:$BM$7) -> 45940 | X9: =_xlfn.XLOOKUP(X8,EHS!$M$6:$BM$6,EHS!$M$7:$BM$7) -> 45947 | AC9: automatic | AE9: =_xlfn.XLOOKUP(AE8,EHS!$M$6:$BM$6,EHS!$M$7:$BM$7) -> 45919 | AF9: =_xlfn.XLOOKUP(AF8,EHS!$M$6:$BM$6,EHS!$M$7:$BM$7) -> 45926 | AG9: =_xlfn.XLOOKUP(AG8,EHS!$M$6:$BM$6,EHS!$M$7:$BM$7) -> 45933 | AH9: =_xlfn.XLOOKUP(AH8,EHS!$M$6:$BM$6,EHS!$M$7:$BM$7) -> 45940 | AI9: =_xlfn.XLOOKUP(AI8,EHS!$M$6:$BM$6,EHS!$M$7:$BM$7) -> 45947
Z10: Days lost over - 3 incidents
A11: =F11&"-"&C11 -> EHS-KPI P1 | B11: =+'KPI Stats'!G10 -> Above Zero | C11: =+'KPI Stats'!C10 -> KPI P1 | F11: =+'KPI Stats'!B9 -> EHS | G11: =+'KPI Stats'!C9 -> Neil Laing | H11: W | I11: =+'KPI Stats'!F9 -> 42 | J11: =+'KPI Stats'!D10 -> Productivity | K11: =+'KPI Stats'!E10 -> Lost Working Days | L11: =+'KPI Stats'!F10 -> Lost Days | M11: =INDEX('KPI Analysis'!$CO$7:$EU$123,MATCH($A11,'KPI Analysis'!$CO$7:$CO$123,FALSE),MATCH(M$8,'KPI Analysis'!$CO$7:$EU$7,FALSE)) -> Act Result | P11: =IF( OR( INDEX('KPI Analysis'!$AH$7:$CM$123, MATCH($A11,'KPI Analysis'!$AH$7:$AH$123,FALSE), MATCH(P$8,'KPI Analysis'!$AH$7:$CM$7,FALSE) )="R", INDEX('KPI Analysis'!$AH$7:$CM$123, MATCH($A11,'KPI Analysis'!$AH$7:$AH$123,FALSE), MATCH(P$8,'KPI Analysis'!$AH$7:$CM$7,FALSE) )="G", INDEX('KPI Analysis'!$AH$7:$CM$123, MATCH($A11,'KPI Analysis'!$AH$7:$AH$123,FALSE), MATCH(P$8,'KPI Analysis'!$AH$7:$CM$7,FALSE) )="A"), INDEX('KPI Analysis'!$AH$7:$CM$123,MATCH($A11,'KPI Analysis'!$AH$7:$AH$123,FALSE),MATCH(P$8,'KPI Analysis'!$AH$7:$CM$7,FALSE)),"") -> G | Q11: =INDEX('KPI Analysis'!$EW$7:$HC$123,MATCH($A11,'KPI Analysis'!$EW$7:$EW$123,FALSE),MATCH(P$8,'KPI Analysis'!$EW$7:$HC$7,FALSE)) -> 0 | R11: =IF( OR( INDEX('KPI Analysis'!$AH$7:$CM$123, MATCH($A11,'KPI Analysis'!$AH$7:$AH$123,FALSE), MATCH(R$8,'KPI Analysis'!$AH$7:$CM$7,FALSE) )="R", INDEX('KPI Analysis'!$AH$7:$CM$123, MATCH($A11,'KPI Analysis'!$AH$7:$AH$123,FALSE), MATCH(R$8,'KPI Analysis'!$AH$7:$CM$7,FALSE) )="G", INDEX('KPI Analysis'!$AH$7:$CM$123, MATCH($A11,'KPI Analysis'!$AH$7:$AH$123,FALSE), MATCH(R$8,'KPI Analysis'!$AH$7:$CM$7,FALSE) )="A"), INDEX('KPI Analysis'!$AH$7:$CM$123,MATCH($A11,'KPI Analysis'!$AH$7:$AH$123,FALSE),MATCH(R$8,'KPI Analysis'!$AH$7:$CM$7,FALSE)),"") -> G | S11: =INDEX('KPI Analysis'!$EW$7:$HC$123,MATCH($A11,'KPI Analysis'!$EW$7:$EW$123,FALSE),MATCH(R$8,'KPI Analysis'!$EW$7:$HC$7,FALSE)) -> 0 | T11: =IF( OR( INDEX('KPI Analysis'!$AH$7:$CM$123, MATCH($A11,'KPI Analysis'!$AH$7:$AH$123,FALSE), MATCH(T$8,'KPI Analysis'!$AH$7:$CM$7,FALSE) )="R", INDEX('KPI Analysis'!$AH$7:$CM$123, MATCH($A11,'KPI Analysis'!$AH$7:$AH$123,FALSE), MATCH(T$8,'KPI Analysis'!$AH$7:$CM$7,FALSE) )="G", INDEX('KPI Analysis'!$AH$7:$CM$123, MATCH($A11,'KPI Analysis'!$AH$7:$AH$123,FALSE), MATCH(T$8,'KPI Analysis'!$AH$7:$CM$7,FALSE) )="A"), INDEX('KPI Analysis'!$AH$7:$CM$123,MATCH($A11,'KPI Analysis'!$AH$7:$AH$123,FALSE),MATCH(T$8,'KPI Analysis'!$AH$7:$CM$7,FALSE)),"") -> G | U11: =INDEX('KPI Analysis'!$EW$7:$HC$123,MATCH($A11,'KPI Analysis'!$EW$7:$EW$123,FALSE),MATCH(T$8,'KPI Analysis'!$EW$7:$HC$7,FALSE)) -> 0 | V11: =IF( OR( INDEX('KPI Analysis'!$AH$7:$CM$123, MATCH($A11,'KPI Analysis'!$AH$7:$AH$123,FALSE), MATCH(V$8,'KPI Analysis'!$AH$7:$CM$7,FALSE) )="R", INDEX('KPI Analysis'!$AH$7:$CM$123, MATCH($A11,'KPI Analysis'!$AH$7:$AH$123,FALSE), MATCH(V$8,'KPI Analysis'!$AH$7:$CM$7,FALSE) )="G", INDEX('KPI Analysis'!$AH$7:$CM$123, MATCH($A11,'KPI Analysis'!$AH$7:$AH$123,FALSE), MATCH(V$8,'KPI Analysis'!$AH$7:$CM$7,FALSE) )="A"), INDEX('KPI Analysis'!$AH$7:$CM$123,MATCH($A11,'KPI Analysis'!$AH$7:$AH$123,FALSE),MATCH(V$8,'KPI Analysis'!$AH$7:$CM$7,FALSE)),"") -> G | W11: =INDEX('KPI Analysis'!$EW$7:$HC$123,MATCH($A11,'KPI Analysis'!$EW$7:$EW$123,FALSE),MATCH(V$8,'KPI Analysis'!$EW$7:$HC$7,FALSE)) -> 0 | X11: =IF( OR( INDEX('KPI Analysis'!$AH$7:$CM$123, MATCH($A11,'KPI Analysis'!$AH$7:$AH$123,FALSE), MATCH(X$8,'KPI Analysis'!$AH$7:$CM$7,FALSE) )="R", INDEX('KPI Analysis'!$AH$7:$CM$123, MATCH($A11,'KPI Analysis'!$AH$7:$AH$123,FALSE), MATCH(X$8,'KPI Analysis'!$AH$7:$CM$7,FALSE) )="G", INDEX('KPI Analysis'!$AH$7:$CM$123, MATCH($A11,'KPI Analysis'!$AH$7:$AH$123,FALSE), MATCH(X$8,'KPI Analysis'!$AH$7:$CM$7,FALSE) )="A"), INDEX('KPI Analysis'!$AH$7:$CM$123,MATCH($A11,'KPI Analysis'!$AH$7:$AH$123,FALSE),MATCH(X$8,'KPI Analysis'!$AH$7:$CM$7,FALSE)),"") -> G | Y11: =IF(INDEX('KPI Analysis'!$CO$7:$EU$123,MATCH($A11,'KPI Analysis'!$CO$7:$CO$123,FALSE),MATCH(X$8,'KPI Analysis'!$CO$7:$EU$7,FALSE))="OD","OD",INDEX('KPI Analysis'!$EW$7:$HC$123,MATCH($A11,'KPI Analysis'!$EW$7:$EW$123,FALSE),MATCH(X$8,'KPI Analysis'!$EW$7:$HC$7,FALSE))) -> 0 | Z11: FYTD 27 days lost (details on last pg) | AC11: EW HC | AE11: =INDEX('KPI Analysis'!$CO$7:$EU$123,MATCH($A11,'KPI Analysis'!$CO$7:$CO$123,FALSE),MATCH(AE$8,'KPI Analysis'!$CO$7:$EU$7,FALSE)) -> 0 | AF11: =INDEX('KPI Analysis'!$CO$7:$EU$123,MATCH($A11,'KPI Analysis'!$CO$7:$CO$123,FALSE),MATCH(AF$8,'KPI Analysis'!$CO$7:$EU$7,FALSE)) -> 0 | AG11: =INDEX('KPI Analysis'!$CO$7:$EU$123,MATCH($A11,'KPI Analysis'!$CO$7:$CO$123,FALSE),MATCH(AG$8,'KPI Analysis'!$CO$7:$EU$7,FALSE)) -> 0 | AH11: =INDEX('KPI Analysis'!$CO$7:$EU$123,MATCH($A11,'KPI Analysis'!$CO$7:$CO$123,FALSE),MATCH(AH$8,'KPI Analysis'!$CO$7:$EU$7,FALSE)) -> 0 | AI11: =INDEX('KPI Analysis'!$CO$7:$EU$123,MATCH($A11,'KPI Analysis'!$CO$7:$CO$123,FALSE),MATCH(AI$8,'KPI Analysis'!$CO$7:$EU$7,FALSE)) -> 0
A12: =F11&"-"&C12 -> EHS-KPI D1 | B12: =+'KPI Stats'!G11 -> Under | C12: =+'KPI Stats'!C11 -> KPI D1 | H12: W | I12: =+'KPI Stats'!F9 -> 42 | J12: =+'KPI Stats'!D11 -> Delivery | K12: =+'KPI Stats'!E11 -> Visual Inspection Count | L12: =+'KPI Stats'!F11 -> Count | M12: % of target | P12: =IF( OR( INDEX('KPI Analysis'!$AH$7:$CM$123, MATCH($A12,'KPI Analysis'!$AH$7:$AH$123,FALSE), MATCH(P$8,'KPI Analysis'!$AH$7:$CM$7,FALSE) )="R", INDEX('KPI Analysis'!$AH$7:$CM$123, MATCH($A12,'KPI Analysis'!$AH$7:$AH$123,FALSE), MATCH(P$8,'KPI Analysis'!$AH$7:$CM$7,FALSE) )="G", INDEX('KPI Analysis'!$AH$7:$CM$123, MATCH($A12,'KPI Analysis'!$AH$7:$AH$123,FALSE), MATCH(P$8,'KPI Analysis'!$AH$7:$CM$7,FALSE) )="A"), INDEX('KPI Analysis'!$AH$7:$CM$123,MATCH($A12,'KPI Analysis'!$AH$7:$AH$123,FALSE),MATCH(P$8,'KPI Analysis'!$AH$7:$CM$7,FALSE)),"") -> G | Q12: =INDEX('KPI Analysis'!$CO$7:$EU$123,MATCH($A12,'KPI Analysis'!$CO$7:$CO$123,FALSE),MATCH(P$8,'KPI Analysis'!$CO$7:$EU$7,FALSE)) -> 1.4428571 | R12: =IF( OR( INDEX('KPI Analysis'!$AH$7:$CM$123, MATCH($A12,'KPI Analysis'!$AH$7:$AH$123,FALSE), MATCH(R$8,'KPI Analysis'!$AH$7:$CM$7,FALSE) )="R", INDEX('KPI Analysis'!$AH$7:$CM$123, MATCH($A12,'KPI Analysis'!$AH$7:$AH$123,FALSE), MATCH(R$8,'KPI Analysis'!$AH$7:$CM$7,FALSE) )="G", INDEX('KPI Analysis'!$AH$7:$CM$123, MATCH($A12,'KPI Analysis'!$AH$7:$AH$123,FALSE), MATCH(R$8,'KPI Analysis'!$AH$7:$CM$7,FALSE) )="A"), INDEX('KPI Analysis'!$AH$7:$CM$123,MATCH($A12,'KPI Analysis'!$AH$7:$AH$123,FALSE),MATCH(R$8,'KPI Analysis'!$AH$7:$CM$7,FALSE)),"") -> G | S12: =INDEX('KPI Analysis'!$CO$7:$EU$123,MATCH($A12,'KPI Analysis'!$CO$7:$CO$123,FALSE),MATCH(R$8,'KPI Analysis'!$CO$7:$EU$7,FALSE)) -> 1.4142857 | T12: =IF( OR( INDEX('KPI Analysis'!$AH$7:$CM$123, MATCH($A12,'KPI Analysis'!$AH$7:$AH$123,FALSE), MATCH(T$8,'KPI Analysis'!$AH$7:$CM$7,FALSE) )="R", INDEX('KPI Analysis'!$AH$7:$CM$123, MATCH($A12,'KPI Analysis'!$AH$7:$AH$123,FALSE), MATCH(T$8,'KPI Analysis'!$AH$7:$CM$7,FALSE) )="G", INDEX('KPI Analysis'!$AH$7:$CM$123, MATCH($A12,'KPI Analysis'!$AH$7:$AH$123,FALSE), MATCH(T$8,'KPI Analysis'!$AH$7:$CM$7,FALSE) )="A"), INDEX('KPI Analysis'!$AH$7:$CM$123,MATCH($A12,'KPI Analysis'!$AH$7:$AH$123,FALSE),MATCH(T$8,'KPI Analysis'!$AH$7:$CM$7,FALSE)),"") -> G | U12: =INDEX('KPI Analysis'!$CO$7:$EU$123,MATCH($A12,'KPI Analysis'!$CO$7:$CO$123,FALSE),MATCH(T$8,'KPI Analysis'!$CO$7:$EU$7,FALSE)) -> 1.12 | V12: =IF( OR( INDEX('KPI Analysis'!$AH$7:$CM$123, MATCH($A12,'KPI Analysis'!$AH$7:$AH$123,FALSE), MATCH(V$8,'KPI Analysis'!$AH$7:$CM$7,FALSE) )="R", INDEX('KPI Analysis'!$AH$7:$CM$123, MATCH($A12,'KPI Analysis'!$AH$7:$AH$123,FALSE), MATCH(V$8,'KPI Analysis'!$AH$7:$CM$7,FALSE) )="G", INDEX('KPI Analysis'!$AH$7:$CM$123, MATCH($A12,'KPI Analysis'!$AH$7:$AH$123,FALSE), MATCH(V$8,'KPI Analysis'!$AH$7:$CM$7,FALSE) )="A"), INDEX('KPI Analysis'!$AH$7:$CM$123,MATCH($A12,'KPI Analysis'!$AH$7:$AH$123,FALSE),MATCH(V$8,'KPI Analysis'!$AH$7:$CM$7,FALSE)),"") -> G | W12: =INDEX('KPI Analysis'!$CO$7:$EU$123,MATCH($A12,'KPI Analysis'!$CO$7:$CO$123,FALSE),MATCH(V$8,'KPI Analysis'!$CO$7:$EU$7,FALSE)) -> 1.04 | X12: =IF( OR( INDEX('KPI Analysis'!$AH$7:$CM$123, MATCH($A12,'KPI Analysis'!$AH$7:$AH$123,FALSE), MATCH(X$8,'KPI Analysis'!$AH$7:$CM$7,FALSE) )="R", INDEX('KPI Analysis'!$AH$7:$CM$123, MATCH($A12,'KPI Analysis'!$AH$7:$AH$123,FALSE), MATCH(X$8,'KPI Analysis'!$AH$7:$CM$7,FALSE) )="G", INDEX('KPI Analysis'!$AH$7:$CM$123, MATCH($A12,'KPI Analysis'!$AH$7:$AH$123,FALSE), MATCH(X$8,'KPI Analysis'!$AH$7:$CM$7,FALSE) )="A"), INDEX('KPI Analysis'!$AH$7:$CM$123,MATCH($A12,'KPI Analysis'!$AH$7:$AH$123,FALSE),MATCH(X$8,'KPI Analysis'!$AH$7:$CM$7,FALSE)),"") -> G | Y12: =INDEX('KPI Analysis'!$CO$7:$EU$123,MATCH($A12,'KPI Analysis'!$CO$7:$CO$123,FALSE),MATCH(X$8,'KPI Analysis'!$CO$7:$EU$7,FALSE)) -> 1.03 | AC12: Co EU | AE12: =INDEX('KPI Analysis'!$CO$7:$EU$123,MATCH($A12,'KPI Analysis'!$CO$7:$CO$123,FALSE),MATCH(AE$8,'KPI Analysis'!$CO$7:$EU$7,FALSE)) -> 1.4428571 | AF12: =INDEX('KPI Analysis'!$CO$7:$EU$123,MATCH($A12,'KPI Analysis'!$CO$7:$CO$123,FALSE),MATCH(AF$8,'KPI Analysis'!$CO$7:$EU$7,FALSE)) -> 1.4142857 | AG12: =INDEX('KPI Analysis'!$CO$7:$EU$123,MATCH($A12,'KPI Analysis'!$CO$7:$CO$123,FALSE),MATCH(AG$8,'KPI Analysis'!$CO$7:$EU$7,FALSE)) -> 1.12 | AH12: =INDEX('KPI Analysis'!$CO$7:$EU$123,MATCH($A12,'KPI Analysis'!$CO$7:$CO$123,FALSE),MATCH(AH$8,'KPI Analysis'!$CO$7:$EU$7,FALSE)) -> 1.04 | AI12: =INDEX('KPI Analysis'!$CO$7:$EU$123,MATCH($A12,'KPI Analysis'!$CO$7:$CO$123,FALSE),MATCH(AI$8,'KPI Analysis'!$CO$7:$EU$7,FALSE)) -> 1.03
A13: =F11&"-"&C13 -> EHS-KPI Q1 | B13: =+'KPI Stats'!G12 -> Under | C13: =+'KPI Stats'!C12 -> KPI Q1 | H13: W | I13: =+'KPI Stats'!F9 -> 42 | J13: =+'KPI Stats'!D12 -> Quality | K13: =+'KPI Stats'!E12 -> Visual Inspection Pass Rate | L13: =+'KPI Stats'!F12 -> Percentage | M13: Act Result | P13: =IF( OR( INDEX('KPI Analysis'!$AH$7:$CM$123, MATCH($A13,'KPI Analysis'!$AH$7:$AH$123,FALSE), MATCH(P$8,'KPI Analysis'!$AH$7:$CM$7,FALSE) )="R", INDEX('KPI Analysis'!$AH$7:$CM$123, MATCH($A13,'KPI Analysis'!$AH$7:$AH$123,FALSE), MATCH(P$8,'KPI Analysis'!$AH$7:$CM$7,FALSE) )="G", INDEX('KPI Analysis'!$AH$7:$CM$123, MATCH($A13,'KPI Analysis'!$AH$7:$AH$123,FALSE), MATCH(P$8,'KPI Analysis'!$AH$7:$CM$7,FALSE) )="A"), INDEX('KPI Analysis'!$AH$7:$CM$123,MATCH($A13,'KPI Analysis'!$AH$7:$AH$123,FALSE),MATCH(P$8,'KPI Analysis'!$AH$7:$CM$7,FALSE)),"") -> A | Q13: =INDEX('KPI Analysis'!$EW$7:$HC$123,MATCH($A13,'KPI Analysis'!$EW$7:$EW$123,FALSE),MATCH(P$8,'KPI Analysis'!$EW$7:$HC$7,FALSE))/100 -> 0.86 | R13: =IF( OR( INDEX('KPI Analysis'!$AH$7:$CM$123, MATCH($A13,'KPI Analysis'!$AH$7:$AH$123,FALSE), MATCH(R$8,'KPI Analysis'!$AH$7:$CM$7,FALSE) )="R", INDEX('KPI Analysis'!$AH$7:$CM$123, MATCH($A13,'KPI Analysis'!$AH$7:$AH$123,FALSE), MATCH(R$8,'KPI Analysis'!$AH$7:$CM$7,FALSE) )="G", INDEX('KPI Analysis'!$AH$7:$CM$123, MATCH($A13,'KPI Analysis'!$AH$7:$AH$123,FALSE), MATCH(R$8,'KPI Analysis'!$AH$7:$CM$7,FALSE) )="A"), INDEX('KPI Analysis'!$AH$7:$CM$123,MATCH($A13,'KPI Analysis'!$AH$7:$AH$123,FALSE),MATCH(R$8,'KPI Analysis'!$AH$7:$CM$7,FALSE)),"") -> A | S13: =INDEX('KPI Analysis'!$EW$7:$HC$123,MATCH($A13,'KPI Analysis'!$EW$7:$EW$123,FALSE),MATCH(R$8,'KPI Analysis'!$EW$7:$HC$7,FALSE))/100 -> 0.86 | T13: =IF( OR( INDEX('KPI Analysis'!$AH$7:$CM$123, MATCH($A13,'KPI Analysis'!$AH$7:$AH$123,FALSE), MATCH(T$8,'KPI Analysis'!$AH$7:$CM$7,FALSE) )="R", INDEX('KPI Analysis'!$AH$7:$CM$123, MATCH($A13,'KPI Analysis'!$AH$7:$AH$123,FALSE), MATCH(T$8,'KPI Analysis'!$AH$7:$CM$7,FALSE) )="G", INDEX('KPI Analysis'!$AH$7:$CM$123, MATCH($A13,'KPI Analysis'!$AH$7:$AH$123,FALSE), MATCH(T$8,'KPI Analysis'!$AH$7:$CM$7,FALSE) )="A"), INDEX('KPI Analysis'!$AH$7:$CM$123,MATCH($A13,'KPI Analysis'!$AH$7:$AH$123,FALSE),MATCH(T$8,'KPI Analysis'!$AH$7:$CM$7,FALSE)),"") -> G | U13: =INDEX('KPI Analysis'!$EW$7:$HC$123,MATCH($A13,'KPI Analysis'!$EW$7:$EW$123,FALSE),MATCH(T$8,'KPI Analysis'!$EW$7:$HC$7,FALSE))/100 -> 0.91 | V13: =IF( OR( INDEX('KPI Analysis'!$AH$7:$CM$123, MATCH($A13,'KPI Analysis'!$AH$7:$AH$123,FALSE), MATCH(V$8,'KPI Analysis'!$AH$7:$CM$7,FALSE) )="R", INDEX('KPI Analysis'!$AH$7:$CM$123, MATCH($A13,'KPI Analysis'!$AH$7:$AH$123,FALSE), MATCH(V$8,'KPI Analysis'!$AH$7:$CM$7,FALSE) )="G", INDEX('KPI Analysis'!$AH$7:$CM$123, MATCH($A13,'KPI Analysis'!$AH$7:$AH$123,FALSE), MATCH(V$8,'KPI Analysis'!$AH$7:$CM$7,FALSE) )="A"), INDEX('KPI Analysis'!$AH$7:$CM$123,MATCH($A13,'KPI Analysis'!$AH$7:$AH$123,FALSE),MATCH(V$8,'KPI Analysis'!$AH$7:$CM$7,FALSE)),"") -> G | W13: =INDEX('KPI Analysis'!$EW$7:$HC$123,MATCH($A13,'KPI Analysis'!$EW$7:$EW$123,FALSE),MATCH(V$8,'KPI Analysis'!$EW$7:$HC$7,FALSE))/100 -> 0.9 | X13: =IF( OR( INDEX('KPI Analysis'!$AH$7:$CM$123, MATCH($A13,'KPI Analysis'!$AH$7:$AH$123,FALSE), MATCH(X$8,'KPI Analysis'!$AH$7:$CM$7,FALSE) )="R", INDEX('KPI Analysis'!$AH$7:$CM$123, MATCH($A13,'KPI Analysis'!$AH$7:$AH$123,FALSE), MATCH(X$8,'KPI Analysis'!$AH$7:$CM$7,FALSE) )="G", INDEX('KPI Analysis'!$AH$7:$CM$123, MATCH($A13,'KPI Analysis'!$AH$7:$AH$123,FALSE), MATCH(X$8,'KPI Analysis'!$AH$7:$CM$7,FALSE) )="A"), INDEX('KPI Analysis'!$AH$7:$CM$123,MATCH($A13,'KPI Analysis'!$AH$7:$AH$123,FALSE),MATCH(X$8,'KPI Analysis'!$AH$7:$CM$7,FALSE)),"") -> G | Y13: =IF(INDEX('KPI Analysis'!$CO$7:$EU$123,MATCH($A13,'KPI Analysis'!$CO$7:$CO$123,FALSE),MATCH(X$8,'KPI Analysis'!$CO$7:$EU$7,FALSE))="OD","OD",INDEX('KPI Analysis'!$EW$7:$HC$123,MATCH($A13,'KPI Analysis'!$EW$7:$EW$123,FALSE),MATCH(X$8,'KPI Analysis'!$EW$7:$HC$7,FALSE))/100) -> 0.92 | Z13: (Target 90%) 6S project should help | AC13: EW HC | AE13: =INDEX('KPI Analysis'!$CO$7:$EU$123,MATCH($A13,'KPI Analysis'!$CO$7:$CO$123,FALSE),MATCH(AE$8,'KPI Analysis'!$CO$7:$EU$7,FALSE)) -> 0.95555556 | AF13: =INDEX('KPI Analysis'!$CO$7:$EU$123,MATCH($A13,'KPI Analysis'!$CO$7:$CO$123,FALSE),MATCH(AF$8,'KPI Analysis'!$CO$7:$EU$7,FALSE)) -> 0.95555556 | AG13: =INDEX('KPI Analysis'!$CO$7:$EU$123,MATCH($A13,'KPI Analysis'!$CO$7:$CO$123,FALSE),MATCH(AG$8,'KPI Analysis'!$CO$7:$EU$7,FALSE)) -> 1.0111111 | AH13: =INDEX('KPI Analysis'!$CO$7:$EU$123,MATCH($A13,'KPI Analysis'!$CO$7:$CO$123,FALSE),MATCH(AH$8,'KPI Analysis'!$CO$7:$EU$7,FALSE)) -> 1 | AI13: =INDEX('KPI Analysis'!$CO$7:$EU$123,MATCH($A13,'KPI Analysis'!$CO$7:$CO$123,FALSE),MATCH(AI$8,'KPI Analysis'!$CO$7:$EU$7,FALSE)) -> 1.0222222
A14: =F11&"-"&C14 -> EHS-KPI C1 | B14: =+'KPI Stats'!G13 -> Over | C14: =+'KPI Stats'!C13 -> KPI C1 | H14: W | I14: =+'KPI Stats'!F9 -> 42 | J14: =+'KPI Stats'!D13 -> Cost | K14: =+'KPI Stats'!E13 -> Ratio of Gas / Elec emissions to prod Quantity | L14: =+'KPI Stats'!F13 -> Ratio | M14: % of target | P14: =IF( OR( INDEX('KPI Analysis'!$AH$7:$CM$123, MATCH($A14,'KPI Analysis'!$AH$7:$AH$123,FALSE), MATCH(P$8,'KPI Analysis'!$AH$7:$CM$7,FALSE) )="R", INDEX('KPI Analysis'!$AH$7:$CM$123, MATCH($A14,'KPI Analysis'!$AH$7:$AH$123,FALSE), MATCH(P$8,'KPI Analysis'!$AH$7:$CM$7,FALSE) )="G", INDEX('KPI Analysis'!$AH$7:$CM$123, MATCH($A14,'KPI Analysis'!$AH$7:$AH$123,FALSE), MATCH(P$8,'KPI Analysis'!$AH$7:$CM$7,FALSE) )="A"), INDEX('KPI Analysis'!$AH$7:$CM$123,MATCH($A14,'KPI Analysis'!$AH$7:$AH$123,FALSE),MATCH(P$8,'KPI Analysis'!$AH$7:$CM$7,FALSE)),"") -> G | Q14: =INDEX('KPI Analysis'!$CO$7:$EU$123,MATCH($A14,'KPI Analysis'!$CO$7:$CO$123,FALSE),MATCH(P$8,'KPI Analysis'!$CO$7:$EU$7,FALSE)) -> 1.3513514 | R14: =IF( OR( INDEX('KPI Analysis'!$AH$7:$CM$123, MATCH($A14,'KPI Analysis'!$AH$7:$AH$123,FALSE), MATCH(R$8,'KPI Analysis'!$AH$7:$CM$7,FALSE) )="R", INDEX('KPI Analysis'!$AH$7:$CM$123, MATCH($A14,'KPI Analysis'!$AH$7:$AH$123,FALSE), MATCH(R$8,'KPI Analysis'!$AH$7:$CM$7,FALSE) )="G", INDEX('KPI Analysis'!$AH$7:$CM$123, MATCH($A14,'KPI Analysis'!$AH$7:$AH$123,FALSE), MATCH(R$8,'KPI Analysis'!$AH$7:$CM$7,FALSE) )="A"), INDEX('KPI Analysis'!$AH$7:$CM$123,MATCH($A14,'KPI Analysis'!$AH$7:$AH$123,FALSE),MATCH(R$8,'KPI Analysis'!$AH$7:$CM$7,FALSE)),"") -> G | S14: =INDEX('KPI Analysis'!$CO$7:$EU$123,MATCH($A14,'KPI Analysis'!$CO$7:$CO$123,FALSE),MATCH(R$8,'KPI Analysis'!$CO$7:$EU$7,FALSE)) -> 1.0204082 | T14: =IF( OR( INDEX('KPI Analysis'!$AH$7:$CM$123, MATCH($A14,'KPI Analysis'!$AH$7:$AH$123,FALSE), MATCH(T$8,'KPI Analysis'!$AH$7:$CM$7,FALSE) )="R", INDEX('KPI Analysis'!$AH$7:$CM$123, MATCH($A14,'KPI Analysis'!$AH$7:$AH$123,FALSE), MATCH(T$8,'KPI Analysis'!$AH$7:$CM$7,FALSE) )="G", INDEX('KPI Analysis'!$AH$7:$CM$123, MATCH($A14,'KPI Analysis'!$AH$7:$AH$123,FALSE), MATCH(T$8,'KPI Analysis'!$AH$7:$CM$7,FALSE) )="A"), INDEX('KPI Analysis'!$AH$7:$CM$123,MATCH($A14,'KPI Analysis'!$AH$7:$AH$123,FALSE),MATCH(T$8,'KPI Analysis'!$AH$7:$CM$7,FALSE)),"") -> G | U14: =INDEX('KPI Analysis'!$CO$7:$EU$123,MATCH($A14,'KPI Analysis'!$CO$7:$CO$123,FALSE),MATCH(T$8,'KPI Analysis'!$CO$7:$EU$7,FALSE)) -> 1.2048193 | V14: =IF( OR( INDEX('KPI Analysis'!$AH$7:$CM$123, MATCH($A14,'KPI Analysis'!$AH$7:$AH$123,FALSE), MATCH(V$8,'KPI Analysis'!$AH$7:$CM$7,FALSE) )="R", INDEX('KPI Analysis'!$AH$7:$CM$123, MATCH($A14,'KPI Analysis'!$AH$7:$AH$123,FALSE), MATCH(V$8,'KPI Analysis'!$AH$7:$CM$7,FALSE) )="G", INDEX('KPI Analysis'!$AH$7:$CM$123, MATCH($A14,'KPI Analysis'!$AH$7:$AH$123,FALSE), MATCH(V$8,'KPI Analysis'!$AH$7:$CM$7,FALSE) )="A"), INDEX('KPI Analysis'!$AH$7:$CM$123,MATCH($A14,'KPI Analysis'!$AH$7:$AH$123,FALSE),MATCH(V$8,'KPI Analysis'!$AH$7:$CM$7,FALSE)),"") -> G | W14: =INDEX('KPI Analysis'!$CO$7:$EU$123,MATCH($A14,'KPI Analysis'!$CO$7:$CO$123,FALSE),MATCH(V$8,'KPI Analysis'!$CO$7:$EU$7,FALSE)) -> 1.0526316 | X14: =IF( OR( INDEX('KPI Analysis'!$AH$7:$CM$123, MATCH($A14,'KPI Analysis'!$AH$7:$AH$123,FALSE), MATCH(X$8,'KPI Analysis'!$AH$7:$CM$7,FALSE) )="R", INDEX('KPI Analysis'!$AH$7:$CM$123, MATCH($A14,'KPI Analysis'!$AH$7:$AH$123,FALSE), MATCH(X$8,'KPI Analysis'!$AH$7:$CM$7,FALSE) )="G", INDEX('KPI Analysis'!$AH$7:$CM$123, MATCH($A14,'KPI Analysis'!$AH$7:$AH$123,FALSE), MATCH(X$8,'KPI Analysis'!$AH$7:$CM$7,FALSE) )="A"), INDEX('KPI Analysis'!$AH$7:$CM$123,MATCH($A14,'KPI Analysis'!$AH$7:$AH$123,FALSE),MATCH(X$8,'KPI Analysis'!$AH$7:$CM$7,FALSE)),"") | Y14: =INDEX('KPI Analysis'!$CO$7:$EU$123,MATCH($A14,'KPI Analysis'!$CO$7:$CO$123,FALSE),MATCH(X$8,'KPI Analysis'!$CO$7:$EU$7,FALSE)) -> OD | Z14: Reported 1 Wk in arrears (Target 1) | AC14: Co EU | AE14: =INDEX('KPI Analysis'!$CO$7:$EU$123,MATCH($A14,'KPI Analysis'!$CO$7:$CO$123,FALSE),MATCH(AE$8,'KPI Analysis'!$CO$7:$EU$7,FALSE)) -> 1.3513514 | AF14: =INDEX('KPI Analysis'!$CO$7:$EU$123,MATCH($A14,'KPI Analysis'!$CO$7:$CO$123,FALSE),MATCH(AF$8,'KPI Analysis'!$CO$7:$EU$7,FALSE)) -> 1.0204082 | AG14: =INDEX('KPI Analysis'!$CO$7:$EU$123,MATCH($A14,'KPI Analysis'!$CO$7:$CO$123,FALSE),MATCH(AG$8,'KPI Analysis'!$CO$7:$EU$7,FALSE)) -> 1.2048193 | AH14: =INDEX('KPI Analysis'!$CO$7:$EU$123,MATCH($A14,'KPI Analysis'!$CO$7:$CO$123,FALSE),MATCH(AH$8,'KPI Analysis'!$CO$7:$EU$7,FALSE)) -> 1.0526316 | AI14: =INDEX('KPI Analysis'!$CO$7:$EU$123,MATCH($A14,'KPI Analysis'!$CO$7:$CO$123,FALSE),MATCH(AI$8,'KPI Analysis'!$CO$7:$EU$7,FALSE)) -> OD
A15: =F11&"-"&C15 -> EHS-KPI C2 | B15: =+'KPI Stats'!G14 -> Over | C15: =+'KPI Stats'!C14 -> KPI C2 | H15: W | I15: =+'KPI Stats'!F9 -> 42 | J15: =+'KPI Stats'!D14 -> Cost | K15: =+'KPI Stats'!E14 -> Ratio of Gas / Elec emissions to prod Volume M2 | L15: =+'KPI Stats'!F14 -> Ratio | M15: % of target | P15: =IF( OR( INDEX('KPI Analysis'!$AH$7:$CM$123, MATCH($A15,'KPI Analysis'!$AH$7:$AH$123,FALSE), MATCH(P$8,'KPI Analysis'!$AH$7:$CM$7,FALSE) )="R", INDEX('KPI Analysis'!$AH$7:$CM$123, MATCH($A15,'KPI Analysis'!$AH$7:$AH$123,FALSE), MATCH(P$8,'KPI Analysis'!$AH$7:$CM$7,FALSE) )="G", INDEX('KPI Analysis'!$AH$7:$CM$123, MATCH($A15,'KPI Analysis'!$AH$7:$AH$123,FALSE), MATCH(P$8,'KPI Analysis'!$AH$7:$CM$7,FALSE) )="A"), INDEX('KPI Analysis'!$AH$7:$CM$123,MATCH($A15,'KPI Analysis'!$AH$7:$AH$123,FALSE),MATCH(P$8,'KPI Analysis'!$AH$7:$CM$7,FALSE)),"") -> G | Q15: =INDEX('KPI Analysis'!$CO$7:$EU$123,MATCH($A15,'KPI Analysis'!$CO$7:$CO$123,FALSE),MATCH(P$8,'KPI Analysis'!$CO$7:$EU$7,FALSE)) -> 1.122449 | R15: =IF( OR( INDEX('KPI Analysis'!$AH$7:$CM$123, MATCH($A15,'KPI Analysis'!$AH$7:$AH$123,FALSE), MATCH(R$8,'KPI Analysis'!$AH$7:$CM$7,FALSE) )="R", INDEX('KPI Analysis'!$AH$7:$CM$123, MATCH($A15,'KPI Analysis'!$AH$7:$AH$123,FALSE), MATCH(R$8,'KPI Analysis'!$AH$7:$CM$7,FALSE) )="G", INDEX('KPI Analysis'!$AH$7:$CM$123, MATCH($A15,'KPI Analysis'!$AH$7:$AH$123,FALSE), MATCH(R$8,'KPI Analysis'!$AH$7:$CM$7,FALSE) )="A"), INDEX('KPI Analysis'!$AH$7:$CM$123,MATCH($A15,'KPI Analysis'!$AH$7:$AH$123,FALSE),MATCH(R$8,'KPI Analysis'!$AH$7:$CM$7,FALSE)),"") -> G | S15: =INDEX('KPI Analysis'!$CO$7:$EU$123,MATCH($A15,'KPI Analysis'!$CO$7:$CO$123,FALSE),MATCH(R$8,'KPI Analysis'!$CO$7:$EU$7,FALSE)) -> 1.0338346 | T15: =IF( OR( INDEX('KPI Analysis'!$AH$7:$CM$123, MATCH($A15,'KPI Analysis'!$AH$7:$AH$123,FALSE), MATCH(T$8,'KPI Analysis'!$AH$7:$CM$7,FALSE) )="R", INDEX('KPI Analysis'!$AH$7:$CM$123, MATCH($A15,'KPI Analysis'!$AH$7:$AH$123,FALSE), MATCH(T$8,'KPI Analysis'!$AH$7:$CM$7,FALSE) )="G", INDEX('KPI Analysis'!$AH$7:$CM$123, MATCH($A15,'KPI Analysis'!$AH$7:$AH$123,FALSE), MATCH(T$8,'KPI Analysis'!$AH$7:$CM$7,FALSE) )="A"), INDEX('KPI Analysis'!$AH$7:$CM$123,MATCH($A15,'KPI Analysis'!$AH$7:$AH$123,FALSE),MATCH(T$8,'KPI Analysis'!$AH$7:$CM$7,FALSE)),"") -> G | U15: =INDEX('KPI Analysis'!$CO$7:$EU$123,MATCH($A15,'KPI Analysis'!$CO$7:$CO$123,FALSE),MATCH(T$8,'KPI Analysis'!$CO$7:$EU$7,FALSE)) -> 1.0742188 | V15: =IF( OR( INDEX('KPI Analysis'!$AH$7:$CM$123, MATCH($A15,'KPI Analysis'!$AH$7:$AH$123,FALSE), MATCH(V$8,'KPI Analysis'!$AH$7:$CM$7,FALSE) )="R", INDEX('KPI Analysis'!$AH$7:$CM$123, MATCH($A15,'KPI Analysis'!$AH$7:$AH$123,FALSE), MATCH(V$8,'KPI Analysis'!$AH$7:$CM$7,FALSE) )="G", INDEX('KPI Analysis'!$AH$7:$CM$123, MATCH($A15,'KPI Analysis'!$AH$7:$AH$123,FALSE), MATCH(V$8,'KPI Analysis'!$AH$7:$CM$7,FALSE) )="A"), INDEX('KPI Analysis'!$AH$7:$CM$123,MATCH($A15,'KPI Analysis'!$AH$7:$AH$123,FALSE),MATCH(V$8,'KPI Analysis'!$AH$7:$CM$7,FALSE)),"") -> G | W15: =INDEX('KPI Analysis'!$CO$7:$EU$123,MATCH($A15,'KPI Analysis'!$CO$7:$CO$123,FALSE),MATCH(V$8,'KPI Analysis'!$CO$7:$EU$7,FALSE)) -> 1.0456274 | X15: =IF( OR( INDEX('KPI Analysis'!$AH$7:$CM$123, MATCH($A15,'KPI Analysis'!$AH$7:$AH$123,FALSE), MATCH(X$8,'KPI Analysis'!$AH$7:$CM$7,FALSE) )="R", INDEX('KPI Analysis'!$AH$7:$CM$123, MATCH($A15,'KPI Analysis'!$AH$7:$AH$123,FALSE), MATCH(X$8,'KPI Analysis'!$AH$7:$CM$7,FALSE) )="G", INDEX('KPI Analysis'!$AH$7:$CM$123, MATCH($A15,'KPI Analysis'!$AH$7:$AH$123,FALSE), MATCH(X$8,'KPI Analysis'!$AH$7:$CM$7,FALSE) )="A"), INDEX('KPI Analysis'!$AH$7:$CM$123,MATCH($A15,'KPI Analysis'!$AH$7:$AH$123,FALSE),MATCH(X$8,'KPI Analysis'!$AH$7:$CM$7,FALSE)),"") | Y15: =INDEX('KPI Analysis'!$CO$7:$EU$123,MATCH($A15,'KPI Analysis'!$CO$7:$CO$123,FALSE),MATCH(X$8,'KPI Analysis'!$CO$7:$EU$7,FALSE)) -> OD | Z15: Reported 1 Wk in arrears (Target 2.75) | AC15: Co EU | AE15: =INDEX('KPI Analysis'!$CO$7:$EU$123,MATCH($A15,'KPI Analysis'!$CO$7:$CO$123,FALSE),MATCH(AE$8,'KPI Analysis'!$CO$7:$EU$7,FALSE)) -> 1.122449 | AF15: =INDEX('KPI Analysis'!$CO$7:$EU$123,MATCH($A15,'KPI Analysis'!$CO$7:$CO$123,FALSE),MATCH(AF$8,'KPI Analysis'!$CO$7:$EU$7,FALSE)) -> 1.0338346 | AG15: =INDEX('KPI Analysis'!$CO$7:$EU$123,MATCH($A15,'KPI Analysis'!$CO$7:$CO$123,FALSE),MATCH(AG$8,'KPI Analysis'!$CO$7:$EU$7,FALSE)) -> 1.0742188 | AH15: =INDEX('KPI Analysis'!$CO$7:$EU$123,MATCH($A15,'KPI Analysis'!$CO$7:$CO$123,FALSE),MATCH(AH$8,'KPI Analysis'!$CO$7:$EU$7,FALSE)) -> 1.0456274 | AI15: =INDEX('KPI Analysis'!$CO$7:$EU$123,MATCH($A15,'KPI Analysis'!$CO$7:$CO$123,FALSE),MATCH(AI$8,'KPI Analysis'!$CO$7:$EU$7,FALSE)) -> OD
A18: =F18&"-"&C18 -> Estimating-KPI P1 | B18: =+'KPI Stats'!G17 -> Under | C18: =+'KPI Stats'!C17 -> KPI P1 | F18: =+'KPI Stats'!$B$16 -> Estimating | G18: Julian Sparrow | H18: W | I18: =+'KPI Stats'!$F$16 -> 42 | J18: =+'KPI Stats'!D17 -> Productivity | K18: =+'KPI Stats'!E17 -> Quotes Issued | L18: =+'KPI Stats'!F17 -> Count | M18: =INDEX('KPI Analysis'!$CO$7:$EU$123,MATCH($A18,'KPI Analysis'!$CO$7:$CO$123,FALSE),MATCH(M$8,'KPI Analysis'!$CO$7:$EU$7,FALSE)) -> % of target | P18: =IF( OR( INDEX('KPI Analysis'!$AH$7:$CM$123, MATCH($A18,'KPI Analysis'!$AH$7:$AH$123,FALSE), MATCH(P$8,'KPI Analysis'!$AH$7:$CM$7,FALSE) )="R", INDEX('KPI Analysis'!$AH$7:$CM$123, MATCH($A18,'KPI Analysis'!$AH$7:$AH$123,FALSE), MATCH(P$8,'KPI Analysis'!$AH$7:$CM$7,FALSE) )="G", INDEX('KPI Analysis'!$AH$7:$CM$123, MATCH($A18,'KPI Analysis'!$AH$7:$AH$123,FALSE), MATCH(P$8,'KPI Analysis'!$AH$7:$CM$7,FALSE) )="A"), INDEX('KPI Analysis'!$AH$7:$CM$123,MATCH($A18,'KPI Analysis'!$AH$7:$AH$123,FALSE),MATCH(P$8,'KPI Analysis'!$AH$7:$CM$7,FALSE)),"") -> R | Q18: =INDEX('KPI Analysis'!$CO$7:$EU$123,MATCH($A18,'KPI Analysis'!$CO$7:$CO$123,FALSE),MATCH(P$8,'KPI Analysis'!$CO$7:$EU$7,FALSE)) -> 0.91269841 | R18: =IF( OR( INDEX('KPI Analysis'!$AH$7:$CM$123, MATCH($A18,'KPI Analysis'!$AH$7:$AH$123,FALSE), MATCH(R$8,'KPI Analysis'!$AH$7:$CM$7,FALSE) )="R", INDEX('KPI Analysis'!$AH$7:$CM$123, MATCH($A18,'KPI Analysis'!$AH$7:$AH$123,FALSE), MATCH(R$8,'KPI Analysis'!$AH$7:$CM$7,FALSE) )="G", INDEX('KPI Analysis'!$AH$7:$CM$123, MATCH($A18,'KPI Analysis'!$AH$7:$AH$123,FALSE), MATCH(R$8,'KPI Analysis'!$AH$7:$CM$7,FALSE) )="A"), INDEX('KPI Analysis'!$AH$7:$CM$123,MATCH($A18,'KPI Analysis'!$AH$7:$AH$123,FALSE),MATCH(R$8,'KPI Analysis'!$AH$7:$CM$7,FALSE)),"") -> R | S18: =INDEX('KPI Analysis'!$CO$7:$EU$123,MATCH($A18,'KPI Analysis'!$CO$7:$CO$123,FALSE),MATCH(R$8,'KPI Analysis'!$CO$7:$EU$7,FALSE)) -> 0.86507937 | T18: =IF( OR( INDEX('KPI Analysis'!$AH$7:$CM$123, MATCH($A18,'KPI Analysis'!$AH$7:$AH$123,FALSE), MATCH(T$8,'KPI Analysis'!$AH$7:$CM$7,FALSE) )="R", INDEX('KPI Analysis'!$AH$7:$CM$123, MATCH($A18,'KPI Analysis'!$AH$7:$AH$123,FALSE), MATCH(T$8,'KPI Analysis'!$AH$7:$CM$7,FALSE) )="G", INDEX('KPI Analysis'!$AH$7:$CM$123, MATCH($A18,'KPI Analysis'!$AH$7:$AH$123,FALSE), MATCH(T$8,'KPI Analysis'!$AH$7:$CM$7,FALSE) )="A"), INDEX('KPI Analysis'!$AH$7:$CM$123,MATCH($A18,'KPI Analysis'!$AH$7:$AH$123,FALSE),MATCH(T$8,'KPI Analysis'!$AH$7:$CM$7,FALSE)),"") -> R | U18: =INDEX('KPI Analysis'!$CO$7:$EU$123,MATCH($A18,'KPI Analysis'!$CO$7:$CO$123,FALSE),MATCH(T$8,'KPI Analysis'!$CO$7:$EU$7,FALSE)) -> 0.73809524 | V18: =IF( OR( INDEX('KPI Analysis'!$AH$7:$CM$123, MATCH($A18,'KPI Analysis'!$AH$7:$AH$123,FALSE), MATCH(V$8,'KPI Analysis'!$AH$7:$CM$7,FALSE) )="R", INDEX('KPI Analysis'!$AH$7:$CM$123, MATCH($A18,'KPI Analysis'!$AH$7:$AH$123,FALSE), MATCH(V$8,'KPI Analysis'!$AH$7:$CM$7,FALSE) )="G", INDEX('KPI Analysis'!$AH$7:$CM$123, MATCH($A18,'KPI Analysis'!$AH$7:$AH$123,FALSE), MATCH(V$8,'KPI Analysis'!$AH$7:$CM$7,FALSE) )="A"), INDEX('KPI Analysis'!$AH$7:$CM$123,MATCH($A18,'KPI Analysis'!$AH$7:$AH$123,FALSE),MATCH(V$8,'KPI Analysis'!$AH$7:$CM$7,FALSE)),"") -> A | W18: =INDEX('KPI Analysis'!$CO$7:$EU$123,MATCH($A18,'KPI Analysis'!$CO$7:$CO$123,FALSE),MATCH(V$8,'KPI Analysis'!$CO$7:$EU$7,FALSE)) -> 0.98412698 | X18: =IF( OR( INDEX('KPI Analysis'!$AH$7:$CM$123, MATCH($A18,'KPI Analysis'!$AH$7:$AH$123,FALSE), MATCH(X$8,'KPI Analysis'!$AH$7:$CM$7,FALSE) )="R", INDEX('KPI Analysis'!$AH$7:$CM$123, MATCH($A18,'KPI Analysis'!$AH$7:$AH$123,FALSE), MATCH(X$8,'KPI Analysis'!$AH$7:$CM$7,FALSE) )="G", INDEX('KPI Analysis'!$AH$7:$CM$123, MATCH($A18,'KPI Analysis'!$AH$7:$AH$123,FALSE), MATCH(X$8,'KPI Analysis'!$AH$7:$CM$7,FALSE) )="A"), INDEX('KPI Analysis'!$AH$7:$CM$123,MATCH($A18,'KPI Analysis'!$AH$7:$AH$123,FALSE),MATCH(X$8,'KPI Analysis'!$AH$7:$CM$7,FALSE)),"") -> A | Y18: =INDEX('KPI Analysis'!$CO$7:$EU$123,MATCH($A18,'KPI Analysis'!$CO$7:$CO$123,FALSE),MATCH(X$8,'KPI Analysis'!$CO$7:$EU$7,FALSE)) -> 0.97619048 | AC18: Co EU | AE18: =INDEX('KPI Analysis'!$CO$7:$EU$123,MATCH($A18,'KPI Analysis'!$CO$7:$CO$123,FALSE),MATCH(AE$8,'KPI Analysis'!$CO$7:$EU$7,FALSE)) -> 0.91269841 | AF18: =INDEX('KPI Analysis'!$CO$7:$EU$123,MATCH($A18,'KPI Analysis'!$CO$7:$CO$123,FALSE),MATCH(AF$8,'KPI Analysis'!$CO$7:$EU$7,FALSE)) -> 0.86507937 | AG18: =INDEX('KPI Analysis'!$CO$7:$EU$123,MATCH($A18,'KPI Analysis'!$CO$7:$CO$123,FALSE),MATCH(AG$8,'KPI Analysis'!$CO$7:$EU$7,FALSE)) -> 0.73809524 | AH18: =INDEX('KPI Analysis'!$CO$7:$EU$123,MATCH($A18,'KPI Analysis'!$CO$7:$CO$123,FALSE),MATCH(AH$8,'KPI Analysis'!$CO$7:$EU$7,FALSE)) -> 0.98412698 | AI18: =INDEX('KPI Analysis'!$CO$7:$EU$123,MATCH($A18,'KPI Analysis'!$CO$7:$CO$123,FALSE),MATCH(AI$8,'KPI Analysis'!$CO$7:$EU$7,FALSE)) -> 0.97619048
A19: =F19&"-"&C19 -> Estimating-KPI D1 | B19: =+'KPI Stats'!G18 -> Under | C19: =+'KPI Stats'!C18 -> KPI D1 | F19: =+'KPI Stats'!$B$16 -> Estimating | G19: =+'KPI Stats'!$B$16 -> Estimating | H19: W | I19: =+'KPI Stats'!$F$16 -> 42 | J19: =+'KPI Stats'!D18 -> Delivery | K19: =+'KPI Stats'!E18 -> Quotes issued on time | L19: =+'KPI Stats'!F18 -> Percentage | M19: =INDEX('KPI Analysis'!$CO$7:$EU$123,MATCH($A19,'KPI Analysis'!$CO$7:$CO$123,FALSE),MATCH(M$8,'KPI Analysis'!$CO$7:$EU$7,FALSE)) -> % of target | P19: =IF( OR( INDEX('KPI Analysis'!$AH$7:$CM$123, MATCH($A19,'KPI Analysis'!$AH$7:$AH$123,FALSE), MATCH(P$8,'KPI Analysis'!$AH$7:$CM$7,FALSE) )="R", INDEX('KPI Analysis'!$AH$7:$CM$123, MATCH($A19,'KPI Analysis'!$AH$7:$AH$123,FALSE), MATCH(P$8,'KPI Analysis'!$AH$7:$CM$7,FALSE) )="G", INDEX('KPI Analysis'!$AH$7:$CM$123, MATCH($A19,'KPI Analysis'!$AH$7:$AH$123,FALSE), MATCH(P$8,'KPI Analysis'!$AH$7:$CM$7,FALSE) )="A"), INDEX('KPI Analysis'!$AH$7:$CM$123,MATCH($A19,'KPI Analysis'!$AH$7:$AH$123,FALSE),MATCH(P$8,'KPI Analysis'!$AH$7:$CM$7,FALSE)),"") -> R | Q19: =INDEX('KPI Analysis'!$CO$7:$EU$123,MATCH($A19,'KPI Analysis'!$CO$7:$CO$123,FALSE),MATCH(P$8,'KPI Analysis'!$CO$7:$EU$7,FALSE)) -> 0.80818414 | R19: =IF( OR( INDEX('KPI Analysis'!$AH$7:$CM$123, MATCH($A19,'KPI Analysis'!$AH$7:$AH$123,FALSE), MATCH(R$8,'KPI Analysis'!$AH$7:$CM$7,FALSE) )="R", INDEX('KPI Analysis'!$AH$7:$CM$123, MATCH($A19,'KPI Analysis'!$AH$7:$AH$123,FALSE), MATCH(R$8,'KPI Analysis'!$AH$7:$CM$7,FALSE) )="G", INDEX('KPI Analysis'!$AH$7:$CM$123, MATCH($A19,'KPI Analysis'!$AH$7:$AH$123,FALSE), MATCH(R$8,'KPI Analysis'!$AH$7:$CM$7,FALSE) )="A"), INDEX('KPI Analysis'!$AH$7:$CM$123,MATCH($A19,'KPI Analysis'!$AH$7:$AH$123,FALSE),MATCH(R$8,'KPI Analysis'!$AH$7:$CM$7,FALSE)),"") -> R | S19: =INDEX('KPI Analysis'!$CO$7:$EU$123,MATCH($A19,'KPI Analysis'!$CO$7:$CO$123,FALSE),MATCH(R$8,'KPI Analysis'!$CO$7:$EU$7,FALSE)) -> 0.91743119 | T19: =IF( OR( INDEX('KPI Analysis'!$AH$7:$CM$123, MATCH($A19,'KPI Analysis'!$AH$7:$AH$123,FALSE), MATCH(T$8,'KPI Analysis'!$AH$7:$CM$7,FALSE) )="R", INDEX('KPI Analysis'!$AH$7:$CM$123, MATCH($A19,'KPI Analysis'!$AH$7:$AH$123,FALSE), MATCH(T$8,'KPI Analysis'!$AH$7:$CM$7,FALSE) )="G", INDEX('KPI Analysis'!$AH$7:$CM$123, MATCH($A19,'KPI Analysis'!$AH$7:$AH$123,FALSE), MATCH(T$8,'KPI Analysis'!$AH$7:$CM$7,FALSE) )="A"), INDEX('KPI Analysis'!$AH$7:$CM$123,MATCH($A19,'KPI Analysis'!$AH$7:$AH$123,FALSE),MATCH(T$8,'KPI Analysis'!$AH$7:$CM$7,FALSE)),"") -> A | U19: =INDEX('KPI Analysis'!$CO$7:$EU$123,MATCH($A19,'KPI Analysis'!$CO$7:$CO$123,FALSE),MATCH(T$8,'KPI Analysis'!$CO$7:$EU$7,FALSE)) -> 0.97406705 | V19: =IF( OR( INDEX('KPI Analysis'!$AH$7:$CM$123, MATCH($A19,'KPI Analysis'!$AH$7:$AH$123,FALSE), MATCH(V$8,'KPI Analysis'!$AH$7:$CM$7,FALSE) )="R", INDEX('KPI Analysis'!$AH$7:$CM$123, MATCH($A19,'KPI Analysis'!$AH$7:$AH$123,FALSE), MATCH(V$8,'KPI Analysis'!$AH$7:$CM$7,FALSE) )="G", INDEX('KPI Analysis'!$AH$7:$CM$123, MATCH($A19,'KPI Analysis'!$AH$7:$AH$123,FALSE), MATCH(V$8,'KPI Analysis'!$AH$7:$CM$7,FALSE) )="A"), INDEX('KPI Analysis'!$AH$7:$CM$123,MATCH($A19,'KPI Analysis'!$AH$7:$AH$123,FALSE),MATCH(V$8,'KPI Analysis'!$AH$7:$CM$7,FALSE)),"") -> R | W19: =INDEX('KPI Analysis'!$CO$7:$EU$123,MATCH($A19,'KPI Analysis'!$CO$7:$CO$123,FALSE),MATCH(V$8,'KPI Analysis'!$CO$7:$EU$7,FALSE)) -> 0.88235294 | X19: =IF( OR( INDEX('KPI Analysis'!$AH$7:$CM$123, MATCH($A19,'KPI Analysis'!$AH$7:$AH$123,FALSE), MATCH(X$8,'KPI Analysis'!$AH$7:$CM$7,FALSE) )="R", INDEX('KPI Analysis'!$AH$7:$CM$123, MATCH($A19,'KPI Analysis'!$AH$7:$AH$123,FALSE), MATCH(X$8,'KPI Analysis'!$AH$7:$CM$7,FALSE) )="G", INDEX('KPI Analysis'!$AH$7:$CM$123, MATCH($A19,'KPI Analysis'!$AH$7:$AH$123,FALSE), MATCH(X$8,'KPI Analysis'!$AH$7:$CM$7,FALSE) )="A"), INDEX('KPI Analysis'!$AH$7:$CM$123,MATCH($A19,'KPI Analysis'!$AH$7:$AH$123,FALSE),MATCH(X$8,'KPI Analysis'!$AH$7:$CM$7,FALSE)),"") -> A | Y19: =INDEX('KPI Analysis'!$CO$7:$EU$123,MATCH($A19,'KPI Analysis'!$CO$7:$CO$123,FALSE),MATCH(X$8,'KPI Analysis'!$CO$7:$EU$7,FALSE)) -> 0.96588235 | AC19: Co EU | AE19: =INDEX('KPI Analysis'!$CO$7:$EU$123,MATCH($A19,'KPI Analysis'!$CO$7:$CO$123,FALSE),MATCH(AE$8,'KPI Analysis'!$CO$7:$EU$7,FALSE)) -> 0.80818414 | AF19: =INDEX('KPI Analysis'!$CO$7:$EU$123,MATCH($A19,'KPI Analysis'!$CO$7:$CO$123,FALSE),MATCH(AF$8,'KPI Analysis'!$CO$7:$EU$7,FALSE)) -> 0.91743119 | AG19: =INDEX('KPI Analysis'!$CO$7:$EU$123,MATCH($A19,'KPI Analysis'!$CO$7:$CO$123,FALSE),MATCH(AG$8,'KPI Analysis'!$CO$7:$EU$7,FALSE)) -> 0.97406705 | AH19: =INDEX('KPI Analysis'!$CO$7:$EU$123,MATCH($A19,'KPI Analysis'!$CO$7:$CO$123,FALSE),MATCH(AH$8,'KPI Analysis'!$CO$7:$EU$7,FALSE)) -> 0.88235294 | AI19: =INDEX('KPI Analysis'!$CO$7:$EU$123,MATCH($A19,'KPI Analysis'!$CO$7:$CO$123,FALSE),MATCH(AI$8,'KPI Analysis'!$CO$7:$EU$7,FALSE)) -> 0.96588235
A20: =F20&"-"&C20 -> Estimating-KPI Q1 | B20: =+'KPI Stats'!G19 -> Over | C20: =+'KPI Stats'!C19 -> KPI Q1 | F20: =+'KPI Stats'!$B$16 -> Estimating | G20: =+'KPI Stats'!$B$16 -> Estimating | H20: W | I20: =+'KPI Stats'!$F$16 -> 42 | J20: =+'KPI Stats'!D19 -> Quality | K20: =+'KPI Stats'!E19 -> Hours on each Estimate | L20: =+'KPI Stats'!F19 -> Hours | M20: =INDEX('KPI Analysis'!$CO$7:$EU$123,MATCH($A20,'KPI Analysis'!$CO$7:$CO$123,FALSE),MATCH(M$8,'KPI Analysis'!$CO$7:$EU$7,FALSE)) -> % of target | P20: =IF( OR( INDEX('KPI Analysis'!$AH$7:$CM$123, MATCH($A20,'KPI Analysis'!$AH$7:$AH$123,FALSE), MATCH(P$8,'KPI Analysis'!$AH$7:$CM$7,FALSE) )="R", INDEX('KPI Analysis'!$AH$7:$CM$123, MATCH($A20,'KPI Analysis'!$AH$7:$AH$123,FALSE), MATCH(P$8,'KPI Analysis'!$AH$7:$CM$7,FALSE) )="G", INDEX('KPI Analysis'!$AH$7:$CM$123, MATCH($A20,'KPI Analysis'!$AH$7:$AH$123,FALSE), MATCH(P$8,'KPI Analysis'!$AH$7:$CM$7,FALSE) )="A"), INDEX('KPI Analysis'!$AH$7:$CM$123,MATCH($A20,'KPI Analysis'!$AH$7:$AH$123,FALSE),MATCH(P$8,'KPI Analysis'!$AH$7:$CM$7,FALSE)),"") -> R | Q20: =INDEX('KPI Analysis'!$CO$7:$EU$123,MATCH($A20,'KPI Analysis'!$CO$7:$CO$123,FALSE),MATCH(P$8,'KPI Analysis'!$CO$7:$EU$7,FALSE)) -> 0.525 | R20: =IF( OR( INDEX('KPI Analysis'!$AH$7:$CM$123, MATCH($A20,'KPI Analysis'!$AH$7:$AH$123,FALSE), MATCH(R$8,'KPI Analysis'!$AH$7:$CM$7,FALSE) )="R", INDEX('KPI Analysis'!$AH$7:$CM$123, MATCH($A20,'KPI Analysis'!$AH$7:$AH$123,FALSE), MATCH(R$8,'KPI Analysis'!$AH$7:$CM$7,FALSE) )="G", INDEX('KPI Analysis'!$AH$7:$CM$123, MATCH($A20,'KPI Analysis'!$AH$7:$AH$123,FALSE), MATCH(R$8,'KPI Analysis'!$AH$7:$CM$7,FALSE) )="A"), INDEX('KPI Analysis'!$AH$7:$CM$123,MATCH($A20,'KPI Analysis'!$AH$7:$AH$123,FALSE),MATCH(R$8,'KPI Analysis'!$AH$7:$CM$7,FALSE)),"") -> R | S20: =INDEX('KPI Analysis'!$CO$7:$EU$123,MATCH($A20,'KPI Analysis'!$CO$7:$CO$123,FALSE),MATCH(R$8,'KPI Analysis'!$CO$7:$EU$7,FALSE)) -> 0.94164194 | T20: =IF( OR( INDEX('KPI Analysis'!$AH$7:$CM$123, MATCH($A20,'KPI Analysis'!$AH$7:$AH$123,FALSE), MATCH(T$8,'KPI Analysis'!$AH$7:$CM$7,FALSE) )="R", INDEX('KPI Analysis'!$AH$7:$CM$123, MATCH($A20,'KPI Analysis'!$AH$7:$AH$123,FALSE), MATCH(T$8,'KPI Analysis'!$AH$7:$CM$7,FALSE) )="G", INDEX('KPI Analysis'!$AH$7:$CM$123, MATCH($A20,'KPI Analysis'!$AH$7:$AH$123,FALSE), MATCH(T$8,'KPI Analysis'!$AH$7:$CM$7,FALSE) )="A"), INDEX('KPI Analysis'!$AH$7:$CM$123,MATCH($A20,'KPI Analysis'!$AH$7:$AH$123,FALSE),MATCH(T$8,'KPI Analysis'!$AH$7:$CM$7,FALSE)),"") -> R | U20: =INDEX('KPI Analysis'!$CO$7:$EU$123,MATCH($A20,'KPI Analysis'!$CO$7:$CO$123,FALSE),MATCH(T$8,'KPI Analysis'!$CO$7:$EU$7,FALSE)) -> 0.82608696 | V20: =IF( OR( INDEX('KPI Analysis'!$AH$7:$CM$123, MATCH($A20,'KPI Analysis'!$AH$7:$AH$123,FALSE), MATCH(V$8,'KPI Analysis'!$AH$7:$CM$7,FALSE) )="R", INDEX('KPI Analysis'!$AH$7:$CM$123, MATCH($A20,'KPI Analysis'!$AH$7:$AH$123,FALSE), MATCH(V$8,'KPI Analysis'!$AH$7:$CM$7,FALSE) )="G", INDEX('KPI Analysis'!$AH$7:$CM$123, MATCH($A20,'KPI Analysis'!$AH$7:$AH$123,FALSE), MATCH(V$8,'KPI Analysis'!$AH$7:$CM$7,FALSE) )="A"), INDEX('KPI Analysis'!$AH$7:$CM$123,MATCH($A20,'KPI Analysis'!$AH$7:$AH$123,FALSE),MATCH(V$8,'KPI Analysis'!$AH$7:$CM$7,FALSE)),"") -> R | W20: =INDEX('KPI Analysis'!$CO$7:$EU$123,MATCH($A20,'KPI Analysis'!$CO$7:$CO$123,FALSE),MATCH(V$8,'KPI Analysis'!$CO$7:$EU$7,FALSE)) -> 0.58355847 | X20: =IF( OR( INDEX('KPI Analysis'!$AH$7:$CM$123, MATCH($A20,'KPI Analysis'!$AH$7:$AH$123,FALSE), MATCH(X$8,'KPI Analysis'!$AH$7:$CM$7,FALSE) )="R", INDEX('KPI Analysis'!$AH$7:$CM$123, MATCH($A20,'KPI Analysis'!$AH$7:$AH$123,FALSE), MATCH(X$8,'KPI Analysis'!$AH$7:$CM$7,FALSE) )="G", INDEX('KPI Analysis'!$AH$7:$CM$123, MATCH($A20,'KPI Analysis'!$AH$7:$AH$123,FALSE), MATCH(X$8,'KPI Analysis'!$AH$7:$CM$7,FALSE) )="A"), INDEX('KPI Analysis'!$AH$7:$CM$123,MATCH($A20,'KPI Analysis'!$AH$7:$AH$123,FALSE),MATCH(X$8,'KPI Analysis'!$AH$7:$CM$7,FALSE)),"") -> G | Y20: =INDEX('KPI Analysis'!$CO$7:$EU$123,MATCH($A20,'KPI Analysis'!$CO$7:$CO$123,FALSE),MATCH(X$8,'KPI Analysis'!$CO$7:$EU$7,FALSE)) -> 1.0687023 | AC20: Co EU | AE20: =INDEX('KPI Analysis'!$CO$7:$EU$123,MATCH($A20,'KPI Analysis'!$CO$7:$CO$123,FALSE),MATCH(AE$8,'KPI Analysis'!$CO$7:$EU$7,FALSE)) -> 0.525 | AF20: =INDEX('KPI Analysis'!$CO$7:$EU$123,MATCH($A20,'KPI Analysis'!$CO$7:$CO$123,FALSE),MATCH(AF$8,'KPI Analysis'!$CO$7:$EU$7,FALSE)) -> 0.94164194 | AG20: =INDEX('KPI Analysis'!$CO$7:$EU$123,MATCH($A20,'KPI Analysis'!$CO$7:$CO$123,FALSE),MATCH(AG$8,'KPI Analysis'!$CO$7:$EU$7,FALSE)) -> 0.82608696 | AH20: =INDEX('KPI Analysis'!$CO$7:$EU$123,MATCH($A20,'KPI Analysis'!$CO$7:$CO$123,FALSE),MATCH(AH$8,'KPI Analysis'!$CO$7:$EU$7,FALSE)) -> 0.58355847 | AI20: =INDEX('KPI Analysis'!$CO$7:$EU$123,MATCH($A20,'KPI Analysis'!$CO$7:$CO$123,FALSE),MATCH(AI$8,'KPI Analysis'!$CO$7:$EU$7,FALSE)) -> 1.0687023
A21: =F21&"-"&C21 -> Estimating-KPI C1 | B21: =+'KPI Stats'!G20 -> Under | C21: =+'KPI Stats'!C20 -> KPI C1 | F21: =+'KPI Stats'!$B$16 -> Estimating | G21: =+'KPI Stats'!$B$16 -> Estimating | H21: W | I21: =+'KPI Stats'!$F$16 -> 42 | J21: =+'KPI Stats'!D20 -> Cost | K21: =+'KPI Stats'!E20 -> Rate of Sales per sq Meter | L21: =+'KPI Stats'!F20 -> £ | M21: =INDEX('KPI Analysis'!$CO$7:$EU$123,MATCH($A21,'KPI Analysis'!$CO$7:$CO$123,FALSE),MATCH(M$8,'KPI Analysis'!$CO$7:$EU$7,FALSE)) -> % of target | P21: =IF( OR( INDEX('KPI Analysis'!$AH$7:$CM$123, MATCH($A21,'KPI Analysis'!$AH$7:$AH$123,FALSE), MATCH(P$8,'KPI Analysis'!$AH$7:$CM$7,FALSE) )="R", INDEX('KPI Analysis'!$AH$7:$CM$123, MATCH($A21,'KPI Analysis'!$AH$7:$AH$123,FALSE), MATCH(P$8,'KPI Analysis'!$AH$7:$CM$7,FALSE) )="G", INDEX('KPI Analysis'!$AH$7:$CM$123, MATCH($A21,'KPI Analysis'!$AH$7:$AH$123,FALSE), MATCH(P$8,'KPI Analysis'!$AH$7:$CM$7,FALSE) )="A"), INDEX('KPI Analysis'!$AH$7:$CM$123,MATCH($A21,'KPI Analysis'!$AH$7:$AH$123,FALSE),MATCH(P$8,'KPI Analysis'!$AH$7:$CM$7,FALSE)),"") -> G | Q21: =INDEX('KPI Analysis'!$CO$7:$EU$123,MATCH($A21,'KPI Analysis'!$CO$7:$CO$123,FALSE),MATCH(P$8,'KPI Analysis'!$CO$7:$EU$7,FALSE)) -> 1.0661967 | R21: =IF( OR( INDEX('KPI Analysis'!$AH$7:$CM$123, MATCH($A21,'KPI Analysis'!$AH$7:$AH$123,FALSE), MATCH(R$8,'KPI Analysis'!$AH$7:$CM$7,FALSE) )="R", INDEX('KPI Analysis'!$AH$7:$CM$123, MATCH($A21,'KPI Analysis'!$AH$7:$AH$123,FALSE), MATCH(R$8,'KPI Analysis'!$AH$7:$CM$7,FALSE) )="G", INDEX('KPI Analysis'!$AH$7:$CM$123, MATCH($A21,'KPI Analysis'!$AH$7:$AH$123,FALSE), MATCH(R$8,'KPI Analysis'!$AH$7:$CM$7,FALSE) )="A"), INDEX('KPI Analysis'!$AH$7:$CM$123,MATCH($A21,'KPI Analysis'!$AH$7:$AH$123,FALSE),MATCH(R$8,'KPI Analysis'!$AH$7:$CM$7,FALSE)),"") -> G | S21: =INDEX('KPI Analysis'!$CO$7:$EU$123,MATCH($A21,'KPI Analysis'!$CO$7:$CO$123,FALSE),MATCH(R$8,'KPI Analysis'!$CO$7:$EU$7,FALSE)) -> 1.4345885 | T21: =IF( OR( INDEX('KPI Analysis'!$AH$7:$CM$123, MATCH($A21,'KPI Analysis'!$AH$7:$AH$123,FALSE), MATCH(T$8,'KPI Analysis'!$AH$7:$CM$7,FALSE) )="R", INDEX('KPI Analysis'!$AH$7:$CM$123, MATCH($A21,'KPI Analysis'!$AH$7:$AH$123,FALSE), MATCH(T$8,'KPI Analysis'!$AH$7:$CM$7,FALSE) )="G", INDEX('KPI Analysis'!$AH$7:$CM$123, MATCH($A21,'KPI Analysis'!$AH$7:$AH$123,FALSE), MATCH(T$8,'KPI Analysis'!$AH$7:$CM$7,FALSE) )="A"), INDEX('KPI Analysis'!$AH$7:$CM$123,MATCH($A21,'KPI Analysis'!$AH$7:$AH$123,FALSE),MATCH(T$8,'KPI Analysis'!$AH$7:$CM$7,FALSE)),"") -> G | U21: =INDEX('KPI Analysis'!$CO$7:$EU$123,MATCH($A21,'KPI Analysis'!$CO$7:$CO$123,FALSE),MATCH(T$8,'KPI Analysis'!$CO$7:$EU$7,FALSE)) -> 1.0694805 | V21: =IF( OR( INDEX('KPI Analysis'!$AH$7:$CM$123, MATCH($A21,'KPI Analysis'!$AH$7:$AH$123,FALSE), MATCH(V$8,'KPI Analysis'!$AH$7:$CM$7,FALSE) )="R", INDEX('KPI Analysis'!$AH$7:$CM$123, MATCH($A21,'KPI Analysis'!$AH$7:$AH$123,FALSE), MATCH(V$8,'KPI Analysis'!$AH$7:$CM$7,FALSE) )="G", INDEX('KPI Analysis'!$AH$7:$CM$123, MATCH($A21,'KPI Analysis'!$AH$7:$AH$123,FALSE), MATCH(V$8,'KPI Analysis'!$AH$7:$CM$7,FALSE) )="A"), INDEX('KPI Analysis'!$AH$7:$CM$123,MATCH($A21,'KPI Analysis'!$AH$7:$AH$123,FALSE),MATCH(V$8,'KPI Analysis'!$AH$7:$CM$7,FALSE)),"") -> G | W21: =INDEX('KPI Analysis'!$CO$7:$EU$123,MATCH($A21,'KPI Analysis'!$CO$7:$CO$123,FALSE),MATCH(V$8,'KPI Analysis'!$CO$7:$EU$7,FALSE)) -> 1.0598483 | X21: =IF( OR( INDEX('KPI Analysis'!$AH$7:$CM$123, MATCH($A21,'KPI Analysis'!$AH$7:$AH$123,FALSE), MATCH(X$8,'KPI Analysis'!$AH$7:$CM$7,FALSE) )="R", INDEX('KPI Analysis'!$AH$7:$CM$123, MATCH($A21,'KPI Analysis'!$AH$7:$AH$123,FALSE), MATCH(X$8,'KPI Analysis'!$AH$7:$CM$7,FALSE) )="G", INDEX('KPI Analysis'!$AH$7:$CM$123, MATCH($A21,'KPI Analysis'!$AH$7:$AH$123,FALSE), MATCH(X$8,'KPI Analysis'!$AH$7:$CM$7,FALSE) )="A"), INDEX('KPI Analysis'!$AH$7:$CM$123,MATCH($A21,'KPI Analysis'!$AH$7:$AH$123,FALSE),MATCH(X$8,'KPI Analysis'!$AH$7:$CM$7,FALSE)),"") -> G | Y21: =INDEX('KPI Analysis'!$CO$7:$EU$123,MATCH($A21,'KPI Analysis'!$CO$7:$CO$123,FALSE),MATCH(X$8,'KPI Analysis'!$CO$7:$EU$7,FALSE)) -> 1.0754667 | Z21: Test added but Target to be clarified | AC21: Co EU | AE21: =INDEX('KPI Analysis'!$CO$7:$EU$123,MATCH($A21,'KPI Analysis'!$CO$7:$CO$123,FALSE),MATCH(AE$8,'KPI Analysis'!$CO$7:$EU$7,FALSE)) -> 1.0661967 | AF21: =INDEX('KPI Analysis'!$CO$7:$EU$123,MATCH($A21,'KPI Analysis'!$CO$7:$CO$123,FALSE),MATCH(AF$8,'KPI Analysis'!$CO$7:$EU$7,FALSE)) -> 1.4345885 | AG21: =INDEX('KPI Analysis'!$CO$7:$EU$123,MATCH($A21,'KPI Analysis'!$CO$7:$CO$123,FALSE),MATCH(AG$8,'KPI Analysis'!$CO$7:$EU$7,FALSE)) -> 1.0694805 | AH21: =INDEX('KPI Analysis'!$CO$7:$EU$123,MATCH($A21,'KPI Analysis'!$CO$7:$CO$123,FALSE),MATCH(AH$8,'KPI Analysis'!$CO$7:$EU$7,FALSE)) -> 1.0598483 | AI21: =INDEX('KPI Analysis'!$CO$7:$EU$123,MATCH($A21,'KPI Analysis'!$CO$7:$CO$123,FALSE),MATCH(AI$8,'KPI Analysis'!$CO$7:$EU$7,FALSE)) -> 1.0754667
K22: Target avg of the actual results Q1
A24: =F24&"-"&C24 -> SOP-KPI P1 | B24: =+'KPI Stats'!G23 -> Under | C24: =+'KPI Stats'!C23 -> KPI P1 | F24: =+'KPI Stats'!B22 -> SOP | G24: =+'KPI Stats'!C22 -> Sam Westwood | H24: W | I24: =+'KPI Stats'!F22 -> 42 | J24: =+'KPI Stats'!D23 -> Productivity | K24: =+'KPI Stats'!E23 -> Order Lines Released | L24: =+'KPI Stats'!F23 -> Count | M24: =INDEX('KPI Analysis'!$CO$7:$EU$123,MATCH($A24,'KPI Analysis'!$CO$7:$CO$123,FALSE),MATCH(M$8,'KPI Analysis'!$CO$7:$EU$7,FALSE)) -> % of target | P24: =IF( OR( INDEX('KPI Analysis'!$AH$7:$CM$123, MATCH($A24,'KPI Analysis'!$AH$7:$AH$123,FALSE), MATCH(P$8,'KPI Analysis'!$AH$7:$CM$7,FALSE) )="R", INDEX('KPI Analysis'!$AH$7:$CM$123, MATCH($A24,'KPI Analysis'!$AH$7:$AH$123,FALSE), MATCH(P$8,'KPI Analysis'!$AH$7:$CM$7,FALSE) )="G", INDEX('KPI Analysis'!$AH$7:$CM$123, MATCH($A24,'KPI Analysis'!$AH$7:$AH$123,FALSE), MATCH(P$8,'KPI Analysis'!$AH$7:$CM$7,FALSE) )="A"), INDEX('KPI Analysis'!$AH$7:$CM$123,MATCH($A24,'KPI Analysis'!$AH$7:$AH$123,FALSE),MATCH(P$8,'KPI Analysis'!$AH$7:$CM$7,FALSE)),"") -> G | Q24: =INDEX('KPI Analysis'!$CO$7:$EU$123,MATCH($A24,'KPI Analysis'!$CO$7:$CO$123,FALSE),MATCH(P$8,'KPI Analysis'!$CO$7:$EU$7,FALSE)) -> 1.2124864 | R24: =IF( OR( INDEX('KPI Analysis'!$AH$7:$CM$123, MATCH($A24,'KPI Analysis'!$AH$7:$AH$123,FALSE), MATCH(R$8,'KPI Analysis'!$AH$7:$CM$7,FALSE) )="R", INDEX('KPI Analysis'!$AH$7:$CM$123, MATCH($A24,'KPI Analysis'!$AH$7:$AH$123,FALSE), MATCH(R$8,'KPI Analysis'!$AH$7:$CM$7,FALSE) )="G", INDEX('KPI Analysis'!$AH$7:$CM$123, MATCH($A24,'KPI Analysis'!$AH$7:$AH$123,FALSE), MATCH(R$8,'KPI Analysis'!$AH$7:$CM$7,FALSE) )="A"), INDEX('KPI Analysis'!$AH$7:$CM$123,MATCH($A24,'KPI Analysis'!$AH$7:$AH$123,FALSE),MATCH(R$8,'KPI Analysis'!$AH$7:$CM$7,FALSE)),"") -> G | S24: =INDEX('KPI Analysis'!$CO$7:$EU$123,MATCH($A24,'KPI Analysis'!$CO$7:$CO$123,FALSE),MATCH(R$8,'KPI Analysis'!$CO$7:$EU$7,FALSE)) -> 1.3772879 | T24: =IF( OR( INDEX('KPI Analysis'!$AH$7:$CM$123, MATCH($A24,'KPI Analysis'!$AH$7:$AH$123,FALSE), MATCH(T$8,'KPI Analysis'!$AH$7:$CM$7,FALSE) )="R", INDEX('KPI Analysis'!$AH$7:$CM$123, MATCH($A24,'KPI Analysis'!$AH$7:$AH$123,FALSE), MATCH(T$8,'KPI Analysis'!$AH$7:$CM$7,FALSE) )="G", INDEX('KPI Analysis'!$AH$7:$CM$123, MATCH($A24,'KPI Analysis'!$AH$7:$AH$123,FALSE), MATCH(T$8,'KPI Analysis'!$AH$7:$CM$7,FALSE) )="A"), INDEX('KPI Analysis'!$AH$7:$CM$123,MATCH($A24,'KPI Analysis'!$AH$7:$AH$123,FALSE),MATCH(T$8,'KPI Analysis'!$AH$7:$CM$7,FALSE)),"") -> A | U24: =INDEX('KPI Analysis'!$CO$7:$EU$123,MATCH($A24,'KPI Analysis'!$CO$7:$CO$123,FALSE),MATCH(T$8,'KPI Analysis'!$CO$7:$EU$7,FALSE)) -> 0.98372381 | V24: =IF( OR( INDEX('KPI Analysis'!$AH$7:$CM$123, MATCH($A24,'KPI Analysis'!$AH$7:$AH$123,FALSE), MATCH(V$8,'KPI Analysis'!$AH$7:$CM$7,FALSE) )="R", INDEX('KPI Analysis'!$AH$7:$CM$123, MATCH($A24,'KPI Analysis'!$AH$7:$AH$123,FALSE), MATCH(V$8,'KPI Analysis'!$AH$7:$CM$7,FALSE) )="G", INDEX('KPI Analysis'!$AH$7:$CM$123, MATCH($A24,'KPI Analysis'!$AH$7:$AH$123,FALSE), MATCH(V$8,'KPI Analysis'!$AH$7:$CM$7,FALSE) )="A"), INDEX('KPI Analysis'!$AH$7:$CM$123,MATCH($A24,'KPI Analysis'!$AH$7:$AH$123,FALSE),MATCH(V$8,'KPI Analysis'!$AH$7:$CM$7,FALSE)),"") -> R | W24: =INDEX('KPI Analysis'!$CO$7:$EU$123,MATCH($A24,'KPI Analysis'!$CO$7:$CO$123,FALSE),MATCH(V$8,'KPI Analysis'!$CO$7:$EU$7,FALSE)) -> 0.90159064 | X24: =IF( OR( INDEX('KPI Analysis'!$AH$7:$CM$123, MATCH($A24,'KPI Analysis'!$AH$7:$AH$123,FALSE), MATCH(X$8,'KPI Analysis'!$AH$7:$CM$7,FALSE) )="R", INDEX('KPI Analysis'!$AH$7:$CM$123, MATCH($A24,'KPI Analysis'!$AH$7:$AH$123,FALSE), MATCH(X$8,'KPI Analysis'!$AH$7:$CM$7,FALSE) )="G", INDEX('KPI Analysis'!$AH$7:$CM$123, MATCH($A24,'KPI Analysis'!$AH$7:$AH$123,FALSE), MATCH(X$8,'KPI Analysis'!$AH$7:$CM$7,FALSE) )="A"), INDEX('KPI Analysis'!$AH$7:$CM$123,MATCH($A24,'KPI Analysis'!$AH$7:$AH$123,FALSE),MATCH(X$8,'KPI Analysis'!$AH$7:$CM$7,FALSE)),"") -> R | Y24: =INDEX('KPI Analysis'!$CO$7:$EU$123,MATCH($A24,'KPI Analysis'!$CO$7:$CO$123,FALSE),MATCH(X$8,'KPI Analysis'!$CO$7:$EU$7,FALSE)) -> 0.82391137 | AC24: Co EU | AE24: =INDEX('KPI Analysis'!$CO$7:$EU$123,MATCH($A24,'KPI Analysis'!$CO$7:$CO$123,FALSE),MATCH(AE$8,'KPI Analysis'!$CO$7:$EU$7,FALSE)) -> 1.2124864 | AF24: =INDEX('KPI Analysis'!$CO$7:$EU$123,MATCH($A24,'KPI Analysis'!$CO$7:$CO$123,FALSE),MATCH(AF$8,'KPI Analysis'!$CO$7:$EU$7,FALSE)) -> 1.3772879 | AG24: =INDEX('KPI Analysis'!$CO$7:$EU$123,MATCH($A24,'KPI Analysis'!$CO$7:$CO$123,FALSE),MATCH(AG$8,'KPI Analysis'!$CO$7:$EU$7,FALSE)) -> 0.98372381 | AH24: =INDEX('KPI Analysis'!$CO$7:$EU$123,MATCH($A24,'KPI Analysis'!$CO$7:$CO$123,FALSE),MATCH(AH$8,'KPI Analysis'!$CO$7:$EU$7,FALSE)) -> 0.90159064 | AI24: =INDEX('KPI Analysis'!$CO$7:$EU$123,MATCH($A24,'KPI Analysis'!$CO$7:$CO$123,FALSE),MATCH(AI$8,'KPI Analysis'!$CO$7:$EU$7,FALSE)) -> 0.82391137
A25: =F25&"-"&C25 -> SOP-KPI D1 | B25: =+'KPI Stats'!G24 -> Under | C25: =+'KPI Stats'!C24 -> KPI D1 | F25: =+'KPI Stats'!B22 -> SOP | G25: =+'KPI Stats'!C22 -> Sam Westwood | H25: W | I25: =+'KPI Stats'!F22 -> 42 | J25: =+'KPI Stats'!D24 -> Delivery | K25: =+'KPI Stats'!E24 -> Order Cleansing On Target / In Full (OTIF) days to complete | L25: =+'KPI Stats'!F24 -> Percentage | M25: Act Result | P25: =IF( OR( INDEX('KPI Analysis'!$AH$7:$CM$123, MATCH($A25,'KPI Analysis'!$AH$7:$AH$123,FALSE), MATCH(P$8,'KPI Analysis'!$AH$7:$CM$7,FALSE) )="R", INDEX('KPI Analysis'!$AH$7:$CM$123, MATCH($A25,'KPI Analysis'!$AH$7:$AH$123,FALSE), MATCH(P$8,'KPI Analysis'!$AH$7:$CM$7,FALSE) )="G", INDEX('KPI Analysis'!$AH$7:$CM$123, MATCH($A25,'KPI Analysis'!$AH$7:$AH$123,FALSE), MATCH(P$8,'KPI Analysis'!$AH$7:$CM$7,FALSE) )="A"), INDEX('KPI Analysis'!$AH$7:$CM$123,MATCH($A25,'KPI Analysis'!$AH$7:$AH$123,FALSE),MATCH(P$8,'KPI Analysis'!$AH$7:$CM$7,FALSE)),"") -> R | Q25: =INDEX('KPI Analysis'!$EW$7:$HC$123,MATCH($A25,'KPI Analysis'!$EW$7:$EW$123,FALSE),MATCH(P$8,'KPI Analysis'!$EW$7:$HC$7,FALSE)) -> 0.38709677 | R25: =IF( OR( INDEX('KPI Analysis'!$AH$7:$CM$123, MATCH($A25,'KPI Analysis'!$AH$7:$AH$123,FALSE), MATCH(R$8,'KPI Analysis'!$AH$7:$CM$7,FALSE) )="R", INDEX('KPI Analysis'!$AH$7:$CM$123, MATCH($A25,'KPI Analysis'!$AH$7:$AH$123,FALSE), MATCH(R$8,'KPI Analysis'!$AH$7:$CM$7,FALSE) )="G", INDEX('KPI Analysis'!$AH$7:$CM$123, MATCH($A25,'KPI Analysis'!$AH$7:$AH$123,FALSE), MATCH(R$8,'KPI Analysis'!$AH$7:$CM$7,FALSE) )="A"), INDEX('KPI Analysis'!$AH$7:$CM$123,MATCH($A25,'KPI Analysis'!$AH$7:$AH$123,FALSE),MATCH(R$8,'KPI Analysis'!$AH$7:$CM$7,FALSE)),"") -> R | S25: =INDEX('KPI Analysis'!$EW$7:$HC$123,MATCH($A25,'KPI Analysis'!$EW$7:$EW$123,FALSE),MATCH(R$8,'KPI Analysis'!$EW$7:$HC$7,FALSE)) -> 0.57692308 | T25: =IF( OR( INDEX('KPI Analysis'!$AH$7:$CM$123, MATCH($A25,'KPI Analysis'!$AH$7:$AH$123,FALSE), MATCH(T$8,'KPI Analysis'!$AH$7:$CM$7,FALSE) )="R", INDEX('KPI Analysis'!$AH$7:$CM$123, MATCH($A25,'KPI Analysis'!$AH$7:$AH$123,FALSE), MATCH(T$8,'KPI Analysis'!$AH$7:$CM$7,FALSE) )="G", INDEX('KPI Analysis'!$AH$7:$CM$123, MATCH($A25,'KPI Analysis'!$AH$7:$AH$123,FALSE), MATCH(T$8,'KPI Analysis'!$AH$7:$CM$7,FALSE) )="A"), INDEX('KPI Analysis'!$AH$7:$CM$123,MATCH($A25,'KPI Analysis'!$AH$7:$AH$123,FALSE),MATCH(T$8,'KPI Analysis'!$AH$7:$CM$7,FALSE)),"") -> G | U25: =INDEX('KPI Analysis'!$EW$7:$HC$123,MATCH($A25,'KPI Analysis'!$EW$7:$EW$123,FALSE),MATCH(T$8,'KPI Analysis'!$EW$7:$HC$7,FALSE)) -> 1 | V25: =IF( OR( INDEX('KPI Analysis'!$AH$7:$CM$123, MATCH($A25,'KPI Analysis'!$AH$7:$AH$123,FALSE), MATCH(V$8,'KPI Analysis'!$AH$7:$CM$7,FALSE) )="R", INDEX('KPI Analysis'!$AH$7:$CM$123, MATCH($A25,'KPI Analysis'!$AH$7:$AH$123,FALSE), MATCH(V$8,'KPI Analysis'!$AH$7:$CM$7,FALSE) )="G", INDEX('KPI Analysis'!$AH$7:$CM$123, MATCH($A25,'KPI Analysis'!$AH$7:$AH$123,FALSE), MATCH(V$8,'KPI Analysis'!$AH$7:$CM$7,FALSE) )="A"), INDEX('KPI Analysis'!$AH$7:$CM$123,MATCH($A25,'KPI Analysis'!$AH$7:$AH$123,FALSE),MATCH(V$8,'KPI Analysis'!$AH$7:$CM$7,FALSE)),"") -> G | W25: =INDEX('KPI Analysis'!$EW$7:$HC$123,MATCH($A25,'KPI Analysis'!$EW$7:$EW$123,FALSE),MATCH(V$8,'KPI Analysis'!$EW$7:$HC$7,FALSE)) -> 1 | X25: =IF( OR( INDEX('KPI Analysis'!$AH$7:$CM$123, MATCH($A25,'KPI Analysis'!$AH$7:$AH$123,FALSE), MATCH(X$8,'KPI Analysis'!$AH$7:$CM$7,FALSE) )="R", INDEX('KPI Analysis'!$AH$7:$CM$123, MATCH($A25,'KPI Analysis'!$AH$7:$AH$123,FALSE), MATCH(X$8,'KPI Analysis'!$AH$7:$CM$7,FALSE) )="G", INDEX('KPI Analysis'!$AH$7:$CM$123, MATCH($A25,'KPI Analysis'!$AH$7:$AH$123,FALSE), MATCH(X$8,'KPI Analysis'!$AH$7:$CM$7,FALSE) )="A"), INDEX('KPI Analysis'!$AH$7:$CM$123,MATCH($A25,'KPI Analysis'!$AH$7:$AH$123,FALSE),MATCH(X$8,'KPI Analysis'!$AH$7:$CM$7,FALSE)),"") -> G | Y25: =IF(INDEX('KPI Analysis'!$CO$7:$EU$123,MATCH($A25,'KPI Analysis'!$CO$7:$CO$123,FALSE),MATCH(X$8,'KPI Analysis'!$CO$7:$EU$7,FALSE))="OD","OD",INDEX('KPI Analysis'!$EW$7:$HC$123,MATCH($A25,'KPI Analysis'!$EW$7:$EW$123,FALSE),MATCH(X$8,'KPI Analysis'!$EW$7:$HC$7,FALSE))) -> 1 | Z25: Target 1 day | AC25: EW HC | AE25: =INDEX('KPI Analysis'!$CO$7:$EU$123,MATCH($A25,'KPI Analysis'!$CO$7:$CO$123,FALSE),MATCH(AE$8,'KPI Analysis'!$CO$7:$EU$7,FALSE)) -> 0.40747029 | AF25: =INDEX('KPI Analysis'!$CO$7:$EU$123,MATCH($A25,'KPI Analysis'!$CO$7:$CO$123,FALSE),MATCH(AF$8,'KPI Analysis'!$CO$7:$EU$7,FALSE)) -> 0.60728745 | AG25: =INDEX('KPI Analysis'!$CO$7:$EU$123,MATCH($A25,'KPI Analysis'!$CO$7:$CO$123,FALSE),MATCH(AG$8,'KPI Analysis'!$CO$7:$EU$7,FALSE)) -> 1.0526316 | AH25: =INDEX('KPI Analysis'!$CO$7:$EU$123,MATCH($A25,'KPI Analysis'!$CO$7:$CO$123,FALSE),MATCH(AH$8,'KPI Analysis'!$CO$7:$EU$7,FALSE)) -> 1.0526316 | AI25: =INDEX('KPI Analysis'!$CO$7:$EU$123,MATCH($A25,'KPI Analysis'!$CO$7:$CO$123,FALSE),MATCH(AI$8,'KPI Analysis'!$CO$7:$EU$7,FALSE)) -> 1.0526316
A26: =F24&"-"&C26 -> SOP-KPI D2 | B26: =+'KPI Stats'!G25 -> Under | C26: =+'KPI Stats'!C25 -> KPI D2 | H26: W | I26: =+'KPI Stats'!F22 -> 42 | J26: =+'KPI Stats'!D25 -> Delivery | K26: =+'KPI Stats'!E25 -> Order Sign off On Target / In Full (OTIF) days to complete | L26: =+'KPI Stats'!F25 -> Percentage | M26: Act Result | P26: =IF( OR( INDEX('KPI Analysis'!$AH$7:$CM$123, MATCH($A26,'KPI Analysis'!$AH$7:$AH$123,FALSE), MATCH(P$8,'KPI Analysis'!$AH$7:$CM$7,FALSE) )="R", INDEX('KPI Analysis'!$AH$7:$CM$123, MATCH($A26,'KPI Analysis'!$AH$7:$AH$123,FALSE), MATCH(P$8,'KPI Analysis'!$AH$7:$CM$7,FALSE) )="G", INDEX('KPI Analysis'!$AH$7:$CM$123, MATCH($A26,'KPI Analysis'!$AH$7:$AH$123,FALSE), MATCH(P$8,'KPI Analysis'!$AH$7:$CM$7,FALSE) )="A"), INDEX('KPI Analysis'!$AH$7:$CM$123,MATCH($A26,'KPI Analysis'!$AH$7:$AH$123,FALSE),MATCH(P$8,'KPI Analysis'!$AH$7:$CM$7,FALSE)),"") -> R | Q26: =INDEX('KPI Analysis'!$EW$7:$HC$123,MATCH($A26,'KPI Analysis'!$EW$7:$EW$123,FALSE),MATCH(P$8,'KPI Analysis'!$EW$7:$HC$7,FALSE)) -> 0.80645161 | R26: =IF( OR( INDEX('KPI Analysis'!$AH$7:$CM$123, MATCH($A26,'KPI Analysis'!$AH$7:$AH$123,FALSE), MATCH(R$8,'KPI Analysis'!$AH$7:$CM$7,FALSE) )="R", INDEX('KPI Analysis'!$AH$7:$CM$123, MATCH($A26,'KPI Analysis'!$AH$7:$AH$123,FALSE), MATCH(R$8,'KPI Analysis'!$AH$7:$CM$7,FALSE) )="G", INDEX('KPI Analysis'!$AH$7:$CM$123, MATCH($A26,'KPI Analysis'!$AH$7:$AH$123,FALSE), MATCH(R$8,'KPI Analysis'!$AH$7:$CM$7,FALSE) )="A"), INDEX('KPI Analysis'!$AH$7:$CM$123,MATCH($A26,'KPI Analysis'!$AH$7:$AH$123,FALSE),MATCH(R$8,'KPI Analysis'!$AH$7:$CM$7,FALSE)),"") -> R | S26: =INDEX('KPI Analysis'!$EW$7:$HC$123,MATCH($A26,'KPI Analysis'!$EW$7:$EW$123,FALSE),MATCH(R$8,'KPI Analysis'!$EW$7:$HC$7,FALSE)) -> 0.75 | T26: =IF( OR( INDEX('KPI Analysis'!$AH$7:$CM$123, MATCH($A26,'KPI Analysis'!$AH$7:$AH$123,FALSE), MATCH(T$8,'KPI Analysis'!$AH$7:$CM$7,FALSE) )="R", INDEX('KPI Analysis'!$AH$7:$CM$123, MATCH($A26,'KPI Analysis'!$AH$7:$AH$123,FALSE), MATCH(T$8,'KPI Analysis'!$AH$7:$CM$7,FALSE) )="G", INDEX('KPI Analysis'!$AH$7:$CM$123, MATCH($A26,'KPI Analysis'!$AH$7:$AH$123,FALSE), MATCH(T$8,'KPI Analysis'!$AH$7:$CM$7,FALSE) )="A"), INDEX('KPI Analysis'!$AH$7:$CM$123,MATCH($A26,'KPI Analysis'!$AH$7:$AH$123,FALSE),MATCH(T$8,'KPI Analysis'!$AH$7:$CM$7,FALSE)),"") -> A | U26: =INDEX('KPI Analysis'!$EW$7:$HC$123,MATCH($A26,'KPI Analysis'!$EW$7:$EW$123,FALSE),MATCH(T$8,'KPI Analysis'!$EW$7:$HC$7,FALSE)) -> 0.91666667 | V26: =IF( OR( INDEX('KPI Analysis'!$AH$7:$CM$123, MATCH($A26,'KPI Analysis'!$AH$7:$AH$123,FALSE), MATCH(V$8,'KPI Analysis'!$AH$7:$CM$7,FALSE) )="R", INDEX('KPI Analysis'!$AH$7:$CM$123, MATCH($A26,'KPI Analysis'!$AH$7:$AH$123,FALSE), MATCH(V$8,'KPI Analysis'!$AH$7:$CM$7,FALSE) )="G", INDEX('KPI Analysis'!$AH$7:$CM$123, MATCH($A26,'KPI Analysis'!$AH$7:$AH$123,FALSE), MATCH(V$8,'KPI Analysis'!$AH$7:$CM$7,FALSE) )="A"), INDEX('KPI Analysis'!$AH$7:$CM$123,MATCH($A26,'KPI Analysis'!$AH$7:$AH$123,FALSE),MATCH(V$8,'KPI Analysis'!$AH$7:$CM$7,FALSE)),"") -> R | W26: =INDEX('KPI Analysis'!$EW$7:$HC$123,MATCH($A26,'KPI Analysis'!$EW$7:$EW$123,FALSE),MATCH(V$8,'KPI Analysis'!$EW$7:$HC$7,FALSE)) -> 0.875 | X26: =IF( OR( INDEX('KPI Analysis'!$AH$7:$CM$123, MATCH($A26,'KPI Analysis'!$AH$7:$AH$123,FALSE), MATCH(X$8,'KPI Analysis'!$AH$7:$CM$7,FALSE) )="R", INDEX('KPI Analysis'!$AH$7:$CM$123, MATCH($A26,'KPI Analysis'!$AH$7:$AH$123,FALSE), MATCH(X$8,'KPI Analysis'!$AH$7:$CM$7,FALSE) )="G", INDEX('KPI Analysis'!$AH$7:$CM$123, MATCH($A26,'KPI Analysis'!$AH$7:$AH$123,FALSE), MATCH(X$8,'KPI Analysis'!$AH$7:$CM$7,FALSE) )="A"), INDEX('KPI Analysis'!$AH$7:$CM$123,MATCH($A26,'KPI Analysis'!$AH$7:$AH$123,FALSE),MATCH(X$8,'KPI Analysis'!$AH$7:$CM$7,FALSE)),"") -> G | Y26: =IF(INDEX('KPI Analysis'!$CO$7:$EU$123,MATCH($A26,'KPI Analysis'!$CO$7:$CO$123,FALSE),MATCH(X$8,'KPI Analysis'!$CO$7:$EU$7,FALSE))="OD","OD",INDEX('KPI Analysis'!$EW$7:$HC$123,MATCH($A26,'KPI Analysis'!$EW$7:$EW$123,FALSE),MATCH(X$8,'KPI Analysis'!$EW$7:$HC$7,FALSE))) -> 1 | Z26: Target 5 days | AC26: EW HC | AE26: =INDEX('KPI Analysis'!$CO$7:$EU$123,MATCH($A26,'KPI Analysis'!$CO$7:$CO$123,FALSE),MATCH(AE$8,'KPI Analysis'!$CO$7:$EU$7,FALSE)) -> 0.84889643 | AF26: =INDEX('KPI Analysis'!$CO$7:$EU$123,MATCH($A26,'KPI Analysis'!$CO$7:$CO$123,FALSE),MATCH(AF$8,'KPI Analysis'!$CO$7:$EU$7,FALSE)) -> 0.78947368 | AG26: =INDEX('KPI Analysis'!$CO$7:$EU$123,MATCH($A26,'KPI Analysis'!$CO$7:$CO$123,FALSE),MATCH(AG$8,'KPI Analysis'!$CO$7:$EU$7,FALSE)) -> 0.96491228 | AH26: =INDEX('KPI Analysis'!$CO$7:$EU$123,MATCH($A26,'KPI Analysis'!$CO$7:$CO$123,FALSE),MATCH(AH$8,'KPI Analysis'!$CO$7:$EU$7,FALSE)) -> 0.92105263 | AI26: =INDEX('KPI Analysis'!$CO$7:$EU$123,MATCH($A26,'KPI Analysis'!$CO$7:$CO$123,FALSE),MATCH(AI$8,'KPI Analysis'!$CO$7:$EU$7,FALSE)) -> 1.0526316
A27: =F27&"-"&C27 -> SOP-KPI Q1 | B27: =+'KPI Stats'!G26 -> Above Zero | C27: =+'KPI Stats'!C26 -> KPI Q1 | F27: =+'KPI Stats'!B22 -> SOP | G27: =+'KPI Stats'!C22 -> Sam Westwood | H27: W | I27: =+'KPI Stats'!F22 -> 42 | J27: =+'KPI Stats'!D26 -> Quality | K27: =+'KPI Stats'!E26 -> Customer Complaints | L27: =+'KPI Stats'!F26 -> Count | M27: =INDEX('KPI Analysis'!$CO$7:$EU$123,MATCH($A27,'KPI Analysis'!$CO$7:$CO$123,FALSE),MATCH(M$8,'KPI Analysis'!$CO$7:$EU$7,FALSE)) -> Act Result | P27: =IF( OR( INDEX('KPI Analysis'!$AH$7:$CM$123, MATCH($A27,'KPI Analysis'!$AH$7:$AH$123,FALSE), MATCH(P$8,'KPI Analysis'!$AH$7:$CM$7,FALSE) )="R", INDEX('KPI Analysis'!$AH$7:$CM$123, MATCH($A27,'KPI Analysis'!$AH$7:$AH$123,FALSE), MATCH(P$8,'KPI Analysis'!$AH$7:$CM$7,FALSE) )="G", INDEX('KPI Analysis'!$AH$7:$CM$123, MATCH($A27,'KPI Analysis'!$AH$7:$AH$123,FALSE), MATCH(P$8,'KPI Analysis'!$AH$7:$CM$7,FALSE) )="A"), INDEX('KPI Analysis'!$AH$7:$CM$123,MATCH($A27,'KPI Analysis'!$AH$7:$AH$123,FALSE),MATCH(P$8,'KPI Analysis'!$AH$7:$CM$7,FALSE)),"") -> R | Q27: =INDEX('KPI Analysis'!$EW$7:$HC$123,MATCH($A27,'KPI Analysis'!$EW$7:$EW$123,FALSE),MATCH(P$8,'KPI Analysis'!$EW$7:$HC$7,FALSE)) -> 1 | R27: =IF( OR( INDEX('KPI Analysis'!$AH$7:$CM$123, MATCH($A27,'KPI Analysis'!$AH$7:$AH$123,FALSE), MATCH(R$8,'KPI Analysis'!$AH$7:$CM$7,FALSE) )="R", INDEX('KPI Analysis'!$AH$7:$CM$123, MATCH($A27,'KPI Analysis'!$AH$7:$AH$123,FALSE), MATCH(R$8,'KPI Analysis'!$AH$7:$CM$7,FALSE) )="G", INDEX('KPI Analysis'!$AH$7:$CM$123, MATCH($A27,'KPI Analysis'!$AH$7:$AH$123,FALSE), MATCH(R$8,'KPI Analysis'!$AH$7:$CM$7,FALSE) )="A"), INDEX('KPI Analysis'!$AH$7:$CM$123,MATCH($A27,'KPI Analysis'!$AH$7:$AH$123,FALSE),MATCH(R$8,'KPI Analysis'!$AH$7:$CM$7,FALSE)),"") -> R | S27: =INDEX('KPI Analysis'!$EW$7:$HC$123,MATCH($A27,'KPI Analysis'!$EW$7:$EW$123,FALSE),MATCH(R$8,'KPI Analysis'!$EW$7:$HC$7,FALSE)) -> 3 | T27: =IF( OR( INDEX('KPI Analysis'!$AH$7:$CM$123, MATCH($A27,'KPI Analysis'!$AH$7:$AH$123,FALSE), MATCH(T$8,'KPI Analysis'!$AH$7:$CM$7,FALSE) )="R", INDEX('KPI Analysis'!$AH$7:$CM$123, MATCH($A27,'KPI Analysis'!$AH$7:$AH$123,FALSE), MATCH(T$8,'KPI Analysis'!$AH$7:$CM$7,FALSE) )="G", INDEX('KPI Analysis'!$AH$7:$CM$123, MATCH($A27,'KPI Analysis'!$AH$7:$AH$123,FALSE), MATCH(T$8,'KPI Analysis'!$AH$7:$CM$7,FALSE) )="A"), INDEX('KPI Analysis'!$AH$7:$CM$123,MATCH($A27,'KPI Analysis'!$AH$7:$AH$123,FALSE),MATCH(T$8,'KPI Analysis'!$AH$7:$CM$7,FALSE)),"") -> R | U27: =INDEX('KPI Analysis'!$EW$7:$HC$123,MATCH($A27,'KPI Analysis'!$EW$7:$EW$123,FALSE),MATCH(T$8,'KPI Analysis'!$EW$7:$HC$7,FALSE)) -> 2 | V27: =IF( OR( INDEX('KPI Analysis'!$AH$7:$CM$123, MATCH($A27,'KPI Analysis'!$AH$7:$AH$123,FALSE), MATCH(V$8,'KPI Analysis'!$AH$7:$CM$7,FALSE) )="R", INDEX('KPI Analysis'!$AH$7:$CM$123, MATCH($A27,'KPI Analysis'!$AH$7:$AH$123,FALSE), MATCH(V$8,'KPI Analysis'!$AH$7:$CM$7,FALSE) )="G", INDEX('KPI Analysis'!$AH$7:$CM$123, MATCH($A27,'KPI Analysis'!$AH$7:$AH$123,FALSE), MATCH(V$8,'KPI Analysis'!$AH$7:$CM$7,FALSE) )="A"), INDEX('KPI Analysis'!$AH$7:$CM$123,MATCH($A27,'KPI Analysis'!$AH$7:$AH$123,FALSE),MATCH(V$8,'KPI Analysis'!$AH$7:$CM$7,FALSE)),"") -> R | W27: =INDEX('KPI Analysis'!$EW$7:$HC$123,MATCH($A27,'KPI Analysis'!$EW$7:$EW$123,FALSE),MATCH(V$8,'KPI Analysis'!$EW$7:$HC$7,FALSE)) -> 4 | X27: =IF( OR( INDEX('KPI Analysis'!$AH$7:$CM$123, MATCH($A27,'KPI Analysis'!$AH$7:$AH$123,FALSE), MATCH(X$8,'KPI Analysis'!$AH$7:$CM$7,FALSE) )="R", INDEX('KPI Analysis'!$AH$7:$CM$123, MATCH($A27,'KPI Analysis'!$AH$7:$AH$123,FALSE), MATCH(X$8,'KPI Analysis'!$AH$7:$CM$7,FALSE) )="G", INDEX('KPI Analysis'!$AH$7:$CM$123, MATCH($A27,'KPI Analysis'!$AH$7:$AH$123,FALSE), MATCH(X$8,'KPI Analysis'!$AH$7:$CM$7,FALSE) )="A"), INDEX('KPI Analysis'!$AH$7:$CM$123,MATCH($A27,'KPI Analysis'!$AH$7:$AH$123,FALSE),MATCH(X$8,'KPI Analysis'!$AH$7:$CM$7,FALSE)),"") -> G | Y27: =IF(INDEX('KPI Analysis'!$CO$7:$EU$123,MATCH($A27,'KPI Analysis'!$CO$7:$CO$123,FALSE),MATCH(X$8,'KPI Analysis'!$CO$7:$EU$7,FALSE))="OD","OD",INDEX('KPI Analysis'!$EW$7:$HC$123,MATCH($A27,'KPI Analysis'!$EW$7:$EW$123,FALSE),MATCH(X$8,'KPI Analysis'!$EW$7:$HC$7,FALSE))) -> 0 | Z27: (Target 0) Act Result Shown | AC27: EW HC | AE27: =INDEX('KPI Analysis'!$CO$7:$EU$123,MATCH($A27,'KPI Analysis'!$CO$7:$CO$123,FALSE),MATCH(AE$8,'KPI Analysis'!$CO$7:$EU$7,FALSE)) -> 1 | AF27: =INDEX('KPI Analysis'!$CO$7:$EU$123,MATCH($A27,'KPI Analysis'!$CO$7:$CO$123,FALSE),MATCH(AF$8,'KPI Analysis'!$CO$7:$EU$7,FALSE)) -> 3 | AG27: =INDEX('KPI Analysis'!$CO$7:$EU$123,MATCH($A27,'KPI Analysis'!$CO$7:$CO$123,FALSE),MATCH(AG$8,'KPI Analysis'!$CO$7:$EU$7,FALSE)) -> 2 | AH27: =INDEX('KPI Analysis'!$CO$7:$EU$123,MATCH($A27,'KPI Analysis'!$CO$7:$CO$123,FALSE),MATCH(AH$8,'KPI Analysis'!$CO$7:$EU$7,FALSE)) -> 4 | AI27: =INDEX('KPI Analysis'!$CO$7:$EU$123,MATCH($A27,'KPI Analysis'!$CO$7:$CO$123,FALSE),MATCH(AI$8,'KPI Analysis'!$CO$7:$EU$7,FALSE)) -> 0
A28: =F28&"-"&C28 -> SOP-KPI C1 | B28: =+'KPI Stats'!G27 -> Under | C28: =+'KPI Stats'!C27 -> KPI C1 | F28: =+'KPI Stats'!B22 -> SOP | G28: =+'KPI Stats'!C22 -> Sam Westwood | H28: W | I28: =+'KPI Stats'!F22 -> 42 | J28: =+'KPI Stats'!D27 -> Cost | K28: =+'KPI Stats'!E27 -> Order Value completed per FTE head | L28: =+'KPI Stats'!F27 -> £'s | M28: =INDEX('KPI Analysis'!$CO$7:$EU$123,MATCH($A28,'KPI Analysis'!$CO$7:$CO$123,FALSE),MATCH(M$8,'KPI Analysis'!$CO$7:$EU$7,FALSE)) -> % of target | P28: =IF( OR( INDEX('KPI Analysis'!$AH$7:$CM$123, MATCH($A28,'KPI Analysis'!$AH$7:$AH$123,FALSE), MATCH(P$8,'KPI Analysis'!$AH$7:$CM$7,FALSE) )="R", INDEX('KPI Analysis'!$AH$7:$CM$123, MATCH($A28,'KPI Analysis'!$AH$7:$AH$123,FALSE), MATCH(P$8,'KPI Analysis'!$AH$7:$CM$7,FALSE) )="G", INDEX('KPI Analysis'!$AH$7:$CM$123, MATCH($A28,'KPI Analysis'!$AH$7:$AH$123,FALSE), MATCH(P$8,'KPI Analysis'!$AH$7:$CM$7,FALSE) )="A"), INDEX('KPI Analysis'!$AH$7:$CM$123,MATCH($A28,'KPI Analysis'!$AH$7:$AH$123,FALSE),MATCH(P$8,'KPI Analysis'!$AH$7:$CM$7,FALSE)),"") -> G | Q28: =INDEX('KPI Analysis'!$CO$7:$EU$123,MATCH($A28,'KPI Analysis'!$CO$7:$CO$123,FALSE),MATCH(P$8,'KPI Analysis'!$CO$7:$EU$7,FALSE)) -> 1.294575 | R28: =IF( OR( INDEX('KPI Analysis'!$AH$7:$CM$123, MATCH($A28,'KPI Analysis'!$AH$7:$AH$123,FALSE), MATCH(R$8,'KPI Analysis'!$AH$7:$CM$7,FALSE) )="R", INDEX('KPI Analysis'!$AH$7:$CM$123, MATCH($A28,'KPI Analysis'!$AH$7:$AH$123,FALSE), MATCH(R$8,'KPI Analysis'!$AH$7:$CM$7,FALSE) )="G", INDEX('KPI Analysis'!$AH$7:$CM$123, MATCH($A28,'KPI Analysis'!$AH$7:$AH$123,FALSE), MATCH(R$8,'KPI Analysis'!$AH$7:$CM$7,FALSE) )="A"), INDEX('KPI Analysis'!$AH$7:$CM$123,MATCH($A28,'KPI Analysis'!$AH$7:$AH$123,FALSE),MATCH(R$8,'KPI Analysis'!$AH$7:$CM$7,FALSE)),"") -> R | S28: =INDEX('KPI Analysis'!$CO$7:$EU$123,MATCH($A28,'KPI Analysis'!$CO$7:$CO$123,FALSE),MATCH(R$8,'KPI Analysis'!$CO$7:$EU$7,FALSE)) -> 0.7283871 | T28: =IF( OR( INDEX('KPI Analysis'!$AH$7:$CM$123, MATCH($A28,'KPI Analysis'!$AH$7:$AH$123,FALSE), MATCH(T$8,'KPI Analysis'!$AH$7:$CM$7,FALSE) )="R", INDEX('KPI Analysis'!$AH$7:$CM$123, MATCH($A28,'KPI Analysis'!$AH$7:$AH$123,FALSE), MATCH(T$8,'KPI Analysis'!$AH$7:$CM$7,FALSE) )="G", INDEX('KPI Analysis'!$AH$7:$CM$123, MATCH($A28,'KPI Analysis'!$AH$7:$AH$123,FALSE), MATCH(T$8,'KPI Analysis'!$AH$7:$CM$7,FALSE) )="A"), INDEX('KPI Analysis'!$AH$7:$CM$123,MATCH($A28,'KPI Analysis'!$AH$7:$AH$123,FALSE),MATCH(T$8,'KPI Analysis'!$AH$7:$CM$7,FALSE)),"") -> R | U28: =INDEX('KPI Analysis'!$CO$7:$EU$123,MATCH($A28,'KPI Analysis'!$CO$7:$CO$123,FALSE),MATCH(T$8,'KPI Analysis'!$CO$7:$EU$7,FALSE)) -> 0.83726755 | V28: =IF( OR( INDEX('KPI Analysis'!$AH$7:$CM$123, MATCH($A28,'KPI Analysis'!$AH$7:$AH$123,FALSE), MATCH(V$8,'KPI Analysis'!$AH$7:$CM$7,FALSE) )="R", INDEX('KPI Analysis'!$AH$7:$CM$123, MATCH($A28,'KPI Analysis'!$AH$7:$AH$123,FALSE), MATCH(V$8,'KPI Analysis'!$AH$7:$CM$7,FALSE) )="G", INDEX('KPI Analysis'!$AH$7:$CM$123, MATCH($A28,'KPI Analysis'!$AH$7:$AH$123,FALSE), MATCH(V$8,'KPI Analysis'!$AH$7:$CM$7,FALSE) )="A"), INDEX('KPI Analysis'!$AH$7:$CM$123,MATCH($A28,'KPI Analysis'!$AH$7:$AH$123,FALSE),MATCH(V$8,'KPI Analysis'!$AH$7:$CM$7,FALSE)),"") -> G | W28: =INDEX('KPI Analysis'!$CO$7:$EU$123,MATCH($A28,'KPI Analysis'!$CO$7:$CO$123,FALSE),MATCH(V$8,'KPI Analysis'!$CO$7:$EU$7,FALSE)) -> 1.6848585 | X28: =IF( OR( INDEX('KPI Analysis'!$AH$7:$CM$123, MATCH($A28,'KPI Analysis'!$AH$7:$AH$123,FALSE), MATCH(X$8,'KPI Analysis'!$AH$7:$CM$7,FALSE) )="R", INDEX('KPI Analysis'!$AH$7:$CM$123, MATCH($A28,'KPI Analysis'!$AH$7:$AH$123,FALSE), MATCH(X$8,'KPI Analysis'!$AH$7:$CM$7,FALSE) )="G", INDEX('KPI Analysis'!$AH$7:$CM$123, MATCH($A28,'KPI Analysis'!$AH$7:$AH$123,FALSE), MATCH(X$8,'KPI Analysis'!$AH$7:$CM$7,FALSE) )="A"), INDEX('KPI Analysis'!$AH$7:$CM$123,MATCH($A28,'KPI Analysis'!$AH$7:$AH$123,FALSE),MATCH(X$8,'KPI Analysis'!$AH$7:$CM$7,FALSE)),"") -> G | Y28: =INDEX('KPI Analysis'!$CO$7:$EU$123,MATCH($A28,'KPI Analysis'!$CO$7:$CO$123,FALSE),MATCH(X$8,'KPI Analysis'!$CO$7:$EU$7,FALSE)) -> 1.3757558 | AC28: Co EU | AE28: =INDEX('KPI Analysis'!$CO$7:$EU$123,MATCH($A28,'KPI Analysis'!$CO$7:$CO$123,FALSE),MATCH(AE$8,'KPI Analysis'!$CO$7:$EU$7,FALSE)) -> 1.294575 | AF28: =INDEX('KPI Analysis'!$CO$7:$EU$123,MATCH($A28,'KPI Analysis'!$CO$7:$CO$123,FALSE),MATCH(AF$8,'KPI Analysis'!$CO$7:$EU$7,FALSE)) -> 0.7283871 | AG28: =INDEX('KPI Analysis'!$CO$7:$EU$123,MATCH($A28,'KPI Analysis'!$CO$7:$CO$123,FALSE),MATCH(AG$8,'KPI Analysis'!$CO$7:$EU$7,FALSE)) -> 0.83726755 | AH28: =INDEX('KPI Analysis'!$CO$7:$EU$123,MATCH($A28,'KPI Analysis'!$CO$7:$CO$123,FALSE),MATCH(AH$8,'KPI Analysis'!$CO$7:$EU$7,FALSE)) -> 1.6848585 | AI28: =INDEX('KPI Analysis'!$CO$7:$EU$123,MATCH($A28,'KPI Analysis'!$CO$7:$CO$123,FALSE),MATCH(AI$8,'KPI Analysis'!$CO$7:$EU$7,FALSE)) -> 1.3757558
A31: =F31&"-"&C31 -> Design-KPI P1 | B31: =+'KPI Stats'!G30 -> Under | C31: =+'KPI Stats'!C30 -> KPI P1 | F31: =+'KPI Stats'!$B$29 -> Design | G31: =+'KPI Stats'!$C$29 -> Andrew Skitt | H31: W | I31: =+'KPI Stats'!$F$29 -> 42 | J31: =+'KPI Stats'!D30 -> Productivity | K31: =+'KPI Stats'!E30 -> Design requests closed | L31: =+'KPI Stats'!F30 -> Count | M31: =INDEX('KPI Analysis'!$CO$7:$EU$123,MATCH($A31,'KPI Analysis'!$CO$7:$CO$123,FALSE),MATCH(M$8,'KPI Analysis'!$CO$7:$EU$7,FALSE)) -> % of target | P31: =IF( OR( INDEX('KPI Analysis'!$AH$7:$CM$123, MATCH($A31,'KPI Analysis'!$AH$7:$AH$123,FALSE), MATCH(P$8,'KPI Analysis'!$AH$7:$CM$7,FALSE) )="R", INDEX('KPI Analysis'!$AH$7:$CM$123, MATCH($A31,'KPI Analysis'!$AH$7:$AH$123,FALSE), MATCH(P$8,'KPI Analysis'!$AH$7:$CM$7,FALSE) )="G", INDEX('KPI Analysis'!$AH$7:$CM$123, MATCH($A31,'KPI Analysis'!$AH$7:$AH$123,FALSE), MATCH(P$8,'KPI Analysis'!$AH$7:$CM$7,FALSE) )="A"), INDEX('KPI Analysis'!$AH$7:$CM$123,MATCH($A31,'KPI Analysis'!$AH$7:$AH$123,FALSE),MATCH(P$8,'KPI Analysis'!$AH$7:$CM$7,FALSE)),"") -> R | Q31: =INDEX('KPI Analysis'!$CO$7:$EU$123,MATCH($A31,'KPI Analysis'!$CO$7:$CO$123,FALSE),MATCH(P$8,'KPI Analysis'!$CO$7:$EU$7,FALSE)) -> 0.71428571 | R31: =IF( OR( INDEX('KPI Analysis'!$AH$7:$CM$123, MATCH($A31,'KPI Analysis'!$AH$7:$AH$123,FALSE), MATCH(R$8,'KPI Analysis'!$AH$7:$CM$7,FALSE) )="R", INDEX('KPI Analysis'!$AH$7:$CM$123, MATCH($A31,'KPI Analysis'!$AH$7:$AH$123,FALSE), MATCH(R$8,'KPI Analysis'!$AH$7:$CM$7,FALSE) )="G", INDEX('KPI Analysis'!$AH$7:$CM$123, MATCH($A31,'KPI Analysis'!$AH$7:$AH$123,FALSE), MATCH(R$8,'KPI Analysis'!$AH$7:$CM$7,FALSE) )="A"), INDEX('KPI Analysis'!$AH$7:$CM$123,MATCH($A31,'KPI Analysis'!$AH$7:$AH$123,FALSE),MATCH(R$8,'KPI Analysis'!$AH$7:$CM$7,FALSE)),"") -> R | S31: =INDEX('KPI Analysis'!$CO$7:$EU$123,MATCH($A31,'KPI Analysis'!$CO$7:$CO$123,FALSE),MATCH(R$8,'KPI Analysis'!$CO$7:$EU$7,FALSE)) -> 0.62857143 | T31: =IF( OR( INDEX('KPI Analysis'!$AH$7:$CM$123, MATCH($A31,'KPI Analysis'!$AH$7:$AH$123,FALSE), MATCH(T$8,'KPI Analysis'!$AH$7:$CM$7,FALSE) )="R", INDEX('KPI Analysis'!$AH$7:$CM$123, MATCH($A31,'KPI Analysis'!$AH$7:$AH$123,FALSE), MATCH(T$8,'KPI Analysis'!$AH$7:$CM$7,FALSE) )="G", INDEX('KPI Analysis'!$AH$7:$CM$123, MATCH($A31,'KPI Analysis'!$AH$7:$AH$123,FALSE), MATCH(T$8,'KPI Analysis'!$AH$7:$CM$7,FALSE) )="A"), INDEX('KPI Analysis'!$AH$7:$CM$123,MATCH($A31,'KPI Analysis'!$AH$7:$AH$123,FALSE),MATCH(T$8,'KPI Analysis'!$AH$7:$CM$7,FALSE)),"") -> R | U31: =INDEX('KPI Analysis'!$CO$7:$EU$123,MATCH($A31,'KPI Analysis'!$CO$7:$CO$123,FALSE),MATCH(T$8,'KPI Analysis'!$CO$7:$EU$7,FALSE)) -> 0.74285714 | V31: =IF( OR( INDEX('KPI Analysis'!$AH$7:$CM$123, MATCH($A31,'KPI Analysis'!$AH$7:$AH$123,FALSE), MATCH(V$8,'KPI Analysis'!$AH$7:$CM$7,FALSE) )="R", INDEX('KPI Analysis'!$AH$7:$CM$123, MATCH($A31,'KPI Analysis'!$AH$7:$AH$123,FALSE), MATCH(V$8,'KPI Analysis'!$AH$7:$CM$7,FALSE) )="G", INDEX('KPI Analysis'!$AH$7:$CM$123, MATCH($A31,'KPI Analysis'!$AH$7:$AH$123,FALSE), MATCH(V$8,'KPI Analysis'!$AH$7:$CM$7,FALSE) )="A"), INDEX('KPI Analysis'!$AH$7:$CM$123,MATCH($A31,'KPI Analysis'!$AH$7:$AH$123,FALSE),MATCH(V$8,'KPI Analysis'!$AH$7:$CM$7,FALSE)),"") -> R | W31: =INDEX('KPI Analysis'!$CO$7:$EU$123,MATCH($A31,'KPI Analysis'!$CO$7:$CO$123,FALSE),MATCH(V$8,'KPI Analysis'!$CO$7:$EU$7,FALSE)) -> 0.77142857 | X31: =IF( OR( INDEX('KPI Analysis'!$AH$7:$CM$123, MATCH($A31,'KPI Analysis'!$AH$7:$AH$123,FALSE), MATCH(X$8,'KPI Analysis'!$AH$7:$CM$7,FALSE) )="R", INDEX('KPI Analysis'!$AH$7:$CM$123, MATCH($A31,'KPI Analysis'!$AH$7:$AH$123,FALSE), MATCH(X$8,'KPI Analysis'!$AH$7:$CM$7,FALSE) )="G", INDEX('KPI Analysis'!$AH$7:$CM$123, MATCH($A31,'KPI Analysis'!$AH$7:$AH$123,FALSE), MATCH(X$8,'KPI Analysis'!$AH$7:$CM$7,FALSE) )="A"), INDEX('KPI Analysis'!$AH$7:$CM$123,MATCH($A31,'KPI Analysis'!$AH$7:$AH$123,FALSE),MATCH(X$8,'KPI Analysis'!$AH$7:$CM$7,FALSE)),"") -> R | Y31: =INDEX('KPI Analysis'!$CO$7:$EU$123,MATCH($A31,'KPI Analysis'!$CO$7:$CO$123,FALSE),MATCH(X$8,'KPI Analysis'!$CO$7:$EU$7,FALSE)) -> 0.68571429 | AC31: Co EU | AE31: =INDEX('KPI Analysis'!$CO$7:$EU$123,MATCH($A31,'KPI Analysis'!$CO$7:$CO$123,FALSE),MATCH(AE$8,'KPI Analysis'!$CO$7:$EU$7,FALSE)) -> 0.71428571 | AF31: =INDEX('KPI Analysis'!$CO$7:$EU$123,MATCH($A31,'KPI Analysis'!$CO$7:$CO$123,FALSE),MATCH(AF$8,'KPI Analysis'!$CO$7:$EU$7,FALSE)) -> 0.62857143 | AG31: =INDEX('KPI Analysis'!$CO$7:$EU$123,MATCH($A31,'KPI Analysis'!$CO$7:$CO$123,FALSE),MATCH(AG$8,'KPI Analysis'!$CO$7:$EU$7,FALSE)) -> 0.74285714 | AH31: =INDEX('KPI Analysis'!$CO$7:$EU$123,MATCH($A31,'KPI Analysis'!$CO$7:$CO$123,FALSE),MATCH(AH$8,'KPI Analysis'!$CO$7:$EU$7,FALSE)) -> 0.77142857 | AI31: =INDEX('KPI Analysis'!$CO$7:$EU$123,MATCH($A31,'KPI Analysis'!$CO$7:$CO$123,FALSE),MATCH(AI$8,'KPI Analysis'!$CO$7:$EU$7,FALSE)) -> 0.68571429
A32: =F32&"-"&C32 -> Design-KPI D1 | B32: =+'KPI Stats'!G31 -> Under | C32: =+'KPI Stats'!C31 -> KPI D1 | F32: =+'KPI Stats'!$B$29 -> Design | G32: =+'KPI Stats'!$B$29 -> Design | H32: W | I32: =+'KPI Stats'!$F$29 -> 42 | J32: =+'KPI Stats'!D31 -> Delivery | K32: =+'KPI Stats'!E31 -> Designs completed to internal days estimate | L32: =+'KPI Stats'!F31 -> Percentage | M32: =INDEX('KPI Analysis'!$CO$7:$EU$123,MATCH($A32,'KPI Analysis'!$CO$7:$CO$123,FALSE),MATCH(M$8,'KPI Analysis'!$CO$7:$EU$7,FALSE)) -> % of target | P32: =IF( OR( INDEX('KPI Analysis'!$AH$7:$CM$123, MATCH($A32,'KPI Analysis'!$AH$7:$AH$123,FALSE), MATCH(P$8,'KPI Analysis'!$AH$7:$CM$7,FALSE) )="R", INDEX('KPI Analysis'!$AH$7:$CM$123, MATCH($A32,'KPI Analysis'!$AH$7:$AH$123,FALSE), MATCH(P$8,'KPI Analysis'!$AH$7:$CM$7,FALSE) )="G", INDEX('KPI Analysis'!$AH$7:$CM$123, MATCH($A32,'KPI Analysis'!$AH$7:$AH$123,FALSE), MATCH(P$8,'KPI Analysis'!$AH$7:$CM$7,FALSE) )="A"), INDEX('KPI Analysis'!$AH$7:$CM$123,MATCH($A32,'KPI Analysis'!$AH$7:$AH$123,FALSE),MATCH(P$8,'KPI Analysis'!$AH$7:$CM$7,FALSE)),"") -> R | Q32: =INDEX('KPI Analysis'!$CO$7:$EU$123,MATCH($A32,'KPI Analysis'!$CO$7:$CO$123,FALSE),MATCH(P$8,'KPI Analysis'!$CO$7:$EU$7,FALSE)) -> 0.68 | R32: =IF( OR( INDEX('KPI Analysis'!$AH$7:$CM$123, MATCH($A32,'KPI Analysis'!$AH$7:$AH$123,FALSE), MATCH(R$8,'KPI Analysis'!$AH$7:$CM$7,FALSE) )="R", INDEX('KPI Analysis'!$AH$7:$CM$123, MATCH($A32,'KPI Analysis'!$AH$7:$AH$123,FALSE), MATCH(R$8,'KPI Analysis'!$AH$7:$CM$7,FALSE) )="G", INDEX('KPI Analysis'!$AH$7:$CM$123, MATCH($A32,'KPI Analysis'!$AH$7:$AH$123,FALSE), MATCH(R$8,'KPI Analysis'!$AH$7:$CM$7,FALSE) )="A"), INDEX('KPI Analysis'!$AH$7:$CM$123,MATCH($A32,'KPI Analysis'!$AH$7:$AH$123,FALSE),MATCH(R$8,'KPI Analysis'!$AH$7:$CM$7,FALSE)),"") -> R | S32: =INDEX('KPI Analysis'!$CO$7:$EU$123,MATCH($A32,'KPI Analysis'!$CO$7:$CO$123,FALSE),MATCH(R$8,'KPI Analysis'!$CO$7:$EU$7,FALSE)) -> 0.77 | T32: =IF( OR( INDEX('KPI Analysis'!$AH$7:$CM$123, MATCH($A32,'KPI Analysis'!$AH$7:$AH$123,FALSE), MATCH(T$8,'KPI Analysis'!$AH$7:$CM$7,FALSE) )="R", INDEX('KPI Analysis'!$AH$7:$CM$123, MATCH($A32,'KPI Analysis'!$AH$7:$AH$123,FALSE), MATCH(T$8,'KPI Analysis'!$AH$7:$CM$7,FALSE) )="G", INDEX('KPI Analysis'!$AH$7:$CM$123, MATCH($A32,'KPI Analysis'!$AH$7:$AH$123,FALSE), MATCH(T$8,'KPI Analysis'!$AH$7:$CM$7,FALSE) )="A"), INDEX('KPI Analysis'!$AH$7:$CM$123,MATCH($A32,'KPI Analysis'!$AH$7:$AH$123,FALSE),MATCH(T$8,'KPI Analysis'!$AH$7:$CM$7,FALSE)),"") -> R | U32: =INDEX('KPI Analysis'!$CO$7:$EU$123,MATCH($A32,'KPI Analysis'!$CO$7:$CO$123,FALSE),MATCH(T$8,'KPI Analysis'!$CO$7:$EU$7,FALSE)) -> 0.77 | V32: =IF( OR( INDEX('KPI Analysis'!$AH$7:$CM$123, MATCH($A32,'KPI Analysis'!$AH$7:$AH$123,FALSE), MATCH(V$8,'KPI Analysis'!$AH$7:$CM$7,FALSE) )="R", INDEX('KPI Analysis'!$AH$7:$CM$123, MATCH($A32,'KPI Analysis'!$AH$7:$AH$123,FALSE), MATCH(V$8,'KPI Analysis'!$AH$7:$CM$7,FALSE) )="G", INDEX('KPI Analysis'!$AH$7:$CM$123, MATCH($A32,'KPI Analysis'!$AH$7:$AH$123,FALSE), MATCH(V$8,'KPI Analysis'!$AH$7:$CM$7,FALSE) )="A"), INDEX('KPI Analysis'!$AH$7:$CM$123,MATCH($A32,'KPI Analysis'!$AH$7:$AH$123,FALSE),MATCH(V$8,'KPI Analysis'!$AH$7:$CM$7,FALSE)),"") -> R | W32: =INDEX('KPI Analysis'!$CO$7:$EU$123,MATCH($A32,'KPI Analysis'!$CO$7:$CO$123,FALSE),MATCH(V$8,'KPI Analysis'!$CO$7:$EU$7,FALSE)) -> 0.81 | X32: =IF( OR( INDEX('KPI Analysis'!$AH$7:$CM$123, MATCH($A32,'KPI Analysis'!$AH$7:$AH$123,FALSE), MATCH(X$8,'KPI Analysis'!$AH$7:$CM$7,FALSE) )="R", INDEX('KPI Analysis'!$AH$7:$CM$123, MATCH($A32,'KPI Analysis'!$AH$7:$AH$123,FALSE), MATCH(X$8,'KPI Analysis'!$AH$7:$CM$7,FALSE) )="G", INDEX('KPI Analysis'!$AH$7:$CM$123, MATCH($A32,'KPI Analysis'!$AH$7:$AH$123,FALSE), MATCH(X$8,'KPI Analysis'!$AH$7:$CM$7,FALSE) )="A"), INDEX('KPI Analysis'!$AH$7:$CM$123,MATCH($A32,'KPI Analysis'!$AH$7:$AH$123,FALSE),MATCH(X$8,'KPI Analysis'!$AH$7:$CM$7,FALSE)),"") -> R | Y32: =INDEX('KPI Analysis'!$CO$7:$EU$123,MATCH($A32,'KPI Analysis'!$CO$7:$CO$123,FALSE),MATCH(X$8,'KPI Analysis'!$CO$7:$EU$7,FALSE)) -> 0.76 | AC32: Co EU | AE32: =INDEX('KPI Analysis'!$CO$7:$EU$123,MATCH($A32,'KPI Analysis'!$CO$7:$CO$123,FALSE),MATCH(AE$8,'KPI Analysis'!$CO$7:$EU$7,FALSE)) -> 0.68 | AF32: =INDEX('KPI Analysis'!$CO$7:$EU$123,MATCH($A32,'KPI Analysis'!$CO$7:$CO$123,FALSE),MATCH(AF$8,'KPI Analysis'!$CO$7:$EU$7,FALSE)) -> 0.77 | AG32: =INDEX('KPI Analysis'!$CO$7:$EU$123,MATCH($A32,'KPI Analysis'!$CO$7:$CO$123,FALSE),MATCH(AG$8,'KPI Analysis'!$CO$7:$EU$7,FALSE)) -> 0.77 | AH32: =INDEX('KPI Analysis'!$CO$7:$EU$123,MATCH($A32,'KPI Analysis'!$CO$7:$CO$123,FALSE),MATCH(AH$8,'KPI Analysis'!$CO$7:$EU$7,FALSE)) -> 0.81 | AI32: =INDEX('KPI Analysis'!$CO$7:$EU$123,MATCH($A32,'KPI Analysis'!$CO$7:$CO$123,FALSE),MATCH(AI$8,'KPI Analysis'!$CO$7:$EU$7,FALSE)) -> 0.76
A33: =F33&"-"&C33 -> Design-KPI Q1 | B33: =+'KPI Stats'!G32 -> Above Zero | C33: =+'KPI Stats'!C32 -> KPI Q1 | F33: =+'KPI Stats'!$B$29 -> Design | G33: =+'KPI Stats'!$B$29 -> Design | H33: W | I33: =+'KPI Stats'!$F$29 -> 42 | J33: =+'KPI Stats'!D32 -> Quality | K33: =+'KPI Stats'!E32 -> Designs rejected (Internal) | L33: =+'KPI Stats'!F32 -> Count | M33: =INDEX('KPI Analysis'!$CO$7:$EU$123,MATCH($A33,'KPI Analysis'!$CO$7:$CO$123,FALSE),MATCH(M$8,'KPI Analysis'!$CO$7:$EU$7,FALSE)) -> Act Result | P33: =IF( OR( INDEX('KPI Analysis'!$AH$7:$CM$123, MATCH($A33,'KPI Analysis'!$AH$7:$AH$123,FALSE), MATCH(P$8,'KPI Analysis'!$AH$7:$CM$7,FALSE) )="R", INDEX('KPI Analysis'!$AH$7:$CM$123, MATCH($A33,'KPI Analysis'!$AH$7:$AH$123,FALSE), MATCH(P$8,'KPI Analysis'!$AH$7:$CM$7,FALSE) )="G", INDEX('KPI Analysis'!$AH$7:$CM$123, MATCH($A33,'KPI Analysis'!$AH$7:$AH$123,FALSE), MATCH(P$8,'KPI Analysis'!$AH$7:$CM$7,FALSE) )="A"), INDEX('KPI Analysis'!$AH$7:$CM$123,MATCH($A33,'KPI Analysis'!$AH$7:$AH$123,FALSE),MATCH(P$8,'KPI Analysis'!$AH$7:$CM$7,FALSE)),"") -> R | Q33: =INDEX('KPI Analysis'!$EW$7:$HC$123,MATCH($A33,'KPI Analysis'!$EW$7:$EW$123,FALSE),MATCH(P$8,'KPI Analysis'!$EW$7:$HC$7,FALSE)) -> 3 | R33: =IF( OR( INDEX('KPI Analysis'!$AH$7:$CM$123, MATCH($A33,'KPI Analysis'!$AH$7:$AH$123,FALSE), MATCH(R$8,'KPI Analysis'!$AH$7:$CM$7,FALSE) )="R", INDEX('KPI Analysis'!$AH$7:$CM$123, MATCH($A33,'KPI Analysis'!$AH$7:$AH$123,FALSE), MATCH(R$8,'KPI Analysis'!$AH$7:$CM$7,FALSE) )="G", INDEX('KPI Analysis'!$AH$7:$CM$123, MATCH($A33,'KPI Analysis'!$AH$7:$AH$123,FALSE), MATCH(R$8,'KPI Analysis'!$AH$7:$CM$7,FALSE) )="A"), INDEX('KPI Analysis'!$AH$7:$CM$123,MATCH($A33,'KPI Analysis'!$AH$7:$AH$123,FALSE),MATCH(R$8,'KPI Analysis'!$AH$7:$CM$7,FALSE)),"") | S33: =INDEX('KPI Analysis'!$EW$7:$HC$123,MATCH($A33,'KPI Analysis'!$EW$7:$EW$123,FALSE),MATCH(R$8,'KPI Analysis'!$EW$7:$HC$7,FALSE)) -> OD | T33: =IF( OR( INDEX('KPI Analysis'!$AH$7:$CM$123, MATCH($A33,'KPI Analysis'!$AH$7:$AH$123,FALSE), MATCH(T$8,'KPI Analysis'!$AH$7:$CM$7,FALSE) )="R", INDEX('KPI Analysis'!$AH$7:$CM$123, MATCH($A33,'KPI Analysis'!$AH$7:$AH$123,FALSE), MATCH(T$8,'KPI Analysis'!$AH$7:$CM$7,FALSE) )="G", INDEX('KPI Analysis'!$AH$7:$CM$123, MATCH($A33,'KPI Analysis'!$AH$7:$AH$123,FALSE), MATCH(T$8,'KPI Analysis'!$AH$7:$CM$7,FALSE) )="A"), INDEX('KPI Analysis'!$AH$7:$CM$123,MATCH($A33,'KPI Analysis'!$AH$7:$AH$123,FALSE),MATCH(T$8,'KPI Analysis'!$AH$7:$CM$7,FALSE)),"") | U33: =INDEX('KPI Analysis'!$EW$7:$HC$123,MATCH($A33,'KPI Analysis'!$EW$7:$EW$123,FALSE),MATCH(T$8,'KPI Analysis'!$EW$7:$HC$7,FALSE)) -> OD | V33: =IF( OR( INDEX('KPI Analysis'!$AH$7:$CM$123, MATCH($A33,'KPI Analysis'!$AH$7:$AH$123,FALSE), MATCH(V$8,'KPI Analysis'!$AH$7:$CM$7,FALSE) )="R", INDEX('KPI Analysis'!$AH$7:$CM$123, MATCH($A33,'KPI Analysis'!$AH$7:$AH$123,FALSE), MATCH(V$8,'KPI Analysis'!$AH$7:$CM$7,FALSE) )="G", INDEX('KPI Analysis'!$AH$7:$CM$123, MATCH($A33,'KPI Analysis'!$AH$7:$AH$123,FALSE), MATCH(V$8,'KPI Analysis'!$AH$7:$CM$7,FALSE) )="A"), INDEX('KPI Analysis'!$AH$7:$CM$123,MATCH($A33,'KPI Analysis'!$AH$7:$AH$123,FALSE),MATCH(V$8,'KPI Analysis'!$AH$7:$CM$7,FALSE)),"") | W33: =INDEX('KPI Analysis'!$EW$7:$HC$123,MATCH($A33,'KPI Analysis'!$EW$7:$EW$123,FALSE),MATCH(V$8,'KPI Analysis'!$EW$7:$HC$7,FALSE)) -> OD | X33: =IF( OR( INDEX('KPI Analysis'!$AH$7:$CM$123, MATCH($A33,'KPI Analysis'!$AH$7:$AH$123,FALSE), MATCH(X$8,'KPI Analysis'!$AH$7:$CM$7,FALSE) )="R", INDEX('KPI Analysis'!$AH$7:$CM$123, MATCH($A33,'KPI Analysis'!$AH$7:$AH$123,FALSE), MATCH(X$8,'KPI Analysis'!$AH$7:$CM$7,FALSE) )="G", INDEX('KPI Analysis'!$AH$7:$CM$123, MATCH($A33,'KPI Analysis'!$AH$7:$AH$123,FALSE), MATCH(X$8,'KPI Analysis'!$AH$7:$CM$7,FALSE) )="A"), INDEX('KPI Analysis'!$AH$7:$CM$123,MATCH($A33,'KPI Analysis'!$AH$7:$AH$123,FALSE),MATCH(X$8,'KPI Analysis'!$AH$7:$CM$7,FALSE)),"") | Y33: =IF(INDEX('KPI Analysis'!$CO$7:$EU$123,MATCH($A33,'KPI Analysis'!$CO$7:$CO$123,FALSE),MATCH(X$8,'KPI Analysis'!$CO$7:$EU$7,FALSE))="OD","OD",INDEX('KPI Analysis'!$EW$7:$HC$123,MATCH($A33,'KPI Analysis'!$EW$7:$EW$123,FALSE),MATCH(X$8,'KPI Analysis'!$EW$7:$HC$7,FALSE))) -> OD | Z33: (Target 0) Act Result Shown | AC33: EW HC | AE33: =INDEX('KPI Analysis'!$CO$7:$EU$123,MATCH($A33,'KPI Analysis'!$CO$7:$CO$123,FALSE),MATCH(AE$8,'KPI Analysis'!$CO$7:$EU$7,FALSE)) -> 3 | AF33: =INDEX('KPI Analysis'!$CO$7:$EU$123,MATCH($A33,'KPI Analysis'!$CO$7:$CO$123,FALSE),MATCH(AF$8,'KPI Analysis'!$CO$7:$EU$7,FALSE)) -> OD | AG33: =INDEX('KPI Analysis'!$CO$7:$EU$123,MATCH($A33,'KPI Analysis'!$CO$7:$CO$123,FALSE),MATCH(AG$8,'KPI Analysis'!$CO$7:$EU$7,FALSE)) -> OD | AH33: =INDEX('KPI Analysis'!$CO$7:$EU$123,MATCH($A33,'KPI Analysis'!$CO$7:$CO$123,FALSE),MATCH(AH$8,'KPI Analysis'!$CO$7:$EU$7,FALSE)) -> OD | AI33: =INDEX('KPI Analysis'!$CO$7:$EU$123,MATCH($A33,'KPI Analysis'!$CO$7:$CO$123,FALSE),MATCH(AI$8,'KPI Analysis'!$CO$7:$EU$7,FALSE)) -> OD
A34: =F34&"-"&C34 -> Design-KPI C1 | B34: =+'KPI Stats'!G33 -> Under | C34: =+'KPI Stats'!C33 -> KPI C1 | F34: =+'KPI Stats'!$B$29 -> Design | G34: =+'KPI Stats'!$B$29 -> Design | H34: W | I34: =+'KPI Stats'!$F$29 -> 42 | J34: =+'KPI Stats'!D33 -> Cost | K34: =+'KPI Stats'!E33 -> Opportunity Value Per design | L34: =+'KPI Stats'!F33 -> £'s | M34: =INDEX('KPI Analysis'!$CO$7:$EU$123,MATCH($A34,'KPI Analysis'!$CO$7:$CO$123,FALSE),MATCH(M$8,'KPI Analysis'!$CO$7:$EU$7,FALSE)) -> % of target | P34: =IF( OR( INDEX('KPI Analysis'!$AH$7:$CM$123, MATCH($A34,'KPI Analysis'!$AH$7:$AH$123,FALSE), MATCH(P$8,'KPI Analysis'!$AH$7:$CM$7,FALSE) )="R", INDEX('KPI Analysis'!$AH$7:$CM$123, MATCH($A34,'KPI Analysis'!$AH$7:$AH$123,FALSE), MATCH(P$8,'KPI Analysis'!$AH$7:$CM$7,FALSE) )="G", INDEX('KPI Analysis'!$AH$7:$CM$123, MATCH($A34,'KPI Analysis'!$AH$7:$AH$123,FALSE), MATCH(P$8,'KPI Analysis'!$AH$7:$CM$7,FALSE) )="A"), INDEX('KPI Analysis'!$AH$7:$CM$123,MATCH($A34,'KPI Analysis'!$AH$7:$AH$123,FALSE),MATCH(P$8,'KPI Analysis'!$AH$7:$CM$7,FALSE)),"") -> R | Q34: =INDEX('KPI Analysis'!$CO$7:$EU$123,MATCH($A34,'KPI Analysis'!$CO$7:$CO$123,FALSE),MATCH(P$8,'KPI Analysis'!$CO$7:$EU$7,FALSE)) -> 0.726714 | R34: =IF( OR( INDEX('KPI Analysis'!$AH$7:$CM$123, MATCH($A34,'KPI Analysis'!$AH$7:$AH$123,FALSE), MATCH(R$8,'KPI Analysis'!$AH$7:$CM$7,FALSE) )="R", INDEX('KPI Analysis'!$AH$7:$CM$123, MATCH($A34,'KPI Analysis'!$AH$7:$AH$123,FALSE), MATCH(R$8,'KPI Analysis'!$AH$7:$CM$7,FALSE) )="G", INDEX('KPI Analysis'!$AH$7:$CM$123, MATCH($A34,'KPI Analysis'!$AH$7:$AH$123,FALSE), MATCH(R$8,'KPI Analysis'!$AH$7:$CM$7,FALSE) )="A"), INDEX('KPI Analysis'!$AH$7:$CM$123,MATCH($A34,'KPI Analysis'!$AH$7:$AH$123,FALSE),MATCH(R$8,'KPI Analysis'!$AH$7:$CM$7,FALSE)),"") -> R | S34: =INDEX('KPI Analysis'!$CO$7:$EU$123,MATCH($A34,'KPI Analysis'!$CO$7:$CO$123,FALSE),MATCH(R$8,'KPI Analysis'!$CO$7:$EU$7,FALSE)) -> 0.90017102 | T34: =IF( OR( INDEX('KPI Analysis'!$AH$7:$CM$123, MATCH($A34,'KPI Analysis'!$AH$7:$AH$123,FALSE), MATCH(T$8,'KPI Analysis'!$AH$7:$CM$7,FALSE) )="R", INDEX('KPI Analysis'!$AH$7:$CM$123, MATCH($A34,'KPI Analysis'!$AH$7:$AH$123,FALSE), MATCH(T$8,'KPI Analysis'!$AH$7:$CM$7,FALSE) )="G", INDEX('KPI Analysis'!$AH$7:$CM$123, MATCH($A34,'KPI Analysis'!$AH$7:$AH$123,FALSE), MATCH(T$8,'KPI Analysis'!$AH$7:$CM$7,FALSE) )="A"), INDEX('KPI Analysis'!$AH$7:$CM$123,MATCH($A34,'KPI Analysis'!$AH$7:$AH$123,FALSE),MATCH(T$8,'KPI Analysis'!$AH$7:$CM$7,FALSE)),"") -> G | U34: =INDEX('KPI Analysis'!$CO$7:$EU$123,MATCH($A34,'KPI Analysis'!$CO$7:$CO$123,FALSE),MATCH(T$8,'KPI Analysis'!$CO$7:$EU$7,FALSE)) -> 1.0603918 | V34: =IF( OR( INDEX('KPI Analysis'!$AH$7:$CM$123, MATCH($A34,'KPI Analysis'!$AH$7:$AH$123,FALSE), MATCH(V$8,'KPI Analysis'!$AH$7:$CM$7,FALSE) )="R", INDEX('KPI Analysis'!$AH$7:$CM$123, MATCH($A34,'KPI Analysis'!$AH$7:$AH$123,FALSE), MATCH(V$8,'KPI Analysis'!$AH$7:$CM$7,FALSE) )="G", INDEX('KPI Analysis'!$AH$7:$CM$123, MATCH($A34,'KPI Analysis'!$AH$7:$AH$123,FALSE), MATCH(V$8,'KPI Analysis'!$AH$7:$CM$7,FALSE) )="A"), INDEX('KPI Analysis'!$AH$7:$CM$123,MATCH($A34,'KPI Analysis'!$AH$7:$AH$123,FALSE),MATCH(V$8,'KPI Analysis'!$AH$7:$CM$7,FALSE)),"") -> G | W34: =INDEX('KPI Analysis'!$CO$7:$EU$123,MATCH($A34,'KPI Analysis'!$CO$7:$CO$123,FALSE),MATCH(V$8,'KPI Analysis'!$CO$7:$EU$7,FALSE)) -> 1.2367953 | X34: =IF( OR( INDEX('KPI Analysis'!$AH$7:$CM$123, MATCH($A34,'KPI Analysis'!$AH$7:$AH$123,FALSE), MATCH(X$8,'KPI Analysis'!$AH$7:$CM$7,FALSE) )="R", INDEX('KPI Analysis'!$AH$7:$CM$123, MATCH($A34,'KPI Analysis'!$AH$7:$AH$123,FALSE), MATCH(X$8,'KPI Analysis'!$AH$7:$CM$7,FALSE) )="G", INDEX('KPI Analysis'!$AH$7:$CM$123, MATCH($A34,'KPI Analysis'!$AH$7:$AH$123,FALSE), MATCH(X$8,'KPI Analysis'!$AH$7:$CM$7,FALSE) )="A"), INDEX('KPI Analysis'!$AH$7:$CM$123,MATCH($A34,'KPI Analysis'!$AH$7:$AH$123,FALSE),MATCH(X$8,'KPI Analysis'!$AH$7:$CM$7,FALSE)),"") -> G | Y34: =INDEX('KPI Analysis'!$CO$7:$EU$123,MATCH($A34,'KPI Analysis'!$CO$7:$CO$123,FALSE),MATCH(X$8,'KPI Analysis'!$CO$7:$EU$7,FALSE)) -> 1.6772339 | AC34: Co EU | AE34: =INDEX('KPI Analysis'!$CO$7:$EU$123,MATCH($A34,'KPI Analysis'!$CO$7:$CO$123,FALSE),MATCH(AE$8,'KPI Analysis'!$CO$7:$EU$7,FALSE)) -> 0.726714 | AF34: =INDEX('KPI Analysis'!$CO$7:$EU$123,MATCH($A34,'KPI Analysis'!$CO$7:$CO$123,FALSE),MATCH(AF$8,'KPI Analysis'!$CO$7:$EU$7,FALSE)) -> 0.90017102 | AG34: =INDEX('KPI Analysis'!$CO$7:$EU$123,MATCH($A34,'KPI Analysis'!$CO$7:$CO$123,FALSE),MATCH(AG$8,'KPI Analysis'!$CO$7:$EU$7,FALSE)) -> 1.0603918 | AH34: =INDEX('KPI Analysis'!$CO$7:$EU$123,MATCH($A34,'KPI Analysis'!$CO$7:$CO$123,FALSE),MATCH(AH$8,'KPI Analysis'!$CO$7:$EU$7,FALSE)) -> 1.2367953 | AI34: =INDEX('KPI Analysis'!$CO$7:$EU$123,MATCH($A34,'KPI Analysis'!$CO$7:$CO$123,FALSE),MATCH(AI$8,'KPI Analysis'!$CO$7:$EU$7,FALSE)) -> 1.6772339
Z36: Sum Last 4 Weeks
K37: Value of New orders into SOP (UK) | L37: £'000 | Q37: 399 | S37: 736 | U37: 1050 | W37: 1074 | Y37: 1362.188 | Z37: =SUM(R37:Y37) -> 4222.188
K38: Value of Orders Released (UK) | L38: £'000 | Q38: 979 | S38: 577 | U38: 641 | W38: 1360 | Y38: 1018.62 | Z38: =SUM(R38:Y38) -> 3596.62
C42: Tab | F42: =+F$6 -> Department | G42: Manager | H42: =+H$6 -> Freq | I42: =+I$6 -> Wk | J42: =+J$6 -> Category | K42: =+K$6 -> KPI | L42: =+L$6 -> UOM | M42: =+M$6 -> Shown | P42: Week KPI Calc | AE42: =+AE$6 -> Week KPI Calc | AF42: =+AF$6 -> Week KPI Calc | AG42: =+AG$6 -> Week KPI Calc | AH42: =+AH$6 -> Week KPI Calc | AI42: =+AI$6 -> Week KPI Calc
A43: Lookup Drivers for | F43: =+F$7 -> Mth No | H43: =+H$7 -> For Monthly KPIs | P43: =_xlfn.XLOOKUP('KPI Linked Table for Report'!P44,'KPI Analysis'!$CU$7:$EU$7,'KPI Analysis'!$CU$8:$EU$8) -> 8 | R43: =_xlfn.XLOOKUP('KPI Linked Table for Report'!R44,'KPI Analysis'!$CU$7:$EU$7,'KPI Analysis'!$CU$8:$EU$8) -> 8 | T43: =_xlfn.XLOOKUP('KPI Linked Table for Report'!T44,'KPI Analysis'!$CU$7:$EU$7,'KPI Analysis'!$CU$8:$EU$8) -> 9 | V43: =_xlfn.XLOOKUP('KPI Linked Table for Report'!V44,'KPI Analysis'!$CU$7:$EU$7,'KPI Analysis'!$CU$8:$EU$8) -> 9 | X43: =_xlfn.XLOOKUP('KPI Linked Table for Report'!X44,'KPI Analysis'!$CU$7:$EU$7,'KPI Analysis'!$CU$8:$EU$8) -> 9 | AE43: =+AE$7 -> 8 | AF43: =+AF$7 -> 8 | AG43: =+AG$7 -> 9 | AH43: =+AH$7 -> 9 | AI43: =+AI$7 -> 9
F44: =+F$8 -> Wk No | H44: =+H$8 -> For Weekly KPI's | P44: =+P$8 -> 38 | R44: =+R$8 -> 39 | T44: =+T$8 -> 40 | V44: =+V$8 -> 41 | X44: =+X$8 -> 42 | AE44: =+AE$8 -> 38 | AF44: =+AF$8 -> 39 | AG44: =+AG$8 -> 40 | AH44: =+AH$8 -> 41 | AI44: =+AI$8 -> 42
F45: =+F$9 -> Date | H45: =+H$9 -> Week Ending (Fri) | P45: =_xlfn.XLOOKUP(P44,EHS!$M$6:$BM$6,EHS!$M$7:$BM$7) -> 45919 | R45: =_xlfn.XLOOKUP(R44,EHS!$M$6:$BM$6,EHS!$M$7:$BM$7) -> 45926 | T45: =_xlfn.XLOOKUP(T44,EHS!$M$6:$BM$6,EHS!$M$7:$BM$7) -> 45933 | V45: =_xlfn.XLOOKUP(V44,EHS!$M$6:$BM$6,EHS!$M$7:$BM$7) -> 45940 | X45: =_xlfn.XLOOKUP(X44,EHS!$M$6:$BM$6,EHS!$M$7:$BM$7) -> 45947 | AE45: =+AE$9 -> 45919 | AF45: =+AF$9 -> 45926 | AG45: =+AG$9 -> 45933 | AH45: =+AH$9 -> 45940 | AI45: =+AI$9 -> 45947
A47: =F47&"-"&C47 -> Product Design-KPI P1 | B47: =+'KPI Stats'!G36 -> Under | C47: =+'KPI Stats'!C36 -> KPI P1 | F47: =+'KPI Stats'!$B$35 -> Product Design | G47: =+'KPI Stats'!$C$35 -> Paul Dolan | H47: W | I47: =+'KPI Stats'!$F$35 -> 42 | J47: =+'KPI Stats'!D36 -> Productivity | K47: =+'KPI Stats'!E36 -> Drawings Completed - Order Lines | L47: =+'KPI Stats'!F36 -> Count | M47: Act Result | P47: =IF(INDEX('KPI Analysis'!$AH$7:$CM$123,MATCH($A47,'KPI Analysis'!$AH$7:$AH$123,FALSE),MATCH(P$8,'KPI Analysis'!$AH$7:$CM$7,FALSE))="OD","",INDEX('KPI Analysis'!$AH$7:$CM$123,MATCH($A47,'KPI Analysis'!$AH$7:$AH$123,FALSE),MATCH(P$8,'KPI Analysis'!$AH$7:$CM$7,FALSE))) -> R | Q47: =IF(INDEX('KPI Analysis'!$CO$7:$EU$123,MATCH($A47,'KPI Analysis'!$CO$7:$CO$123,FALSE),MATCH(P$8,'KPI Analysis'!$CO$7:$EU$7,FALSE))="OD","OD",INDEX('KPI Analysis'!$EW$7:$HC$123,MATCH($A47,'KPI Analysis'!$EW$7:$EW$123,FALSE),MATCH(P$8,'KPI Analysis'!$EW$7:$HC$7,FALSE))) -> 279 | R47: =IF(INDEX('KPI Analysis'!$AH$7:$CM$123,MATCH($A47,'KPI Analysis'!$AH$7:$AH$123,FALSE),MATCH(R$8,'KPI Analysis'!$AH$7:$CM$7,FALSE))="OD","",INDEX('KPI Analysis'!$AH$7:$CM$123,MATCH($A47,'KPI Analysis'!$AH$7:$AH$123,FALSE),MATCH(R$8,'KPI Analysis'!$AH$7:$CM$7,FALSE))) -> R | S47: =IF(INDEX('KPI Analysis'!$CO$7:$EU$123,MATCH($A47,'KPI Analysis'!$CO$7:$CO$123,FALSE),MATCH(R$8,'KPI Analysis'!$CO$7:$EU$7,FALSE))="OD","OD",INDEX('KPI Analysis'!$EW$7:$HC$123,MATCH($A47,'KPI Analysis'!$EW$7:$EW$123,FALSE),MATCH(R$8,'KPI Analysis'!$EW$7:$HC$7,FALSE))) -> 326 | T47: =IF(INDEX('KPI Analysis'!$AH$7:$CM$123,MATCH($A47,'KPI Analysis'!$AH$7:$AH$123,FALSE),MATCH(T$8,'KPI Analysis'!$AH$7:$CM$7,FALSE))="OD","",INDEX('KPI Analysis'!$AH$7:$CM$123,MATCH($A47,'KPI Analysis'!$AH$7:$AH$123,FALSE),MATCH(T$8,'KPI Analysis'!$AH$7:$CM$7,FALSE))) -> R | U47: =IF(INDEX('KPI Analysis'!$CO$7:$EU$123,MATCH($A47,'KPI Analysis'!$CO$7:$CO$123,FALSE),MATCH(T$8,'KPI Analysis'!$CO$7:$EU$7,FALSE))="OD","OD",INDEX('KPI Analysis'!$EW$7:$HC$123,MATCH($A47,'KPI Analysis'!$EW$7:$EW$123,FALSE),MATCH(T$8,'KPI Analysis'!$EW$7:$HC$7,FALSE))) -> 271 | V47: =IF(INDEX('KPI Analysis'!$AH$7:$CM$123,MATCH($A47,'KPI Analysis'!$AH$7:$AH$123,FALSE),MATCH(V$8,'KPI Analysis'!$AH$7:$CM$7,FALSE))="OD","",INDEX('KPI Analysis'!$AH$7:$CM$123,MATCH($A47,'KPI Analysis'!$AH$7:$AH$123,FALSE),MATCH(V$8,'KPI Analysis'!$AH$7:$CM$7,FALSE))) -> G | W47: =IF(INDEX('KPI Analysis'!$CO$7:$EU$123,MATCH($A47,'KPI Analysis'!$CO$7:$CO$123,FALSE),MATCH(V$8,'KPI Analysis'!$CO$7:$EU$7,FALSE))="OD","OD",INDEX('KPI Analysis'!$EW$7:$HC$123,MATCH($A47,'KPI Analysis'!$EW$7:$EW$123,FALSE),MATCH(V$8,'KPI Analysis'!$EW$7:$HC$7,FALSE))) -> 427 | X47: =IF(INDEX('KPI Analysis'!$AH$7:$CM$123,MATCH($A47,'KPI Analysis'!$AH$7:$AH$123,FALSE),MATCH(X$8,'KPI Analysis'!$AH$7:$CM$7,FALSE))="OD","",INDEX('KPI Analysis'!$AH$7:$CM$123,MATCH($A47,'KPI Analysis'!$AH$7:$AH$123,FALSE),MATCH(X$8,'KPI Analysis'!$AH$7:$CM$7,FALSE))) | Y47: =IF(INDEX('KPI Analysis'!$CO$7:$EU$123,MATCH($A47,'KPI Analysis'!$CO$7:$CO$123,FALSE),MATCH(X$8,'KPI Analysis'!$CO$7:$EU$7,FALSE))="OD","OD",INDEX('KPI Analysis'!$EW$7:$HC$123,MATCH($A47,'KPI Analysis'!$EW$7:$EW$123,FALSE),MATCH(X$8,'KPI Analysis'!$EW$7:$HC$7,FALSE))) -> OD | Z47: (Target 250) | AC47: EW HC | AE47: =INDEX('KPI Analysis'!$CO$7:$EU$123,MATCH($A47,'KPI Analysis'!$CO$7:$CO$123,FALSE),MATCH(AE$8,'KPI Analysis'!$CO$7:$EU$7,FALSE)) -> 0.79714286 | AF47: =INDEX('KPI Analysis'!$CO$7:$EU$123,MATCH($A47,'KPI Analysis'!$CO$7:$CO$123,FALSE),MATCH(AF$8,'KPI Analysis'!$CO$7:$EU$7,FALSE)) -> 0.93142857 | AG47: =INDEX('KPI Analysis'!$CO$7:$EU$123,MATCH($A47,'KPI Analysis'!$CO$7:$CO$123,FALSE),MATCH(AG$8,'KPI Analysis'!$CO$7:$EU$7,FALSE)) -> 0.77428571 | AH47: =INDEX('KPI Analysis'!$CO$7:$EU$123,MATCH($A47,'KPI Analysis'!$CO$7:$CO$123,FALSE),MATCH(AH$8,'KPI Analysis'!$CO$7:$EU$7,FALSE)) -> 1.22 | AI47: =INDEX('KPI Analysis'!$CO$7:$EU$123,MATCH($A47,'KPI Analysis'!$CO$7:$CO$123,FALSE),MATCH(AI$8,'KPI Analysis'!$CO$7:$EU$7,FALSE)) -> OD
A48: =F47&"-"&C48 -> Product Design-KPI D1 | B48: =+'KPI Stats'!G37 -> Under | C48: =+'KPI Stats'!C37 -> KPI D1 | H48: W | I48: =+'KPI Stats'!$F$35 -> 42 | J48: =+'KPI Stats'!D37 -> Delivery | K48: =+'KPI Stats'!E37 -> Delivery against Target as a percentage | L48: =+'KPI Stats'!F37 -> Percentage | M48: Act Result | P48: =IF(INDEX('KPI Analysis'!$AH$7:$CM$123,MATCH($A48,'KPI Analysis'!$AH$7:$AH$123,FALSE),MATCH(P$8,'KPI Analysis'!$AH$7:$CM$7,FALSE))="OD","",INDEX('KPI Analysis'!$AH$7:$CM$123,MATCH($A48,'KPI Analysis'!$AH$7:$AH$123,FALSE),MATCH(P$8,'KPI Analysis'!$AH$7:$CM$7,FALSE))) -> G | Q48: =IF(INDEX('KPI Analysis'!$CO$7:$EU$123,MATCH($A48,'KPI Analysis'!$CO$7:$CO$123,FALSE),MATCH(P$8,'KPI Analysis'!$CO$7:$EU$7,FALSE))="OD","OD",IFERROR(INDEX('KPI Analysis'!$EW$7:$HC$123,MATCH($A48,'KPI Analysis'!$EW$7:$EW$123,FALSE),MATCH(P$8,'KPI Analysis'!$EW$7:$HC$7,FALSE))/100,"OD")) -> 0.94 | R48: =IF(INDEX('KPI Analysis'!$AH$7:$CM$123,MATCH($A48,'KPI Analysis'!$AH$7:$AH$123,FALSE),MATCH(R$8,'KPI Analysis'!$AH$7:$CM$7,FALSE))="OD","",INDEX('KPI Analysis'!$AH$7:$CM$123,MATCH($A48,'KPI Analysis'!$AH$7:$AH$123,FALSE),MATCH(R$8,'KPI Analysis'!$AH$7:$CM$7,FALSE))) -> G | S48: =IF(INDEX('KPI Analysis'!$CO$7:$EU$123,MATCH($A48,'KPI Analysis'!$CO$7:$CO$123,FALSE),MATCH(R$8,'KPI Analysis'!$CO$7:$EU$7,FALSE))="OD","OD",IFERROR(INDEX('KPI Analysis'!$EW$7:$HC$123,MATCH($A48,'KPI Analysis'!$EW$7:$EW$123,FALSE),MATCH(R$8,'KPI Analysis'!$EW$7:$HC$7,FALSE))/100,"OD")) -> 1 | T48: =IF(INDEX('KPI Analysis'!$AH$7:$CM$123,MATCH($A48,'KPI Analysis'!$AH$7:$AH$123,FALSE),MATCH(T$8,'KPI Analysis'!$AH$7:$CM$7,FALSE))="OD","",INDEX('KPI Analysis'!$AH$7:$CM$123,MATCH($A48,'KPI Analysis'!$AH$7:$AH$123,FALSE),MATCH(T$8,'KPI Analysis'!$AH$7:$CM$7,FALSE))) -> G | U48: =IF(INDEX('KPI Analysis'!$CO$7:$EU$123,MATCH($A48,'KPI Analysis'!$CO$7:$CO$123,FALSE),MATCH(T$8,'KPI Analysis'!$CO$7:$EU$7,FALSE))="OD","OD",IFERROR(INDEX('KPI Analysis'!$EW$7:$HC$123,MATCH($A48,'KPI Analysis'!$EW$7:$EW$123,FALSE),MATCH(T$8,'KPI Analysis'!$EW$7:$HC$7,FALSE))/100,"OD")) -> 0.913 | V48: =IF(INDEX('KPI Analysis'!$AH$7:$CM$123,MATCH($A48,'KPI Analysis'!$AH$7:$AH$123,FALSE),MATCH(V$8,'KPI Analysis'!$AH$7:$CM$7,FALSE))="OD","",INDEX('KPI Analysis'!$AH$7:$CM$123,MATCH($A48,'KPI Analysis'!$AH$7:$AH$123,FALSE),MATCH(V$8,'KPI Analysis'!$AH$7:$CM$7,FALSE))) -> R | W48: =IF(INDEX('KPI Analysis'!$CO$7:$EU$123,MATCH($A48,'KPI Analysis'!$CO$7:$CO$123,FALSE),MATCH(V$8,'KPI Analysis'!$CO$7:$EU$7,FALSE))="OD","OD",IFERROR(INDEX('KPI Analysis'!$EW$7:$HC$123,MATCH($A48,'KPI Analysis'!$EW$7:$EW$123,FALSE),MATCH(V$8,'KPI Analysis'!$EW$7:$HC$7,FALSE))/100,"OD")) -> 0.852 | X48: =IF(INDEX('KPI Analysis'!$AH$7:$CM$123,MATCH($A48,'KPI Analysis'!$AH$7:$AH$123,FALSE),MATCH(X$8,'KPI Analysis'!$AH$7:$CM$7,FALSE))="OD","",INDEX('KPI Analysis'!$AH$7:$CM$123,MATCH($A48,'KPI Analysis'!$AH$7:$AH$123,FALSE),MATCH(X$8,'KPI Analysis'!$AH$7:$CM$7,FALSE))) | Y48: =IF(INDEX('KPI Analysis'!$CO$7:$EU$123,MATCH($A48,'KPI Analysis'!$CO$7:$CO$123,FALSE),MATCH(X$8,'KPI Analysis'!$CO$7:$EU$7,FALSE))="OD","OD",IFERROR(INDEX('KPI Analysis'!$EW$7:$HC$123,MATCH($A48,'KPI Analysis'!$EW$7:$EW$123,FALSE),MATCH(X$8,'KPI Analysis'!$EW$7:$HC$7,FALSE))/100,"OD")) -> OD | Z48: (Target 90%) | AC48: EW HC | AE48: =INDEX('KPI Analysis'!$CO$7:$EU$123,MATCH($A48,'KPI Analysis'!$CO$7:$CO$123,FALSE),MATCH(AE$8,'KPI Analysis'!$CO$7:$EU$7,FALSE)) -> 1.0444444 | AF48: =INDEX('KPI Analysis'!$CO$7:$EU$123,MATCH($A48,'KPI Analysis'!$CO$7:$CO$123,FALSE),MATCH(AF$8,'KPI Analysis'!$CO$7:$EU$7,FALSE)) -> 1.1111111 | AG48: =INDEX('KPI Analysis'!$CO$7:$EU$123,MATCH($A48,'KPI Analysis'!$CO$7:$CO$123,FALSE),MATCH(AG$8,'KPI Analysis'!$CO$7:$EU$7,FALSE)) -> 1.0144444 | AH48: =INDEX('KPI Analysis'!$CO$7:$EU$123,MATCH($A48,'KPI Analysis'!$CO$7:$CO$123,FALSE),MATCH(AH$8,'KPI Analysis'!$CO$7:$EU$7,FALSE)) -> 0.94666667 | AI48: =INDEX('KPI Analysis'!$CO$7:$EU$123,MATCH($A48,'KPI Analysis'!$CO$7:$CO$123,FALSE),MATCH(AI$8,'KPI Analysis'!$CO$7:$EU$7,FALSE)) -> OD
A49: =F47&"-"&C49 -> Product Design-KPI D2 | B49: =+'KPI Stats'!G38 -> Over | C49: =+'KPI Stats'!C38 -> KPI D2 | H49: W | I49: =+'KPI Stats'!$F$35 -> 42 | J49: =+'KPI Stats'!D38 -> Delivery | K49: =+'KPI Stats'!E38 -> Lead Time Days to Full Task Completion | L49: =+'KPI Stats'!F38 -> Days | M49: Act Result | P49: =IF(INDEX('KPI Analysis'!$AH$7:$CM$123,MATCH($A49,'KPI Analysis'!$AH$7:$AH$123,FALSE),MATCH(P$8,'KPI Analysis'!$AH$7:$CM$7,FALSE))="OD","",INDEX('KPI Analysis'!$AH$7:$CM$123,MATCH($A49,'KPI Analysis'!$AH$7:$AH$123,FALSE),MATCH(P$8,'KPI Analysis'!$AH$7:$CM$7,FALSE))) -> G | Q49: =IF(INDEX('KPI Analysis'!$CO$7:$EU$123,MATCH($A49,'KPI Analysis'!$CO$7:$CO$123,FALSE),MATCH(P$8,'KPI Analysis'!$CO$7:$EU$7,FALSE))="OD","OD",INDEX('KPI Analysis'!$EW$7:$HC$123,MATCH($A49,'KPI Analysis'!$EW$7:$EW$123,FALSE),MATCH(P$8,'KPI Analysis'!$EW$7:$HC$7,FALSE))) -> 6.5 | R49: =IF(INDEX('KPI Analysis'!$AH$7:$CM$123,MATCH($A49,'KPI Analysis'!$AH$7:$AH$123,FALSE),MATCH(R$8,'KPI Analysis'!$AH$7:$CM$7,FALSE))="OD","",INDEX('KPI Analysis'!$AH$7:$CM$123,MATCH($A49,'KPI Analysis'!$AH$7:$AH$123,FALSE),MATCH(R$8,'KPI Analysis'!$AH$7:$CM$7,FALSE))) -> G | S49: =IF(INDEX('KPI Analysis'!$CO$7:$EU$123,MATCH($A49,'KPI Analysis'!$CO$7:$CO$123,FALSE),MATCH(R$8,'KPI Analysis'!$CO$7:$EU$7,FALSE))="OD","OD",INDEX('KPI Analysis'!$EW$7:$HC$123,MATCH($A49,'KPI Analysis'!$EW$7:$EW$123,FALSE),MATCH(R$8,'KPI Analysis'!$EW$7:$HC$7,FALSE))) -> 2.6 | T49: =IF(INDEX('KPI Analysis'!$AH$7:$CM$123,MATCH($A49,'KPI Analysis'!$AH$7:$AH$123,FALSE),MATCH(T$8,'KPI Analysis'!$AH$7:$CM$7,FALSE))="OD","",INDEX('KPI Analysis'!$AH$7:$CM$123,MATCH($A49,'KPI Analysis'!$AH$7:$AH$123,FALSE),MATCH(T$8,'KPI Analysis'!$AH$7:$CM$7,FALSE))) -> G | U49: =IF(INDEX('KPI Analysis'!$CO$7:$EU$123,MATCH($A49,'KPI Analysis'!$CO$7:$CO$123,FALSE),MATCH(T$8,'KPI Analysis'!$CO$7:$EU$7,FALSE))="OD","OD",INDEX('KPI Analysis'!$EW$7:$HC$123,MATCH($A49,'KPI Analysis'!$EW$7:$EW$123,FALSE),MATCH(T$8,'KPI Analysis'!$EW$7:$HC$7,FALSE))) -> 7 | V49: =IF(INDEX('KPI Analysis'!$AH$7:$CM$123,MATCH($A49,'KPI Analysis'!$AH$7:$AH$123,FALSE),MATCH(V$8,'KPI Analysis'!$AH$7:$CM$7,FALSE))="OD","",INDEX('KPI Analysis'!$AH$7:$CM$123,MATCH($A49,'KPI Analysis'!$AH$7:$AH$123,FALSE),MATCH(V$8,'KPI Analysis'!$AH$7:$CM$7,FALSE))) -> R | W49: =IF(INDEX('KPI Analysis'!$CO$7:$EU$123,MATCH($A49,'KPI Analysis'!$CO$7:$CO$123,FALSE),MATCH(V$8,'KPI Analysis'!$CO$7:$EU$7,FALSE))="OD","OD",INDEX('KPI Analysis'!$EW$7:$HC$123,MATCH($A49,'KPI Analysis'!$EW$7:$EW$123,FALSE),MATCH(V$8,'KPI Analysis'!$EW$7:$HC$7,FALSE))) -> 9.8 | X49: =IF(INDEX('KPI Analysis'!$AH$7:$CM$123,MATCH($A49,'KPI Analysis'!$AH$7:$AH$123,FALSE),MATCH(X$8,'KPI Analysis'!$AH$7:$CM$7,FALSE))="OD","",INDEX('KPI Analysis'!$AH$7:$CM$123,MATCH($A49,'KPI Analysis'!$AH$7:$AH$123,FALSE),MATCH(X$8,'KPI Analysis'!$AH$7:$CM$7,FALSE))) | Y49: =IF(INDEX('KPI Analysis'!$CO$7:$EU$123,MATCH($A49,'KPI Analysis'!$CO$7:$CO$123,FALSE),MATCH(X$8,'KPI Analysis'!$CO$7:$EU$7,FALSE))="OD","OD",INDEX('KPI Analysis'!$EW$7:$HC$123,MATCH($A49,'KPI Analysis'!$EW$7:$EW$123,FALSE),MATCH(X$8,'KPI Analysis'!$EW$7:$HC$7,FALSE))) -> OD | Z49: (Target 7 days) | AC49: EW HC | AE49: =INDEX('KPI Analysis'!$CO$7:$EU$123,MATCH($A49,'KPI Analysis'!$CO$7:$CO$123,FALSE),MATCH(AE$8,'KPI Analysis'!$CO$7:$EU$7,FALSE)) -> 1.0769231 | AF49: =INDEX('KPI Analysis'!$CO$7:$EU$123,MATCH($A49,'KPI Analysis'!$CO$7:$CO$123,FALSE),MATCH(AF$8,'KPI Analysis'!$CO$7:$EU$7,FALSE)) -> 2.6923077 | AG49: =INDEX('KPI Analysis'!$CO$7:$EU$123,MATCH($A49,'KPI Analysis'!$CO$7:$CO$123,FALSE),MATCH(AG$8,'KPI Analysis'!$CO$7:$EU$7,FALSE)) -> 1 | AH49: =INDEX('KPI Analysis'!$CO$7:$EU$123,MATCH($A49,'KPI Analysis'!$CO$7:$CO$123,FALSE),MATCH(AH$8,'KPI Analysis'!$CO$7:$EU$7,FALSE)) -> 0.71428571 | AI49: =INDEX('KPI Analysis'!$CO$7:$EU$123,MATCH($A49,'KPI Analysis'!$CO$7:$CO$123,FALSE),MATCH(AI$8,'KPI Analysis'!$CO$7:$EU$7,FALSE)) -> OD
A50: =F47&"-"&C50 -> Product Design-KPI Q1 | B50: =+'KPI Stats'!G39 -> Over | C50: =+'KPI Stats'!C39 -> KPI Q1 | H50: W | I50: =+'KPI Stats'!$F$35 -> 42 | J50: =+'KPI Stats'!D39 -> Quality | K50: =+'KPI Stats'!E39 -> No of complaints | L50: =+'KPI Stats'!F39 -> Count | M50: Act Result | P50: =IF(INDEX('KPI Analysis'!$AH$7:$CM$123,MATCH($A50,'KPI Analysis'!$AH$7:$AH$123,FALSE),MATCH(P$8,'KPI Analysis'!$AH$7:$CM$7,FALSE))="OD","",INDEX('KPI Analysis'!$AH$7:$CM$123,MATCH($A50,'KPI Analysis'!$AH$7:$AH$123,FALSE),MATCH(P$8,'KPI Analysis'!$AH$7:$CM$7,FALSE))) -> G | Q50: =IF(INDEX('KPI Analysis'!$CO$7:$EU$123,MATCH($A50,'KPI Analysis'!$CO$7:$CO$123,FALSE),MATCH(P$8,'KPI Analysis'!$CO$7:$EU$7,FALSE))="OD","OD",INDEX('KPI Analysis'!$EW$7:$HC$123,MATCH($A50,'KPI Analysis'!$EW$7:$EW$123,FALSE),MATCH(P$8,'KPI Analysis'!$EW$7:$HC$7,FALSE))) -> 0 | R50: =IF(INDEX('KPI Analysis'!$AH$7:$CM$123,MATCH($A50,'KPI Analysis'!$AH$7:$AH$123,FALSE),MATCH(R$8,'KPI Analysis'!$AH$7:$CM$7,FALSE))="OD","",INDEX('KPI Analysis'!$AH$7:$CM$123,MATCH($A50,'KPI Analysis'!$AH$7:$AH$123,FALSE),MATCH(R$8,'KPI Analysis'!$AH$7:$CM$7,FALSE))) -> G | S50: =IF(INDEX('KPI Analysis'!$CO$7:$EU$123,MATCH($A50,'KPI Analysis'!$CO$7:$CO$123,FALSE),MATCH(R$8,'KPI Analysis'!$CO$7:$EU$7,FALSE))="OD","OD",INDEX('KPI Analysis'!$EW$7:$HC$123,MATCH($A50,'KPI Analysis'!$EW$7:$EW$123,FALSE),MATCH(R$8,'KPI Analysis'!$EW$7:$HC$7,FALSE))) -> 0 | T50: =IF(INDEX('KPI Analysis'!$AH$7:$CM$123,MATCH($A50,'KPI Analysis'!$AH$7:$AH$123,FALSE),MATCH(T$8,'KPI Analysis'!$AH$7:$CM$7,FALSE))="OD","",INDEX('KPI Analysis'!$AH$7:$CM$123,MATCH($A50,'KPI Analysis'!$AH$7:$AH$123,FALSE),MATCH(T$8,'KPI Analysis'!$AH$7:$CM$7,FALSE))) -> R | U50: =IF(INDEX('KPI Analysis'!$CO$7:$EU$123,MATCH($A50,'KPI Analysis'!$CO$7:$CO$123,FALSE),MATCH(T$8,'KPI Analysis'!$CO$7:$EU$7,FALSE))="OD","OD",INDEX('KPI Analysis'!$EW$7:$HC$123,MATCH($A50,'KPI Analysis'!$EW$7:$EW$123,FALSE),MATCH(T$8,'KPI Analysis'!$EW$7:$HC$7,FALSE))) -> 2 | V50: =IF(INDEX('KPI Analysis'!$AH$7:$CM$123,MATCH($A50,'KPI Analysis'!$AH$7:$AH$123,FALSE),MATCH(V$8,'KPI Analysis'!$AH$7:$CM$7,FALSE))="OD","",INDEX('KPI Analysis'!$AH$7:$CM$123,MATCH($A50,'KPI Analysis'!$AH$7:$AH$123,FALSE),MATCH(V$8,'KPI Analysis'!$AH$7:$CM$7,FALSE))) -> G | W50: =IF(INDEX('KPI Analysis'!$CO$7:$EU$123,MATCH($A50,'KPI Analysis'!$CO$7:$CO$123,FALSE),MATCH(V$8,'KPI Analysis'!$CO$7:$EU$7,FALSE))="OD","OD",INDEX('KPI Analysis'!$EW$7:$HC$123,MATCH($A50,'KPI Analysis'!$EW$7:$EW$123,FALSE),MATCH(V$8,'KPI Analysis'!$EW$7:$HC$7,FALSE))) -> 0 | X50: =IF(INDEX('KPI Analysis'!$AH$7:$CM$123,MATCH($A50,'KPI Analysis'!$AH$7:$AH$123,FALSE),MATCH(X$8,'KPI Analysis'!$AH$7:$CM$7,FALSE))="OD","",INDEX('KPI Analysis'!$AH$7:$CM$123,MATCH($A50,'KPI Analysis'!$AH$7:$AH$123,FALSE),MATCH(X$8,'KPI Analysis'!$AH$7:$CM$7,FALSE))) | Y50: =IF(INDEX('KPI Analysis'!$CO$7:$EU$123,MATCH($A50,'KPI Analysis'!$CO$7:$CO$123,FALSE),MATCH(X$8,'KPI Analysis'!$CO$7:$EU$7,FALSE))="OD","OD",INDEX('KPI Analysis'!$EW$7:$HC$123,MATCH($A50,'KPI Analysis'!$EW$7:$EW$123,FALSE),MATCH(X$8,'KPI Analysis'!$EW$7:$HC$7,FALSE))) -> OD | Z50: (Target 1) | AC50: EW HC | AE50: =INDEX('KPI Analysis'!$CO$7:$EU$123,MATCH($A50,'KPI Analysis'!$CO$7:$CO$123,FALSE),MATCH(AE$8,'KPI Analysis'!$CO$7:$EU$7,FALSE)) -> 100% | AF50: =INDEX('KPI Analysis'!$CO$7:$EU$123,MATCH($A50,'KPI Analysis'!$CO$7:$CO$123,FALSE),MATCH(AF$8,'KPI Analysis'!$CO$7:$EU$7,FALSE)) -> 100% | AG50: =INDEX('KPI Analysis'!$CO$7:$EU$123,MATCH($A50,'KPI Analysis'!$CO$7:$CO$123,FALSE),MATCH(AG$8,'KPI Analysis'!$CO$7:$EU$7,FALSE)) -> 0.5 | AH50: =INDEX('KPI Analysis'!$CO$7:$EU$123,MATCH($A50,'KPI Analysis'!$CO$7:$CO$123,FALSE),MATCH(AH$8,'KPI Analysis'!$CO$7:$EU$7,FALSE)) -> 100% | AI50: =INDEX('KPI Analysis'!$CO$7:$EU$123,MATCH($A50,'KPI Analysis'!$CO$7:$CO$123,FALSE),MATCH(AI$8,'KPI Analysis'!$CO$7:$EU$7,FALSE)) -> OD
A51: =F47&"-"&C51 -> Product Design-KPI C1 | B51: =+'KPI Stats'!G40 -> Undefined | C51: =+'KPI Stats'!C40 -> KPI C1 | H51: W | I51: =+'KPI Stats'!$F$35 -> 42 | J51: =+'KPI Stats'!D40 -> Cost | K51: =+'KPI Stats'!E40 -> Needs defining | L51: =+'KPI Stats'!F40 -> Undefined | M51: =INDEX('KPI Analysis'!$CO$7:$EU$123,MATCH($A51,'KPI Analysis'!$CO$7:$CO$123,FALSE),MATCH(M$8,'KPI Analysis'!$CO$7:$EU$7,FALSE)) -> Undefined | P51: =IF( OR( INDEX('KPI Analysis'!$AH$7:$CM$123, MATCH($A51,'KPI Analysis'!$AH$7:$AH$123,FALSE), MATCH(P$8,'KPI Analysis'!$AH$7:$CM$7,FALSE) )="R", INDEX('KPI Analysis'!$AH$7:$CM$123, MATCH($A51,'KPI Analysis'!$AH$7:$AH$123,FALSE), MATCH(P$8,'KPI Analysis'!$AH$7:$CM$7,FALSE) )="G", INDEX('KPI Analysis'!$AH$7:$CM$123, MATCH($A51,'KPI Analysis'!$AH$7:$AH$123,FALSE), MATCH(P$8,'KPI Analysis'!$AH$7:$CM$7,FALSE) )="A"), INDEX('KPI Analysis'!$AH$7:$CM$123,MATCH($A51,'KPI Analysis'!$AH$7:$AH$123,FALSE),MATCH(P$8,'KPI Analysis'!$AH$7:$CM$7,FALSE)),"") | Q51: =INDEX('KPI Analysis'!$EW$7:$HC$123,MATCH($A51,'KPI Analysis'!$EW$7:$EW$123,FALSE),MATCH(P$8,'KPI Analysis'!$EW$7:$HC$7,FALSE)) -> undefined | R51: =IF( OR( INDEX('KPI Analysis'!$AH$7:$CM$123, MATCH($A51,'KPI Analysis'!$AH$7:$AH$123,FALSE), MATCH(R$8,'KPI Analysis'!$AH$7:$CM$7,FALSE) )="R", INDEX('KPI Analysis'!$AH$7:$CM$123, MATCH($A51,'KPI Analysis'!$AH$7:$AH$123,FALSE), MATCH(R$8,'KPI Analysis'!$AH$7:$CM$7,FALSE) )="G", INDEX('KPI Analysis'!$AH$7:$CM$123, MATCH($A51,'KPI Analysis'!$AH$7:$AH$123,FALSE), MATCH(R$8,'KPI Analysis'!$AH$7:$CM$7,FALSE) )="A"), INDEX('KPI Analysis'!$AH$7:$CM$123,MATCH($A51,'KPI Analysis'!$AH$7:$AH$123,FALSE),MATCH(R$8,'KPI Analysis'!$AH$7:$CM$7,FALSE)),"") | S51: =INDEX('KPI Analysis'!$EW$7:$HC$123,MATCH($A51,'KPI Analysis'!$EW$7:$EW$123,FALSE),MATCH(R$8,'KPI Analysis'!$EW$7:$HC$7,FALSE)) -> undefined | T51: =IF( OR( INDEX('KPI Analysis'!$AH$7:$CM$123, MATCH($A51,'KPI Analysis'!$AH$7:$AH$123,FALSE), MATCH(T$8,'KPI Analysis'!$AH$7:$CM$7,FALSE) )="R", INDEX('KPI Analysis'!$AH$7:$CM$123, MATCH($A51,'KPI Analysis'!$AH$7:$AH$123,FALSE), MATCH(T$8,'KPI Analysis'!$AH$7:$CM$7,FALSE) )="G", INDEX('KPI Analysis'!$AH$7:$CM$123, MATCH($A51,'KPI Analysis'!$AH$7:$AH$123,FALSE), MATCH(T$8,'KPI Analysis'!$AH$7:$CM$7,FALSE) )="A"), INDEX('KPI Analysis'!$AH$7:$CM$123,MATCH($A51,'KPI Analysis'!$AH$7:$AH$123,FALSE),MATCH(T$8,'KPI Analysis'!$AH$7:$CM$7,FALSE)),"") | U51: =INDEX('KPI Analysis'!$EW$7:$HC$123,MATCH($A51,'KPI Analysis'!$EW$7:$EW$123,FALSE),MATCH(T$8,'KPI Analysis'!$EW$7:$HC$7,FALSE)) -> undefined | V51: =IF( OR( INDEX('KPI Analysis'!$AH$7:$CM$123, MATCH($A51,'KPI Analysis'!$AH$7:$AH$123,FALSE), MATCH(V$8,'KPI Analysis'!$AH$7:$CM$7,FALSE) )="R", INDEX('KPI Analysis'!$AH$7:$CM$123, MATCH($A51,'KPI Analysis'!$AH$7:$AH$123,FALSE), MATCH(V$8,'KPI Analysis'!$AH$7:$CM$7,FALSE) )="G", INDEX('KPI Analysis'!$AH$7:$CM$123, MATCH($A51,'KPI Analysis'!$AH$7:$AH$123,FALSE), MATCH(V$8,'KPI Analysis'!$AH$7:$CM$7,FALSE) )="A"), INDEX('KPI Analysis'!$AH$7:$CM$123,MATCH($A51,'KPI Analysis'!$AH$7:$AH$123,FALSE),MATCH(V$8,'KPI Analysis'!$AH$7:$CM$7,FALSE)),"") | W51: =INDEX('KPI Analysis'!$EW$7:$HC$123,MATCH($A51,'KPI Analysis'!$EW$7:$EW$123,FALSE),MATCH(V$8,'KPI Analysis'!$EW$7:$HC$7,FALSE)) -> undefined | X51: =IF( OR( INDEX('KPI Analysis'!$AH$7:$CM$123, MATCH($A51,'KPI Analysis'!$AH$7:$AH$123,FALSE), MATCH(X$8,'KPI Analysis'!$AH$7:$CM$7,FALSE) )="R", INDEX('KPI Analysis'!$AH$7:$CM$123, MATCH($A51,'KPI Analysis'!$AH$7:$AH$123,FALSE), MATCH(X$8,'KPI Analysis'!$AH$7:$CM$7,FALSE) )="G", INDEX('KPI Analysis'!$AH$7:$CM$123, MATCH($A51,'KPI Analysis'!$AH$7:$AH$123,FALSE), MATCH(X$8,'KPI Analysis'!$AH$7:$CM$7,FALSE) )="A"), INDEX('KPI Analysis'!$AH$7:$CM$123,MATCH($A51,'KPI Analysis'!$AH$7:$AH$123,FALSE),MATCH(X$8,'KPI Analysis'!$AH$7:$CM$7,FALSE)),"") | Y51: =INDEX('KPI Analysis'!$EW$7:$HC$123,MATCH($A51,'KPI Analysis'!$EW$7:$EW$123,FALSE),MATCH(X$8,'KPI Analysis'!$EW$7:$HC$7,FALSE)) -> undefined | Z51: No KPI Defined | AC51: EW HC | AE51: =INDEX('KPI Analysis'!$CO$7:$EU$123,MATCH($A51,'KPI Analysis'!$CO$7:$CO$123,FALSE),MATCH(AE$8,'KPI Analysis'!$CO$7:$EU$7,FALSE)) -> Undefined | AF51: =INDEX('KPI Analysis'!$CO$7:$EU$123,MATCH($A51,'KPI Analysis'!$CO$7:$CO$123,FALSE),MATCH(AF$8,'KPI Analysis'!$CO$7:$EU$7,FALSE)) -> Undefined | AG51: =INDEX('KPI Analysis'!$CO$7:$EU$123,MATCH($A51,'KPI Analysis'!$CO$7:$CO$123,FALSE),MATCH(AG$8,'KPI Analysis'!$CO$7:$EU$7,FALSE)) -> Undefined | AH51: =INDEX('KPI Analysis'!$CO$7:$EU$123,MATCH($A51,'KPI Analysis'!$CO$7:$CO$123,FALSE),MATCH(AH$8,'KPI Analysis'!$CO$7:$EU$7,FALSE)) -> Undefined | AI51: =INDEX('KPI Analysis'!$CO$7:$EU$123,MATCH($A51,'KPI Analysis'!$CO$7:$CO$123,FALSE),MATCH(AI$8,'KPI Analysis'!$CO$7:$EU$7,FALSE)) -> Undefined
A52: =F52&"-"&C52 -> Product Eng - MB-KPI P1 | B52: =+'KPI Stats'!G43 -> Under | C52: =+'KPI Stats'!C43 -> KPI P1 | F52: =+'KPI Stats'!$B$42 -> Product Eng - MB | G52: =+'KPI Stats'!$C$42 -> Paul Dolan | H52: W | I52: =+'KPI Stats'!$F$42 -> 42 | J52: =+'KPI Stats'!D43 -> Productivity | K52: =+'KPI Stats'!E43 -> Output lines as a percentage of capacity | L52: =+'KPI Stats'!F43 -> Percentage | M52: Act Result | P52: =IF(INDEX('KPI Analysis'!$AH$7:$CM$123,MATCH($A52,'KPI Analysis'!$AH$7:$AH$123,FALSE),MATCH(P$8,'KPI Analysis'!$AH$7:$CM$7,FALSE))="OD","",INDEX('KPI Analysis'!$AH$7:$CM$123,MATCH($A52,'KPI Analysis'!$AH$7:$AH$123,FALSE),MATCH(P$8,'KPI Analysis'!$AH$7:$CM$7,FALSE))) -> G | Q52: =IF(INDEX('KPI Analysis'!$CO$7:$EU$123,MATCH($A52,'KPI Analysis'!$CO$7:$CO$123,FALSE),MATCH(P$8,'KPI Analysis'!$CO$7:$EU$7,FALSE))="OD","OD",IFERROR(INDEX('KPI Analysis'!$EW$7:$HC$123,MATCH($A52,'KPI Analysis'!$EW$7:$EW$123,FALSE),MATCH(P$8,'KPI Analysis'!$EW$7:$HC$7,FALSE))/100,"OD")) -> 1.05 | R52: =IF(INDEX('KPI Analysis'!$AH$7:$CM$123,MATCH($A52,'KPI Analysis'!$AH$7:$AH$123,FALSE),MATCH(R$8,'KPI Analysis'!$AH$7:$CM$7,FALSE))="OD","",INDEX('KPI Analysis'!$AH$7:$CM$123,MATCH($A52,'KPI Analysis'!$AH$7:$AH$123,FALSE),MATCH(R$8,'KPI Analysis'!$AH$7:$CM$7,FALSE))) -> A | S52: =IF(INDEX('KPI Analysis'!$CO$7:$EU$123,MATCH($A52,'KPI Analysis'!$CO$7:$CO$123,FALSE),MATCH(R$8,'KPI Analysis'!$CO$7:$EU$7,FALSE))="OD","OD",IFERROR(INDEX('KPI Analysis'!$EW$7:$HC$123,MATCH($A52,'KPI Analysis'!$EW$7:$EW$123,FALSE),MATCH(R$8,'KPI Analysis'!$EW$7:$HC$7,FALSE))/100,"OD")) -> 0.77 | T52: =IF(INDEX('KPI Analysis'!$AH$7:$CM$123,MATCH($A52,'KPI Analysis'!$AH$7:$AH$123,FALSE),MATCH(T$8,'KPI Analysis'!$AH$7:$CM$7,FALSE))="OD","",INDEX('KPI Analysis'!$AH$7:$CM$123,MATCH($A52,'KPI Analysis'!$AH$7:$AH$123,FALSE),MATCH(T$8,'KPI Analysis'!$AH$7:$CM$7,FALSE))) -> G | U52: =IF(INDEX('KPI Analysis'!$CO$7:$EU$123,MATCH($A52,'KPI Analysis'!$CO$7:$CO$123,FALSE),MATCH(T$8,'KPI Analysis'!$CO$7:$EU$7,FALSE))="OD","OD",IFERROR(INDEX('KPI Analysis'!$EW$7:$HC$123,MATCH($A52,'KPI Analysis'!$EW$7:$EW$123,FALSE),MATCH(T$8,'KPI Analysis'!$EW$7:$HC$7,FALSE))/100,"OD")) -> 2.31 | V52: =IF(INDEX('KPI Analysis'!$AH$7:$CM$123,MATCH($A52,'KPI Analysis'!$AH$7:$AH$123,FALSE),MATCH(V$8,'KPI Analysis'!$AH$7:$CM$7,FALSE))="OD","",INDEX('KPI Analysis'!$AH$7:$CM$123,MATCH($A52,'KPI Analysis'!$AH$7:$AH$123,FALSE),MATCH(V$8,'KPI Analysis'!$AH$7:$CM$7,FALSE))) -> G | W52: =IF(INDEX('KPI Analysis'!$CO$7:$EU$123,MATCH($A52,'KPI Analysis'!$CO$7:$CO$123,FALSE),MATCH(V$8,'KPI Analysis'!$CO$7:$EU$7,FALSE))="OD","OD",IFERROR(INDEX('KPI Analysis'!$EW$7:$HC$123,MATCH($A52,'KPI Analysis'!$EW$7:$EW$123,FALSE),MATCH(V$8,'KPI Analysis'!$EW$7:$HC$7,FALSE))/100,"OD")) -> 3.19 | X52: =IF(INDEX('KPI Analysis'!$AH$7:$CM$123,MATCH($A52,'KPI Analysis'!$AH$7:$AH$123,FALSE),MATCH(X$8,'KPI Analysis'!$AH$7:$CM$7,FALSE))="OD","",INDEX('KPI Analysis'!$AH$7:$CM$123,MATCH($A52,'KPI Analysis'!$AH$7:$AH$123,FALSE),MATCH(X$8,'KPI Analysis'!$AH$7:$CM$7,FALSE))) | Y52: =IF(INDEX('KPI Analysis'!$CO$7:$EU$123,MATCH($A52,'KPI Analysis'!$CO$7:$CO$123,FALSE),MATCH(X$8,'KPI Analysis'!$CO$7:$EU$7,FALSE))="OD","OD",IFERROR(INDEX('KPI Analysis'!$EW$7:$HC$123,MATCH($A52,'KPI Analysis'!$EW$7:$EW$123,FALSE),MATCH(X$8,'KPI Analysis'!$EW$7:$HC$7,FALSE))/100,"OD")) -> OD | Z52: (Target 80%) | AC52: EW HC | AE52: =INDEX('KPI Analysis'!$CO$7:$EU$123,MATCH($A52,'KPI Analysis'!$CO$7:$CO$123,FALSE),MATCH(AE$8,'KPI Analysis'!$CO$7:$EU$7,FALSE)) -> 1.3125 | AF52: =INDEX('KPI Analysis'!$CO$7:$EU$123,MATCH($A52,'KPI Analysis'!$CO$7:$CO$123,FALSE),MATCH(AF$8,'KPI Analysis'!$CO$7:$EU$7,FALSE)) -> 0.9625 | AG52: =INDEX('KPI Analysis'!$CO$7:$EU$123,MATCH($A52,'KPI Analysis'!$CO$7:$CO$123,FALSE),MATCH(AG$8,'KPI Analysis'!$CO$7:$EU$7,FALSE)) -> 2.8875 | AH52: =INDEX('KPI Analysis'!$CO$7:$EU$123,MATCH($A52,'KPI Analysis'!$CO$7:$CO$123,FALSE),MATCH(AH$8,'KPI Analysis'!$CO$7:$EU$7,FALSE)) -> 3.9875 | AI52: =INDEX('KPI Analysis'!$CO$7:$EU$123,MATCH($A52,'KPI Analysis'!$CO$7:$CO$123,FALSE),MATCH(AI$8,'KPI Analysis'!$CO$7:$EU$7,FALSE)) -> OD
A53: =F53&"-"&C53 -> Product Eng - MB-KPI D1 | B53: =+'KPI Stats'!G44 -> Under | C53: =+'KPI Stats'!C44 -> KPI D1 | F53: =+'KPI Stats'!$B$42 -> Product Eng - MB | G53: =+'KPI Stats'!$B$42 -> Product Eng - MB | H53: W | I53: =+'KPI Stats'!$F$42 -> 42 | J53: =+'KPI Stats'!D44 -> Delivery | K53: =+'KPI Stats'!E44 -> BOM Lead time | L53: =+'KPI Stats'!F44 -> Days | M53: Act Result | P53: =IF(INDEX('KPI Analysis'!$AH$7:$CM$123,MATCH($A53,'KPI Analysis'!$AH$7:$AH$123,FALSE),MATCH(P$8,'KPI Analysis'!$AH$7:$CM$7,FALSE))="OD","",INDEX('KPI Analysis'!$AH$7:$CM$123,MATCH($A53,'KPI Analysis'!$AH$7:$AH$123,FALSE),MATCH(P$8,'KPI Analysis'!$AH$7:$CM$7,FALSE))) -> G | Q53: =IF(INDEX('KPI Analysis'!$CO$7:$EU$123,MATCH($A53,'KPI Analysis'!$CO$7:$CO$123,FALSE),MATCH(P$8,'KPI Analysis'!$CO$7:$EU$7,FALSE))="OD","OD",INDEX('KPI Analysis'!$EW$7:$HC$123,MATCH($A53,'KPI Analysis'!$EW$7:$EW$123,FALSE),MATCH(P$8,'KPI Analysis'!$EW$7:$HC$7,FALSE))) -> 3 | R53: =IF(INDEX('KPI Analysis'!$AH$7:$CM$123,MATCH($A53,'KPI Analysis'!$AH$7:$AH$123,FALSE),MATCH(R$8,'KPI Analysis'!$AH$7:$CM$7,FALSE))="OD","",INDEX('KPI Analysis'!$AH$7:$CM$123,MATCH($A53,'KPI Analysis'!$AH$7:$AH$123,FALSE),MATCH(R$8,'KPI Analysis'!$AH$7:$CM$7,FALSE))) -> G | S53: =IF(INDEX('KPI Analysis'!$CO$7:$EU$123,MATCH($A53,'KPI Analysis'!$CO$7:$CO$123,FALSE),MATCH(R$8,'KPI Analysis'!$CO$7:$EU$7,FALSE))="OD","OD",INDEX('KPI Analysis'!$EW$7:$HC$123,MATCH($A53,'KPI Analysis'!$EW$7:$EW$123,FALSE),MATCH(R$8,'KPI Analysis'!$EW$7:$HC$7,FALSE))) -> 3 | T53: =IF(INDEX('KPI Analysis'!$AH$7:$CM$123,MATCH($A53,'KPI Analysis'!$AH$7:$AH$123,FALSE),MATCH(T$8,'KPI Analysis'!$AH$7:$CM$7,FALSE))="OD","",INDEX('KPI Analysis'!$AH$7:$CM$123,MATCH($A53,'KPI Analysis'!$AH$7:$AH$123,FALSE),MATCH(T$8,'KPI Analysis'!$AH$7:$CM$7,FALSE))) -> G | U53: =IF(INDEX('KPI Analysis'!$CO$7:$EU$123,MATCH($A53,'KPI Analysis'!$CO$7:$CO$123,FALSE),MATCH(T$8,'KPI Analysis'!$CO$7:$EU$7,FALSE))="OD","OD",INDEX('KPI Analysis'!$EW$7:$HC$123,MATCH($A53,'KPI Analysis'!$EW$7:$EW$123,FALSE),MATCH(T$8,'KPI Analysis'!$EW$7:$HC$7,FALSE))) -> 2 | V53: =IF(INDEX('KPI Analysis'!$AH$7:$CM$123,MATCH($A53,'KPI Analysis'!$AH$7:$AH$123,FALSE),MATCH(V$8,'KPI Analysis'!$AH$7:$CM$7,FALSE))="OD","",INDEX('KPI Analysis'!$AH$7:$CM$123,MATCH($A53,'KPI Analysis'!$AH$7:$AH$123,FALSE),MATCH(V$8,'KPI Analysis'!$AH$7:$CM$7,FALSE))) -> G | W53: =IF(INDEX('KPI Analysis'!$CO$7:$EU$123,MATCH($A53,'KPI Analysis'!$CO$7:$CO$123,FALSE),MATCH(V$8,'KPI Analysis'!$CO$7:$EU$7,FALSE))="OD","OD",INDEX('KPI Analysis'!$EW$7:$HC$123,MATCH($A53,'KPI Analysis'!$EW$7:$EW$123,FALSE),MATCH(V$8,'KPI Analysis'!$EW$7:$HC$7,FALSE))) -> 3 | X53: =IF(INDEX('KPI Analysis'!$AH$7:$CM$123,MATCH($A53,'KPI Analysis'!$AH$7:$AH$123,FALSE),MATCH(X$8,'KPI Analysis'!$AH$7:$CM$7,FALSE))="OD","",INDEX('KPI Analysis'!$AH$7:$CM$123,MATCH($A53,'KPI Analysis'!$AH$7:$AH$123,FALSE),MATCH(X$8,'KPI Analysis'!$AH$7:$CM$7,FALSE))) | Y53: =IF(INDEX('KPI Analysis'!$CO$7:$EU$123,MATCH($A53,'KPI Analysis'!$CO$7:$CO$123,FALSE),MATCH(X$8,'KPI Analysis'!$CO$7:$EU$7,FALSE))="OD","OD",INDEX('KPI Analysis'!$EW$7:$HC$123,MATCH($A53,'KPI Analysis'!$EW$7:$EW$123,FALSE),MATCH(X$8,'KPI Analysis'!$EW$7:$HC$7,FALSE))) -> OD | Z53: (Target 5) | AC53: EW HC | AE53: =INDEX('KPI Analysis'!$CO$7:$EU$123,MATCH($A53,'KPI Analysis'!$CO$7:$CO$123,FALSE),MATCH(AE$8,'KPI Analysis'!$CO$7:$EU$7,FALSE)) -> 1.6666667 | AF53: =INDEX('KPI Analysis'!$CO$7:$EU$123,MATCH($A53,'KPI Analysis'!$CO$7:$CO$123,FALSE),MATCH(AF$8,'KPI Analysis'!$CO$7:$EU$7,FALSE)) -> 1.6666667 | AG53: =INDEX('KPI Analysis'!$CO$7:$EU$123,MATCH($A53,'KPI Analysis'!$CO$7:$CO$123,FALSE),MATCH(AG$8,'KPI Analysis'!$CO$7:$EU$7,FALSE)) -> 2.5 | AH53: =INDEX('KPI Analysis'!$CO$7:$EU$123,MATCH($A53,'KPI Analysis'!$CO$7:$CO$123,FALSE),MATCH(AH$8,'KPI Analysis'!$CO$7:$EU$7,FALSE)) -> 1.6666667 | AI53: =INDEX('KPI Analysis'!$CO$7:$EU$123,MATCH($A53,'KPI Analysis'!$CO$7:$CO$123,FALSE),MATCH(AI$8,'KPI Analysis'!$CO$7:$EU$7,FALSE)) -> OD
A54: =F54&"-"&C54 -> Product Eng - MB-KPI D2 | B54: =+'KPI Stats'!G45 -> Over | C54: =+'KPI Stats'!C45 -> KPI D2 | F54: =+'KPI Stats'!$B$42 -> Product Eng - MB | G54: =+'KPI Stats'!$B$42 -> Product Eng - MB | H54: W | I54: =+'KPI Stats'!$F$42 -> 42 | J54: =+'KPI Stats'!D45 -> Delivery | K54: =+'KPI Stats'!E45 -> Lead Time for full order conversion | L54: =+'KPI Stats'!F45 -> Days | M54: Act Result | P54: =IF(INDEX('KPI Analysis'!$AH$7:$CM$123,MATCH($A54,'KPI Analysis'!$AH$7:$AH$123,FALSE),MATCH(P$8,'KPI Analysis'!$AH$7:$CM$7,FALSE))="OD","",INDEX('KPI Analysis'!$AH$7:$CM$123,MATCH($A54,'KPI Analysis'!$AH$7:$AH$123,FALSE),MATCH(P$8,'KPI Analysis'!$AH$7:$CM$7,FALSE))) -> G | Q54: =IF(INDEX('KPI Analysis'!$CO$7:$EU$123,MATCH($A54,'KPI Analysis'!$CO$7:$CO$123,FALSE),MATCH(P$8,'KPI Analysis'!$CO$7:$EU$7,FALSE))="OD","OD",INDEX('KPI Analysis'!$EW$7:$HC$123,MATCH($A54,'KPI Analysis'!$EW$7:$EW$123,FALSE),MATCH(P$8,'KPI Analysis'!$EW$7:$HC$7,FALSE))) -> 6 | R54: =IF(INDEX('KPI Analysis'!$AH$7:$CM$123,MATCH($A54,'KPI Analysis'!$AH$7:$AH$123,FALSE),MATCH(R$8,'KPI Analysis'!$AH$7:$CM$7,FALSE))="OD","",INDEX('KPI Analysis'!$AH$7:$CM$123,MATCH($A54,'KPI Analysis'!$AH$7:$AH$123,FALSE),MATCH(R$8,'KPI Analysis'!$AH$7:$CM$7,FALSE))) -> R | S54: =IF(INDEX('KPI Analysis'!$CO$7:$EU$123,MATCH($A54,'KPI Analysis'!$CO$7:$CO$123,FALSE),MATCH(R$8,'KPI Analysis'!$CO$7:$EU$7,FALSE))="OD","OD",INDEX('KPI Analysis'!$EW$7:$HC$123,MATCH($A54,'KPI Analysis'!$EW$7:$EW$123,FALSE),MATCH(R$8,'KPI Analysis'!$EW$7:$HC$7,FALSE))) -> 14 | T54: =IF(INDEX('KPI Analysis'!$AH$7:$CM$123,MATCH($A54,'KPI Analysis'!$AH$7:$AH$123,FALSE),MATCH(T$8,'KPI Analysis'!$AH$7:$CM$7,FALSE))="OD","",INDEX('KPI Analysis'!$AH$7:$CM$123,MATCH($A54,'KPI Analysis'!$AH$7:$AH$123,FALSE),MATCH(T$8,'KPI Analysis'!$AH$7:$CM$7,FALSE))) -> R | U54: =IF(INDEX('KPI Analysis'!$CO$7:$EU$123,MATCH($A54,'KPI Analysis'!$CO$7:$CO$123,FALSE),MATCH(T$8,'KPI Analysis'!$CO$7:$EU$7,FALSE))="OD","OD",INDEX('KPI Analysis'!$EW$7:$HC$123,MATCH($A54,'KPI Analysis'!$EW$7:$EW$123,FALSE),MATCH(T$8,'KPI Analysis'!$EW$7:$HC$7,FALSE))) -> 26 | V54: =IF(INDEX('KPI Analysis'!$AH$7:$CM$123,MATCH($A54,'KPI Analysis'!$AH$7:$AH$123,FALSE),MATCH(V$8,'KPI Analysis'!$AH$7:$CM$7,FALSE))="OD","",INDEX('KPI Analysis'!$AH$7:$CM$123,MATCH($A54,'KPI Analysis'!$AH$7:$AH$123,FALSE),MATCH(V$8,'KPI Analysis'!$AH$7:$CM$7,FALSE))) -> R | W54: =IF(INDEX('KPI Analysis'!$CO$7:$EU$123,MATCH($A54,'KPI Analysis'!$CO$7:$CO$123,FALSE),MATCH(V$8,'KPI Analysis'!$CO$7:$EU$7,FALSE))="OD","OD",INDEX('KPI Analysis'!$EW$7:$HC$123,MATCH($A54,'KPI Analysis'!$EW$7:$EW$123,FALSE),MATCH(V$8,'KPI Analysis'!$EW$7:$HC$7,FALSE))) -> 12 | X54: =IF(INDEX('KPI Analysis'!$AH$7:$CM$123,MATCH($A54,'KPI Analysis'!$AH$7:$AH$123,FALSE),MATCH(X$8,'KPI Analysis'!$AH$7:$CM$7,FALSE))="OD","",INDEX('KPI Analysis'!$AH$7:$CM$123,MATCH($A54,'KPI Analysis'!$AH$7:$AH$123,FALSE),MATCH(X$8,'KPI Analysis'!$AH$7:$CM$7,FALSE))) | Y54: =IF(INDEX('KPI Analysis'!$CO$7:$EU$123,MATCH($A54,'KPI Analysis'!$CO$7:$CO$123,FALSE),MATCH(X$8,'KPI Analysis'!$CO$7:$EU$7,FALSE))="OD","OD",INDEX('KPI Analysis'!$EW$7:$HC$123,MATCH($A54,'KPI Analysis'!$EW$7:$EW$123,FALSE),MATCH(X$8,'KPI Analysis'!$EW$7:$HC$7,FALSE))) -> OD | Z54: (Target 10) | AC54: EW HC | AE54: =INDEX('KPI Analysis'!$CO$7:$EU$123,MATCH($A54,'KPI Analysis'!$CO$7:$CO$123,FALSE),MATCH(AE$8,'KPI Analysis'!$CO$7:$EU$7,FALSE)) -> 1.6666667 | AF54: =INDEX('KPI Analysis'!$CO$7:$EU$123,MATCH($A54,'KPI Analysis'!$CO$7:$CO$123,FALSE),MATCH(AF$8,'KPI Analysis'!$CO$7:$EU$7,FALSE)) -> 0.71428571 | AG54: =INDEX('KPI Analysis'!$CO$7:$EU$123,MATCH($A54,'KPI Analysis'!$CO$7:$CO$123,FALSE),MATCH(AG$8,'KPI Analysis'!$CO$7:$EU$7,FALSE)) -> 0.38461538 | AH54: =INDEX('KPI Analysis'!$CO$7:$EU$123,MATCH($A54,'KPI Analysis'!$CO$7:$CO$123,FALSE),MATCH(AH$8,'KPI Analysis'!$CO$7:$EU$7,FALSE)) -> 0.83333333 | AI54: =INDEX('KPI Analysis'!$CO$7:$EU$123,MATCH($A54,'KPI Analysis'!$CO$7:$CO$123,FALSE),MATCH(AI$8,'KPI Analysis'!$CO$7:$EU$7,FALSE)) -> OD
A55: =F55&"-"&C55 -> Product Eng - MB-KPI Q1 | B55: =+'KPI Stats'!G46 -> Over | C55: =+'KPI Stats'!C46 -> KPI Q1 | F55: =+'KPI Stats'!$B$42 -> Product Eng - MB | G55: =+'KPI Stats'!$B$42 -> Product Eng - MB | H55: W | I55: =+'KPI Stats'!$F$42 -> 42 | J55: =+'KPI Stats'!D46 -> Quality | K55: =+'KPI Stats'!E46 -> Quality Defects / Items Output as a percentage | L55: =+'KPI Stats'!F46 -> Percentage | M55: Act Result | P55: =IF(INDEX('KPI Analysis'!$AH$7:$CM$123,MATCH($A55,'KPI Analysis'!$AH$7:$AH$123,FALSE),MATCH(P$8,'KPI Analysis'!$AH$7:$CM$7,FALSE))="OD","",INDEX('KPI Analysis'!$AH$7:$CM$123,MATCH($A55,'KPI Analysis'!$AH$7:$AH$123,FALSE),MATCH(P$8,'KPI Analysis'!$AH$7:$CM$7,FALSE))) -> G | Q55: =IF(INDEX('KPI Analysis'!$CO$7:$EU$123,MATCH($A55,'KPI Analysis'!$CO$7:$CO$123,FALSE),MATCH(P$8,'KPI Analysis'!$CO$7:$EU$7,FALSE))="OD","OD",IFERROR(INDEX('KPI Analysis'!$EW$7:$HC$123,MATCH($A55,'KPI Analysis'!$EW$7:$EW$123,FALSE),MATCH(P$8,'KPI Analysis'!$EW$7:$HC$7,FALSE))/100,"OD")) -> 0.008 | R55: =IF(INDEX('KPI Analysis'!$AH$7:$CM$123,MATCH($A55,'KPI Analysis'!$AH$7:$AH$123,FALSE),MATCH(R$8,'KPI Analysis'!$AH$7:$CM$7,FALSE))="OD","",INDEX('KPI Analysis'!$AH$7:$CM$123,MATCH($A55,'KPI Analysis'!$AH$7:$AH$123,FALSE),MATCH(R$8,'KPI Analysis'!$AH$7:$CM$7,FALSE))) -> G | S55: =IF(INDEX('KPI Analysis'!$CO$7:$EU$123,MATCH($A55,'KPI Analysis'!$CO$7:$CO$123,FALSE),MATCH(R$8,'KPI Analysis'!$CO$7:$EU$7,FALSE))="OD","OD",IFERROR(INDEX('KPI Analysis'!$EW$7:$HC$123,MATCH($A55,'KPI Analysis'!$EW$7:$EW$123,FALSE),MATCH(R$8,'KPI Analysis'!$EW$7:$HC$7,FALSE))/100,"OD")) -> 0 | T55: =IF(INDEX('KPI Analysis'!$AH$7:$CM$123,MATCH($A55,'KPI Analysis'!$AH$7:$AH$123,FALSE),MATCH(T$8,'KPI Analysis'!$AH$7:$CM$7,FALSE))="OD","",INDEX('KPI Analysis'!$AH$7:$CM$123,MATCH($A55,'KPI Analysis'!$AH$7:$AH$123,FALSE),MATCH(T$8,'KPI Analysis'!$AH$7:$CM$7,FALSE))) -> G | U55: =IF(INDEX('KPI Analysis'!$CO$7:$EU$123,MATCH($A55,'KPI Analysis'!$CO$7:$CO$123,FALSE),MATCH(T$8,'KPI Analysis'!$CO$7:$EU$7,FALSE))="OD","OD",IFERROR(INDEX('KPI Analysis'!$EW$7:$HC$123,MATCH($A55,'KPI Analysis'!$EW$7:$EW$123,FALSE),MATCH(T$8,'KPI Analysis'!$EW$7:$HC$7,FALSE))/100,"OD")) -> 0 | V55: =IF(INDEX('KPI Analysis'!$AH$7:$CM$123,MATCH($A55,'KPI Analysis'!$AH$7:$AH$123,FALSE),MATCH(V$8,'KPI Analysis'!$AH$7:$CM$7,FALSE))="OD","",INDEX('KPI Analysis'!$AH$7:$CM$123,MATCH($A55,'KPI Analysis'!$AH$7:$AH$123,FALSE),MATCH(V$8,'KPI Analysis'!$AH$7:$CM$7,FALSE))) -> G | W55: =IF(INDEX('KPI Analysis'!$CO$7:$EU$123,MATCH($A55,'KPI Analysis'!$CO$7:$CO$123,FALSE),MATCH(V$8,'KPI Analysis'!$CO$7:$EU$7,FALSE))="OD","OD",IFERROR(INDEX('KPI Analysis'!$EW$7:$HC$123,MATCH($A55,'KPI Analysis'!$EW$7:$EW$123,FALSE),MATCH(V$8,'KPI Analysis'!$EW$7:$HC$7,FALSE))/100,"OD")) -> 0.002 | X55: =IF(INDEX('KPI Analysis'!$AH$7:$CM$123,MATCH($A55,'KPI Analysis'!$AH$7:$AH$123,FALSE),MATCH(X$8,'KPI Analysis'!$AH$7:$CM$7,FALSE))="OD","",INDEX('KPI Analysis'!$AH$7:$CM$123,MATCH($A55,'KPI Analysis'!$AH$7:$AH$123,FALSE),MATCH(X$8,'KPI Analysis'!$AH$7:$CM$7,FALSE))) | Y55: =IF(INDEX('KPI Analysis'!$CO$7:$EU$123,MATCH($A55,'KPI Analysis'!$CO$7:$CO$123,FALSE),MATCH(X$8,'KPI Analysis'!$CO$7:$EU$7,FALSE))="OD","OD",IFERROR(INDEX('KPI Analysis'!$EW$7:$HC$123,MATCH($A55,'KPI Analysis'!$EW$7:$EW$123,FALSE),MATCH(X$8,'KPI Analysis'!$EW$7:$HC$7,FALSE))/100,"OD")) -> OD | Z55: Target 2.5%) | AC55: EW HC | AE55: =INDEX('KPI Analysis'!$CO$7:$EU$123,MATCH($A55,'KPI Analysis'!$CO$7:$CO$123,FALSE),MATCH(AE$8,'KPI Analysis'!$CO$7:$EU$7,FALSE)) -> 3.125 | AF55: =INDEX('KPI Analysis'!$CO$7:$EU$123,MATCH($A55,'KPI Analysis'!$CO$7:$CO$123,FALSE),MATCH(AF$8,'KPI Analysis'!$CO$7:$EU$7,FALSE)) -> 1 | AG55: =INDEX('KPI Analysis'!$CO$7:$EU$123,MATCH($A55,'KPI Analysis'!$CO$7:$CO$123,FALSE),MATCH(AG$8,'KPI Analysis'!$CO$7:$EU$7,FALSE)) -> 1 | AH55: =INDEX('KPI Analysis'!$CO$7:$EU$123,MATCH($A55,'KPI Analysis'!$CO$7:$CO$123,FALSE),MATCH(AH$8,'KPI Analysis'!$CO$7:$EU$7,FALSE)) -> 12.5 | AI55: =INDEX('KPI Analysis'!$CO$7:$EU$123,MATCH($A55,'KPI Analysis'!$CO$7:$CO$123,FALSE),MATCH(AI$8,'KPI Analysis'!$CO$7:$EU$7,FALSE)) -> OD
A56: =F56&"-"&C56 -> Product Eng - MB-KPI C1 | B56: =+'KPI Stats'!G47 -> Over | C56: =+'KPI Stats'!C47 -> KPI C1 | F56: =+'KPI Stats'!$B$42 -> Product Eng - MB | G56: =+'KPI Stats'!$B$42 -> Product Eng - MB | H56: W | I56: =+'KPI Stats'!$F$42 -> 42 | J56: =+'KPI Stats'!D47 -> Cost | K56: =+'KPI Stats'!E47 -> Cost Transfer Value per Day | L56: =+'KPI Stats'!F47 -> £s | M56: Act Result | P56: =IF(INDEX('KPI Analysis'!$AH$7:$CM$123,MATCH($A56,'KPI Analysis'!$AH$7:$AH$123,FALSE),MATCH(P$8,'KPI Analysis'!$AH$7:$CM$7,FALSE))="OD","",INDEX('KPI Analysis'!$AH$7:$CM$123,MATCH($A56,'KPI Analysis'!$AH$7:$AH$123,FALSE),MATCH(P$8,'KPI Analysis'!$AH$7:$CM$7,FALSE))) -> G | Q56: =IF(INDEX('KPI Analysis'!$CO$7:$EU$123,MATCH($A56,'KPI Analysis'!$CO$7:$CO$123,FALSE),MATCH(P$8,'KPI Analysis'!$CO$7:$EU$7,FALSE))="OD","OD",INDEX('KPI Analysis'!$EW$7:$HC$123,MATCH($A56,'KPI Analysis'!$EW$7:$EW$123,FALSE),MATCH(P$8,'KPI Analysis'!$EW$7:$HC$7,FALSE))) -> 1.2 | R56: =IF(INDEX('KPI Analysis'!$AH$7:$CM$123,MATCH($A56,'KPI Analysis'!$AH$7:$AH$123,FALSE),MATCH(R$8,'KPI Analysis'!$AH$7:$CM$7,FALSE))="OD","",INDEX('KPI Analysis'!$AH$7:$CM$123,MATCH($A56,'KPI Analysis'!$AH$7:$AH$123,FALSE),MATCH(R$8,'KPI Analysis'!$AH$7:$CM$7,FALSE))) -> G | S56: =IF(INDEX('KPI Analysis'!$CO$7:$EU$123,MATCH($A56,'KPI Analysis'!$CO$7:$CO$123,FALSE),MATCH(R$8,'KPI Analysis'!$CO$7:$EU$7,FALSE))="OD","OD",INDEX('KPI Analysis'!$EW$7:$HC$123,MATCH($A56,'KPI Analysis'!$EW$7:$EW$123,FALSE),MATCH(R$8,'KPI Analysis'!$EW$7:$HC$7,FALSE))) -> 37 | T56: =IF(INDEX('KPI Analysis'!$AH$7:$CM$123,MATCH($A56,'KPI Analysis'!$AH$7:$AH$123,FALSE),MATCH(T$8,'KPI Analysis'!$AH$7:$CM$7,FALSE))="OD","",INDEX('KPI Analysis'!$AH$7:$CM$123,MATCH($A56,'KPI Analysis'!$AH$7:$AH$123,FALSE),MATCH(T$8,'KPI Analysis'!$AH$7:$CM$7,FALSE))) -> R | U56: =IF(INDEX('KPI Analysis'!$CO$7:$EU$123,MATCH($A56,'KPI Analysis'!$CO$7:$CO$123,FALSE),MATCH(T$8,'KPI Analysis'!$CO$7:$EU$7,FALSE))="OD","OD",INDEX('KPI Analysis'!$EW$7:$HC$123,MATCH($A56,'KPI Analysis'!$EW$7:$EW$123,FALSE),MATCH(T$8,'KPI Analysis'!$EW$7:$HC$7,FALSE))) -> 49 | V56: =IF(INDEX('KPI Analysis'!$AH$7:$CM$123,MATCH($A56,'KPI Analysis'!$AH$7:$AH$123,FALSE),MATCH(V$8,'KPI Analysis'!$AH$7:$CM$7,FALSE))="OD","",INDEX('KPI Analysis'!$AH$7:$CM$123,MATCH($A56,'KPI Analysis'!$AH$7:$AH$123,FALSE),MATCH(V$8,'KPI Analysis'!$AH$7:$CM$7,FALSE))) -> G | W56: =IF(INDEX('KPI Analysis'!$CO$7:$EU$123,MATCH($A56,'KPI Analysis'!$CO$7:$CO$123,FALSE),MATCH(V$8,'KPI Analysis'!$CO$7:$EU$7,FALSE))="OD","OD",INDEX('KPI Analysis'!$EW$7:$HC$123,MATCH($A56,'KPI Analysis'!$EW$7:$EW$123,FALSE),MATCH(V$8,'KPI Analysis'!$EW$7:$HC$7,FALSE))) -> 10 | X56: =IF(INDEX('KPI Analysis'!$AH$7:$CM$123,MATCH($A56,'KPI Analysis'!$AH$7:$AH$123,FALSE),MATCH(X$8,'KPI Analysis'!$AH$7:$CM$7,FALSE))="OD","",INDEX('KPI Analysis'!$AH$7:$CM$123,MATCH($A56,'KPI Analysis'!$AH$7:$AH$123,FALSE),MATCH(X$8,'KPI Analysis'!$AH$7:$CM$7,FALSE))) | Y56: =IF(INDEX('KPI Analysis'!$CO$7:$EU$123,MATCH($A56,'KPI Analysis'!$CO$7:$CO$123,FALSE),MATCH(X$8,'KPI Analysis'!$CO$7:$EU$7,FALSE))="OD","OD",INDEX('KPI Analysis'!$EW$7:$HC$123,MATCH($A56,'KPI Analysis'!$EW$7:$EW$123,FALSE),MATCH(X$8,'KPI Analysis'!$EW$7:$HC$7,FALSE))) -> OD | Z56: (Target 40) | AC56: EW HC | AE56: =INDEX('KPI Analysis'!$CO$7:$EU$123,MATCH($A56,'KPI Analysis'!$CO$7:$CO$123,FALSE),MATCH(AE$8,'KPI Analysis'!$CO$7:$EU$7,FALSE)) -> 0.03 | AF56: =INDEX('KPI Analysis'!$CO$7:$EU$123,MATCH($A56,'KPI Analysis'!$CO$7:$CO$123,FALSE),MATCH(AF$8,'KPI Analysis'!$CO$7:$EU$7,FALSE)) -> 0.925 | AG56: =INDEX('KPI Analysis'!$CO$7:$EU$123,MATCH($A56,'KPI Analysis'!$CO$7:$CO$123,FALSE),MATCH(AG$8,'KPI Analysis'!$CO$7:$EU$7,FALSE)) -> 1.225 | AH56: =INDEX('KPI Analysis'!$CO$7:$EU$123,MATCH($A56,'KPI Analysis'!$CO$7:$CO$123,FALSE),MATCH(AH$8,'KPI Analysis'!$CO$7:$EU$7,FALSE)) -> 0.25 | AI56: =INDEX('KPI Analysis'!$CO$7:$EU$123,MATCH($A56,'KPI Analysis'!$CO$7:$CO$123,FALSE),MATCH(AI$8,'KPI Analysis'!$CO$7:$EU$7,FALSE)) -> OD
A57: =F57&"-"&C57 -> Product Eng - BE-KPI P1 | B57: Under | C57: =+'KPI Stats'!C50 -> KPI P1 | F57: =+'KPI Stats'!$B$49 -> Product Eng - BE | G57: =+'KPI Stats'!$C$49 -> Paul Dolan | H57: W | I57: =+'KPI Stats'!$F$49 -> 42 | J57: =+'KPI Stats'!D50 -> Productivity | K57: =+'KPI Stats'!E50 -> Output lines as a percentage of capacity | L57: =+'KPI Stats'!F50 -> Percentage | M57: Act Result | P57: =IF(INDEX('KPI Analysis'!$AH$7:$CM$123,MATCH($A57,'KPI Analysis'!$AH$7:$AH$123,FALSE),MATCH(P$8,'KPI Analysis'!$AH$7:$CM$7,FALSE))="OD","",INDEX('KPI Analysis'!$AH$7:$CM$123,MATCH($A57,'KPI Analysis'!$AH$7:$AH$123,FALSE),MATCH(P$8,'KPI Analysis'!$AH$7:$CM$7,FALSE))) -> R | Q57: =IF(INDEX('KPI Analysis'!$CO$7:$EU$123,MATCH($A57,'KPI Analysis'!$CO$7:$CO$123,FALSE),MATCH(P$8,'KPI Analysis'!$CO$7:$EU$7,FALSE))="OD","OD",IFERROR(INDEX('KPI Analysis'!$EW$7:$HC$123,MATCH($A57,'KPI Analysis'!$EW$7:$EW$123,FALSE),MATCH(P$8,'KPI Analysis'!$EW$7:$HC$7,FALSE))/100,"OD")) -> 0.6 | R57: =IF(INDEX('KPI Analysis'!$AH$7:$CM$123,MATCH($A57,'KPI Analysis'!$AH$7:$AH$123,FALSE),MATCH(R$8,'KPI Analysis'!$AH$7:$CM$7,FALSE))="OD","",INDEX('KPI Analysis'!$AH$7:$CM$123,MATCH($A57,'KPI Analysis'!$AH$7:$AH$123,FALSE),MATCH(R$8,'KPI Analysis'!$AH$7:$CM$7,FALSE))) -> R | S57: =IF(INDEX('KPI Analysis'!$CO$7:$EU$123,MATCH($A57,'KPI Analysis'!$CO$7:$CO$123,FALSE),MATCH(R$8,'KPI Analysis'!$CO$7:$EU$7,FALSE))="OD","OD",IFERROR(INDEX('KPI Analysis'!$EW$7:$HC$123,MATCH($A57,'KPI Analysis'!$EW$7:$EW$123,FALSE),MATCH(R$8,'KPI Analysis'!$EW$7:$HC$7,FALSE))/100,"OD")) -> 0.71 | T57: =IF(INDEX('KPI Analysis'!$AH$7:$CM$123,MATCH($A57,'KPI Analysis'!$AH$7:$AH$123,FALSE),MATCH(T$8,'KPI Analysis'!$AH$7:$CM$7,FALSE))="OD","",INDEX('KPI Analysis'!$AH$7:$CM$123,MATCH($A57,'KPI Analysis'!$AH$7:$AH$123,FALSE),MATCH(T$8,'KPI Analysis'!$AH$7:$CM$7,FALSE))) -> G | U57: =IF(INDEX('KPI Analysis'!$CO$7:$EU$123,MATCH($A57,'KPI Analysis'!$CO$7:$CO$123,FALSE),MATCH(T$8,'KPI Analysis'!$CO$7:$EU$7,FALSE))="OD","OD",IFERROR(INDEX('KPI Analysis'!$EW$7:$HC$123,MATCH($A57,'KPI Analysis'!$EW$7:$EW$123,FALSE),MATCH(T$8,'KPI Analysis'!$EW$7:$HC$7,FALSE))/100,"OD")) -> 1.22 | V57: =IF(INDEX('KPI Analysis'!$AH$7:$CM$123,MATCH($A57,'KPI Analysis'!$AH$7:$AH$123,FALSE),MATCH(V$8,'KPI Analysis'!$AH$7:$CM$7,FALSE))="OD","",INDEX('KPI Analysis'!$AH$7:$CM$123,MATCH($A57,'KPI Analysis'!$AH$7:$AH$123,FALSE),MATCH(V$8,'KPI Analysis'!$AH$7:$CM$7,FALSE))) -> G | W57: =IF(INDEX('KPI Analysis'!$CO$7:$EU$123,MATCH($A57,'KPI Analysis'!$CO$7:$CO$123,FALSE),MATCH(V$8,'KPI Analysis'!$CO$7:$EU$7,FALSE))="OD","OD",IFERROR(INDEX('KPI Analysis'!$EW$7:$HC$123,MATCH($A57,'KPI Analysis'!$EW$7:$EW$123,FALSE),MATCH(V$8,'KPI Analysis'!$EW$7:$HC$7,FALSE))/100,"OD")) -> 1.14 | X57: =IF(INDEX('KPI Analysis'!$AH$7:$CM$123,MATCH($A57,'KPI Analysis'!$AH$7:$AH$123,FALSE),MATCH(X$8,'KPI Analysis'!$AH$7:$CM$7,FALSE))="OD","",INDEX('KPI Analysis'!$AH$7:$CM$123,MATCH($A57,'KPI Analysis'!$AH$7:$AH$123,FALSE),MATCH(X$8,'KPI Analysis'!$AH$7:$CM$7,FALSE))) | Y57: =IF(INDEX('KPI Analysis'!$CO$7:$EU$123,MATCH($A57,'KPI Analysis'!$CO$7:$CO$123,FALSE),MATCH(X$8,'KPI Analysis'!$CO$7:$EU$7,FALSE))="OD","OD",IFERROR(INDEX('KPI Analysis'!$EW$7:$HC$123,MATCH($A57,'KPI Analysis'!$EW$7:$EW$123,FALSE),MATCH(X$8,'KPI Analysis'!$EW$7:$HC$7,FALSE))/100,"OD")) -> OD | Z57: (Target 80%) - | AC57: EW HC | AE57: =INDEX('KPI Analysis'!$CO$7:$EU$123,MATCH($A57,'KPI Analysis'!$CO$7:$CO$123,FALSE),MATCH(AE$8,'KPI Analysis'!$CO$7:$EU$7,FALSE)) -> 0.75 | AF57: =INDEX('KPI Analysis'!$CO$7:$EU$123,MATCH($A57,'KPI Analysis'!$CO$7:$CO$123,FALSE),MATCH(AF$8,'KPI Analysis'!$CO$7:$EU$7,FALSE)) -> 0.8875 | AG57: =INDEX('KPI Analysis'!$CO$7:$EU$123,MATCH($A57,'KPI Analysis'!$CO$7:$CO$123,FALSE),MATCH(AG$8,'KPI Analysis'!$CO$7:$EU$7,FALSE)) -> 1.525 | AH57: =INDEX('KPI Analysis'!$CO$7:$EU$123,MATCH($A57,'KPI Analysis'!$CO$7:$CO$123,FALSE),MATCH(AH$8,'KPI Analysis'!$CO$7:$EU$7,FALSE)) -> 1.425 | AI57: =INDEX('KPI Analysis'!$CO$7:$EU$123,MATCH($A57,'KPI Analysis'!$CO$7:$CO$123,FALSE),MATCH(AI$8,'KPI Analysis'!$CO$7:$EU$7,FALSE)) -> OD
A58: =F58&"-"&C58 -> Product Eng - BE-KPI D1 | B58: =+'KPI Stats'!G51 -> Over | C58: =+'KPI Stats'!C51 -> KPI D1 | F58: =+'KPI Stats'!$B$49 -> Product Eng - BE | G58: =+'KPI Stats'!$B$49 -> Product Eng - BE | H58: W | I58: =+'KPI Stats'!$F$49 -> 42 | J58: =+'KPI Stats'!D51 -> Delivery | K58: =+'KPI Stats'!E51 -> BOM Lead time | L58: =+'KPI Stats'!F51 -> Days | M58: Act Result | P58: =IF(INDEX('KPI Analysis'!$AH$7:$CM$123,MATCH($A58,'KPI Analysis'!$AH$7:$AH$123,FALSE),MATCH(P$8,'KPI Analysis'!$AH$7:$CM$7,FALSE))="OD","",INDEX('KPI Analysis'!$AH$7:$CM$123,MATCH($A58,'KPI Analysis'!$AH$7:$AH$123,FALSE),MATCH(P$8,'KPI Analysis'!$AH$7:$CM$7,FALSE))) -> R | Q58: =IF(INDEX('KPI Analysis'!$CO$7:$EU$123,MATCH($A58,'KPI Analysis'!$CO$7:$CO$123,FALSE),MATCH(P$8,'KPI Analysis'!$CO$7:$EU$7,FALSE))="OD","OD",INDEX('KPI Analysis'!$EW$7:$HC$123,MATCH($A58,'KPI Analysis'!$EW$7:$EW$123,FALSE),MATCH(P$8,'KPI Analysis'!$EW$7:$HC$7,FALSE))) -> 6 | R58: =IF(INDEX('KPI Analysis'!$AH$7:$CM$123,MATCH($A58,'KPI Analysis'!$AH$7:$AH$123,FALSE),MATCH(R$8,'KPI Analysis'!$AH$7:$CM$7,FALSE))="OD","",INDEX('KPI Analysis'!$AH$7:$CM$123,MATCH($A58,'KPI Analysis'!$AH$7:$AH$123,FALSE),MATCH(R$8,'KPI Analysis'!$AH$7:$CM$7,FALSE))) -> G | S58: =IF(INDEX('KPI Analysis'!$CO$7:$EU$123,MATCH($A58,'KPI Analysis'!$CO$7:$CO$123,FALSE),MATCH(R$8,'KPI Analysis'!$CO$7:$EU$7,FALSE))="OD","OD",INDEX('KPI Analysis'!$EW$7:$HC$123,MATCH($A58,'KPI Analysis'!$EW$7:$EW$123,FALSE),MATCH(R$8,'KPI Analysis'!$EW$7:$HC$7,FALSE))) -> 4 | T58: =IF(INDEX('KPI Analysis'!$AH$7:$CM$123,MATCH($A58,'KPI Analysis'!$AH$7:$AH$123,FALSE),MATCH(T$8,'KPI Analysis'!$AH$7:$CM$7,FALSE))="OD","",INDEX('KPI Analysis'!$AH$7:$CM$123,MATCH($A58,'KPI Analysis'!$AH$7:$AH$123,FALSE),MATCH(T$8,'KPI Analysis'!$AH$7:$CM$7,FALSE))) -> R | U58: =IF(INDEX('KPI Analysis'!$CO$7:$EU$123,MATCH($A58,'KPI Analysis'!$CO$7:$CO$123,FALSE),MATCH(T$8,'KPI Analysis'!$CO$7:$EU$7,FALSE))="OD","OD",INDEX('KPI Analysis'!$EW$7:$HC$123,MATCH($A58,'KPI Analysis'!$EW$7:$EW$123,FALSE),MATCH(T$8,'KPI Analysis'!$EW$7:$HC$7,FALSE))) -> 6 | V58: =IF(INDEX('KPI Analysis'!$AH$7:$CM$123,MATCH($A58,'KPI Analysis'!$AH$7:$AH$123,FALSE),MATCH(V$8,'KPI Analysis'!$AH$7:$CM$7,FALSE))="OD","",INDEX('KPI Analysis'!$AH$7:$CM$123,MATCH($A58,'KPI Analysis'!$AH$7:$AH$123,FALSE),MATCH(V$8,'KPI Analysis'!$AH$7:$CM$7,FALSE))) -> G | W58: =IF(INDEX('KPI Analysis'!$CO$7:$EU$123,MATCH($A58,'KPI Analysis'!$CO$7:$CO$123,FALSE),MATCH(V$8,'KPI Analysis'!$CO$7:$EU$7,FALSE))="OD","OD",INDEX('KPI Analysis'!$EW$7:$HC$123,MATCH($A58,'KPI Analysis'!$EW$7:$EW$123,FALSE),MATCH(V$8,'KPI Analysis'!$EW$7:$HC$7,FALSE))) -> 3 | X58: =IF(INDEX('KPI Analysis'!$AH$7:$CM$123,MATCH($A58,'KPI Analysis'!$AH$7:$AH$123,FALSE),MATCH(X$8,'KPI Analysis'!$AH$7:$CM$7,FALSE))="OD","",INDEX('KPI Analysis'!$AH$7:$CM$123,MATCH($A58,'KPI Analysis'!$AH$7:$AH$123,FALSE),MATCH(X$8,'KPI Analysis'!$AH$7:$CM$7,FALSE))) | Y58: =IF(INDEX('KPI Analysis'!$CO$7:$EU$123,MATCH($A58,'KPI Analysis'!$CO$7:$CO$123,FALSE),MATCH(X$8,'KPI Analysis'!$CO$7:$EU$7,FALSE))="OD","OD",INDEX('KPI Analysis'!$EW$7:$HC$123,MATCH($A58,'KPI Analysis'!$EW$7:$EW$123,FALSE),MATCH(X$8,'KPI Analysis'!$EW$7:$HC$7,FALSE))) -> OD | Z58: (Target 5) | AC58: EW HC | AE58: =INDEX('KPI Analysis'!$CO$7:$EU$123,MATCH($A58,'KPI Analysis'!$CO$7:$CO$123,FALSE),MATCH(AE$8,'KPI Analysis'!$CO$7:$EU$7,FALSE)) -> 0.83333333 | AF58: =INDEX('KPI Analysis'!$CO$7:$EU$123,MATCH($A58,'KPI Analysis'!$CO$7:$CO$123,FALSE),MATCH(AF$8,'KPI Analysis'!$CO$7:$EU$7,FALSE)) -> 1.25 | AG58: =INDEX('KPI Analysis'!$CO$7:$EU$123,MATCH($A58,'KPI Analysis'!$CO$7:$CO$123,FALSE),MATCH(AG$8,'KPI Analysis'!$CO$7:$EU$7,FALSE)) -> 0.83333333 | AH58: =INDEX('KPI Analysis'!$CO$7:$EU$123,MATCH($A58,'KPI Analysis'!$CO$7:$CO$123,FALSE),MATCH(AH$8,'KPI Analysis'!$CO$7:$EU$7,FALSE)) -> 1.6666667 | AI58: =INDEX('KPI Analysis'!$CO$7:$EU$123,MATCH($A58,'KPI Analysis'!$CO$7:$CO$123,FALSE),MATCH(AI$8,'KPI Analysis'!$CO$7:$EU$7,FALSE)) -> OD
A59: =F59&"-"&C59 -> Product Eng - BE-KPI D2 | B59: =+'KPI Stats'!G52 -> Over | C59: =+'KPI Stats'!C52 -> KPI D2 | F59: =+'KPI Stats'!$B$49 -> Product Eng - BE | G59: =+'KPI Stats'!$B$49 -> Product Eng - BE | H59: W | I59: =+'KPI Stats'!$F$49 -> 42 | J59: =+'KPI Stats'!D52 -> Delivery | K59: =+'KPI Stats'!E52 -> Lead Time for full order conversion | L59: =+'KPI Stats'!F52 -> Days | M59: Act Result | P59: =IF(INDEX('KPI Analysis'!$AH$7:$CM$123,MATCH($A59,'KPI Analysis'!$AH$7:$AH$123,FALSE),MATCH(P$8,'KPI Analysis'!$AH$7:$CM$7,FALSE))="OD","",INDEX('KPI Analysis'!$AH$7:$CM$123,MATCH($A59,'KPI Analysis'!$AH$7:$AH$123,FALSE),MATCH(P$8,'KPI Analysis'!$AH$7:$CM$7,FALSE))) -> R | Q59: =IF(INDEX('KPI Analysis'!$CO$7:$EU$123,MATCH($A59,'KPI Analysis'!$CO$7:$CO$123,FALSE),MATCH(P$8,'KPI Analysis'!$CO$7:$EU$7,FALSE))="OD","OD",INDEX('KPI Analysis'!$EW$7:$HC$123,MATCH($A59,'KPI Analysis'!$EW$7:$EW$123,FALSE),MATCH(P$8,'KPI Analysis'!$EW$7:$HC$7,FALSE))) -> 21 | R59: =IF(INDEX('KPI Analysis'!$AH$7:$CM$123,MATCH($A59,'KPI Analysis'!$AH$7:$AH$123,FALSE),MATCH(R$8,'KPI Analysis'!$AH$7:$CM$7,FALSE))="OD","",INDEX('KPI Analysis'!$AH$7:$CM$123,MATCH($A59,'KPI Analysis'!$AH$7:$AH$123,FALSE),MATCH(R$8,'KPI Analysis'!$AH$7:$CM$7,FALSE))) -> R | S59: =IF(INDEX('KPI Analysis'!$CO$7:$EU$123,MATCH($A59,'KPI Analysis'!$CO$7:$CO$123,FALSE),MATCH(R$8,'KPI Analysis'!$CO$7:$EU$7,FALSE))="OD","OD",INDEX('KPI Analysis'!$EW$7:$HC$123,MATCH($A59,'KPI Analysis'!$EW$7:$EW$123,FALSE),MATCH(R$8,'KPI Analysis'!$EW$7:$HC$7,FALSE))) -> 23 | T59: =IF(INDEX('KPI Analysis'!$AH$7:$CM$123,MATCH($A59,'KPI Analysis'!$AH$7:$AH$123,FALSE),MATCH(T$8,'KPI Analysis'!$AH$7:$CM$7,FALSE))="OD","",INDEX('KPI Analysis'!$AH$7:$CM$123,MATCH($A59,'KPI Analysis'!$AH$7:$AH$123,FALSE),MATCH(T$8,'KPI Analysis'!$AH$7:$CM$7,FALSE))) -> R | U59: =IF(INDEX('KPI Analysis'!$CO$7:$EU$123,MATCH($A59,'KPI Analysis'!$CO$7:$CO$123,FALSE),MATCH(T$8,'KPI Analysis'!$CO$7:$EU$7,FALSE))="OD","OD",INDEX('KPI Analysis'!$EW$7:$HC$123,MATCH($A59,'KPI Analysis'!$EW$7:$EW$123,FALSE),MATCH(T$8,'KPI Analysis'!$EW$7:$HC$7,FALSE))) -> 25 | V59: =IF(INDEX('KPI Analysis'!$AH$7:$CM$123,MATCH($A59,'KPI Analysis'!$AH$7:$AH$123,FALSE),MATCH(V$8,'KPI Analysis'!$AH$7:$CM$7,FALSE))="OD","",INDEX('KPI Analysis'!$AH$7:$CM$123,MATCH($A59,'KPI Analysis'!$AH$7:$AH$123,FALSE),MATCH(V$8,'KPI Analysis'!$AH$7:$CM$7,FALSE))) -> R | W59: =IF(INDEX('KPI Analysis'!$CO$7:$EU$123,MATCH($A59,'KPI Analysis'!$CO$7:$CO$123,FALSE),MATCH(V$8,'KPI Analysis'!$CO$7:$EU$7,FALSE))="OD","OD",INDEX('KPI Analysis'!$EW$7:$HC$123,MATCH($A59,'KPI Analysis'!$EW$7:$EW$123,FALSE),MATCH(V$8,'KPI Analysis'!$EW$7:$HC$7,FALSE))) -> 19 | X59: =IF(INDEX('KPI Analysis'!$AH$7:$CM$123,MATCH($A59,'KPI Analysis'!$AH$7:$AH$123,FALSE),MATCH(X$8,'KPI Analysis'!$AH$7:$CM$7,FALSE))="OD","",INDEX('KPI Analysis'!$AH$7:$CM$123,MATCH($A59,'KPI Analysis'!$AH$7:$AH$123,FALSE),MATCH(X$8,'KPI Analysis'!$AH$7:$CM$7,FALSE))) | Y59: =IF(INDEX('KPI Analysis'!$CO$7:$EU$123,MATCH($A59,'KPI Analysis'!$CO$7:$CO$123,FALSE),MATCH(X$8,'KPI Analysis'!$CO$7:$EU$7,FALSE))="OD","OD",INDEX('KPI Analysis'!$EW$7:$HC$123,MATCH($A59,'KPI Analysis'!$EW$7:$EW$123,FALSE),MATCH(X$8,'KPI Analysis'!$EW$7:$HC$7,FALSE))) -> OD | Z59: (Target 10) | AC59: EW HC | AE59: =INDEX('KPI Analysis'!$CO$7:$EU$123,MATCH($A59,'KPI Analysis'!$CO$7:$CO$123,FALSE),MATCH(AE$8,'KPI Analysis'!$CO$7:$EU$7,FALSE)) -> 0.47619048 | AF59: =INDEX('KPI Analysis'!$CO$7:$EU$123,MATCH($A59,'KPI Analysis'!$CO$7:$CO$123,FALSE),MATCH(AF$8,'KPI Analysis'!$CO$7:$EU$7,FALSE)) -> 0.43478261 | AG59: =INDEX('KPI Analysis'!$CO$7:$EU$123,MATCH($A59,'KPI Analysis'!$CO$7:$CO$123,FALSE),MATCH(AG$8,'KPI Analysis'!$CO$7:$EU$7,FALSE)) -> 0.4 | AH59: =INDEX('KPI Analysis'!$CO$7:$EU$123,MATCH($A59,'KPI Analysis'!$CO$7:$CO$123,FALSE),MATCH(AH$8,'KPI Analysis'!$CO$7:$EU$7,FALSE)) -> 0.52631579 | AI59: =INDEX('KPI Analysis'!$CO$7:$EU$123,MATCH($A59,'KPI Analysis'!$CO$7:$CO$123,FALSE),MATCH(AI$8,'KPI Analysis'!$CO$7:$EU$7,FALSE)) -> OD
A60: =F60&"-"&C60 -> Product Eng - BE-KPI Q1 | B60: =+'KPI Stats'!G53 -> Over | C60: =+'KPI Stats'!C53 -> KPI Q1 | F60: =+'KPI Stats'!$B$49 -> Product Eng - BE | G60: =+'KPI Stats'!$B$49 -> Product Eng - BE | H60: W | I60: =+'KPI Stats'!$F$49 -> 42 | J60: =+'KPI Stats'!D53 -> Quality | K60: =+'KPI Stats'!E53 -> Quality Defects / Items Output as a percentage | L60: =+'KPI Stats'!F53 -> Percentage | M60: Act Result | P60: =IF(INDEX('KPI Analysis'!$AH$7:$CM$123,MATCH($A60,'KPI Analysis'!$AH$7:$AH$123,FALSE),MATCH(P$8,'KPI Analysis'!$AH$7:$CM$7,FALSE))="OD","",INDEX('KPI Analysis'!$AH$7:$CM$123,MATCH($A60,'KPI Analysis'!$AH$7:$AH$123,FALSE),MATCH(P$8,'KPI Analysis'!$AH$7:$CM$7,FALSE))) -> R | Q60: =IF(INDEX('KPI Analysis'!$CO$7:$EU$123,MATCH($A60,'KPI Analysis'!$CO$7:$CO$123,FALSE),MATCH(P$8,'KPI Analysis'!$CO$7:$EU$7,FALSE))="OD","OD",IFERROR(INDEX('KPI Analysis'!$EW$7:$HC$123,MATCH($A60,'KPI Analysis'!$EW$7:$EW$123,FALSE),MATCH(P$8,'KPI Analysis'!$EW$7:$HC$7,FALSE))/100,"OD")) -> 0.15 | R60: =IF(INDEX('KPI Analysis'!$AH$7:$CM$123,MATCH($A60,'KPI Analysis'!$AH$7:$AH$123,FALSE),MATCH(R$8,'KPI Analysis'!$AH$7:$CM$7,FALSE))="OD","",INDEX('KPI Analysis'!$AH$7:$CM$123,MATCH($A60,'KPI Analysis'!$AH$7:$AH$123,FALSE),MATCH(R$8,'KPI Analysis'!$AH$7:$CM$7,FALSE))) -> R | S60: =IF(INDEX('KPI Analysis'!$CO$7:$EU$123,MATCH($A60,'KPI Analysis'!$CO$7:$CO$123,FALSE),MATCH(R$8,'KPI Analysis'!$CO$7:$EU$7,FALSE))="OD","OD",IFERROR(INDEX('KPI Analysis'!$EW$7:$HC$123,MATCH($A60,'KPI Analysis'!$EW$7:$EW$123,FALSE),MATCH(R$8,'KPI Analysis'!$EW$7:$HC$7,FALSE))/100,"OD")) -> 0.087 | T60: =IF(INDEX('KPI Analysis'!$AH$7:$CM$123,MATCH($A60,'KPI Analysis'!$AH$7:$AH$123,FALSE),MATCH(T$8,'KPI Analysis'!$AH$7:$CM$7,FALSE))="OD","",INDEX('KPI Analysis'!$AH$7:$CM$123,MATCH($A60,'KPI Analysis'!$AH$7:$AH$123,FALSE),MATCH(T$8,'KPI Analysis'!$AH$7:$CM$7,FALSE))) -> R | U60: =IF(INDEX('KPI Analysis'!$CO$7:$EU$123,MATCH($A60,'KPI Analysis'!$CO$7:$CO$123,FALSE),MATCH(T$8,'KPI Analysis'!$CO$7:$EU$7,FALSE))="OD","OD",IFERROR(INDEX('KPI Analysis'!$EW$7:$HC$123,MATCH($A60,'KPI Analysis'!$EW$7:$EW$123,FALSE),MATCH(T$8,'KPI Analysis'!$EW$7:$HC$7,FALSE))/100,"OD")) -> 0.1 | V60: =IF(INDEX('KPI Analysis'!$AH$7:$CM$123,MATCH($A60,'KPI Analysis'!$AH$7:$AH$123,FALSE),MATCH(V$8,'KPI Analysis'!$AH$7:$CM$7,FALSE))="OD","",INDEX('KPI Analysis'!$AH$7:$CM$123,MATCH($A60,'KPI Analysis'!$AH$7:$AH$123,FALSE),MATCH(V$8,'KPI Analysis'!$AH$7:$CM$7,FALSE))) -> R | W60: =IF(INDEX('KPI Analysis'!$CO$7:$EU$123,MATCH($A60,'KPI Analysis'!$CO$7:$CO$123,FALSE),MATCH(V$8,'KPI Analysis'!$CO$7:$EU$7,FALSE))="OD","OD",IFERROR(INDEX('KPI Analysis'!$EW$7:$HC$123,MATCH($A60,'KPI Analysis'!$EW$7:$EW$123,FALSE),MATCH(V$8,'KPI Analysis'!$EW$7:$HC$7,FALSE))/100,"OD")) -> 0.072 | X60: =IF(INDEX('KPI Analysis'!$AH$7:$CM$123,MATCH($A60,'KPI Analysis'!$AH$7:$AH$123,FALSE),MATCH(X$8,'KPI Analysis'!$AH$7:$CM$7,FALSE))="OD","",INDEX('KPI Analysis'!$AH$7:$CM$123,MATCH($A60,'KPI Analysis'!$AH$7:$AH$123,FALSE),MATCH(X$8,'KPI Analysis'!$AH$7:$CM$7,FALSE))) | Y60: =IF(INDEX('KPI Analysis'!$CO$7:$EU$123,MATCH($A60,'KPI Analysis'!$CO$7:$CO$123,FALSE),MATCH(X$8,'KPI Analysis'!$CO$7:$EU$7,FALSE))="OD","OD",IFERROR(INDEX('KPI Analysis'!$EW$7:$HC$123,MATCH($A60,'KPI Analysis'!$EW$7:$EW$123,FALSE),MATCH(X$8,'KPI Analysis'!$EW$7:$HC$7,FALSE))/100,"OD")) -> OD | Z60: Target 2.5%) | AC60: EW HC | AE60: =INDEX('KPI Analysis'!$CO$7:$EU$123,MATCH($A60,'KPI Analysis'!$CO$7:$CO$123,FALSE),MATCH(AE$8,'KPI Analysis'!$CO$7:$EU$7,FALSE)) -> 0.16666667 | AF60: =INDEX('KPI Analysis'!$CO$7:$EU$123,MATCH($A60,'KPI Analysis'!$CO$7:$CO$123,FALSE),MATCH(AF$8,'KPI Analysis'!$CO$7:$EU$7,FALSE)) -> 0.28735632 | AG60: =INDEX('KPI Analysis'!$CO$7:$EU$123,MATCH($A60,'KPI Analysis'!$CO$7:$CO$123,FALSE),MATCH(AG$8,'KPI Analysis'!$CO$7:$EU$7,FALSE)) -> 0.25 | AH60: =INDEX('KPI Analysis'!$CO$7:$EU$123,MATCH($A60,'KPI Analysis'!$CO$7:$CO$123,FALSE),MATCH(AH$8,'KPI Analysis'!$CO$7:$EU$7,FALSE)) -> 0.34722222 | AI60: =INDEX('KPI Analysis'!$CO$7:$EU$123,MATCH($A60,'KPI Analysis'!$CO$7:$CO$123,FALSE),MATCH(AI$8,'KPI Analysis'!$CO$7:$EU$7,FALSE)) -> OD
A61: =F61&"-"&C61 -> Product Eng - BE-KPI C1 | B61: =+'KPI Stats'!G54 -> Over | C61: =+'KPI Stats'!C54 -> KPI C1 | F61: =+'KPI Stats'!$B$49 -> Product Eng - BE | G61: =+'KPI Stats'!$B$49 -> Product Eng - BE | H61: W | I61: =+'KPI Stats'!$F$49 -> 42 | J61: =+'KPI Stats'!D54 -> Cost | K61: =+'KPI Stats'!E54 -> Cost Transfer Value per Day | L61: =+'KPI Stats'!F54 -> £'s | M61: Act Result | P61: =IF(INDEX('KPI Analysis'!$AH$7:$CM$123,MATCH($A61,'KPI Analysis'!$AH$7:$AH$123,FALSE),MATCH(P$8,'KPI Analysis'!$AH$7:$CM$7,FALSE))="OD","",INDEX('KPI Analysis'!$AH$7:$CM$123,MATCH($A61,'KPI Analysis'!$AH$7:$AH$123,FALSE),MATCH(P$8,'KPI Analysis'!$AH$7:$CM$7,FALSE))) -> G | Q61: =IF(INDEX('KPI Analysis'!$CO$7:$EU$123,MATCH($A61,'KPI Analysis'!$CO$7:$CO$123,FALSE),MATCH(P$8,'KPI Analysis'!$CO$7:$EU$7,FALSE))="OD","OD",INDEX('KPI Analysis'!$EW$7:$HC$123,MATCH($A61,'KPI Analysis'!$EW$7:$EW$123,FALSE),MATCH(P$8,'KPI Analysis'!$EW$7:$HC$7,FALSE))) -> 62 | R61: =IF(INDEX('KPI Analysis'!$AH$7:$CM$123,MATCH($A61,'KPI Analysis'!$AH$7:$AH$123,FALSE),MATCH(R$8,'KPI Analysis'!$AH$7:$CM$7,FALSE))="OD","",INDEX('KPI Analysis'!$AH$7:$CM$123,MATCH($A61,'KPI Analysis'!$AH$7:$AH$123,FALSE),MATCH(R$8,'KPI Analysis'!$AH$7:$CM$7,FALSE))) -> G | S61: =IF(INDEX('KPI Analysis'!$CO$7:$EU$123,MATCH($A61,'KPI Analysis'!$CO$7:$CO$123,FALSE),MATCH(R$8,'KPI Analysis'!$CO$7:$EU$7,FALSE))="OD","OD",INDEX('KPI Analysis'!$EW$7:$HC$123,MATCH($A61,'KPI Analysis'!$EW$7:$EW$123,FALSE),MATCH(R$8,'KPI Analysis'!$EW$7:$HC$7,FALSE))) -> 61 | T61: =IF(INDEX('KPI Analysis'!$AH$7:$CM$123,MATCH($A61,'KPI Analysis'!$AH$7:$AH$123,FALSE),MATCH(T$8,'KPI Analysis'!$AH$7:$CM$7,FALSE))="OD","",INDEX('KPI Analysis'!$AH$7:$CM$123,MATCH($A61,'KPI Analysis'!$AH$7:$AH$123,FALSE),MATCH(T$8,'KPI Analysis'!$AH$7:$CM$7,FALSE))) -> G | U61: =IF(INDEX('KPI Analysis'!$CO$7:$EU$123,MATCH($A61,'KPI Analysis'!$CO$7:$CO$123,FALSE),MATCH(T$8,'KPI Analysis'!$CO$7:$EU$7,FALSE))="OD","OD",INDEX('KPI Analysis'!$EW$7:$HC$123,MATCH($A61,'KPI Analysis'!$EW$7:$EW$123,FALSE),MATCH(T$8,'KPI Analysis'!$EW$7:$HC$7,FALSE))) -> 74 | V61: =IF(INDEX('KPI Analysis'!$AH$7:$CM$123,MATCH($A61,'KPI Analysis'!$AH$7:$AH$123,FALSE),MATCH(V$8,'KPI Analysis'!$AH$7:$CM$7,FALSE))="OD","",INDEX('KPI Analysis'!$AH$7:$CM$123,MATCH($A61,'KPI Analysis'!$AH$7:$AH$123,FALSE),MATCH(V$8,'KPI Analysis'!$AH$7:$CM$7,FALSE))) -> G | W61: =IF(INDEX('KPI Analysis'!$CO$7:$EU$123,MATCH($A61,'KPI Analysis'!$CO$7:$CO$123,FALSE),MATCH(V$8,'KPI Analysis'!$CO$7:$EU$7,FALSE))="OD","OD",INDEX('KPI Analysis'!$EW$7:$HC$123,MATCH($A61,'KPI Analysis'!$EW$7:$EW$123,FALSE),MATCH(V$8,'KPI Analysis'!$EW$7:$HC$7,FALSE))) -> 66 | X61: =IF(INDEX('KPI Analysis'!$AH$7:$CM$123,MATCH($A61,'KPI Analysis'!$AH$7:$AH$123,FALSE),MATCH(X$8,'KPI Analysis'!$AH$7:$CM$7,FALSE))="OD","",INDEX('KPI Analysis'!$AH$7:$CM$123,MATCH($A61,'KPI Analysis'!$AH$7:$AH$123,FALSE),MATCH(X$8,'KPI Analysis'!$AH$7:$CM$7,FALSE))) | Y61: =IF(INDEX('KPI Analysis'!$CO$7:$EU$123,MATCH($A61,'KPI Analysis'!$CO$7:$CO$123,FALSE),MATCH(X$8,'KPI Analysis'!$CO$7:$EU$7,FALSE))="OD","OD",INDEX('KPI Analysis'!$EW$7:$HC$123,MATCH($A61,'KPI Analysis'!$EW$7:$EW$123,FALSE),MATCH(X$8,'KPI Analysis'!$EW$7:$HC$7,FALSE))) -> OD | Z61: (Target 110) | AC61: EW HC | AE61: =INDEX('KPI Analysis'!$CO$7:$EU$123,MATCH($A61,'KPI Analysis'!$CO$7:$CO$123,FALSE),MATCH(AE$8,'KPI Analysis'!$CO$7:$EU$7,FALSE)) -> 1.7741935 | AF61: =INDEX('KPI Analysis'!$CO$7:$EU$123,MATCH($A61,'KPI Analysis'!$CO$7:$CO$123,FALSE),MATCH(AF$8,'KPI Analysis'!$CO$7:$EU$7,FALSE)) -> 1.8032787 | AG61: =INDEX('KPI Analysis'!$CO$7:$EU$123,MATCH($A61,'KPI Analysis'!$CO$7:$CO$123,FALSE),MATCH(AG$8,'KPI Analysis'!$CO$7:$EU$7,FALSE)) -> 1.4864865 | AH61: =INDEX('KPI Analysis'!$CO$7:$EU$123,MATCH($A61,'KPI Analysis'!$CO$7:$CO$123,FALSE),MATCH(AH$8,'KPI Analysis'!$CO$7:$EU$7,FALSE)) -> 1.6666667 | AI61: =INDEX('KPI Analysis'!$CO$7:$EU$123,MATCH($A61,'KPI Analysis'!$CO$7:$CO$123,FALSE),MATCH(AI$8,'KPI Analysis'!$CO$7:$EU$7,FALSE)) -> OD
A64: =F64&"-"&C64 -> Bridgend Manuf-KPI P1 | B64: =+'KPI Stats'!G57 -> Under | C64: =+'KPI Stats'!C57 -> KPI P1 | F64: =+'KPI Stats'!$B$56 -> Bridgend Manuf | G64: Garin Bowen | H64: W | I64: =+'KPI Stats'!$F$56 -> 42 | J64: =+'KPI Stats'!D57 -> Productivity | K64: =+'KPI Stats'!E57 -> Production Value | L64: =+'KPI Stats'!F57 -> £'s | M64: =INDEX('KPI Analysis'!$CO$7:$EU$123,MATCH($A64,'KPI Analysis'!$CO$7:$CO$123,FALSE),MATCH(M$8,'KPI Analysis'!$CO$7:$EU$7,FALSE)) -> % of target | P64: =IF( OR( INDEX('KPI Analysis'!$AH$7:$CM$123, MATCH($A64,'KPI Analysis'!$AH$7:$AH$123,FALSE), MATCH(P$8,'KPI Analysis'!$AH$7:$CM$7,FALSE) )="R", INDEX('KPI Analysis'!$AH$7:$CM$123, MATCH($A64,'KPI Analysis'!$AH$7:$AH$123,FALSE), MATCH(P$8,'KPI Analysis'!$AH$7:$CM$7,FALSE) )="G", INDEX('KPI Analysis'!$AH$7:$CM$123, MATCH($A64,'KPI Analysis'!$AH$7:$AH$123,FALSE), MATCH(P$8,'KPI Analysis'!$AH$7:$CM$7,FALSE) )="A"), INDEX('KPI Analysis'!$AH$7:$CM$123,MATCH($A64,'KPI Analysis'!$AH$7:$AH$123,FALSE),MATCH(P$8,'KPI Analysis'!$AH$7:$CM$7,FALSE)),"") -> R | Q64: =INDEX('KPI Analysis'!$CO$7:$EU$123,MATCH($A64,'KPI Analysis'!$CO$7:$CO$123,FALSE),MATCH(P$8,'KPI Analysis'!$CO$7:$EU$7,FALSE)) -> 0.800895 | R64: =IF( OR( INDEX('KPI Analysis'!$AH$7:$CM$123, MATCH($A64,'KPI Analysis'!$AH$7:$AH$123,FALSE), MATCH(R$8,'KPI Analysis'!$AH$7:$CM$7,FALSE) )="R", INDEX('KPI Analysis'!$AH$7:$CM$123, MATCH($A64,'KPI Analysis'!$AH$7:$AH$123,FALSE), MATCH(R$8,'KPI Analysis'!$AH$7:$CM$7,FALSE) )="G", INDEX('KPI Analysis'!$AH$7:$CM$123, MATCH($A64,'KPI Analysis'!$AH$7:$AH$123,FALSE), MATCH(R$8,'KPI Analysis'!$AH$7:$CM$7,FALSE) )="A"), INDEX('KPI Analysis'!$AH$7:$CM$123,MATCH($A64,'KPI Analysis'!$AH$7:$AH$123,FALSE),MATCH(R$8,'KPI Analysis'!$AH$7:$CM$7,FALSE)),"") -> G | S64: =INDEX('KPI Analysis'!$CO$7:$EU$123,MATCH($A64,'KPI Analysis'!$CO$7:$CO$123,FALSE),MATCH(R$8,'KPI Analysis'!$CO$7:$EU$7,FALSE)) -> 1.2078916 | T64: =IF( OR( INDEX('KPI Analysis'!$AH$7:$CM$123, MATCH($A64,'KPI Analysis'!$AH$7:$AH$123,FALSE), MATCH(T$8,'KPI Analysis'!$AH$7:$CM$7,FALSE) )="R", INDEX('KPI Analysis'!$AH$7:$CM$123, MATCH($A64,'KPI Analysis'!$AH$7:$AH$123,FALSE), MATCH(T$8,'KPI Analysis'!$AH$7:$CM$7,FALSE) )="G", INDEX('KPI Analysis'!$AH$7:$CM$123, MATCH($A64,'KPI Analysis'!$AH$7:$AH$123,FALSE), MATCH(T$8,'KPI Analysis'!$AH$7:$CM$7,FALSE) )="A"), INDEX('KPI Analysis'!$AH$7:$CM$123,MATCH($A64,'KPI Analysis'!$AH$7:$AH$123,FALSE),MATCH(T$8,'KPI Analysis'!$AH$7:$CM$7,FALSE)),"") | U64: =INDEX('KPI Analysis'!$CO$7:$EU$123,MATCH($A64,'KPI Analysis'!$CO$7:$CO$123,FALSE),MATCH(T$8,'KPI Analysis'!$CO$7:$EU$7,FALSE)) -> OD | V64: =IF( OR( INDEX('KPI Analysis'!$AH$7:$CM$123, MATCH($A64,'KPI Analysis'!$AH$7:$AH$123,FALSE), MATCH(V$8,'KPI Analysis'!$AH$7:$CM$7,FALSE) )="R", INDEX('KPI Analysis'!$AH$7:$CM$123, MATCH($A64,'KPI Analysis'!$AH$7:$AH$123,FALSE), MATCH(V$8,'KPI Analysis'!$AH$7:$CM$7,FALSE) )="G", INDEX('KPI Analysis'!$AH$7:$CM$123, MATCH($A64,'KPI Analysis'!$AH$7:$AH$123,FALSE), MATCH(V$8,'KPI Analysis'!$AH$7:$CM$7,FALSE) )="A"), INDEX('KPI Analysis'!$AH$7:$CM$123,MATCH($A64,'KPI Analysis'!$AH$7:$AH$123,FALSE),MATCH(V$8,'KPI Analysis'!$AH$7:$CM$7,FALSE)),"") | W64: =INDEX('KPI Analysis'!$CO$7:$EU$123,MATCH($A64,'KPI Analysis'!$CO$7:$CO$123,FALSE),MATCH(V$8,'KPI Analysis'!$CO$7:$EU$7,FALSE)) -> OD | X64: =IF( OR( INDEX('KPI Analysis'!$AH$7:$CM$123, MATCH($A64,'KPI Analysis'!$AH$7:$AH$123,FALSE), MATCH(X$8,'KPI Analysis'!$AH$7:$CM$7,FALSE) )="R", INDEX('KPI Analysis'!$AH$7:$CM$123, MATCH($A64,'KPI Analysis'!$AH$7:$AH$123,FALSE), MATCH(X$8,'KPI Analysis'!$AH$7:$CM$7,FALSE) )="G", INDEX('KPI Analysis'!$AH$7:$CM$123, MATCH($A64,'KPI Analysis'!$AH$7:$AH$123,FALSE), MATCH(X$8,'KPI Analysis'!$AH$7:$CM$7,FALSE) )="A"), INDEX('KPI Analysis'!$AH$7:$CM$123,MATCH($A64,'KPI Analysis'!$AH$7:$AH$123,FALSE),MATCH(X$8,'KPI Analysis'!$AH$7:$CM$7,FALSE)),"") | Y64: =INDEX('KPI Analysis'!$CO$7:$EU$123,MATCH($A64,'KPI Analysis'!$CO$7:$CO$123,FALSE),MATCH(X$8,'KPI Analysis'!$CO$7:$EU$7,FALSE)) -> OD | AC64: Co EU | AE64: =INDEX('KPI Analysis'!$CO$7:$EU$123,MATCH($A64,'KPI Analysis'!$CO$7:$CO$123,FALSE),MATCH(AE$8,'KPI Analysis'!$CO$7:$EU$7,FALSE)) -> 0.800895 | AF64: =INDEX('KPI Analysis'!$CO$7:$EU$123,MATCH($A64,'KPI Analysis'!$CO$7:$CO$123,FALSE),MATCH(AF$8,'KPI Analysis'!$CO$7:$EU$7,FALSE)) -> 1.2078916 | AG64: =INDEX('KPI Analysis'!$CO$7:$EU$123,MATCH($A64,'KPI Analysis'!$CO$7:$CO$123,FALSE),MATCH(AG$8,'KPI Analysis'!$CO$7:$EU$7,FALSE)) -> OD | AH64: =INDEX('KPI Analysis'!$CO$7:$EU$123,MATCH($A64,'KPI Analysis'!$CO$7:$CO$123,FALSE),MATCH(AH$8,'KPI Analysis'!$CO$7:$EU$7,FALSE)) -> OD | AI64: =INDEX('KPI Analysis'!$CO$7:$EU$123,MATCH($A64,'KPI Analysis'!$CO$7:$CO$123,FALSE),MATCH(AI$8,'KPI Analysis'!$CO$7:$EU$7,FALSE)) -> OD
A65: =F65&"-"&C65 -> Bridgend Manuf-KPI D1 | B65: =+'KPI Stats'!G58 -> Under | C65: =+'KPI Stats'!C58 -> KPI D1 | F65: =+'KPI Stats'!$B$56 -> Bridgend Manuf | G65: =+'KPI Stats'!$B$56 -> Bridgend Manuf | H65: W | I65: =+'KPI Stats'!$F$56 -> 42 | J65: =+'KPI Stats'!D58 -> Delivery | K65: =+'KPI Stats'!E58 -> Percentage of OTIF that achieved delivery date | L65: =+'KPI Stats'!F58 -> Percentage | M65: Act Result | P65: =IF( OR( INDEX('KPI Analysis'!$AH$7:$CM$123, MATCH($A65,'KPI Analysis'!$AH$7:$AH$123,FALSE), MATCH(P$8,'KPI Analysis'!$AH$7:$CM$7,FALSE) )="R", INDEX('KPI Analysis'!$AH$7:$CM$123, MATCH($A65,'KPI Analysis'!$AH$7:$AH$123,FALSE), MATCH(P$8,'KPI Analysis'!$AH$7:$CM$7,FALSE) )="G", INDEX('KPI Analysis'!$AH$7:$CM$123, MATCH($A65,'KPI Analysis'!$AH$7:$AH$123,FALSE), MATCH(P$8,'KPI Analysis'!$AH$7:$CM$7,FALSE) )="A"), INDEX('KPI Analysis'!$AH$7:$CM$123,MATCH($A65,'KPI Analysis'!$AH$7:$AH$123,FALSE),MATCH(P$8,'KPI Analysis'!$AH$7:$CM$7,FALSE)),"") -> A | Q65: =IF(INDEX('KPI Analysis'!$CO$7:$EU$123,MATCH($A65,'KPI Analysis'!$CO$7:$CO$123,FALSE),MATCH(P$8,'KPI Analysis'!$CO$7:$EU$7,FALSE))="OD","OD",INDEX('KPI Analysis'!$EW$7:$HC$123,MATCH($A65,'KPI Analysis'!$EW$7:$EW$123,FALSE),MATCH(P$8,'KPI Analysis'!$EW$7:$HC$7,FALSE))) -> 0.94 | R65: =IF( OR( INDEX('KPI Analysis'!$AH$7:$CM$123, MATCH($A65,'KPI Analysis'!$AH$7:$AH$123,FALSE), MATCH(R$8,'KPI Analysis'!$AH$7:$CM$7,FALSE) )="R", INDEX('KPI Analysis'!$AH$7:$CM$123, MATCH($A65,'KPI Analysis'!$AH$7:$AH$123,FALSE), MATCH(R$8,'KPI Analysis'!$AH$7:$CM$7,FALSE) )="G", INDEX('KPI Analysis'!$AH$7:$CM$123, MATCH($A65,'KPI Analysis'!$AH$7:$AH$123,FALSE), MATCH(R$8,'KPI Analysis'!$AH$7:$CM$7,FALSE) )="A"), INDEX('KPI Analysis'!$AH$7:$CM$123,MATCH($A65,'KPI Analysis'!$AH$7:$AH$123,FALSE),MATCH(R$8,'KPI Analysis'!$AH$7:$CM$7,FALSE)),"") -> G | S65: =IF(INDEX('KPI Analysis'!$CO$7:$EU$123,MATCH($A65,'KPI Analysis'!$CO$7:$CO$123,FALSE),MATCH(R$8,'KPI Analysis'!$CO$7:$EU$7,FALSE))="OD","OD",INDEX('KPI Analysis'!$EW$7:$HC$123,MATCH($A65,'KPI Analysis'!$EW$7:$EW$123,FALSE),MATCH(R$8,'KPI Analysis'!$EW$7:$HC$7,FALSE))) -> 0.96 | T65: =IF( OR( INDEX('KPI Analysis'!$AH$7:$CM$123, MATCH($A65,'KPI Analysis'!$AH$7:$AH$123,FALSE), MATCH(T$8,'KPI Analysis'!$AH$7:$CM$7,FALSE) )="R", INDEX('KPI Analysis'!$AH$7:$CM$123, MATCH($A65,'KPI Analysis'!$AH$7:$AH$123,FALSE), MATCH(T$8,'KPI Analysis'!$AH$7:$CM$7,FALSE) )="G", INDEX('KPI Analysis'!$AH$7:$CM$123, MATCH($A65,'KPI Analysis'!$AH$7:$AH$123,FALSE), MATCH(T$8,'KPI Analysis'!$AH$7:$CM$7,FALSE) )="A"), INDEX('KPI Analysis'!$AH$7:$CM$123,MATCH($A65,'KPI Analysis'!$AH$7:$AH$123,FALSE),MATCH(T$8,'KPI Analysis'!$AH$7:$CM$7,FALSE)),"") | U65: =IF(INDEX('KPI Analysis'!$CO$7:$EU$123,MATCH($A65,'KPI Analysis'!$CO$7:$CO$123,FALSE),MATCH(T$8,'KPI Analysis'!$CO$7:$EU$7,FALSE))="OD","OD",INDEX('KPI Analysis'!$EW$7:$HC$123,MATCH($A65,'KPI Analysis'!$EW$7:$EW$123,FALSE),MATCH(T$8,'KPI Analysis'!$EW$7:$HC$7,FALSE))) -> OD | V65: =IF( OR( INDEX('KPI Analysis'!$AH$7:$CM$123, MATCH($A65,'KPI Analysis'!$AH$7:$AH$123,FALSE), MATCH(V$8,'KPI Analysis'!$AH$7:$CM$7,FALSE) )="R", INDEX('KPI Analysis'!$AH$7:$CM$123, MATCH($A65,'KPI Analysis'!$AH$7:$AH$123,FALSE), MATCH(V$8,'KPI Analysis'!$AH$7:$CM$7,FALSE) )="G", INDEX('KPI Analysis'!$AH$7:$CM$123, MATCH($A65,'KPI Analysis'!$AH$7:$AH$123,FALSE), MATCH(V$8,'KPI Analysis'!$AH$7:$CM$7,FALSE) )="A"), INDEX('KPI Analysis'!$AH$7:$CM$123,MATCH($A65,'KPI Analysis'!$AH$7:$AH$123,FALSE),MATCH(V$8,'KPI Analysis'!$AH$7:$CM$7,FALSE)),"") | W65: =IF(INDEX('KPI Analysis'!$CO$7:$EU$123,MATCH($A65,'KPI Analysis'!$CO$7:$CO$123,FALSE),MATCH(V$8,'KPI Analysis'!$CO$7:$EU$7,FALSE))="OD","OD",INDEX('KPI Analysis'!$EW$7:$HC$123,MATCH($A65,'KPI Analysis'!$EW$7:$EW$123,FALSE),MATCH(V$8,'KPI Analysis'!$EW$7:$HC$7,FALSE))) -> OD | X65: =IF( OR( INDEX('KPI Analysis'!$AH$7:$CM$123, MATCH($A65,'KPI Analysis'!$AH$7:$AH$123,FALSE), MATCH(X$8,'KPI Analysis'!$AH$7:$CM$7,FALSE) )="R", INDEX('KPI Analysis'!$AH$7:$CM$123, MATCH($A65,'KPI Analysis'!$AH$7:$AH$123,FALSE), MATCH(X$8,'KPI Analysis'!$AH$7:$CM$7,FALSE) )="G", INDEX('KPI Analysis'!$AH$7:$CM$123, MATCH($A65,'KPI Analysis'!$AH$7:$AH$123,FALSE), MATCH(X$8,'KPI Analysis'!$AH$7:$CM$7,FALSE) )="A"), INDEX('KPI Analysis'!$AH$7:$CM$123,MATCH($A65,'KPI Analysis'!$AH$7:$AH$123,FALSE),MATCH(X$8,'KPI Analysis'!$AH$7:$CM$7,FALSE)),"") | Y65: =IF(INDEX('KPI Analysis'!$CO$7:$EU$123,MATCH($A65,'KPI Analysis'!$CO$7:$CO$123,FALSE),MATCH(X$8,'KPI Analysis'!$CO$7:$EU$7,FALSE))="OD","OD",INDEX('KPI Analysis'!$EW$7:$HC$123,MATCH($A65,'KPI Analysis'!$EW$7:$EW$123,FALSE),MATCH(X$8,'KPI Analysis'!$EW$7:$HC$7,FALSE))) -> OD | Z65: (Target 95%) | AC65: EW HC | AE65: =INDEX('KPI Analysis'!$CO$7:$EU$123,MATCH($A65,'KPI Analysis'!$CO$7:$CO$123,FALSE),MATCH(AE$8,'KPI Analysis'!$CO$7:$EU$7,FALSE)) -> 0.98947368 | AF65: =INDEX('KPI Analysis'!$CO$7:$EU$123,MATCH($A65,'KPI Analysis'!$CO$7:$CO$123,FALSE),MATCH(AF$8,'KPI Analysis'!$CO$7:$EU$7,FALSE)) -> 1.0105263 | AG65: =INDEX('KPI Analysis'!$CO$7:$EU$123,MATCH($A65,'KPI Analysis'!$CO$7:$CO$123,FALSE),MATCH(AG$8,'KPI Analysis'!$CO$7:$EU$7,FALSE)) -> OD | AH65: =INDEX('KPI Analysis'!$CO$7:$EU$123,MATCH($A65,'KPI Analysis'!$CO$7:$CO$123,FALSE),MATCH(AH$8,'KPI Analysis'!$CO$7:$EU$7,FALSE)) -> OD | AI65: =INDEX('KPI Analysis'!$CO$7:$EU$123,MATCH($A65,'KPI Analysis'!$CO$7:$CO$123,FALSE),MATCH(AI$8,'KPI Analysis'!$CO$7:$EU$7,FALSE)) -> OD
A66: =F66&"-"&C66 -> Bridgend Manuf-KPI Q1 | B66: =+'KPI Stats'!G59 -> Over | C66: =+'KPI Stats'!C59 -> KPI Q1 | F66: =+'KPI Stats'!$B$56 -> Bridgend Manuf | G66: =+'KPI Stats'!$B$56 -> Bridgend Manuf | H66: W | I66: =+'KPI Stats'!$F$56 -> 42 | J66: =+'KPI Stats'!D59 -> Quality | K66: =+'KPI Stats'!E59 -> Customer Complaints | L66: =+'KPI Stats'!F59 -> Count | M66: Act Result | P66: =IF( OR( INDEX('KPI Analysis'!$AH$7:$CM$123, MATCH($A66,'KPI Analysis'!$AH$7:$AH$123,FALSE), MATCH(P$8,'KPI Analysis'!$AH$7:$CM$7,FALSE) )="R", INDEX('KPI Analysis'!$AH$7:$CM$123, MATCH($A66,'KPI Analysis'!$AH$7:$AH$123,FALSE), MATCH(P$8,'KPI Analysis'!$AH$7:$CM$7,FALSE) )="G", INDEX('KPI Analysis'!$AH$7:$CM$123, MATCH($A66,'KPI Analysis'!$AH$7:$AH$123,FALSE), MATCH(P$8,'KPI Analysis'!$AH$7:$CM$7,FALSE) )="A"), INDEX('KPI Analysis'!$AH$7:$CM$123,MATCH($A66,'KPI Analysis'!$AH$7:$AH$123,FALSE),MATCH(P$8,'KPI Analysis'!$AH$7:$CM$7,FALSE)),"") -> G | Q66: =IF(INDEX('KPI Analysis'!$CO$7:$EU$123,MATCH($A66,'KPI Analysis'!$CO$7:$CO$123,FALSE),MATCH(P$8,'KPI Analysis'!$CO$7:$EU$7,FALSE))="OD","OD",INDEX('KPI Analysis'!$EW$7:$HC$123,MATCH($A66,'KPI Analysis'!$EW$7:$EW$123,FALSE),MATCH(P$8,'KPI Analysis'!$EW$7:$HC$7,FALSE))) -> 2 | R66: =IF( OR( INDEX('KPI Analysis'!$AH$7:$CM$123, MATCH($A66,'KPI Analysis'!$AH$7:$AH$123,FALSE), MATCH(R$8,'KPI Analysis'!$AH$7:$CM$7,FALSE) )="R", INDEX('KPI Analysis'!$AH$7:$CM$123, MATCH($A66,'KPI Analysis'!$AH$7:$AH$123,FALSE), MATCH(R$8,'KPI Analysis'!$AH$7:$CM$7,FALSE) )="G", INDEX('KPI Analysis'!$AH$7:$CM$123, MATCH($A66,'KPI Analysis'!$AH$7:$AH$123,FALSE), MATCH(R$8,'KPI Analysis'!$AH$7:$CM$7,FALSE) )="A"), INDEX('KPI Analysis'!$AH$7:$CM$123,MATCH($A66,'KPI Analysis'!$AH$7:$AH$123,FALSE),MATCH(R$8,'KPI Analysis'!$AH$7:$CM$7,FALSE)),"") -> G | S66: =IF(INDEX('KPI Analysis'!$CO$7:$EU$123,MATCH($A66,'KPI Analysis'!$CO$7:$CO$123,FALSE),MATCH(R$8,'KPI Analysis'!$CO$7:$EU$7,FALSE))="OD","OD",INDEX('KPI Analysis'!$EW$7:$HC$123,MATCH($A66,'KPI Analysis'!$EW$7:$EW$123,FALSE),MATCH(R$8,'KPI Analysis'!$EW$7:$HC$7,FALSE))) -> 3 | T66: =IF( OR( INDEX('KPI Analysis'!$AH$7:$CM$123, MATCH($A66,'KPI Analysis'!$AH$7:$AH$123,FALSE), MATCH(T$8,'KPI Analysis'!$AH$7:$CM$7,FALSE) )="R", INDEX('KPI Analysis'!$AH$7:$CM$123, MATCH($A66,'KPI Analysis'!$AH$7:$AH$123,FALSE), MATCH(T$8,'KPI Analysis'!$AH$7:$CM$7,FALSE) )="G", INDEX('KPI Analysis'!$AH$7:$CM$123, MATCH($A66,'KPI Analysis'!$AH$7:$AH$123,FALSE), MATCH(T$8,'KPI Analysis'!$AH$7:$CM$7,FALSE) )="A"), INDEX('KPI Analysis'!$AH$7:$CM$123,MATCH($A66,'KPI Analysis'!$AH$7:$AH$123,FALSE),MATCH(T$8,'KPI Analysis'!$AH$7:$CM$7,FALSE)),"") | U66: =IF(INDEX('KPI Analysis'!$CO$7:$EU$123,MATCH($A66,'KPI Analysis'!$CO$7:$CO$123,FALSE),MATCH(T$8,'KPI Analysis'!$CO$7:$EU$7,FALSE))="OD","OD",INDEX('KPI Analysis'!$EW$7:$HC$123,MATCH($A66,'KPI Analysis'!$EW$7:$EW$123,FALSE),MATCH(T$8,'KPI Analysis'!$EW$7:$HC$7,FALSE))) -> OD | V66: =IF( OR( INDEX('KPI Analysis'!$AH$7:$CM$123, MATCH($A66,'KPI Analysis'!$AH$7:$AH$123,FALSE), MATCH(V$8,'KPI Analysis'!$AH$7:$CM$7,FALSE) )="R", INDEX('KPI Analysis'!$AH$7:$CM$123, MATCH($A66,'KPI Analysis'!$AH$7:$AH$123,FALSE), MATCH(V$8,'KPI Analysis'!$AH$7:$CM$7,FALSE) )="G", INDEX('KPI Analysis'!$AH$7:$CM$123, MATCH($A66,'KPI Analysis'!$AH$7:$AH$123,FALSE), MATCH(V$8,'KPI Analysis'!$AH$7:$CM$7,FALSE) )="A"), INDEX('KPI Analysis'!$AH$7:$CM$123,MATCH($A66,'KPI Analysis'!$AH$7:$AH$123,FALSE),MATCH(V$8,'KPI Analysis'!$AH$7:$CM$7,FALSE)),"") | W66: =IF(INDEX('KPI Analysis'!$CO$7:$EU$123,MATCH($A66,'KPI Analysis'!$CO$7:$CO$123,FALSE),MATCH(V$8,'KPI Analysis'!$CO$7:$EU$7,FALSE))="OD","OD",INDEX('KPI Analysis'!$EW$7:$HC$123,MATCH($A66,'KPI Analysis'!$EW$7:$EW$123,FALSE),MATCH(V$8,'KPI Analysis'!$EW$7:$HC$7,FALSE))) -> OD | X66: =IF( OR( INDEX('KPI Analysis'!$AH$7:$CM$123, MATCH($A66,'KPI Analysis'!$AH$7:$AH$123,FALSE), MATCH(X$8,'KPI Analysis'!$AH$7:$CM$7,FALSE) )="R", INDEX('KPI Analysis'!$AH$7:$CM$123, MATCH($A66,'KPI Analysis'!$AH$7:$AH$123,FALSE), MATCH(X$8,'KPI Analysis'!$AH$7:$CM$7,FALSE) )="G", INDEX('KPI Analysis'!$AH$7:$CM$123, MATCH($A66,'KPI Analysis'!$AH$7:$AH$123,FALSE), MATCH(X$8,'KPI Analysis'!$AH$7:$CM$7,FALSE) )="A"), INDEX('KPI Analysis'!$AH$7:$CM$123,MATCH($A66,'KPI Analysis'!$AH$7:$AH$123,FALSE),MATCH(X$8,'KPI Analysis'!$AH$7:$CM$7,FALSE)),"") | Y66: =IF(INDEX('KPI Analysis'!$CO$7:$EU$123,MATCH($A66,'KPI Analysis'!$CO$7:$CO$123,FALSE),MATCH(X$8,'KPI Analysis'!$CO$7:$EU$7,FALSE))="OD","OD",INDEX('KPI Analysis'!$EW$7:$HC$123,MATCH($A66,'KPI Analysis'!$EW$7:$EW$123,FALSE),MATCH(X$8,'KPI Analysis'!$EW$7:$HC$7,FALSE))) -> OD | Z66: (Target 3) | AC66: EW HC | AE66: =INDEX('KPI Analysis'!$CO$7:$EU$123,MATCH($A66,'KPI Analysis'!$CO$7:$CO$123,FALSE),MATCH(AE$8,'KPI Analysis'!$CO$7:$EU$7,FALSE)) -> 1.5 | AF66: =INDEX('KPI Analysis'!$CO$7:$EU$123,MATCH($A66,'KPI Analysis'!$CO$7:$CO$123,FALSE),MATCH(AF$8,'KPI Analysis'!$CO$7:$EU$7,FALSE)) -> 1 | AG66: =INDEX('KPI Analysis'!$CO$7:$EU$123,MATCH($A66,'KPI Analysis'!$CO$7:$CO$123,FALSE),MATCH(AG$8,'KPI Analysis'!$CO$7:$EU$7,FALSE)) -> OD | AH66: =INDEX('KPI Analysis'!$CO$7:$EU$123,MATCH($A66,'KPI Analysis'!$CO$7:$CO$123,FALSE),MATCH(AH$8,'KPI Analysis'!$CO$7:$EU$7,FALSE)) -> OD | AI66: =INDEX('KPI Analysis'!$CO$7:$EU$123,MATCH($A66,'KPI Analysis'!$CO$7:$CO$123,FALSE),MATCH(AI$8,'KPI Analysis'!$CO$7:$EU$7,FALSE)) -> OD
A67: =F67&"-"&C67 -> Bridgend Manuf-KPI C1 | B67: =+'KPI Stats'!G60 -> Under | C67: =+'KPI Stats'!C60 -> KPI C1 | F67: =+'KPI Stats'!$B$56 -> Bridgend Manuf | G67: =+'KPI Stats'!$B$56 -> Bridgend Manuf | H67: W | I67: =+'KPI Stats'!$F$56 -> 42 | J67: =+'KPI Stats'!D60 -> Cost | K67: =+'KPI Stats'!E60 -> Production Value per Employee | L67: =+'KPI Stats'!F60 -> £'s | M67: =INDEX('KPI Analysis'!$CO$7:$EU$123,MATCH($A67,'KPI Analysis'!$CO$7:$CO$123,FALSE),MATCH(M$8,'KPI Analysis'!$CO$7:$EU$7,FALSE)) -> % of target | P67: =IF( OR( INDEX('KPI Analysis'!$AH$7:$CM$123, MATCH($A67,'KPI Analysis'!$AH$7:$AH$123,FALSE), MATCH(P$8,'KPI Analysis'!$AH$7:$CM$7,FALSE) )="R", INDEX('KPI Analysis'!$AH$7:$CM$123, MATCH($A67,'KPI Analysis'!$AH$7:$AH$123,FALSE), MATCH(P$8,'KPI Analysis'!$AH$7:$CM$7,FALSE) )="G", INDEX('KPI Analysis'!$AH$7:$CM$123, MATCH($A67,'KPI Analysis'!$AH$7:$AH$123,FALSE), MATCH(P$8,'KPI Analysis'!$AH$7:$CM$7,FALSE) )="A"), INDEX('KPI Analysis'!$AH$7:$CM$123,MATCH($A67,'KPI Analysis'!$AH$7:$AH$123,FALSE),MATCH(P$8,'KPI Analysis'!$AH$7:$CM$7,FALSE)),"") -> R | Q67: =INDEX('KPI Analysis'!$CO$7:$EU$123,MATCH($A67,'KPI Analysis'!$CO$7:$CO$123,FALSE),MATCH(P$8,'KPI Analysis'!$CO$7:$EU$7,FALSE)) -> 0.87226597 | R67: =IF( OR( INDEX('KPI Analysis'!$AH$7:$CM$123, MATCH($A67,'KPI Analysis'!$AH$7:$AH$123,FALSE), MATCH(R$8,'KPI Analysis'!$AH$7:$CM$7,FALSE) )="R", INDEX('KPI Analysis'!$AH$7:$CM$123, MATCH($A67,'KPI Analysis'!$AH$7:$AH$123,FALSE), MATCH(R$8,'KPI Analysis'!$AH$7:$CM$7,FALSE) )="G", INDEX('KPI Analysis'!$AH$7:$CM$123, MATCH($A67,'KPI Analysis'!$AH$7:$AH$123,FALSE), MATCH(R$8,'KPI Analysis'!$AH$7:$CM$7,FALSE) )="A"), INDEX('KPI Analysis'!$AH$7:$CM$123,MATCH($A67,'KPI Analysis'!$AH$7:$AH$123,FALSE),MATCH(R$8,'KPI Analysis'!$AH$7:$CM$7,FALSE)),"") -> G | S67: =INDEX('KPI Analysis'!$CO$7:$EU$123,MATCH($A67,'KPI Analysis'!$CO$7:$CO$123,FALSE),MATCH(R$8,'KPI Analysis'!$CO$7:$EU$7,FALSE)) -> 1.3407699 | T67: =IF( OR( INDEX('KPI Analysis'!$AH$7:$CM$123, MATCH($A67,'KPI Analysis'!$AH$7:$AH$123,FALSE), MATCH(T$8,'KPI Analysis'!$AH$7:$CM$7,FALSE) )="R", INDEX('KPI Analysis'!$AH$7:$CM$123, MATCH($A67,'KPI Analysis'!$AH$7:$AH$123,FALSE), MATCH(T$8,'KPI Analysis'!$AH$7:$CM$7,FALSE) )="G", INDEX('KPI Analysis'!$AH$7:$CM$123, MATCH($A67,'KPI Analysis'!$AH$7:$AH$123,FALSE), MATCH(T$8,'KPI Analysis'!$AH$7:$CM$7,FALSE) )="A"), INDEX('KPI Analysis'!$AH$7:$CM$123,MATCH($A67,'KPI Analysis'!$AH$7:$AH$123,FALSE),MATCH(T$8,'KPI Analysis'!$AH$7:$CM$7,FALSE)),"") | U67: =INDEX('KPI Analysis'!$CO$7:$EU$123,MATCH($A67,'KPI Analysis'!$CO$7:$CO$123,FALSE),MATCH(T$8,'KPI Analysis'!$CO$7:$EU$7,FALSE)) -> OD | V67: =IF( OR( INDEX('KPI Analysis'!$AH$7:$CM$123, MATCH($A67,'KPI Analysis'!$AH$7:$AH$123,FALSE), MATCH(V$8,'KPI Analysis'!$AH$7:$CM$7,FALSE) )="R", INDEX('KPI Analysis'!$AH$7:$CM$123, MATCH($A67,'KPI Analysis'!$AH$7:$AH$123,FALSE), MATCH(V$8,'KPI Analysis'!$AH$7:$CM$7,FALSE) )="G", INDEX('KPI Analysis'!$AH$7:$CM$123, MATCH($A67,'KPI Analysis'!$AH$7:$AH$123,FALSE), MATCH(V$8,'KPI Analysis'!$AH$7:$CM$7,FALSE) )="A"), INDEX('KPI Analysis'!$AH$7:$CM$123,MATCH($A67,'KPI Analysis'!$AH$7:$AH$123,FALSE),MATCH(V$8,'KPI Analysis'!$AH$7:$CM$7,FALSE)),"") | W67: =INDEX('KPI Analysis'!$CO$7:$EU$123,MATCH($A67,'KPI Analysis'!$CO$7:$CO$123,FALSE),MATCH(V$8,'KPI Analysis'!$CO$7:$EU$7,FALSE)) -> OD | X67: =IF( OR( INDEX('KPI Analysis'!$AH$7:$CM$123, MATCH($A67,'KPI Analysis'!$AH$7:$AH$123,FALSE), MATCH(X$8,'KPI Analysis'!$AH$7:$CM$7,FALSE) )="R", INDEX('KPI Analysis'!$AH$7:$CM$123, MATCH($A67,'KPI Analysis'!$AH$7:$AH$123,FALSE), MATCH(X$8,'KPI Analysis'!$AH$7:$CM$7,FALSE) )="G", INDEX('KPI Analysis'!$AH$7:$CM$123, MATCH($A67,'KPI Analysis'!$AH$7:$AH$123,FALSE), MATCH(X$8,'KPI Analysis'!$AH$7:$CM$7,FALSE) )="A"), INDEX('KPI Analysis'!$AH$7:$CM$123,MATCH($A67,'KPI Analysis'!$AH$7:$AH$123,FALSE),MATCH(X$8,'KPI Analysis'!$AH$7:$CM$7,FALSE)),"") | Y67: =INDEX('KPI Analysis'!$CO$7:$EU$123,MATCH($A67,'KPI Analysis'!$CO$7:$CO$123,FALSE),MATCH(X$8,'KPI Analysis'!$CO$7:$EU$7,FALSE)) -> OD | AC67: Co EU | AE67: =INDEX('KPI Analysis'!$CO$7:$EU$123,MATCH($A67,'KPI Analysis'!$CO$7:$CO$123,FALSE),MATCH(AE$8,'KPI Analysis'!$CO$7:$EU$7,FALSE)) -> 0.87226597 | AF67: =INDEX('KPI Analysis'!$CO$7:$EU$123,MATCH($A67,'KPI Analysis'!$CO$7:$CO$123,FALSE),MATCH(AF$8,'KPI Analysis'!$CO$7:$EU$7,FALSE)) -> 1.3407699 | AG67: =INDEX('KPI Analysis'!$CO$7:$EU$123,MATCH($A67,'KPI Analysis'!$CO$7:$CO$123,FALSE),MATCH(AG$8,'KPI Analysis'!$CO$7:$EU$7,FALSE)) -> OD | AH67: =INDEX('KPI Analysis'!$CO$7:$EU$123,MATCH($A67,'KPI Analysis'!$CO$7:$CO$123,FALSE),MATCH(AH$8,'KPI Analysis'!$CO$7:$EU$7,FALSE)) -> OD | AI67: =INDEX('KPI Analysis'!$CO$7:$EU$123,MATCH($A67,'KPI Analysis'!$CO$7:$CO$123,FALSE),MATCH(AI$8,'KPI Analysis'!$CO$7:$EU$7,FALSE)) -> OD
A70: =F70&"-"&C70 -> Maybole Manuf-KPI P1 | B70: =+'KPI Stats'!G63 -> Under | C70: =+'KPI Stats'!C63 -> KPI P1 | F70: =+'KPI Stats'!$B$62 -> Maybole Manuf | G70: =+'KPI Stats'!$C$62 -> Scott McMillan | H70: W | I70: =+'KPI Stats'!$F$62 -> 42 | J70: =+'KPI Stats'!D63 -> Productivity | K70: =+'KPI Stats'!E63 -> Production Value | L70: =+'KPI Stats'!F63 -> £'s | M70: =INDEX('KPI Analysis'!$CO$7:$EU$123,MATCH($A70,'KPI Analysis'!$CO$7:$CO$123,FALSE),MATCH(M$8,'KPI Analysis'!$CO$7:$EU$7,FALSE)) -> % of target | P70: =IF(INDEX('KPI Analysis'!$AH$7:$CM$123,MATCH($A70,'KPI Analysis'!$AH$7:$AH$123,FALSE),MATCH(P$8,'KPI Analysis'!$AH$7:$CM$7,FALSE))="OD","",INDEX('KPI Analysis'!$AH$7:$CM$123,MATCH($A70,'KPI Analysis'!$AH$7:$AH$123,FALSE),MATCH(P$8,'KPI Analysis'!$AH$7:$CM$7,FALSE))) -> R | Q70: =INDEX('KPI Analysis'!$CO$7:$EU$123,MATCH($A70,'KPI Analysis'!$CO$7:$CO$123,FALSE),MATCH(P$8,'KPI Analysis'!$CO$7:$EU$7,FALSE)) -> 0.79375579 | R70: =IF(INDEX('KPI Analysis'!$AH$7:$CM$123,MATCH($A70,'KPI Analysis'!$AH$7:$AH$123,FALSE),MATCH(R$8,'KPI Analysis'!$AH$7:$CM$7,FALSE))="OD","",INDEX('KPI Analysis'!$AH$7:$CM$123,MATCH($A70,'KPI Analysis'!$AH$7:$AH$123,FALSE),MATCH(R$8,'KPI Analysis'!$AH$7:$CM$7,FALSE))) -> R | S70: =INDEX('KPI Analysis'!$CO$7:$EU$123,MATCH($A70,'KPI Analysis'!$CO$7:$CO$123,FALSE),MATCH(R$8,'KPI Analysis'!$CO$7:$EU$7,FALSE)) -> 0.78846408 | T70: =IF(INDEX('KPI Analysis'!$AH$7:$CM$123,MATCH($A70,'KPI Analysis'!$AH$7:$AH$123,FALSE),MATCH(T$8,'KPI Analysis'!$AH$7:$CM$7,FALSE))="OD","",INDEX('KPI Analysis'!$AH$7:$CM$123,MATCH($A70,'KPI Analysis'!$AH$7:$AH$123,FALSE),MATCH(T$8,'KPI Analysis'!$AH$7:$CM$7,FALSE))) -> G | U70: =INDEX('KPI Analysis'!$CO$7:$EU$123,MATCH($A70,'KPI Analysis'!$CO$7:$CO$123,FALSE),MATCH(T$8,'KPI Analysis'!$CO$7:$EU$7,FALSE)) -> 1.0159933 | V70: =IF(INDEX('KPI Analysis'!$AH$7:$CM$123,MATCH($A70,'KPI Analysis'!$AH$7:$AH$123,FALSE),MATCH(V$8,'KPI Analysis'!$AH$7:$CM$7,FALSE))="OD","",INDEX('KPI Analysis'!$AH$7:$CM$123,MATCH($A70,'KPI Analysis'!$AH$7:$AH$123,FALSE),MATCH(V$8,'KPI Analysis'!$AH$7:$CM$7,FALSE))) -> R | W70: =INDEX('KPI Analysis'!$CO$7:$EU$123,MATCH($A70,'KPI Analysis'!$CO$7:$CO$123,FALSE),MATCH(V$8,'KPI Analysis'!$CO$7:$EU$7,FALSE)) -> 0.67405386 | X70: =IF(INDEX('KPI Analysis'!$AH$7:$CM$123,MATCH($A70,'KPI Analysis'!$AH$7:$AH$123,FALSE),MATCH(X$8,'KPI Analysis'!$AH$7:$CM$7,FALSE))="OD","",INDEX('KPI Analysis'!$AH$7:$CM$123,MATCH($A70,'KPI Analysis'!$AH$7:$AH$123,FALSE),MATCH(X$8,'KPI Analysis'!$AH$7:$CM$7,FALSE))) -> R | Y70: =INDEX('KPI Analysis'!$CO$7:$EU$123,MATCH($A70,'KPI Analysis'!$CO$7:$CO$123,FALSE),MATCH(X$8,'KPI Analysis'!$CO$7:$EU$7,FALSE)) -> 0.80557656 | AC70: Co EU | AE70: =INDEX('KPI Analysis'!$CO$7:$EU$123,MATCH($A70,'KPI Analysis'!$CO$7:$CO$123,FALSE),MATCH(AE$8,'KPI Analysis'!$CO$7:$EU$7,FALSE)) -> 0.79375579 | AF70: =INDEX('KPI Analysis'!$CO$7:$EU$123,MATCH($A70,'KPI Analysis'!$CO$7:$CO$123,FALSE),MATCH(AF$8,'KPI Analysis'!$CO$7:$EU$7,FALSE)) -> 0.78846408 | AG70: =INDEX('KPI Analysis'!$CO$7:$EU$123,MATCH($A70,'KPI Analysis'!$CO$7:$CO$123,FALSE),MATCH(AG$8,'KPI Analysis'!$CO$7:$EU$7,FALSE)) -> 1.0159933 | AH70: =INDEX('KPI Analysis'!$CO$7:$EU$123,MATCH($A70,'KPI Analysis'!$CO$7:$CO$123,FALSE),MATCH(AH$8,'KPI Analysis'!$CO$7:$EU$7,FALSE)) -> 0.67405386 | AI70: =INDEX('KPI Analysis'!$CO$7:$EU$123,MATCH($A70,'KPI Analysis'!$CO$7:$CO$123,FALSE),MATCH(AI$8,'KPI Analysis'!$CO$7:$EU$7,FALSE)) -> 0.80557656
A71: =F71&"-"&C71 -> Maybole Manuf-KPI D1 | B71: =+'KPI Stats'!G64 -> Under | C71: =+'KPI Stats'!C64 -> KPI D1 | F71: =+'KPI Stats'!$B$62 -> Maybole Manuf | G71: =+'KPI Stats'!$B$62 -> Maybole Manuf | H71: W | I71: =+'KPI Stats'!$F$62 -> 42 | J71: =+'KPI Stats'!D64 -> Delivery | K71: =+'KPI Stats'!E64 -> Percentage of OTIF that achieved delivery date | L71: =+'KPI Stats'!F64 -> Percentage | M71: Act Result | P71: =IF( OR( INDEX('KPI Analysis'!$AH$7:$CM$123, MATCH($A71,'KPI Analysis'!$AH$7:$AH$123,FALSE), MATCH(P$8,'KPI Analysis'!$AH$7:$CM$7,FALSE) )="R", INDEX('KPI Analysis'!$AH$7:$CM$123, MATCH($A71,'KPI Analysis'!$AH$7:$AH$123,FALSE), MATCH(P$8,'KPI Analysis'!$AH$7:$CM$7,FALSE) )="G", INDEX('KPI Analysis'!$AH$7:$CM$123, MATCH($A71,'KPI Analysis'!$AH$7:$AH$123,FALSE), MATCH(P$8,'KPI Analysis'!$AH$7:$CM$7,FALSE) )="A"), INDEX('KPI Analysis'!$AH$7:$CM$123,MATCH($A71,'KPI Analysis'!$AH$7:$AH$123,FALSE),MATCH(P$8,'KPI Analysis'!$AH$7:$CM$7,FALSE)),"") -> A | Q71: =INDEX('KPI Analysis'!$EW$7:$HC$123,MATCH($A71,'KPI Analysis'!$EW$7:$EW$123,FALSE),MATCH(P$8,'KPI Analysis'!$EW$7:$HC$7,FALSE)) -> 0.92 | R71: =IF( OR( INDEX('KPI Analysis'!$AH$7:$CM$123, MATCH($A71,'KPI Analysis'!$AH$7:$AH$123,FALSE), MATCH(R$8,'KPI Analysis'!$AH$7:$CM$7,FALSE) )="R", INDEX('KPI Analysis'!$AH$7:$CM$123, MATCH($A71,'KPI Analysis'!$AH$7:$AH$123,FALSE), MATCH(R$8,'KPI Analysis'!$AH$7:$CM$7,FALSE) )="G", INDEX('KPI Analysis'!$AH$7:$CM$123, MATCH($A71,'KPI Analysis'!$AH$7:$AH$123,FALSE), MATCH(R$8,'KPI Analysis'!$AH$7:$CM$7,FALSE) )="A"), INDEX('KPI Analysis'!$AH$7:$CM$123,MATCH($A71,'KPI Analysis'!$AH$7:$AH$123,FALSE),MATCH(R$8,'KPI Analysis'!$AH$7:$CM$7,FALSE)),"") -> G | S71: =IF(INDEX('KPI Analysis'!$CO$7:$EU$123,MATCH($A71,'KPI Analysis'!$CO$7:$CO$123,FALSE),MATCH(R$8,'KPI Analysis'!$CO$7:$EU$7,FALSE))="OD","OD",INDEX('KPI Analysis'!$EW$7:$HC$123,MATCH($A71,'KPI Analysis'!$EW$7:$EW$123,FALSE),MATCH(R$8,'KPI Analysis'!$EW$7:$HC$7,FALSE))) -> 0.95 | T71: =IF( OR( INDEX('KPI Analysis'!$AH$7:$CM$123, MATCH($A71,'KPI Analysis'!$AH$7:$AH$123,FALSE), MATCH(T$8,'KPI Analysis'!$AH$7:$CM$7,FALSE) )="R", INDEX('KPI Analysis'!$AH$7:$CM$123, MATCH($A71,'KPI Analysis'!$AH$7:$AH$123,FALSE), MATCH(T$8,'KPI Analysis'!$AH$7:$CM$7,FALSE) )="G", INDEX('KPI Analysis'!$AH$7:$CM$123, MATCH($A71,'KPI Analysis'!$AH$7:$AH$123,FALSE), MATCH(T$8,'KPI Analysis'!$AH$7:$CM$7,FALSE) )="A"), INDEX('KPI Analysis'!$AH$7:$CM$123,MATCH($A71,'KPI Analysis'!$AH$7:$AH$123,FALSE),MATCH(T$8,'KPI Analysis'!$AH$7:$CM$7,FALSE)),"") -> R | U71: =IF(INDEX('KPI Analysis'!$CO$7:$EU$123,MATCH($A71,'KPI Analysis'!$CO$7:$CO$123,FALSE),MATCH(T$8,'KPI Analysis'!$CO$7:$EU$7,FALSE))="OD","OD",INDEX('KPI Analysis'!$EW$7:$HC$123,MATCH($A71,'KPI Analysis'!$EW$7:$EW$123,FALSE),MATCH(T$8,'KPI Analysis'!$EW$7:$HC$7,FALSE))) -> 0.89 | V71: =IF( OR( INDEX('KPI Analysis'!$AH$7:$CM$123, MATCH($A71,'KPI Analysis'!$AH$7:$AH$123,FALSE), MATCH(V$8,'KPI Analysis'!$AH$7:$CM$7,FALSE) )="R", INDEX('KPI Analysis'!$AH$7:$CM$123, MATCH($A71,'KPI Analysis'!$AH$7:$AH$123,FALSE), MATCH(V$8,'KPI Analysis'!$AH$7:$CM$7,FALSE) )="G", INDEX('KPI Analysis'!$AH$7:$CM$123, MATCH($A71,'KPI Analysis'!$AH$7:$AH$123,FALSE), MATCH(V$8,'KPI Analysis'!$AH$7:$CM$7,FALSE) )="A"), INDEX('KPI Analysis'!$AH$7:$CM$123,MATCH($A71,'KPI Analysis'!$AH$7:$AH$123,FALSE),MATCH(V$8,'KPI Analysis'!$AH$7:$CM$7,FALSE)),"") -> G | W71: =IF(INDEX('KPI Analysis'!$CO$7:$EU$123,MATCH($A71,'KPI Analysis'!$CO$7:$CO$123,FALSE),MATCH(V$8,'KPI Analysis'!$CO$7:$EU$7,FALSE))="OD","OD",INDEX('KPI Analysis'!$EW$7:$HC$123,MATCH($A71,'KPI Analysis'!$EW$7:$EW$123,FALSE),MATCH(V$8,'KPI Analysis'!$EW$7:$HC$7,FALSE))) -> 0.95 | X71: =IF( OR( INDEX('KPI Analysis'!$AH$7:$CM$123, MATCH($A71,'KPI Analysis'!$AH$7:$AH$123,FALSE), MATCH(X$8,'KPI Analysis'!$AH$7:$CM$7,FALSE) )="R", INDEX('KPI Analysis'!$AH$7:$CM$123, MATCH($A71,'KPI Analysis'!$AH$7:$AH$123,FALSE), MATCH(X$8,'KPI Analysis'!$AH$7:$CM$7,FALSE) )="G", INDEX('KPI Analysis'!$AH$7:$CM$123, MATCH($A71,'KPI Analysis'!$AH$7:$AH$123,FALSE), MATCH(X$8,'KPI Analysis'!$AH$7:$CM$7,FALSE) )="A"), INDEX('KPI Analysis'!$AH$7:$CM$123,MATCH($A71,'KPI Analysis'!$AH$7:$AH$123,FALSE),MATCH(X$8,'KPI Analysis'!$AH$7:$CM$7,FALSE)),"") -> A | Y71: =IF(INDEX('KPI Analysis'!$CO$7:$EU$123,MATCH($A71,'KPI Analysis'!$CO$7:$CO$123,FALSE),MATCH(X$8,'KPI Analysis'!$CO$7:$EU$7,FALSE))="OD","OD",INDEX('KPI Analysis'!$EW$7:$HC$123,MATCH($A71,'KPI Analysis'!$EW$7:$EW$123,FALSE),MATCH(X$8,'KPI Analysis'!$EW$7:$HC$7,FALSE))) -> 0.94 | Z71: (Target 95%) | AC71: EW HC | AE71: =INDEX('KPI Analysis'!$CO$7:$EU$123,MATCH($A71,'KPI Analysis'!$CO$7:$CO$123,FALSE),MATCH(AE$8,'KPI Analysis'!$CO$7:$EU$7,FALSE)) -> 0.96842105 | AF71: =INDEX('KPI Analysis'!$CO$7:$EU$123,MATCH($A71,'KPI Analysis'!$CO$7:$CO$123,FALSE),MATCH(AF$8,'KPI Analysis'!$CO$7:$EU$7,FALSE)) -> 1 | AG71: =INDEX('KPI Analysis'!$CO$7:$EU$123,MATCH($A71,'KPI Analysis'!$CO$7:$CO$123,FALSE),MATCH(AG$8,'KPI Analysis'!$CO$7:$EU$7,FALSE)) -> 0.93684211 | AH71: =INDEX('KPI Analysis'!$CO$7:$EU$123,MATCH($A71,'KPI Analysis'!$CO$7:$CO$123,FALSE),MATCH(AH$8,'KPI Analysis'!$CO$7:$EU$7,FALSE)) -> 1 | AI71: =INDEX('KPI Analysis'!$CO$7:$EU$123,MATCH($A71,'KPI Analysis'!$CO$7:$CO$123,FALSE),MATCH(AI$8,'KPI Analysis'!$CO$7:$EU$7,FALSE)) -> 0.98947368
A72: =F72&"-"&C72 -> Maybole Manuf-KPI Q1 | B72: =+'KPI Stats'!G65 -> Over | C72: =+'KPI Stats'!C65 -> KPI Q1 | F72: =+'KPI Stats'!$B$62 -> Maybole Manuf | G72: =+'KPI Stats'!$B$62 -> Maybole Manuf | H72: W | I72: =+'KPI Stats'!$F$62 -> 42 | J72: =+'KPI Stats'!D65 -> Quality | K72: =+'KPI Stats'!E65 -> Customer Complaints | L72: =+'KPI Stats'!F65 -> Count | M72: Act Result | P72: =IF( OR( INDEX('KPI Analysis'!$AH$7:$CM$123, MATCH($A72,'KPI Analysis'!$AH$7:$AH$123,FALSE), MATCH(P$8,'KPI Analysis'!$AH$7:$CM$7,FALSE) )="R", INDEX('KPI Analysis'!$AH$7:$CM$123, MATCH($A72,'KPI Analysis'!$AH$7:$AH$123,FALSE), MATCH(P$8,'KPI Analysis'!$AH$7:$CM$7,FALSE) )="G", INDEX('KPI Analysis'!$AH$7:$CM$123, MATCH($A72,'KPI Analysis'!$AH$7:$AH$123,FALSE), MATCH(P$8,'KPI Analysis'!$AH$7:$CM$7,FALSE) )="A"), INDEX('KPI Analysis'!$AH$7:$CM$123,MATCH($A72,'KPI Analysis'!$AH$7:$AH$123,FALSE),MATCH(P$8,'KPI Analysis'!$AH$7:$CM$7,FALSE)),"") -> R | Q72: =INDEX('KPI Analysis'!$EW$7:$HC$123,MATCH($A72,'KPI Analysis'!$EW$7:$EW$123,FALSE),MATCH(P$8,'KPI Analysis'!$EW$7:$HC$7,FALSE)) -> 1 | R72: =IF( OR( INDEX('KPI Analysis'!$AH$7:$CM$123, MATCH($A72,'KPI Analysis'!$AH$7:$AH$123,FALSE), MATCH(R$8,'KPI Analysis'!$AH$7:$CM$7,FALSE) )="R", INDEX('KPI Analysis'!$AH$7:$CM$123, MATCH($A72,'KPI Analysis'!$AH$7:$AH$123,FALSE), MATCH(R$8,'KPI Analysis'!$AH$7:$CM$7,FALSE) )="G", INDEX('KPI Analysis'!$AH$7:$CM$123, MATCH($A72,'KPI Analysis'!$AH$7:$AH$123,FALSE), MATCH(R$8,'KPI Analysis'!$AH$7:$CM$7,FALSE) )="A"), INDEX('KPI Analysis'!$AH$7:$CM$123,MATCH($A72,'KPI Analysis'!$AH$7:$AH$123,FALSE),MATCH(R$8,'KPI Analysis'!$AH$7:$CM$7,FALSE)),"") -> G | S72: =IF(INDEX('KPI Analysis'!$CO$7:$EU$123,MATCH($A72,'KPI Analysis'!$CO$7:$CO$123,FALSE),MATCH(R$8,'KPI Analysis'!$CO$7:$EU$7,FALSE))="OD","OD",INDEX('KPI Analysis'!$EW$7:$HC$123,MATCH($A72,'KPI Analysis'!$EW$7:$EW$123,FALSE),MATCH(R$8,'KPI Analysis'!$EW$7:$HC$7,FALSE))) -> 0 | T72: =IF( OR( INDEX('KPI Analysis'!$AH$7:$CM$123, MATCH($A72,'KPI Analysis'!$AH$7:$AH$123,FALSE), MATCH(T$8,'KPI Analysis'!$AH$7:$CM$7,FALSE) )="R", INDEX('KPI Analysis'!$AH$7:$CM$123, MATCH($A72,'KPI Analysis'!$AH$7:$AH$123,FALSE), MATCH(T$8,'KPI Analysis'!$AH$7:$CM$7,FALSE) )="G", INDEX('KPI Analysis'!$AH$7:$CM$123, MATCH($A72,'KPI Analysis'!$AH$7:$AH$123,FALSE), MATCH(T$8,'KPI Analysis'!$AH$7:$CM$7,FALSE) )="A"), INDEX('KPI Analysis'!$AH$7:$CM$123,MATCH($A72,'KPI Analysis'!$AH$7:$AH$123,FALSE),MATCH(T$8,'KPI Analysis'!$AH$7:$CM$7,FALSE)),"") -> G | U72: =IF(INDEX('KPI Analysis'!$CO$7:$EU$123,MATCH($A72,'KPI Analysis'!$CO$7:$CO$123,FALSE),MATCH(T$8,'KPI Analysis'!$CO$7:$EU$7,FALSE))="OD","OD",INDEX('KPI Analysis'!$EW$7:$HC$123,MATCH($A72,'KPI Analysis'!$EW$7:$EW$123,FALSE),MATCH(T$8,'KPI Analysis'!$EW$7:$HC$7,FALSE))) -> 0 | V72: =IF( OR( INDEX('KPI Analysis'!$AH$7:$CM$123, MATCH($A72,'KPI Analysis'!$AH$7:$AH$123,FALSE), MATCH(V$8,'KPI Analysis'!$AH$7:$CM$7,FALSE) )="R", INDEX('KPI Analysis'!$AH$7:$CM$123, MATCH($A72,'KPI Analysis'!$AH$7:$AH$123,FALSE), MATCH(V$8,'KPI Analysis'!$AH$7:$CM$7,FALSE) )="G", INDEX('KPI Analysis'!$AH$7:$CM$123, MATCH($A72,'KPI Analysis'!$AH$7:$AH$123,FALSE), MATCH(V$8,'KPI Analysis'!$AH$7:$CM$7,FALSE) )="A"), INDEX('KPI Analysis'!$AH$7:$CM$123,MATCH($A72,'KPI Analysis'!$AH$7:$AH$123,FALSE),MATCH(V$8,'KPI Analysis'!$AH$7:$CM$7,FALSE)),"") -> G | W72: =IF(INDEX('KPI Analysis'!$CO$7:$EU$123,MATCH($A72,'KPI Analysis'!$CO$7:$CO$123,FALSE),MATCH(V$8,'KPI Analysis'!$CO$7:$EU$7,FALSE))="OD","OD",INDEX('KPI Analysis'!$EW$7:$HC$123,MATCH($A72,'KPI Analysis'!$EW$7:$EW$123,FALSE),MATCH(V$8,'KPI Analysis'!$EW$7:$HC$7,FALSE))) -> 0 | X72: =IF( OR( INDEX('KPI Analysis'!$AH$7:$CM$123, MATCH($A72,'KPI Analysis'!$AH$7:$AH$123,FALSE), MATCH(X$8,'KPI Analysis'!$AH$7:$CM$7,FALSE) )="R", INDEX('KPI Analysis'!$AH$7:$CM$123, MATCH($A72,'KPI Analysis'!$AH$7:$AH$123,FALSE), MATCH(X$8,'KPI Analysis'!$AH$7:$CM$7,FALSE) )="G", INDEX('KPI Analysis'!$AH$7:$CM$123, MATCH($A72,'KPI Analysis'!$AH$7:$AH$123,FALSE), MATCH(X$8,'KPI Analysis'!$AH$7:$CM$7,FALSE) )="A"), INDEX('KPI Analysis'!$AH$7:$CM$123,MATCH($A72,'KPI Analysis'!$AH$7:$AH$123,FALSE),MATCH(X$8,'KPI Analysis'!$AH$7:$CM$7,FALSE)),"") -> R | Y72: =IF(INDEX('KPI Analysis'!$CO$7:$EU$123,MATCH($A72,'KPI Analysis'!$CO$7:$CO$123,FALSE),MATCH(X$8,'KPI Analysis'!$CO$7:$EU$7,FALSE))="OD","OD",INDEX('KPI Analysis'!$EW$7:$HC$123,MATCH($A72,'KPI Analysis'!$EW$7:$EW$123,FALSE),MATCH(X$8,'KPI Analysis'!$EW$7:$HC$7,FALSE))) -> 1 | Z72: (Target 0) Act Result Shown | AC72: EW HC | AE72: =INDEX('KPI Analysis'!$CO$7:$EU$123,MATCH($A72,'KPI Analysis'!$CO$7:$CO$123,FALSE),MATCH(AE$8,'KPI Analysis'!$CO$7:$EU$7,FALSE)) -> 1 | AF72: =INDEX('KPI Analysis'!$CO$7:$EU$123,MATCH($A72,'KPI Analysis'!$CO$7:$CO$123,FALSE),MATCH(AF$8,'KPI Analysis'!$CO$7:$EU$7,FALSE)) -> 0 | AG72: =INDEX('KPI Analysis'!$CO$7:$EU$123,MATCH($A72,'KPI Analysis'!$CO$7:$CO$123,FALSE),MATCH(AG$8,'KPI Analysis'!$CO$7:$EU$7,FALSE)) -> 0 | AH72: =INDEX('KPI Analysis'!$CO$7:$EU$123,MATCH($A72,'KPI Analysis'!$CO$7:$CO$123,FALSE),MATCH(AH$8,'KPI Analysis'!$CO$7:$EU$7,FALSE)) -> 0 | AI72: =INDEX('KPI Analysis'!$CO$7:$EU$123,MATCH($A72,'KPI Analysis'!$CO$7:$CO$123,FALSE),MATCH(AI$8,'KPI Analysis'!$CO$7:$EU$7,FALSE)) -> 1
A73: =F73&"-"&C73 -> Maybole Manuf-KPI C1 | B73: =+'KPI Stats'!G66 -> Under | C73: =+'KPI Stats'!C66 -> KPI C1 | F73: =+'KPI Stats'!$B$62 -> Maybole Manuf | G73: =+'KPI Stats'!$B$62 -> Maybole Manuf | H73: W | I73: =+'KPI Stats'!$F$62 -> 42 | J73: =+'KPI Stats'!D66 -> Cost | K73: =+'KPI Stats'!E66 -> Production Value per Employee | L73: =+'KPI Stats'!F66 -> £'s | M73: =INDEX('KPI Analysis'!$CO$7:$EU$123,MATCH($A73,'KPI Analysis'!$CO$7:$CO$123,FALSE),MATCH(M$8,'KPI Analysis'!$CO$7:$EU$7,FALSE)) -> % of target | P73: =IF(INDEX('KPI Analysis'!$AH$7:$CM$123,MATCH($A73,'KPI Analysis'!$AH$7:$AH$123,FALSE),MATCH(P$8,'KPI Analysis'!$AH$7:$CM$7,FALSE))="OD","",INDEX('KPI Analysis'!$AH$7:$CM$123,MATCH($A73,'KPI Analysis'!$AH$7:$AH$123,FALSE),MATCH(P$8,'KPI Analysis'!$AH$7:$CM$7,FALSE))) -> R | Q73: =INDEX('KPI Analysis'!$CO$7:$EU$123,MATCH($A73,'KPI Analysis'!$CO$7:$CO$123,FALSE),MATCH(P$8,'KPI Analysis'!$CO$7:$EU$7,FALSE)) -> 0.79396682 | R73: =IF(INDEX('KPI Analysis'!$AH$7:$CM$123,MATCH($A73,'KPI Analysis'!$AH$7:$AH$123,FALSE),MATCH(R$8,'KPI Analysis'!$AH$7:$CM$7,FALSE))="OD","",INDEX('KPI Analysis'!$AH$7:$CM$123,MATCH($A73,'KPI Analysis'!$AH$7:$AH$123,FALSE),MATCH(R$8,'KPI Analysis'!$AH$7:$CM$7,FALSE))) -> R | S73: =INDEX('KPI Analysis'!$CO$7:$EU$123,MATCH($A73,'KPI Analysis'!$CO$7:$CO$123,FALSE),MATCH(R$8,'KPI Analysis'!$CO$7:$EU$7,FALSE)) -> 0.78853695 | T73: =IF(INDEX('KPI Analysis'!$AH$7:$CM$123,MATCH($A73,'KPI Analysis'!$AH$7:$AH$123,FALSE),MATCH(T$8,'KPI Analysis'!$AH$7:$CM$7,FALSE))="OD","",INDEX('KPI Analysis'!$AH$7:$CM$123,MATCH($A73,'KPI Analysis'!$AH$7:$AH$123,FALSE),MATCH(T$8,'KPI Analysis'!$AH$7:$CM$7,FALSE))) -> G | U73: =INDEX('KPI Analysis'!$CO$7:$EU$123,MATCH($A73,'KPI Analysis'!$CO$7:$CO$123,FALSE),MATCH(T$8,'KPI Analysis'!$CO$7:$EU$7,FALSE)) -> 1.0160148 | V73: =IF(INDEX('KPI Analysis'!$AH$7:$CM$123,MATCH($A73,'KPI Analysis'!$AH$7:$AH$123,FALSE),MATCH(V$8,'KPI Analysis'!$AH$7:$CM$7,FALSE))="OD","",INDEX('KPI Analysis'!$AH$7:$CM$123,MATCH($A73,'KPI Analysis'!$AH$7:$AH$123,FALSE),MATCH(V$8,'KPI Analysis'!$AH$7:$CM$7,FALSE))) -> R | W73: =INDEX('KPI Analysis'!$CO$7:$EU$123,MATCH($A73,'KPI Analysis'!$CO$7:$CO$123,FALSE),MATCH(V$8,'KPI Analysis'!$CO$7:$EU$7,FALSE)) -> 0.674375 | X73: =IF(INDEX('KPI Analysis'!$AH$7:$CM$123,MATCH($A73,'KPI Analysis'!$AH$7:$AH$123,FALSE),MATCH(X$8,'KPI Analysis'!$AH$7:$CM$7,FALSE))="OD","",INDEX('KPI Analysis'!$AH$7:$CM$123,MATCH($A73,'KPI Analysis'!$AH$7:$AH$123,FALSE),MATCH(X$8,'KPI Analysis'!$AH$7:$CM$7,FALSE))) -> R | Y73: =INDEX('KPI Analysis'!$CO$7:$EU$123,MATCH($A73,'KPI Analysis'!$CO$7:$CO$123,FALSE),MATCH(X$8,'KPI Analysis'!$CO$7:$EU$7,FALSE)) -> 0.80625 | AC73: Co EU | AE73: =INDEX('KPI Analysis'!$CO$7:$EU$123,MATCH($A73,'KPI Analysis'!$CO$7:$CO$123,FALSE),MATCH(AE$8,'KPI Analysis'!$CO$7:$EU$7,FALSE)) -> 0.79396682 | AF73: =INDEX('KPI Analysis'!$CO$7:$EU$123,MATCH($A73,'KPI Analysis'!$CO$7:$CO$123,FALSE),MATCH(AF$8,'KPI Analysis'!$CO$7:$EU$7,FALSE)) -> 0.78853695 | AG73: =INDEX('KPI Analysis'!$CO$7:$EU$123,MATCH($A73,'KPI Analysis'!$CO$7:$CO$123,FALSE),MATCH(AG$8,'KPI Analysis'!$CO$7:$EU$7,FALSE)) -> 1.0160148 | AH73: =INDEX('KPI Analysis'!$CO$7:$EU$123,MATCH($A73,'KPI Analysis'!$CO$7:$CO$123,FALSE),MATCH(AH$8,'KPI Analysis'!$CO$7:$EU$7,FALSE)) -> 0.674375 | AI73: =INDEX('KPI Analysis'!$CO$7:$EU$123,MATCH($A73,'KPI Analysis'!$CO$7:$CO$123,FALSE),MATCH(AI$8,'KPI Analysis'!$CO$7:$EU$7,FALSE)) -> 0.80625
C76: Tab | F76: =+F$6 -> Department | G76: Manager | H76: =+H$6 -> Freq | I76: =+I$6 -> Wk | J76: =+J$6 -> Category | K76: =+K$6 -> KPI | L76: =+L$6 -> UOM | M76: =+M$6 -> Shown | P76: Week KPI Calc | AE76: =+AE$6 -> Week KPI Calc | AF76: =+AF$6 -> Week KPI Calc | AG76: =+AG$6 -> Week KPI Calc | AH76: =+AH$6 -> Week KPI Calc | AI76: =+AI$6 -> Week KPI Calc
A77: Lookup Drivers for | F77: =+F$7 -> Mth No | H77: =+H$7 -> For Monthly KPIs | P77: =_xlfn.XLOOKUP('KPI Linked Table for Report'!P78,'KPI Analysis'!$CU$7:$EU$7,'KPI Analysis'!$CU$8:$EU$8) -> 8 | R77: =_xlfn.XLOOKUP('KPI Linked Table for Report'!R78,'KPI Analysis'!$CU$7:$EU$7,'KPI Analysis'!$CU$8:$EU$8) -> 8 | T77: =_xlfn.XLOOKUP('KPI Linked Table for Report'!T78,'KPI Analysis'!$CU$7:$EU$7,'KPI Analysis'!$CU$8:$EU$8) -> 9 | V77: =_xlfn.XLOOKUP('KPI Linked Table for Report'!V78,'KPI Analysis'!$CU$7:$EU$7,'KPI Analysis'!$CU$8:$EU$8) -> 9 | X77: =_xlfn.XLOOKUP('KPI Linked Table for Report'!X78,'KPI Analysis'!$CU$7:$EU$7,'KPI Analysis'!$CU$8:$EU$8) -> 9 | AC77: 6,20 | AE77: =+AE$7 -> 8 | AF77: =+AF$7 -> 8 | AG77: =+AG$7 -> 9 | AH77: =+AH$7 -> 9 | AI77: =+AI$7 -> 9
F78: =+F$8 -> Wk No | H78: =+H$8 -> For Weekly KPI's | P78: =+P$8 -> 38 | R78: =+R$8 -> 39 | T78: =+T$8 -> 40 | V78: =+V$8 -> 41 | X78: =+X$8 -> 42 | AC78: 23 | AE78: =+AE$8 -> 38 | AF78: =+AF$8 -> 39 | AG78: =+AG$8 -> 40 | AH78: =+AH$8 -> 41 | AI78: =+AI$8 -> 42
F79: =+F$9 -> Date | H79: =+H$9 -> Week Ending (Fri) | P79: =_xlfn.XLOOKUP(P78,EHS!$M$6:$BM$6,EHS!$M$7:$BM$7) -> 45919 | R79: =_xlfn.XLOOKUP(R78,EHS!$M$6:$BM$6,EHS!$M$7:$BM$7) -> 45926 | T79: =_xlfn.XLOOKUP(T78,EHS!$M$6:$BM$6,EHS!$M$7:$BM$7) -> 45933 | V79: =_xlfn.XLOOKUP(V78,EHS!$M$6:$BM$6,EHS!$M$7:$BM$7) -> 45940 | X79: =_xlfn.XLOOKUP(X78,EHS!$M$6:$BM$6,EHS!$M$7:$BM$7) -> 45947 | AE79: =+AE$9 -> 45919 | AF79: =+AF$9 -> 45926 | AG79: =+AG$9 -> 45933 | AH79: =+AH$9 -> 45940 | AI79: =+AI$9 -> 45947
A81: =F81&"-"&C81 -> Logistics-KPI P1 | B81: =+'KPI Stats'!G69 -> Under | C81: =+'KPI Stats'!C69 -> KPI P1 | F81: =+'KPI Stats'!$B$68 -> Logistics | G81: Garin Bowen | H81: W | I81: =+'KPI Stats'!$F$68 -> 42 | J81: =+'KPI Stats'!D69 -> Productivity | K81: =+'KPI Stats'!E69 -> Sales Value Despatched - Group | L81: =+'KPI Stats'!F69 -> £'s | M81: =INDEX('KPI Analysis'!$CO$7:$EU$123,MATCH($A81,'KPI Analysis'!$CO$7:$CO$123,FALSE),MATCH(M$8,'KPI Analysis'!$CO$7:$EU$7,FALSE)) -> % of target | P81: =IF(INDEX('KPI Analysis'!$AH$7:$CM$123,MATCH($A81,'KPI Analysis'!$AH$7:$AH$123,FALSE),MATCH(P$8,'KPI Analysis'!$AH$7:$CM$7,FALSE))="OD","",INDEX('KPI Analysis'!$AH$7:$CM$123,MATCH($A81,'KPI Analysis'!$AH$7:$AH$123,FALSE),MATCH(P$8,'KPI Analysis'!$AH$7:$CM$7,FALSE))) | Q81: =INDEX('KPI Analysis'!$CO$7:$EU$123,MATCH($A81,'KPI Analysis'!$CO$7:$CO$123,FALSE),MATCH(P$8,'KPI Analysis'!$CO$7:$EU$7,FALSE)) -> OD | R81: =IF(INDEX('KPI Analysis'!$AH$7:$CM$123,MATCH($A81,'KPI Analysis'!$AH$7:$AH$123,FALSE),MATCH(R$8,'KPI Analysis'!$AH$7:$CM$7,FALSE))="OD","",INDEX('KPI Analysis'!$AH$7:$CM$123,MATCH($A81,'KPI Analysis'!$AH$7:$AH$123,FALSE),MATCH(R$8,'KPI Analysis'!$AH$7:$CM$7,FALSE))) | S81: =INDEX('KPI Analysis'!$CO$7:$EU$123,MATCH($A81,'KPI Analysis'!$CO$7:$CO$123,FALSE),MATCH(R$8,'KPI Analysis'!$CO$7:$EU$7,FALSE)) -> OD | T81: =IF(INDEX('KPI Analysis'!$AH$7:$CM$123,MATCH($A81,'KPI Analysis'!$AH$7:$AH$123,FALSE),MATCH(T$8,'KPI Analysis'!$AH$7:$CM$7,FALSE))="OD","",INDEX('KPI Analysis'!$AH$7:$CM$123,MATCH($A81,'KPI Analysis'!$AH$7:$AH$123,FALSE),MATCH(T$8,'KPI Analysis'!$AH$7:$CM$7,FALSE))) | U81: =INDEX('KPI Analysis'!$CO$7:$EU$123,MATCH($A81,'KPI Analysis'!$CO$7:$CO$123,FALSE),MATCH(T$8,'KPI Analysis'!$CO$7:$EU$7,FALSE)) -> OD | V81: =IF(INDEX('KPI Analysis'!$AH$7:$CM$123,MATCH($A81,'KPI Analysis'!$AH$7:$AH$123,FALSE),MATCH(V$8,'KPI Analysis'!$AH$7:$CM$7,FALSE))="OD","",INDEX('KPI Analysis'!$AH$7:$CM$123,MATCH($A81,'KPI Analysis'!$AH$7:$AH$123,FALSE),MATCH(V$8,'KPI Analysis'!$AH$7:$CM$7,FALSE))) | W81: =INDEX('KPI Analysis'!$CO$7:$EU$123,MATCH($A81,'KPI Analysis'!$CO$7:$CO$123,FALSE),MATCH(V$8,'KPI Analysis'!$CO$7:$EU$7,FALSE)) -> OD | X81: =IF(INDEX('KPI Analysis'!$AH$7:$CM$123,MATCH($A81,'KPI Analysis'!$AH$7:$AH$123,FALSE),MATCH(X$8,'KPI Analysis'!$AH$7:$CM$7,FALSE))="OD","",INDEX('KPI Analysis'!$AH$7:$CM$123,MATCH($A81,'KPI Analysis'!$AH$7:$AH$123,FALSE),MATCH(X$8,'KPI Analysis'!$AH$7:$CM$7,FALSE))) | Y81: =INDEX('KPI Analysis'!$CO$7:$EU$123,MATCH($A81,'KPI Analysis'!$CO$7:$CO$123,FALSE),MATCH(X$8,'KPI Analysis'!$CO$7:$EU$7,FALSE)) -> OD | AC81: Co EU | AE81: =INDEX('KPI Analysis'!$CO$7:$EU$123,MATCH($A81,'KPI Analysis'!$CO$7:$CO$123,FALSE),MATCH(AE$8,'KPI Analysis'!$CO$7:$EU$7,FALSE)) -> OD | AF81: =INDEX('KPI Analysis'!$CO$7:$EU$123,MATCH($A81,'KPI Analysis'!$CO$7:$CO$123,FALSE),MATCH(AF$8,'KPI Analysis'!$CO$7:$EU$7,FALSE)) -> OD | AG81: =INDEX('KPI Analysis'!$CO$7:$EU$123,MATCH($A81,'KPI Analysis'!$CO$7:$CO$123,FALSE),MATCH(AG$8,'KPI Analysis'!$CO$7:$EU$7,FALSE)) -> OD | AH81: =INDEX('KPI Analysis'!$CO$7:$EU$123,MATCH($A81,'KPI Analysis'!$CO$7:$CO$123,FALSE),MATCH(AH$8,'KPI Analysis'!$CO$7:$EU$7,FALSE)) -> OD | AI81: =INDEX('KPI Analysis'!$CO$7:$EU$123,MATCH($A81,'KPI Analysis'!$CO$7:$CO$123,FALSE),MATCH(AI$8,'KPI Analysis'!$CO$7:$EU$7,FALSE)) -> OD
A82: =F82&"-"&C82 -> Logistics-KPI D1 | B82: =+'KPI Stats'!G70 -> Under | C82: =+'KPI Stats'!C70 -> KPI D1 | F82: =+'KPI Stats'!$B$68 -> Logistics | G82: =+'KPI Stats'!$B$68 -> Logistics | H82: W | I82: =+'KPI Stats'!$F$68 -> 42 | J82: =+'KPI Stats'!D70 -> Delivery | K82: =+'KPI Stats'!E70 -> Logistics - Delivery - OTIF Group | L82: =+'KPI Stats'!F70 -> Percentage | M82: Act Result | P82: =IF(INDEX('KPI Analysis'!$AH$7:$CM$123,MATCH($A82,'KPI Analysis'!$AH$7:$AH$123,FALSE),MATCH(P$8,'KPI Analysis'!$AH$7:$CM$7,FALSE))="OD","",INDEX('KPI Analysis'!$AH$7:$CM$123,MATCH($A82,'KPI Analysis'!$AH$7:$AH$123,FALSE),MATCH(P$8,'KPI Analysis'!$AH$7:$CM$7,FALSE))) | Q82: =INDEX('KPI Analysis'!$EW$7:$HC$123,MATCH($A82,'KPI Analysis'!$EW$7:$EW$123,FALSE),MATCH(P$8,'KPI Analysis'!$EW$7:$HC$7,FALSE)) -> 0 | R82: =IF(INDEX('KPI Analysis'!$AH$7:$CM$123,MATCH($A82,'KPI Analysis'!$AH$7:$AH$123,FALSE),MATCH(R$8,'KPI Analysis'!$AH$7:$CM$7,FALSE))="OD","",INDEX('KPI Analysis'!$AH$7:$CM$123,MATCH($A82,'KPI Analysis'!$AH$7:$AH$123,FALSE),MATCH(R$8,'KPI Analysis'!$AH$7:$CM$7,FALSE))) | S82: =INDEX('KPI Analysis'!$EW$7:$HC$123,MATCH($A82,'KPI Analysis'!$EW$7:$EW$123,FALSE),MATCH(R$8,'KPI Analysis'!$EW$7:$HC$7,FALSE)) -> 0 | T82: =IF(INDEX('KPI Analysis'!$AH$7:$CM$123,MATCH($A82,'KPI Analysis'!$AH$7:$AH$123,FALSE),MATCH(T$8,'KPI Analysis'!$AH$7:$CM$7,FALSE))="OD","",INDEX('KPI Analysis'!$AH$7:$CM$123,MATCH($A82,'KPI Analysis'!$AH$7:$AH$123,FALSE),MATCH(T$8,'KPI Analysis'!$AH$7:$CM$7,FALSE))) | U82: =IF(INDEX('KPI Analysis'!$CO$7:$EU$123,MATCH($A82,'KPI Analysis'!$CO$7:$CO$123,FALSE),MATCH(T$8,'KPI Analysis'!$CO$7:$EU$7,FALSE))="OD","OD",INDEX('KPI Analysis'!$EW$7:$HC$123,MATCH($A82,'KPI Analysis'!$EW$7:$EW$123,FALSE),MATCH(T$8,'KPI Analysis'!$EW$7:$HC$7,FALSE))) -> OD | V82: =IF(INDEX('KPI Analysis'!$AH$7:$CM$123,MATCH($A82,'KPI Analysis'!$AH$7:$AH$123,FALSE),MATCH(V$8,'KPI Analysis'!$AH$7:$CM$7,FALSE))="OD","",INDEX('KPI Analysis'!$AH$7:$CM$123,MATCH($A82,'KPI Analysis'!$AH$7:$AH$123,FALSE),MATCH(V$8,'KPI Analysis'!$AH$7:$CM$7,FALSE))) | W82: =IF(INDEX('KPI Analysis'!$CO$7:$EU$123,MATCH($A82,'KPI Analysis'!$CO$7:$CO$123,FALSE),MATCH(V$8,'KPI Analysis'!$CO$7:$EU$7,FALSE))="OD","OD",INDEX('KPI Analysis'!$EW$7:$HC$123,MATCH($A82,'KPI Analysis'!$EW$7:$EW$123,FALSE),MATCH(V$8,'KPI Analysis'!$EW$7:$HC$7,FALSE))) -> OD | X82: =IF(INDEX('KPI Analysis'!$AH$7:$CM$123,MATCH($A82,'KPI Analysis'!$AH$7:$AH$123,FALSE),MATCH(X$8,'KPI Analysis'!$AH$7:$CM$7,FALSE))="OD","",INDEX('KPI Analysis'!$AH$7:$CM$123,MATCH($A82,'KPI Analysis'!$AH$7:$AH$123,FALSE),MATCH(X$8,'KPI Analysis'!$AH$7:$CM$7,FALSE))) | Y82: =IF(INDEX('KPI Analysis'!$CO$7:$EU$123,MATCH($A82,'KPI Analysis'!$CO$7:$CO$123,FALSE),MATCH(X$8,'KPI Analysis'!$CO$7:$EU$7,FALSE))="OD","OD",INDEX('KPI Analysis'!$EW$7:$HC$123,MATCH($A82,'KPI Analysis'!$EW$7:$EW$123,FALSE),MATCH(X$8,'KPI Analysis'!$EW$7:$HC$7,FALSE))) -> OD | Z82: (Target 95%) | AC82: EW HC | AE82: =INDEX('KPI Analysis'!$CO$7:$EU$123,MATCH($A82,'KPI Analysis'!$CO$7:$CO$123,FALSE),MATCH(AE$8,'KPI Analysis'!$CO$7:$EU$7,FALSE)) -> OD | AF82: =INDEX('KPI Analysis'!$CO$7:$EU$123,MATCH($A82,'KPI Analysis'!$CO$7:$CO$123,FALSE),MATCH(AF$8,'KPI Analysis'!$CO$7:$EU$7,FALSE)) -> OD | AG82: =INDEX('KPI Analysis'!$CO$7:$EU$123,MATCH($A82,'KPI Analysis'!$CO$7:$CO$123,FALSE),MATCH(AG$8,'KPI Analysis'!$CO$7:$EU$7,FALSE)) -> OD | AH82: =INDEX('KPI Analysis'!$CO$7:$EU$123,MATCH($A82,'KPI Analysis'!$CO$7:$CO$123,FALSE),MATCH(AH$8,'KPI Analysis'!$CO$7:$EU$7,FALSE)) -> OD | AI82: =INDEX('KPI Analysis'!$CO$7:$EU$123,MATCH($A82,'KPI Analysis'!$CO$7:$CO$123,FALSE),MATCH(AI$8,'KPI Analysis'!$CO$7:$EU$7,FALSE)) -> OD
